Workbook
Name precio: 'Supuestos'!$C$2
Name acciones_diluidas: 'Supuestos'!$C$3
Name ingresos_base: 'Supuestos'!$C$4
Name fraccion: 'Supuestos'!$C$5
Name mitad_de_anio: 'Supuestos'!$C$6
Name bin_inicial: 'Supuestos'!$C$7
Name ke: 'Supuestos'!$C$8
Name horizonte_meses: 'Supuestos'!$C$9
Name dpa_horizonte: 'Supuestos'!$C$10
Name ajuste_puente: 'Supuestos'!$C$11
Name deuda_neta: 'Supuestos'!$C$12
Name wacc_calculado: 'Supuestos'!$C$13
Name sbc_coste: 'Supuestos'!$C$14
Name wacc_pes: 'Pesimista'!$C$2
Name g_pes: 'Pesimista'!$C$3
Name peso_pes: 'Pesimista'!$C$4
Name ronic_pes: 'Pesimista'!$C$5
Name multiplo_pes: 'Pesimista'!$C$6
Name fm_pes: 'Pesimista'!$C$7
Name suma_va_pes: 'Pesimista'!$C$34
Name vt_pes: 'Pesimista'!$C$35
Name va_vt_pes: 'Pesimista'!$C$36
Name ev_pes: 'Pesimista'!$C$37
Name fondos_propios_pes: 'Pesimista'!$C$38
Name valor_accion_pes: 'Pesimista'!$C$39
Name valor_h_pes: 'Pesimista'!$C$40
Name wacc_base: 'Base'!$C$2
Name g_base: 'Base'!$C$3
Name peso_base: 'Base'!$C$4
Name ronic_base: 'Base'!$C$5
Name multiplo_base: 'Base'!$C$6
Name fm_base: 'Base'!$C$7
Name suma_va_base: 'Base'!$C$34
Name vt_base: 'Base'!$C$35
Name va_vt_base: 'Base'!$C$36
Name ev_base: 'Base'!$C$37
Name fondos_propios_base: 'Base'!$C$38
Name valor_accion_base: 'Base'!$C$39
Name valor_h_base: 'Base'!$C$40
Name wacc_opt: 'Optimista'!$C$2
Name g_opt: 'Optimista'!$C$3
Name peso_opt: 'Optimista'!$C$4
Name ronic_opt: 'Optimista'!$C$5
Name multiplo_opt: 'Optimista'!$C$6
Name fm_opt: 'Optimista'!$C$7
Name suma_va_opt: 'Optimista'!$C$34
Name vt_opt: 'Optimista'!$C$35
Name va_vt_opt: 'Optimista'!$C$36
Name ev_opt: 'Optimista'!$C$37
Name fondos_propios_opt: 'Optimista'!$C$38
Name valor_accion_opt: 'Optimista'!$C$39
Name valor_h_opt: 'Optimista'!$C$40
Name valor_razonable: 'Resumen'!$C$7
Name po: 'Resumen'!$C$8
Name potencial: 'Resumen'!$C$9
Name margen_seguridad: 'Resumen'!$C$10
Name downside: 'Resumen'!$C$11
Name recorrido_riesgo: 'Resumen'!$C$12

Sheet Supuestos
A1: Rango | B1: Supuesto | C1: Valor | D1: Origen / justificación
A2: precio | B2: Precio: cierre oficial en la fecha de valoración (USD/acción) | C2: 137.1 | D2: Nasdaq
A3: acciones_diluidas | B3: Acciones diluidas | C3: 3104736000 | D3: básicas de la portada + opciones por el método de autocartera (0,0 M) + RSU pendientes (81,0 M)
A4: ingresos_base | B4: Ingresos del año base (USD) | C4: 67357000000 | D4: SEC (hechos verificados)
A5: fraccion | B5: Fracción del ejercicio 1 que queda (f) | C5: 0.67945205 | D5: días hasta el cierre / días del ejercicio
A6: mitad_de_anio | B6: Convención de mitad de año (1 sí, 0 no) | C6: 1 | D6: entradas del analista
A7: bin_inicial | B7: Bases imponibles negativas iniciales (USD) | C7: 0 | D7: entradas del analista
A8: ke | B8: Coste de los fondos propios (Ke) | C8: 0.11638099 | D8: rf + β × ERP + prima
A9: horizonte_meses | B9: Horizonte (meses) | C9: 12 | D9: entradas del analista
A10: dpa_horizonte | B10: Dividendos por acción esperados en el horizonte (USD) | C10: 0 | D10: Nasdaq (últimos cuatro pagos)
A11: ajuste_puente | B11: Ajuste del puente: − deuda + caja + inversiones ± ajustes (USD) | C11: -93260000000 | D11: último balance publicado
A12: deuda_neta | B12: Deuda neta (USD) | C12: 88260000000 | D12: último balance publicado
A13: wacc_calculado | B13: WACC calculado (antes del ajuste por escenario) | C13: 0.099816692 | D13: E/(D+E) × Ke + D/(D+E) × Kd × (1 − t)
A14: sbc_coste | B14: SBC como coste de caja (1 sí, 0 no) | C14: 1 | D14: entradas del analista

Sheet Resumen
A1: Escenario | B1: Probabilidad | C1: V₀ | D1: V_h | E1: WACC
A2: pesimista | B2: =peso_pes | C2: =valor_accion_pes | D2: =valor_h_pes | E2: =wacc_pes
A3: base | B3: =peso_base | C3: =valor_accion_base | D3: =valor_h_base | E3: =wacc_base
A4: optimista | B4: =peso_opt | C4: =valor_accion_opt | D4: =valor_h_opt | E4: =wacc_opt
A7: valor_razonable | B7: Valor razonable hoy (Σ p·V₀) | C7: =SUMPRODUCT(B2:B4,C2:C4)
A8: po | B8: Precio objetivo (Σ p·V_h) | C8: =SUMPRODUCT(B2:B4,D2:D4)
A9: potencial | B9: Potencial | C9: =po/precio-1
A10: margen_seguridad | B10: Margen de seguridad | C10: =1-precio/valor_razonable
A11: downside | B11: Downside pesimista | C11: =valor_h_pes/precio-1
A12: recorrido_riesgo | B12: Recorrido / riesgo | C12: =IF(valor_h_pes>=precio,"sin pérdida",(po-precio)/(precio-valor_h_pes))

Sheet Pesimista
A1: Escenario pesimista: fórmulas vivas del motor (05 §3–§7)
A2: wacc_pes | B2: WACC del escenario | C2: 0.10981669
A3: g_pes | B3: Crecimiento terminal (g) | C3: 0.02
A4: peso_pes | B4: Probabilidad | C4: 0.3
A5: ronic_pes | B5: RONIC | C5: 0.11
A6: multiplo_pes | B6: Múltiplo de salida
A7: fm_pes | B7: ΔFM / Δingresos | C7: -0.05
B9: Año | C9: Año 1 | D9: Año 2 | E9: Año 3 | F9: Año 4 | G9: Año 5 | H9: Año 6 | I9: Año 7 | J9: Año 8 | K9: Año 9 | L9: Año 10
B10: crecimiento | C10: 0.32 | D10: 0.25 | E10: 0.12 | F10: 0.09 | G10: 0.06 | H10: 0.054 | I10: 0.048 | J10: 0.042 | K10: 0.036 | L10: 0.03
B11: margen | C11: 0.3 | D11: 0.265 | E11: 0.23 | F11: 0.225 | G11: 0.22 | H11: 0.224 | I11: 0.228 | J11: 0.232 | K11: 0.236 | L11: 0.24
B12: impuesto | C12: 0.17 | D12: 0.175 | E12: 0.18 | F12: 0.185 | G12: 0.19 | H12: 0.194 | I12: 0.198 | J12: 0.202 | K12: 0.206 | L12: 0.21
B13: da | C13: 0.18 | D13: 0.205 | E13: 0.23 | F13: 0.23 | G13: 0.23 | H13: 0.216 | I13: 0.202 | J13: 0.188 | K13: 0.174 | L13: 0.16
B14: capex | C14: 1.15 | D14: 0.5 | E14: 0.28 | F14: 0.24 | G14: 0.2 | H14: 0.192 | I14: 0.184 | J14: 0.176 | K14: 0.168 | L14: 0.16
B15: sbc | C15: 0.06 | D15: 0.0575 | E15: 0.055 | F15: 0.0525 | G15: 0.05 | H15: 0.049 | I15: 0.048 | J15: 0.047 | K15: 0.046 | L15: 0.045
B17: Ingresos | C17: =ingresos_base*(1+C10) | D17: =C17*(1+D10) | E17: =D17*(1+E10) | F17: =E17*(1+F10) | G17: =F17*(1+G10) | H17: =G17*(1+H10) | I17: =H17*(1+I10) | J17: =I17*(1+J10) | K17: =J17*(1+K10) | L17: =K17*(1+L10)
B18: EBIT | C18: =C17*C11 | D18: =D17*D11 | E18: =E17*E11 | F18: =F17*F11 | G18: =G17*G11 | H18: =H17*H11 | I18: =I17*I11 | J18: =J17*J11 | ... L18: =L17*L11
B19: Bases imponibles negativas al inicio | C19: =bin_inicial | D19: =MAX(0,C19-MAX(C18,0))+MAX(-C18,0) | E19: =MAX(0,D19-MAX(D18,0))+MAX(-D18,0) | F19: =MAX(0,E19-MAX(E18,0))+MAX(-E18,0) | G19: =MAX(0,F19-MAX(F18,0))+MAX(-F18,0) | H19: =MAX(0,G19-MAX(G18,0))+MAX(-G18,0) | I19: =MAX(0,H19-MAX(H18,0))+MAX(-H18,0) | J19: =MAX(0,I19-MAX(I18,0))+MAX(-I18,0) | K19: =MAX(0,J19-MAX(J18,0))+MAX(-J18,0) | L19: =MAX(0,K19-MAX(K18,0))+MAX(-K18,0)
B20: Impuestos en caja | C20: =MAX(0,C18-C19)*C12 | D20: =MAX(0,D18-D19)*D12 | E20: =MAX(0,E18-E19)*E12 | F20: =MAX(0,F18-F19)*F12 | G20: =MAX(0,G18-G19)*G12 | H20: =MAX(0,H18-H19)*H12 | I20: =MAX(0,I18-I19)*I12 | J20: =MAX(0,J18-J19)*J12 | ... L20: =MAX(0,L18-L19)*L12
B21: NOPAT | C21: =C18-C20 | D21: =D18-D20 | E21: =E18-E20 | F21: =F18-F20 | G21: =G18-G20 | H21: =H18-H20 | I21: =I18-I20 | J21: =J18-J20 | ... L21: =L18-L20
B22: D&A | C22: =C17*C13 | D22: =D17*D13 | E22: =E17*E13 | F22: =F17*F13 | G22: =G17*G13 | H22: =H17*H13 | I22: =I17*I13 | J22: =J17*J13 | ... L22: =L17*L13
B23: Capex | C23: =C17*C14 | D23: =D17*D14 | E23: =E17*E14 | F23: =F17*F14 | G23: =G17*G14 | H23: =H17*H14 | I23: =I17*I14 | J23: =J17*J14 | ... L23: =L17*L14
B24: ΔFM | C24: =(C17-ingresos_base)*fm_pes | D24: =(D17-C17)*fm_pes | E24: =(E17-D17)*fm_pes | F24: =(F17-E17)*fm_pes | G24: =(G17-F17)*fm_pes | H24: =(H17-G17)*fm_pes | I24: =(I17-H17)*fm_pes | J24: =(J17-I17)*fm_pes | K24: =(K17-J17)*fm_pes | L24: =(L17-K17)*fm_pes
B25: SBC | C25: =C17*C15*sbc_coste | D25: =D17*D15*sbc_coste | E25: =E17*E15*sbc_coste | F25: =F17*F15*sbc_coste | G25: =G17*G15*sbc_coste | H25: =H17*H15*sbc_coste | I25: =I17*I15*sbc_coste | J25: =J17*J15*sbc_coste | ... L25: =L17*L15*sbc_coste
B26: Partidas del paquete | C26: 0 | D26: 0 | E26: 0 | F26: 0 | G26: 0 | H26: 0 | I26: 0 | J26: 0 | K26: 0 | L26: 0
B27: FCFF | C27: =C21+C22-C23-C24-C25-C26 | D27: =D21+D22-D23-D24-D25-D26 | E27: =E21+E22-E23-E24-E25-E26 | F27: =F21+F22-F23-F24-F25-F26 | G27: =G21+G22-G23-G24-G25-G26 | H27: =H21+H22-H23-H24-H25-H26 | I27: =I21+I22-I23-I24-I25-I26 | J27: =J21+J22-J23-J24-J25-J26 | ... L27: =L21+L22-L23-L24-L25-L26
B28: EBITDA | C28: =C18+C22 | D28: =D18+D22 | E28: =E18+E22 | F28: =F18+F22 | G28: =G18+G22 | H28: =H18+H22 | I28: =I18+I22 | J28: =J18+J22 | ... L28: =L18+L22
B29: Momento de descuento (años) | C29: =IF(mitad_de_anio=1,fraccion/2,fraccion) | D29: =fraccion+1-IF(mitad_de_anio=1,0.5,0) | E29: =fraccion+2-IF(mitad_de_anio=1,0.5,0) | F29: =fraccion+3-IF(mitad_de_anio=1,0.5,0) | G29: =fraccion+4-IF(mitad_de_anio=1,0.5,0) | H29: =fraccion+5-IF(mitad_de_anio=1,0.5,0) | I29: =fraccion+6-IF(mitad_de_anio=1,0.5,0) | J29: =fraccion+7-IF(mitad_de_anio=1,0.5,0) | K29: =fraccion+8-IF(mitad_de_anio=1,0.5,0) | L29: =fraccion+9-IF(mitad_de_anio=1,0.5,0)
B30: Factor de descuento | C30: =(1+wacc_pes)^(-C29) | D30: =(1+wacc_pes)^(-D29) | E30: =(1+wacc_pes)^(-E29) | F30: =(1+wacc_pes)^(-F29) | G30: =(1+wacc_pes)^(-G29) | H30: =(1+wacc_pes)^(-H29) | I30: =(1+wacc_pes)^(-I29) | J30: =(1+wacc_pes)^(-J29) | ... L30: =(1+wacc_pes)^(-L29)
B31: Parte del año que cuenta | C31: =fraccion | D31: 1 | E31: 1 | F31: 1 | G31: 1 | H31: 1 | I31: 1 | J31: 1 | K31: 1 | L31: 1
B32: Valor actual del FCFF | C32: =C27*C30*C31 | D32: =D27*D30*D31 | E32: =E27*E30*E31 | F32: =F27*F30*F31 | G32: =G27*G30*G31 | H32: =H27*H30*H31 | I32: =I27*I30*I31 | J32: =J27*J30*J31 | ... L32: =L27*L30*L31
A34: suma_va_pes | B34: Suma del valor actual de los FCFF | C34: =SUM(C32:L32)
A35: vt_pes | B35: Valor terminal (value_driver) | C35: =L21*(1+g_pes)*(1-g_pes/ronic_pes)/(wacc_pes-g_pes)
A36: va_vt_pes | B36: Valor actual del valor terminal | C36: =C35*(1+wacc_pes)^(-(fraccion+10-1))
A37: ev_pes | B37: Valor de empresa | C37: =C34+C36
A38: fondos_propios_pes | B38: Fondos propios | C38: =C37+ajuste_puente
A39: valor_accion_pes | B39: Valor por acción hoy (V₀) | C39: =C38/acciones_diluidas
A40: valor_h_pes | B40: Valor por acción en el horizonte (V_h) | C40: =C39*(1+ke)^(horizonte_meses/12)-dpa_horizonte

Sheet Base
A1: Escenario base: fórmulas vivas del motor (05 §3–§7)
A2: wacc_base | B2: WACC del escenario | C2: 0.099816692
A3: g_base | B3: Crecimiento terminal (g) | C3: 0.025
A4: peso_base | B4: Probabilidad | C4: 0.45
A5: ronic_base | B5: RONIC | C5: 0.12
A6: multiplo_base | B6: Múltiplo de salida
A7: fm_base | B7: ΔFM / Δingresos | C7: -0.15
B9: Año | C9: Año 1 | D9: Año 2 | E9: Año 3 | F9: Año 4 | G9: Año 5 | H9: Año 6 | I9: Año 7 | J9: Año 8 | K9: Año 9 | L9: Año 10
B10: crecimiento | C10: 0.34 | D10: 0.4 | E10: 0.22 | F10: 0.165 | G10: 0.11 | H10: 0.096 | I10: 0.082 | J10: 0.068 | K10: 0.054 | L10: 0.04
B11: margen | C11: 0.33 | D11: 0.315 | E11: 0.3 | F11: 0.3 | G11: 0.3 | H11: 0.302 | I11: 0.304 | J11: 0.306 | K11: 0.308 | L11: 0.31
B12: impuesto | C12: 0.17 | D12: 0.175 | E12: 0.18 | F12: 0.185 | G12: 0.19 | H12: 0.194 | I12: 0.198 | J12: 0.202 | K12: 0.206 | L12: 0.21
B13: da | C13: 0.18 | D13: 0.2 | E13: 0.22 | F13: 0.22 | G13: 0.22 | H13: 0.21 | I13: 0.2 | J13: 0.19 | K13: 0.18 | L13: 0.17
B14: capex | C14: 1.2 | D14: 0.7 | E14: 0.4 | F14: 0.325 | G14: 0.25 | H14: 0.238 | I14: 0.226 | J14: 0.214 | K14: 0.202 | L14: 0.19
B15: sbc | C15: 0.06 | D15: 0.05625 | E15: 0.0525 | F15: 0.04875 | G15: 0.045 | H15: 0.044 | I15: 0.043 | J15: 0.042 | K15: 0.041 | L15: 0.04
B17: Ingresos | C17: =ingresos_base*(1+C10) | D17: =C17*(1+D10) | E17: =D17*(1+E10) | F17: =E17*(1+F10) | G17: =F17*(1+G10) | H17: =G17*(1+H10) | I17: =H17*(1+I10) | J17: =I17*(1+J10) | K17: =J17*(1+K10) | L17: =K17*(1+L10)
B18: EBIT | C18: =C17*C11 | D18: =D17*D11 | E18: =E17*E11 | F18: =F17*F11 | G18: =G17*G11 | H18: =H17*H11 | I18: =I17*I11 | J18: =J17*J11 | ... L18: =L17*L11
B19: Bases imponibles negativas al inicio | C19: =bin_inicial | D19: =MAX(0,C19-MAX(C18,0))+MAX(-C18,0) | E19: =MAX(0,D19-MAX(D18,0))+MAX(-D18,0) | F19: =MAX(0,E19-MAX(E18,0))+MAX(-E18,0) | G19: =MAX(0,F19-MAX(F18,0))+MAX(-F18,0) | H19: =MAX(0,G19-MAX(G18,0))+MAX(-G18,0) | I19: =MAX(0,H19-MAX(H18,0))+MAX(-H18,0) | J19: =MAX(0,I19-MAX(I18,0))+MAX(-I18,0) | K19: =MAX(0,J19-MAX(J18,0))+MAX(-J18,0) | L19: =MAX(0,K19-MAX(K18,0))+MAX(-K18,0)
B20: Impuestos en caja | C20: =MAX(0,C18-C19)*C12 | D20: =MAX(0,D18-D19)*D12 | E20: =MAX(0,E18-E19)*E12 | F20: =MAX(0,F18-F19)*F12 | G20: =MAX(0,G18-G19)*G12 | H20: =MAX(0,H18-H19)*H12 | I20: =MAX(0,I18-I19)*I12 | J20: =MAX(0,J18-J19)*J12 | ... L20: =MAX(0,L18-L19)*L12
B21: NOPAT | C21: =C18-C20 | D21: =D18-D20 | E21: =E18-E20 | F21: =F18-F20 | G21: =G18-G20 | H21: =H18-H20 | I21: =I18-I20 | J21: =J18-J20 | ... L21: =L18-L20
B22: D&A | C22: =C17*C13 | D22: =D17*D13 | E22: =E17*E13 | F22: =F17*F13 | G22: =G17*G13 | H22: =H17*H13 | I22: =I17*I13 | J22: =J17*J13 | ... L22: =L17*L13
B23: Capex | C23: =C17*C14 | D23: =D17*D14 | E23: =E17*E14 | F23: =F17*F14 | G23: =G17*G14 | H23: =H17*H14 | I23: =I17*I14 | J23: =J17*J14 | ... L23: =L17*L14
B24: ΔFM | C24: =(C17-ingresos_base)*fm_base | D24: =(D17-C17)*fm_base | E24: =(E17-D17)*fm_base | F24: =(F17-E17)*fm_base | G24: =(G17-F17)*fm_base | H24: =(H17-G17)*fm_base | I24: =(I17-H17)*fm_base | J24: =(J17-I17)*fm_base | K24: =(K17-J17)*fm_base | L24: =(L17-K17)*fm_base
B25: SBC | C25: =C17*C15*sbc_coste | D25: =D17*D15*sbc_coste | E25: =E17*E15*sbc_coste | F25: =F17*F15*sbc_coste | G25: =G17*G15*sbc_coste | H25: =H17*H15*sbc_coste | I25: =I17*I15*sbc_coste | J25: =J17*J15*sbc_coste | ... L25: =L17*L15*sbc_coste
B26: Partidas del paquete | C26: 0 | D26: 0 | E26: 0 | F26: 0 | G26: 0 | H26: 0 | I26: 0 | J26: 0 | K26: 0 | L26: 0
B27: FCFF | C27: =C21+C22-C23-C24-C25-C26 | D27: =D21+D22-D23-D24-D25-D26 | E27: =E21+E22-E23-E24-E25-E26 | F27: =F21+F22-F23-F24-F25-F26 | G27: =G21+G22-G23-G24-G25-G26 | H27: =H21+H22-H23-H24-H25-H26 | I27: =I21+I22-I23-I24-I25-I26 | J27: =J21+J22-J23-J24-J25-J26 | ... L27: =L21+L22-L23-L24-L25-L26
B28: EBITDA | C28: =C18+C22 | D28: =D18+D22 | E28: =E18+E22 | F28: =F18+F22 | G28: =G18+G22 | H28: =H18+H22 | I28: =I18+I22 | J28: =J18+J22 | ... L28: =L18+L22
B29: Momento de descuento (años) | C29: =IF(mitad_de_anio=1,fraccion/2,fraccion) | D29: =fraccion+1-IF(mitad_de_anio=1,0.5,0) | E29: =fraccion+2-IF(mitad_de_anio=1,0.5,0) | F29: =fraccion+3-IF(mitad_de_anio=1,0.5,0) | G29: =fraccion+4-IF(mitad_de_anio=1,0.5,0) | H29: =fraccion+5-IF(mitad_de_anio=1,0.5,0) | I29: =fraccion+6-IF(mitad_de_anio=1,0.5,0) | J29: =fraccion+7-IF(mitad_de_anio=1,0.5,0) | K29: =fraccion+8-IF(mitad_de_anio=1,0.5,0) | L29: =fraccion+9-IF(mitad_de_anio=1,0.5,0)
B30: Factor de descuento | C30: =(1+wacc_base)^(-C29) | D30: =(1+wacc_base)^(-D29) | E30: =(1+wacc_base)^(-E29) | F30: =(1+wacc_base)^(-F29) | G30: =(1+wacc_base)^(-G29) | H30: =(1+wacc_base)^(-H29) | I30: =(1+wacc_base)^(-I29) | J30: =(1+wacc_base)^(-J29) | ... L30: =(1+wacc_base)^(-L29)
B31: Parte del año que cuenta | C31: =fraccion | D31: 1 | E31: 1 | F31: 1 | G31: 1 | H31: 1 | I31: 1 | J31: 1 | K31: 1 | L31: 1
B32: Valor actual del FCFF | C32: =C27*C30*C31 | D32: =D27*D30*D31 | E32: =E27*E30*E31 | F32: =F27*F30*F31 | G32: =G27*G30*G31 | H32: =H27*H30*H31 | I32: =I27*I30*I31 | J32: =J27*J30*J31 | ... L32: =L27*L30*L31
A34: suma_va_base | B34: Suma del valor actual de los FCFF | C34: =SUM(C32:L32)
A35: vt_base | B35: Valor terminal (value_driver) | C35: =L21*(1+g_base)*(1-g_base/ronic_base)/(wacc_base-g_base)
A36: va_vt_base | B36: Valor actual del valor terminal | C36: =C35*(1+wacc_base)^(-(fraccion+10-1))
A37: ev_base | B37: Valor de empresa | C37: =C34+C36
A38: fondos_propios_base | B38: Fondos propios | C38: =C37+ajuste_puente
A39: valor_accion_base | B39: Valor por acción hoy (V₀) | C39: =C38/acciones_diluidas
A40: valor_h_base | B40: Valor por acción en el horizonte (V_h) | C40: =C39*(1+ke)^(horizonte_meses/12)-dpa_horizonte

Sheet Optimista
A1: Escenario optimista: fórmulas vivas del motor (05 §3–§7)
A2: wacc_opt | B2: WACC del escenario | C2: 0.099816692
A3: g_opt | B3: Crecimiento terminal (g) | C3: 0.03
A4: peso_opt | B4: Probabilidad | C4: 0.25
A5: ronic_opt | B5: RONIC | C5: 0.15
A6: multiplo_opt | B6: Múltiplo de salida
A7: fm_opt | B7: ΔFM / Δingresos | C7: -0.2
B9: Año | C9: Año 1 | D9: Año 2 | E9: Año 3 | F9: Año 4 | G9: Año 5 | H9: Año 6 | I9: Año 7 | J9: Año 8 | K9: Año 9 | L9: Año 10
B10: crecimiento | C10: 0.36 | D10: 0.48 | E10: 0.28 | F10: 0.21 | G10: 0.14 | H10: 0.121 | I10: 0.102 | J10: 0.083 | K10: 0.064 | L10: 0.045
B11: margen | C11: 0.34 | D11: 0.335 | E11: 0.33 | F11: 0.34 | G11: 0.35 | H11: 0.352 | I11: 0.354 | J11: 0.356 | K11: 0.358 | L11: 0.36
B12: impuesto | C12: 0.17 | D12: 0.175 | E12: 0.18 | F12: 0.185 | G12: 0.19 | H12: 0.194 | I12: 0.198 | J12: 0.202 | K12: 0.206 | L12: 0.21
B13: da | C13: 0.18 | D13: 0.2 | E13: 0.22 | F13: 0.22 | G13: 0.22 | H13: 0.21 | I13: 0.2 | J13: 0.19 | K13: 0.18 | L13: 0.17
B14: capex | C14: 1.2 | D14: 0.72 | E14: 0.42 | F14: 0.34 | G14: 0.26 | H14: 0.246 | I14: 0.232 | J14: 0.218 | K14: 0.204 | L14: 0.19
B15: sbc | C15: 0.06 | D15: 0.05625 | E15: 0.0525 | F15: 0.04875 | G15: 0.045 | H15: 0.044 | I15: 0.043 | J15: 0.042 | K15: 0.041 | L15: 0.04
B17: Ingresos | C17: =ingresos_base*(1+C10) | D17: =C17*(1+D10) | E17: =D17*(1+E10) | F17: =E17*(1+F10) | G17: =F17*(1+G10) | H17: =G17*(1+H10) | I17: =H17*(1+I10) | J17: =I17*(1+J10) | K17: =J17*(1+K10) | L17: =K17*(1+L10)
B18: EBIT | C18: =C17*C11 | D18: =D17*D11 | E18: =E17*E11 | F18: =F17*F11 | G18: =G17*G11 | H18: =H17*H11 | I18: =I17*I11 | J18: =J17*J11 | ... L18: =L17*L11
B19: Bases imponibles negativas al inicio | C19: =bin_inicial | D19: =MAX(0,C19-MAX(C18,0))+MAX(-C18,0) | E19: =MAX(0,D19-MAX(D18,0))+MAX(-D18,0) | F19: =MAX(0,E19-MAX(E18,0))+MAX(-E18,0) | G19: =MAX(0,F19-MAX(F18,0))+MAX(-F18,0) | H19: =MAX(0,G19-MAX(G18,0))+MAX(-G18,0) | I19: =MAX(0,H19-MAX(H18,0))+MAX(-H18,0) | J19: =MAX(0,I19-MAX(I18,0))+MAX(-I18,0) | K19: =MAX(0,J19-MAX(J18,0))+MAX(-J18,0) | L19: =MAX(0,K19-MAX(K18,0))+MAX(-K18,0)
B20: Impuestos en caja | C20: =MAX(0,C18-C19)*C12 | D20: =MAX(0,D18-D19)*D12 | E20: =MAX(0,E18-E19)*E12 | F20: =MAX(0,F18-F19)*F12 | G20: =MAX(0,G18-G19)*G12 | H20: =MAX(0,H18-H19)*H12 | I20: =MAX(0,I18-I19)*I12 | J20: =MAX(0,J18-J19)*J12 | ... L20: =MAX(0,L18-L19)*L12
B21: NOPAT | C21: =C18-C20 | D21: =D18-D20 | E21: =E18-E20 | F21: =F18-F20 | G21: =G18-G20 | H21: =H18-H20 | I21: =I18-I20 | J21: =J18-J20 | ... L21: =L18-L20
B22: D&A | C22: =C17*C13 | D22: =D17*D13 | E22: =E17*E13 | F22: =F17*F13 | G22: =G17*G13 | H22: =H17*H13 | I22: =I17*I13 | J22: =J17*J13 | ... L22: =L17*L13
B23: Capex | C23: =C17*C14 | D23: =D17*D14 | E23: =E17*E14 | F23: =F17*F14 | G23: =G17*G14 | H23: =H17*H14 | I23: =I17*I14 | J23: =J17*J14 | ... L23: =L17*L14
B24: ΔFM | C24: =(C17-ingresos_base)*fm_opt | D24: =(D17-C17)*fm_opt | E24: =(E17-D17)*fm_opt | F24: =(F17-E17)*fm_opt | G24: =(G17-F17)*fm_opt | H24: =(H17-G17)*fm_opt | I24: =(I17-H17)*fm_opt | J24: =(J17-I17)*fm_opt | K24: =(K17-J17)*fm_opt | L24: =(L17-K17)*fm_opt
B25: SBC | C25: =C17*C15*sbc_coste | D25: =D17*D15*sbc_coste | E25: =E17*E15*sbc_coste | F25: =F17*F15*sbc_coste | G25: =G17*G15*sbc_coste | H25: =H17*H15*sbc_coste | I25: =I17*I15*sbc_coste | J25: =J17*J15*sbc_coste | ... L25: =L17*L15*sbc_coste
B26: Partidas del paquete | C26: 0 | D26: 0 | E26: 0 | F26: 0 | G26: 0 | H26: 0 | I26: 0 | J26: 0 | K26: 0 | L26: 0
B27: FCFF | C27: =C21+C22-C23-C24-C25-C26 | D27: =D21+D22-D23-D24-D25-D26 | E27: =E21+E22-E23-E24-E25-E26 | F27: =F21+F22-F23-F24-F25-F26 | G27: =G21+G22-G23-G24-G25-G26 | H27: =H21+H22-H23-H24-H25-H26 | I27: =I21+I22-I23-I24-I25-I26 | J27: =J21+J22-J23-J24-J25-J26 | ... L27: =L21+L22-L23-L24-L25-L26
B28: EBITDA | C28: =C18+C22 | D28: =D18+D22 | E28: =E18+E22 | F28: =F18+F22 | G28: =G18+G22 | H28: =H18+H22 | I28: =I18+I22 | J28: =J18+J22 | ... L28: =L18+L22
B29: Momento de descuento (años) | C29: =IF(mitad_de_anio=1,fraccion/2,fraccion) | D29: =fraccion+1-IF(mitad_de_anio=1,0.5,0) | E29: =fraccion+2-IF(mitad_de_anio=1,0.5,0) | F29: =fraccion+3-IF(mitad_de_anio=1,0.5,0) | G29: =fraccion+4-IF(mitad_de_anio=1,0.5,0) | H29: =fraccion+5-IF(mitad_de_anio=1,0.5,0) | I29: =fraccion+6-IF(mitad_de_anio=1,0.5,0) | J29: =fraccion+7-IF(mitad_de_anio=1,0.5,0) | K29: =fraccion+8-IF(mitad_de_anio=1,0.5,0) | L29: =fraccion+9-IF(mitad_de_anio=1,0.5,0)
B30: Factor de descuento | C30: =(1+wacc_opt)^(-C29) | D30: =(1+wacc_opt)^(-D29) | E30: =(1+wacc_opt)^(-E29) | F30: =(1+wacc_opt)^(-F29) | G30: =(1+wacc_opt)^(-G29) | H30: =(1+wacc_opt)^(-H29) | I30: =(1+wacc_opt)^(-I29) | J30: =(1+wacc_opt)^(-J29) | ... L30: =(1+wacc_opt)^(-L29)
B31: Parte del año que cuenta | C31: =fraccion | D31: 1 | E31: 1 | F31: 1 | G31: 1 | H31: 1 | I31: 1 | J31: 1 | K31: 1 | L31: 1
B32: Valor actual del FCFF | C32: =C27*C30*C31 | D32: =D27*D30*D31 | E32: =E27*E30*E31 | F32: =F27*F30*F31 | G32: =G27*G30*G31 | H32: =H27*H30*H31 | I32: =I27*I30*I31 | J32: =J27*J30*J31 | ... L32: =L27*L30*L31
A34: suma_va_opt | B34: Suma del valor actual de los FCFF | C34: =SUM(C32:L32)
A35: vt_opt | B35: Valor terminal (value_driver) | C35: =L21*(1+g_opt)*(1-g_opt/ronic_opt)/(wacc_opt-g_opt)
A36: va_vt_opt | B36: Valor actual del valor terminal | C36: =C35*(1+wacc_opt)^(-(fraccion+10-1))
A37: ev_opt | B37: Valor de empresa | C37: =C34+C36
A38: fondos_propios_opt | B38: Fondos propios | C38: =C37+ajuste_puente
A39: valor_accion_opt | B39: Valor por acción hoy (V₀) | C39: =C38/acciones_diluidas
A40: valor_h_opt | B40: Valor por acción en el horizonte (V_h) | C40: =C39*(1+ke)^(horizonte_meses/12)-dpa_horizonte

Sheet Sensibilidad
A1: V₀ del escenario base: WACC (filas) × g (columnas)
B2: 0.02 | C2: 0.0225 | D2: 0.025 | E2: 0.0275 | F2: 0.03
A3: 0.089816692 | B3: =IF($A3-B$2<=0,"",(SUMPRODUCT(Base!$C$27:$L$27,Base!$C$31:$L$31,(1+$A3)^(-Base!$C$29:$L$29))+Base!$L$21*(1+B$2)*(1-B$2/0.12)/($A3-B$2)*(1+$A3)^(-(fraccion+10-1))+ajuste_puente)/acciones_diluidas) | C3: =IF($A3-C$2<=0,"",(SUMPRODUCT(Base!$C$27:$L$27,Base!$C$31:$L$31,(1+$A3)^(-Base!$C$29:$L$29))+Base!$L$21*(1+C$2)*(1-C$2/0.12)/($A3-C$2)*(1+$A3)^(-(fraccion+10-1))+ajuste_puente)/acciones_diluidas) | D3: =IF($A3-D$2<=0,"",(SUMPRODUCT(Base!$C$27:$L$27,Base!$C$31:$L$31,(1+$A3)^(-Base!$C$29:$L$29))+Base!$L$21*(1+D$2)*(1-D$2/0.12)/($A3-D$2)*(1+$A3)^(-(fraccion+10-1))+ajuste_puente)/acciones_diluidas) | E3: =IF($A3-E$2<=0,"",(SUMPRODUCT(Base!$C$27:$L$27,Base!$C$31:$L$31,(1+$A3)^(-Base!$C$29:$L$29))+Base!$L$21*(1+E$2)*(1-E$2/0.12)/($A3-E$2)*(1+$A3)^(-(fraccion+10-1))+ajuste_puente)/acciones_diluidas) | F3: =IF($A3-F$2<=0,"",(SUMPRODUCT(Base!$C$27:$L$27,Base!$C$31:$L$31,(1+$A3)^(-Base!$C$29:$L$29))+Base!$L$21*(1+F$2)*(1-F$2/0.12)/($A3-F$2)*(1+$A3)^(-(fraccion+10-1))+ajuste_puente)/acciones_diluidas)
A4: 0.094816692 | B4: =IF($A4-B$2<=0,"",(SUMPRODUCT(Base!$C$27:$L$27,Base!$C$31:$L$31,(1+$A4)^(-Base!$C$29:$L$29))+Base!$L$21*(1+B$2)*(1-B$2/0.12)/($A4-B$2)*(1+$A4)^(-(fraccion+10-1))+ajuste_puente)/acciones_diluidas) | C4: =IF($A4-C$2<=0,"",(SUMPRODUCT(Base!$C$27:$L$27,Base!$C$31:$L$31,(1+$A4)^(-Base!$C$29:$L$29))+Base!$L$21*(1+C$2)*(1-C$2/0.12)/($A4-C$2)*(1+$A4)^(-(fraccion+10-1))+ajuste_puente)/acciones_diluidas) | D4: =IF($A4-D$2<=0,"",(SUMPRODUCT(Base!$C$27:$L$27,Base!$C$31:$L$31,(1+$A4)^(-Base!$C$29:$L$29))+Base!$L$21*(1+D$2)*(1-D$2/0.12)/($A4-D$2)*(1+$A4)^(-(fraccion+10-1))+ajuste_puente)/acciones_diluidas) | E4: =IF($A4-E$2<=0,"",(SUMPRODUCT(Base!$C$27:$L$27,Base!$C$31:$L$31,(1+$A4)^(-Base!$C$29:$L$29))+Base!$L$21*(1+E$2)*(1-E$2/0.12)/($A4-E$2)*(1+$A4)^(-(fraccion+10-1))+ajuste_puente)/acciones_diluidas) | F4: =IF($A4-F$2<=0,"",(SUMPRODUCT(Base!$C$27:$L$27,Base!$C$31:$L$31,(1+$A4)^(-Base!$C$29:$L$29))+Base!$L$21*(1+F$2)*(1-F$2/0.12)/($A4-F$2)*(1+$A4)^(-(fraccion+10-1))+ajuste_puente)/acciones_diluidas)
A5: 0.099816692 | B5: =IF($A5-B$2<=0,"",(SUMPRODUCT(Base!$C$27:$L$27,Base!$C$31:$L$31,(1+$A5)^(-Base!$C$29:$L$29))+Base!$L$21*(1+B$2)*(1-B$2/0.12)/($A5-B$2)*(1+$A5)^(-(fraccion+10-1))+ajuste_puente)/acciones_diluidas) | C5: =IF($A5-C$2<=0,"",(SUMPRODUCT(Base!$C$27:$L$27,Base!$C$31:$L$31,(1+$A5)^(-Base!$C$29:$L$29))+Base!$L$21*(1+C$2)*(1-C$2/0.12)/($A5-C$2)*(1+$A5)^(-(fraccion+10-1))+ajuste_puente)/acciones_diluidas) | D5: =IF($A5-D$2<=0,"",(SUMPRODUCT(Base!$C$27:$L$27,Base!$C$31:$L$31,(1+$A5)^(-Base!$C$29:$L$29))+Base!$L$21*(1+D$2)*(1-D$2/0.12)/($A5-D$2)*(1+$A5)^(-(fraccion+10-1))+ajuste_puente)/acciones_diluidas) | E5: =IF($A5-E$2<=0,"",(SUMPRODUCT(Base!$C$27:$L$27,Base!$C$31:$L$31,(1+$A5)^(-Base!$C$29:$L$29))+Base!$L$21*(1+E$2)*(1-E$2/0.12)/($A5-E$2)*(1+$A5)^(-(fraccion+10-1))+ajuste_puente)/acciones_diluidas) | F5: =IF($A5-F$2<=0,"",(SUMPRODUCT(Base!$C$27:$L$27,Base!$C$31:$L$31,(1+$A5)^(-Base!$C$29:$L$29))+Base!$L$21*(1+F$2)*(1-F$2/0.12)/($A5-F$2)*(1+$A5)^(-(fraccion+10-1))+ajuste_puente)/acciones_diluidas)
A6: 0.10481669 | B6: =IF($A6-B$2<=0,"",(SUMPRODUCT(Base!$C$27:$L$27,Base!$C$31:$L$31,(1+$A6)^(-Base!$C$29:$L$29))+Base!$L$21*(1+B$2)*(1-B$2/0.12)/($A6-B$2)*(1+$A6)^(-(fraccion+10-1))+ajuste_puente)/acciones_diluidas) | C6: =IF($A6-C$2<=0,"",(SUMPRODUCT(Base!$C$27:$L$27,Base!$C$31:$L$31,(1+$A6)^(-Base!$C$29:$L$29))+Base!$L$21*(1+C$2)*(1-C$2/0.12)/($A6-C$2)*(1+$A6)^(-(fraccion+10-1))+ajuste_puente)/acciones_diluidas) | D6: =IF($A6-D$2<=0,"",(SUMPRODUCT(Base!$C$27:$L$27,Base!$C$31:$L$31,(1+$A6)^(-Base!$C$29:$L$29))+Base!$L$21*(1+D$2)*(1-D$2/0.12)/($A6-D$2)*(1+$A6)^(-(fraccion+10-1))+ajuste_puente)/acciones_diluidas) | E6: =IF($A6-E$2<=0,"",(SUMPRODUCT(Base!$C$27:$L$27,Base!$C$31:$L$31,(1+$A6)^(-Base!$C$29:$L$29))+Base!$L$21*(1+E$2)*(1-E$2/0.12)/($A6-E$2)*(1+$A6)^(-(fraccion+10-1))+ajuste_puente)/acciones_diluidas) | F6: =IF($A6-F$2<=0,"",(SUMPRODUCT(Base!$C$27:$L$27,Base!$C$31:$L$31,(1+$A6)^(-Base!$C$29:$L$29))+Base!$L$21*(1+F$2)*(1-F$2/0.12)/($A6-F$2)*(1+$A6)^(-(fraccion+10-1))+ajuste_puente)/acciones_diluidas)
A7: 0.10981669 | B7: =IF($A7-B$2<=0,"",(SUMPRODUCT(Base!$C$27:$L$27,Base!$C$31:$L$31,(1+$A7)^(-Base!$C$29:$L$29))+Base!$L$21*(1+B$2)*(1-B$2/0.12)/($A7-B$2)*(1+$A7)^(-(fraccion+10-1))+ajuste_puente)/acciones_diluidas) | C7: =IF($A7-C$2<=0,"",(SUMPRODUCT(Base!$C$27:$L$27,Base!$C$31:$L$31,(1+$A7)^(-Base!$C$29:$L$29))+Base!$L$21*(1+C$2)*(1-C$2/0.12)/($A7-C$2)*(1+$A7)^(-(fraccion+10-1))+ajuste_puente)/acciones_diluidas) | D7: =IF($A7-D$2<=0,"",(SUMPRODUCT(Base!$C$27:$L$27,Base!$C$31:$L$31,(1+$A7)^(-Base!$C$29:$L$29))+Base!$L$21*(1+D$2)*(1-D$2/0.12)/($A7-D$2)*(1+$A7)^(-(fraccion+10-1))+ajuste_puente)/acciones_diluidas) | E7: =IF($A7-E$2<=0,"",(SUMPRODUCT(Base!$C$27:$L$27,Base!$C$31:$L$31,(1+$A7)^(-Base!$C$29:$L$29))+Base!$L$21*(1+E$2)*(1-E$2/0.12)/($A7-E$2)*(1+$A7)^(-(fraccion+10-1))+ajuste_puente)/acciones_diluidas) | F7: =IF($A7-F$2<=0,"",(SUMPRODUCT(Base!$C$27:$L$27,Base!$C$31:$L$31,(1+$A7)^(-Base!$C$29:$L$29))+Base!$L$21*(1+F$2)*(1-F$2/0.12)/($A7-F$2)*(1+$A7)^(-(fraccion+10-1))+ajuste_puente)/acciones_diluidas)

Sheet Reverse DCF
A1: DCF inverso (motor): qué hay que creer para que V₀ del base sea el precio
