Workbook

Sheet Supuestos
B2: Modelo DCF — Netflix, Inc. (NFLX)
B7: PARÁMETROS GENERALES | C7: Valor | D7: Origen / justificación
B8: Precio de mercado (USD/acción) | C8: 80.32 | D8: Cierre del 14/09/2026. Fuente: StockAnalysis.com. El informe adjunto se redactó el 20/08/2026 con un precio de 80,14 USD.
B9: Precio de entrada del inversor (USD) | C9: 75.5 | D9: Dato facilitado por el inversor
B10: Precio objetivo del inversor (USD) | C10: 100 | D10: Dato facilitado por el inversor
B11: Acciones en circulación (millones) | C11: 4164 | D11: Post-split 10:1. Fuente: StockAnalysis.com
B12: Acciones diluidas (millones) | C12: 4200 | D12: Estimación propia: circulación más dilución previsible por retribución en acciones. Denominador único de todas las valoraciones por acción.
B13: Deuda financiera total (M USD) | C13: 16655 | D13: Balance a 30/06/2026
B14: Caja e inversiones a corto (M USD) | C14: 9128 | D14: Balance a 30/06/2026
B15: Ingresos 2025 (M USD) — año base | C15: 45183 | D15: Cuentas anuales 2025 de Netflix
B16: Margen operativo 2025 | C16: 0.2949 | D16: Resultado operativo de 13.327 M USD
B17: FCF reportado TTM jun-26 (M USD) | C17: 11152 | D17: Incluye 2.800 M USD de la comisión de WBD
B18: Comisión de rescisión de WBD (M USD) | C18: 2800 | D18: Cobro no recurrente registrado en el Q1 2026
B19: FCF 2026E guiado por la compañía (M USD) | C19: 12500 | D19: Guía de la dirección para el ejercicio 2026
... B21: Intereses después de impuestos (M USD) | C21: 600 | D21: Ajuste para desapalancar el FCF reportado
B23: MÉTRICAS DERIVADAS | C23: Valor | D23: Fórmula
B24: Capitalización bursátil (M USD) | C24: =C8*C11 | D24: Sobre 4.164 M acciones en circulación (base de mercado). El valor por acción se calcula sobre 4.200 M diluidas: criterio conservador, declarado aquí a propósito.
B25: Deuda neta (M USD) | C25: =C13-C14 | D25: =C13-C14
B26: Enterprise Value actual (M USD) | C26: =C24+C25 | D26: =C24+C25
B27: FCF 2026E subyacente ex comisión WBD (M USD) | C27: =C19-C18 | D27: =C19-C18
B28: Rentabilidad del FCF subyacente | C28: =C27/C24 | D28: =C27/C24
B29: FCFF económico 2026E implícito (M USD) | C29: =C27+C21 | D29: FCF subyacente + intereses después de impuestos (desapalancado)
B31: PARÁMETROS DE VALORACIÓN POR ESCENARIO | C31: WACC | D31: g terminal | E31: Peso | F31: Origen / justificación
B32: Pesimista | C32: 0.105 | D32: 0.025 | E32: 0.25 | F32: Coste de capital penalizado por deterioro estructural del engagement.
B33: Base | C33: 0.095 | D33: 0.0325 | E33: 0.5 | F33: Rf 4,2% + beta 1,10 x PRM 5,0%; estructura 95,2% FP / 4,8% deuda a valor de mercado. Con la beta estadística de 1,51 el WACC sería 11,4%.
B34: Optimista | C34: 0.09 | D34: 0.035 | E34: 0.25 | F34: Coste de capital de un negocio de suscripción maduro y rentable.
B36: Los tres escenarios leen su WACC, su g y su peso de este bloque. Cambiar aquí recalcula todo el libro, incluida la matriz de sensibilidad.

Sheet Resumen
B2: Resumen de valoración — Netflix, Inc. (NFLX)
B5: Escenario | C5: WACC | D5: g terminal | E5: Valor hoy | F5: Valor rodado 24m | G5: Peso
B6: Pesimista | C6: =Pesimista!$C$5 | D6: =Pesimista!$E$5 | E6: =Pesimista!$C$37 | F6: =Pesimista!$C$40 | G6: =Pesimista!$G$5
B7: Base | C7: =Base!$C$5 | D7: =Base!$E$5 | E7: =Base!$C$37 | F7: =Base!$C$40 | G7: =Base!$G$5
B8: Optimista | C8: =Optimista!$C$5 | D8: =Optimista!$E$5 | E8: =Optimista!$C$37 | F8: =Optimista!$C$40 | G8: =Optimista!$G$5
B9: VALOR RAZONABLE PONDERADO | E9: =SUMPRODUCT(E6:E8,$G$6:$G$8)/SUM($G$6:$G$8) | F9: =SUMPRODUCT(F6:F8,$G$6:$G$8)/SUM($G$6:$G$8)
B11: REFERENCIAS DE PRECIO | C11: Valor | D11: Sobre entrada | E11: Sobre precio actual
B12: Precio de mercado | C12: =Supuestos!$C$8 | D12: =C12/Supuestos!$C$9-1 | E12: =C12/Supuestos!$C$8-1
B13: Precio de entrada del inversor | C13: =Supuestos!$C$9 | D13: =C13/Supuestos!$C$9-1 | E13: =C13/Supuestos!$C$8-1
B14: Precio objetivo Warrants & Co. (calculado) | C14: =ROUND(C30/5,0)*5 | D14: =C14/Supuestos!$C$9-1 | E14: =C14/Supuestos!$C$8-1 | F14: Media de los tres anclajes (fila 30), redondeada al múltiplo de 5 USD más próximo. Convención de la casa. Es el precio objetivo de Warrants & Co.
B15: Precio objetivo del inversor | C15: =Supuestos!$C$10 | D15: =C15/Supuestos!$C$9-1 | E15: =C15/Supuestos!$C$8-1 | F15: Objetivo aportado por el inversor, no calculado por este modelo. Requiere el escenario optimista.
B16: Consenso de analistas (51) | C16: 94.04 | D16: =C16/Supuestos!$C$9-1 | E16: =C16/Supuestos!$C$8-1 | G16: 51 analistas; mediana 93,00; rango 70,00-135,00 USD. Fuente: StockAnalysis.com, consultado el 14/09/2026.
B19: VALORACIÓN POR MÚLTIPLOS | C19: Base de cálculo | D19: Múltiplo actual | E19: Múltiplo objetivo | F19: Valor por acción | G19: Origen del múltiplo objetivo
B20: PER 2026E subyacente (ex comisión WBD) | C20: 3.01 | D20: =Supuestos!$C$8/C20 | E20: 29 | F20: =C20*E20 | G20: 29x: por debajo de la media de 5 años de la propia compañía (~40x) y de las 33x a las que cotiza Spotify con margen operativo muy inferior. | H20: BPA 2026E subyacente: consenso de 3,59 USD menos el efecto por acción de la comisión de WBD después de impuestos.
B21: PER 2027E | C21: 3.95 | D21: =Supuestos!$C$8/C21 | E21: 26 | F21: =C21*E21 | G21: 26x: compresión del múltiplo 2026 conforme avanza el margen; equivale a mantener el PEG en torno a 1. | H21: BPA 2027E: estimación propia derivada del caso base, no del consenso.
B22: P/FCF 2026E subyacente | C22: 9700 | D22: =Supuestos!$C$24/C22 | E22: 38 | F22: =C22*E22/Supuestos!$C$12 | G22: 38x: media aproximada de los últimos doce meses de la propia compañía sobre FCF subyacente. | H22: FCF 2026E subyacente: guía de 12.500 M USD menos los 2.800 M de la comisión de rescisión de WBD.
B23: EV/Ventas 2026E | C23: 51192 | D23: =Supuestos!$C$26/C23 | E23: 7.5 | F23: =(C23*E23-Supuestos!$C$25)/Supuestos!$C$12 | G23: 7,5x: entre las 6,67x actuales y el techo del rango histórico de NFLX; muy por encima de Spotify (4,94x) y Disney (2,29x) por margen. | H23: Ingresos 2026E: caso base (45.183 x 1,133), dentro de la guía de 51.000-51.400 M USD.
B24: Rango por múltiplos — mínimo | F24: =MIN(F20:F23)
B25: Rango por múltiplos — máximo | F25: =MAX(F20:F23)
B26: PRECIO OBJETIVO — media de los tres anclajes
B27: DCF base rodado a 24 meses | C27: =Base!$C$40
B28: Mediana de la valoración por múltiplos | C28: =MEDIAN(F20:F23)
B29: Consenso de analistas | C29: =C16
B30: Objetivo calculado (media) | C30: =AVERAGE(C27:C29)
B32: Aviso de alcance: documento de trabajo de carácter analítico. No constituye recomendación de inversión, asesoramiento financiero ni oferta de compra o venta de valores.

Sheet Pesimista
B2: Escenario pesimista — Proyección 2026E-2035E (M USD)
B5: WACC | C5: =Supuestos!$C$32 | D5: Crecimiento terminal (g) | E5: =Supuestos!$D$32 | F5: Peso en el valor razonable | G5: =Supuestos!$E$32
B7: Concepto | C7: 2026E | D7: 2027E | E7: 2028E | F7: 2029E | G7: 2030E | H7: 2031E | I7: 2032E | J7: 2033E | K7: 2034E | L7: 2035E
B8: Crecimiento de ingresos | C8: 0.133 | D8: 0.075 | E8: 0.055 | F8: 0.045 | G8: 0.038 | H8: 0.032 | I8: 0.028 | J8: 0.025 | K8: 0.022 | L8: 0.02
B9: Margen operativo | C9: 0.315 | D9: 0.322 | E9: 0.33 | F9: 0.336 | G9: 0.34 | H9: 0.344 | I9: 0.347 | J9: 0.35 | K9: 0.35 | L9: 0.35
B10: Tipo impositivo efectivo en caja | C10: 0.14 | D10: 0.15 | E10: 0.16 | F10: 0.17 | G10: 0.17 | H10: 0.18 | I10: 0.18 | J10: 0.18 | K10: 0.18 | L10: 0.18
B11: Amortizaciones no de contenido (% ingresos) | C11: 0.012 | D11: 0.012 | E11: 0.012 | F11: 0.012 | G11: 0.012 | H11: 0.012 | I11: 0.012 | J11: 0.012 | K11: 0.012 | L11: 0.012
B12: Capex (% ingresos) | C12: 0.016 | D12: 0.016 | E12: 0.016 | F12: 0.016 | G12: 0.016 | H12: 0.016 | I12: 0.016 | J12: 0.016 | K12: 0.016 | L12: 0.016
B13: Desfase contenido: gasto en caja − amortización (% ingresos) | C13: 0.066 | D13: 0.048 | E13: 0.038 | F13: 0.032 | G13: 0.03 | H13: 0.028 | I13: 0.027 | J13: 0.026 | K13: 0.026 | L13: 0.026
B14: Retribución en acciones (% ingresos) | C14: 0.023 | D14: 0.023 | E14: 0.023 | F14: 0.022 | G14: 0.022 | H14: 0.022 | I14: 0.021 | J14: 0.021 | K14: 0.021 | L14: 0.021
B16: CÁLCULO DEL FLUJO DE CAJA
B17: Ingresos | C17: =Supuestos!$C$15*(1+C8) | D17: =C17*(1+D8) | E17: =D17*(1+E8) | F17: =E17*(1+F8) | G17: =F17*(1+G8) | H17: =G17*(1+H8) | I17: =H17*(1+I8) | J17: =I17*(1+J8) | K17: =J17*(1+K8) | L17: =K17*(1+L8)
B18: Resultado operativo (EBIT) | C18: =C17*C9 | D18: =D17*D9 | E18: =E17*E9 | F18: =F17*F9 | G18: =G17*G9 | H18: =H17*H9 | I18: =I17*I9 | J18: =J17*J9 | ... L18: =L17*L9
B19: (-) Impuestos en caja | C19: =-C18*C10 | D19: =-D18*D10 | E19: =-E18*E10 | F19: =-F18*F10 | G19: =-G18*G10 | H19: =-H18*H10 | I19: =-I18*I10 | J19: =-J18*J10 | ... L19: =-L18*L10
B20: NOPAT | C20: =C18+C19 | D20: =D18+D19 | E20: =E18+E19 | F20: =F18+F19 | G20: =G18+G19 | H20: =H18+H19 | I20: =I18+I19 | J20: =J18+J19 | ... L20: =L18+L19
B21: (+) Amortizaciones no de contenido | C21: =C17*C11 | D21: =D17*D11 | E21: =E17*E11 | F21: =F17*F11 | G21: =G17*G11 | H21: =H17*H11 | I21: =I17*I11 | J21: =J17*J11 | ... L21: =L17*L11
B22: (-) Capex | C22: =-C17*C12 | D22: =-D17*D12 | E22: =-E17*E12 | F22: =-F17*F12 | G22: =-G17*G12 | H22: =-H17*H12 | I22: =-I17*I12 | J22: =-J17*J12 | ... L22: =-L17*L12
B23: (-) Inversión neta en contenido | C23: =-C17*C13 | D23: =-D17*D13 | E23: =-E17*E13 | F23: =-F17*F13 | G23: =-G17*G13 | H23: =-H17*H13 | I23: =-I17*I13 | J23: =-J17*J13 | ... L23: =-L17*L13
B24: (-) Retribución en acciones | C24: =-C17*C14 | D24: =-D17*D14 | E24: =-E17*E14 | F24: =-F17*F14 | G24: =-G17*G14 | H24: =-H17*H14 | I24: =-I17*I14 | J24: =-J17*J14 | ... L24: =-L17*L14
B25: (+/-) Fondo de maniobra | C25: =(C17-Supuestos!$C$15)*Supuestos!$C$20 | D25: =(D17-C17)*Supuestos!$C$20 | E25: =(E17-D17)*Supuestos!$C$20 | F25: =(F17-E17)*Supuestos!$C$20 | G25: =(G17-F17)*Supuestos!$C$20 | H25: =(H17-G17)*Supuestos!$C$20 | I25: =(I17-H17)*Supuestos!$C$20 | J25: =(J17-I17)*Supuestos!$C$20 | K25: =(K17-J17)*Supuestos!$C$20 | L25: =(L17-K17)*Supuestos!$C$20
B26: FLUJO DE CAJA LIBRE PARA LA FIRMA (FCFF) | C26: =C20+C21+C22+C23+C24+C25 | D26: =D20+D21+D22+D23+D24+D25 | E26: =E20+E21+E22+E23+E24+E25 | F26: =F20+F21+F22+F23+F24+F25 | G26: =G20+G21+G22+G23+G24+G25 | H26: =H20+H21+H22+H23+H24+H25 | I26: =I20+I21+I22+I23+I24+I25 | J26: =J20+J21+J22+J23+J24+J25 | ... L26: =L20+L21+L22+L23+L24+L25
B27: Factor de descuento | C27: =1/(1+$C$5)^1 | D27: =1/(1+$C$5)^2 | E27: =1/(1+$C$5)^3 | F27: =1/(1+$C$5)^4 | G27: =1/(1+$C$5)^5 | H27: =1/(1+$C$5)^6 | I27: =1/(1+$C$5)^7 | J27: =1/(1+$C$5)^8 | K27: =1/(1+$C$5)^9 | L27: =1/(1+$C$5)^10
B28: Valor actual del flujo | C28: =C26*C27 | D28: =D26*D27 | E28: =E26*E27 | F28: =F26*F27 | G28: =G26*G27 | H28: =H26*H27 | I28: =I26*I27 | J28: =J26*J27 | ... L28: =L26*L27
B30: Suma del valor actual de los flujos explícitos | C30: =SUM(C28:L28)
B31: Valor terminal (Gordon) | C31: =L26*(1+$E$5)/($C$5-$E$5)
B32: Valor actual del valor terminal | C32: =C31*L27
B33: VALOR DE EMPRESA (EV) | C33: =C30+C32
B34: Peso del valor terminal sobre el EV | C34: =C32/C33
B35: (-) Deuda neta | C35: =-Supuestos!$C$25
B36: VALOR DE LOS FONDOS PROPIOS | C36: =C33+C35
B37: VALOR POR ACCIÓN — HOY (USD) | C37: =C36/Supuestos!$C$12
B38: Recorrido sobre el precio actual | C38: =C37/Supuestos!$C$8-1
B39: EV rodado a cierre de 2027 | C39: =(C33*(1+$C$5)-C26)*(1+$C$5)-D26
B40: VALOR POR ACCIÓN — RODADO 24 MESES (USD) | C40: =(C39-Supuestos!$C$25)/Supuestos!$C$12 | D40: Sobre las mismas 4.200 M acciones. A 24 meses la recompra habrá retirado en torno a un 5-6% del capital, de modo que esta cifra está conservadoramente infravalorada en esa magnitud. No se ajusta para no introducir un supuesto de precio medio de recompra.
B41: Recorrido rodado sobre la entrada de 75,50 | C41: =C40/Supuestos!$C$9-1

Sheet Base
B2: Escenario base — Proyección 2026E-2035E (M USD)
B5: WACC | C5: =Supuestos!$C$33 | D5: Crecimiento terminal (g) | E5: =Supuestos!$D$33 | F5: Peso en el valor razonable | G5: =Supuestos!$E$33
B7: Concepto | C7: 2026E | D7: 2027E | E7: 2028E | F7: 2029E | G7: 2030E | H7: 2031E | I7: 2032E | J7: 2033E | K7: 2034E | L7: 2035E
B8: Crecimiento de ingresos | C8: 0.133 | D8: 0.115 | E8: 0.105 | F8: 0.095 | G8: 0.085 | H8: 0.075 | I8: 0.065 | J8: 0.055 | K8: 0.05 | L8: 0.045
B9: Margen operativo | C9: 0.315 | D9: 0.335 | E9: 0.355 | F9: 0.37 | G9: 0.385 | H9: 0.395 | I9: 0.4 | J9: 0.405 | K9: 0.41 | L9: 0.41
B10: Tipo impositivo efectivo en caja | C10: 0.14 | D10: 0.15 | E10: 0.16 | F10: 0.16 | G10: 0.17 | H10: 0.17 | I10: 0.17 | J10: 0.18 | K10: 0.18 | L10: 0.18
B11: Amortizaciones no de contenido (% ingresos) | C11: 0.012 | D11: 0.012 | E11: 0.012 | F11: 0.012 | G11: 0.012 | H11: 0.012 | I11: 0.012 | J11: 0.012 | K11: 0.012 | L11: 0.012
B12: Capex (% ingresos) | C12: 0.015 | D12: 0.015 | E12: 0.015 | F12: 0.015 | G12: 0.015 | H12: 0.015 | I12: 0.015 | J12: 0.015 | K12: 0.015 | L12: 0.015
B13: Desfase contenido: gasto en caja − amortización (% ingresos) | C13: 0.066 | D13: 0.05 | E13: 0.04 | F13: 0.032 | G13: 0.026 | H13: 0.022 | I13: 0.018 | J13: 0.015 | K13: 0.012 | L13: 0.01
B14: Retribución en acciones (% ingresos) | C14: 0.022 | D14: 0.021 | E14: 0.02 | F14: 0.019 | G14: 0.018 | H14: 0.017 | I14: 0.016 | J14: 0.015 | K14: 0.015 | L14: 0.015
B16: CÁLCULO DEL FLUJO DE CAJA
B17: Ingresos | C17: =Supuestos!$C$15*(1+C8) | D17: =C17*(1+D8) | E17: =D17*(1+E8) | F17: =E17*(1+F8) | G17: =F17*(1+G8) | H17: =G17*(1+H8) | I17: =H17*(1+I8) | J17: =I17*(1+J8) | K17: =J17*(1+K8) | L17: =K17*(1+L8)
B18: Resultado operativo (EBIT) | C18: =C17*C9 | D18: =D17*D9 | E18: =E17*E9 | F18: =F17*F9 | G18: =G17*G9 | H18: =H17*H9 | I18: =I17*I9 | J18: =J17*J9 | ... L18: =L17*L9
B19: (-) Impuestos en caja | C19: =-C18*C10 | D19: =-D18*D10 | E19: =-E18*E10 | F19: =-F18*F10 | G19: =-G18*G10 | H19: =-H18*H10 | I19: =-I18*I10 | J19: =-J18*J10 | ... L19: =-L18*L10
B20: NOPAT | C20: =C18+C19 | D20: =D18+D19 | E20: =E18+E19 | F20: =F18+F19 | G20: =G18+G19 | H20: =H18+H19 | I20: =I18+I19 | J20: =J18+J19 | ... L20: =L18+L19
B21: (+) Amortizaciones no de contenido | C21: =C17*C11 | D21: =D17*D11 | E21: =E17*E11 | F21: =F17*F11 | G21: =G17*G11 | H21: =H17*H11 | I21: =I17*I11 | J21: =J17*J11 | ... L21: =L17*L11
B22: (-) Capex | C22: =-C17*C12 | D22: =-D17*D12 | E22: =-E17*E12 | F22: =-F17*F12 | G22: =-G17*G12 | H22: =-H17*H12 | I22: =-I17*I12 | J22: =-J17*J12 | ... L22: =-L17*L12
B23: (-) Inversión neta en contenido | C23: =-C17*C13 | D23: =-D17*D13 | E23: =-E17*E13 | F23: =-F17*F13 | G23: =-G17*G13 | H23: =-H17*H13 | I23: =-I17*I13 | J23: =-J17*J13 | ... L23: =-L17*L13
B24: (-) Retribución en acciones | C24: =-C17*C14 | D24: =-D17*D14 | E24: =-E17*E14 | F24: =-F17*F14 | G24: =-G17*G14 | H24: =-H17*H14 | I24: =-I17*I14 | J24: =-J17*J14 | ... L24: =-L17*L14
B25: (+/-) Fondo de maniobra | C25: =(C17-Supuestos!$C$15)*Supuestos!$C$20 | D25: =(D17-C17)*Supuestos!$C$20 | E25: =(E17-D17)*Supuestos!$C$20 | F25: =(F17-E17)*Supuestos!$C$20 | G25: =(G17-F17)*Supuestos!$C$20 | H25: =(H17-G17)*Supuestos!$C$20 | I25: =(I17-H17)*Supuestos!$C$20 | J25: =(J17-I17)*Supuestos!$C$20 | K25: =(K17-J17)*Supuestos!$C$20 | L25: =(L17-K17)*Supuestos!$C$20
B26: FLUJO DE CAJA LIBRE PARA LA FIRMA (FCFF) | C26: =C20+C21+C22+C23+C24+C25 | D26: =D20+D21+D22+D23+D24+D25 | E26: =E20+E21+E22+E23+E24+E25 | F26: =F20+F21+F22+F23+F24+F25 | G26: =G20+G21+G22+G23+G24+G25 | H26: =H20+H21+H22+H23+H24+H25 | I26: =I20+I21+I22+I23+I24+I25 | J26: =J20+J21+J22+J23+J24+J25 | ... L26: =L20+L21+L22+L23+L24+L25
B27: Factor de descuento | C27: =1/(1+$C$5)^1 | D27: =1/(1+$C$5)^2 | E27: =1/(1+$C$5)^3 | F27: =1/(1+$C$5)^4 | G27: =1/(1+$C$5)^5 | H27: =1/(1+$C$5)^6 | I27: =1/(1+$C$5)^7 | J27: =1/(1+$C$5)^8 | K27: =1/(1+$C$5)^9 | L27: =1/(1+$C$5)^10
B28: Valor actual del flujo | C28: =C26*C27 | D28: =D26*D27 | E28: =E26*E27 | F28: =F26*F27 | G28: =G26*G27 | H28: =H26*H27 | I28: =I26*I27 | J28: =J26*J27 | ... L28: =L26*L27
B30: Suma del valor actual de los flujos explícitos | C30: =SUM(C28:L28)
B31: Valor terminal (Gordon) | C31: =L26*(1+$E$5)/($C$5-$E$5)
B32: Valor actual del valor terminal | C32: =C31*L27
B33: VALOR DE EMPRESA (EV) | C33: =C30+C32
B34: Peso del valor terminal sobre el EV | C34: =C32/C33
B35: (-) Deuda neta | C35: =-Supuestos!$C$25
B36: VALOR DE LOS FONDOS PROPIOS | C36: =C33+C35
B37: VALOR POR ACCIÓN — HOY (USD) | C37: =C36/Supuestos!$C$12
B38: Recorrido sobre el precio actual | C38: =C37/Supuestos!$C$8-1
B39: EV rodado a cierre de 2027 | C39: =(C33*(1+$C$5)-C26)*(1+$C$5)-D26
B40: VALOR POR ACCIÓN — RODADO 24 MESES (USD) | C40: =(C39-Supuestos!$C$25)/Supuestos!$C$12 | D40: Sobre las mismas 4.200 M acciones. A 24 meses la recompra habrá retirado en torno a un 5-6% del capital, de modo que esta cifra está conservadoramente infravalorada en esa magnitud. No se ajusta para no introducir un supuesto de precio medio de recompra.
B41: Recorrido rodado sobre la entrada de 75,50 | C41: =C40/Supuestos!$C$9-1

Sheet Optimista
B2: Escenario optimista — Proyección 2026E-2035E (M USD)
B5: WACC | C5: =Supuestos!$C$34 | D5: Crecimiento terminal (g) | E5: =Supuestos!$D$34 | F5: Peso en el valor razonable | G5: =Supuestos!$E$34
B7: Concepto | C7: 2026E | D7: 2027E | E7: 2028E | F7: 2029E | G7: 2030E | H7: 2031E | I7: 2032E | J7: 2033E | K7: 2034E | L7: 2035E
B8: Crecimiento de ingresos | C8: 0.135 | D8: 0.135 | E8: 0.128 | F8: 0.118 | G8: 0.108 | H8: 0.098 | I8: 0.088 | J8: 0.078 | K8: 0.068 | L8: 0.06
B9: Margen operativo | C9: 0.318 | D9: 0.345 | E9: 0.37 | F9: 0.39 | G9: 0.405 | H9: 0.418 | I9: 0.428 | J9: 0.435 | K9: 0.44 | L9: 0.443
B10: Tipo impositivo efectivo en caja | C10: 0.14 | D10: 0.14 | E10: 0.15 | F10: 0.16 | G10: 0.16 | H10: 0.16 | I10: 0.17 | J10: 0.17 | K10: 0.17 | L10: 0.17
B11: Amortizaciones no de contenido (% ingresos) | C11: 0.012 | D11: 0.012 | E11: 0.012 | F11: 0.012 | G11: 0.012 | H11: 0.012 | I11: 0.012 | J11: 0.012 | K11: 0.012 | L11: 0.012
B12: Capex (% ingresos) | C12: 0.014 | D12: 0.014 | E12: 0.014 | F12: 0.014 | G12: 0.014 | H12: 0.014 | I12: 0.014 | J12: 0.014 | K12: 0.014 | L12: 0.014
B13: Desfase contenido: gasto en caja − amortización (% ingresos) | C13: 0.064 | D13: 0.044 | E13: 0.032 | F13: 0.022 | G13: 0.016 | H13: 0.012 | I13: 0.01 | J13: 0.008 | K13: 0.006 | L13: 0.005
B14: Retribución en acciones (% ingresos) | C14: 0.021 | D14: 0.02 | E14: 0.018 | F14: 0.017 | G14: 0.016 | H14: 0.015 | I14: 0.014 | J14: 0.013 | K14: 0.013 | L14: 0.013
B16: CÁLCULO DEL FLUJO DE CAJA
B17: Ingresos | C17: =Supuestos!$C$15*(1+C8) | D17: =C17*(1+D8) | E17: =D17*(1+E8) | F17: =E17*(1+F8) | G17: =F17*(1+G8) | H17: =G17*(1+H8) | I17: =H17*(1+I8) | J17: =I17*(1+J8) | K17: =J17*(1+K8) | L17: =K17*(1+L8)
B18: Resultado operativo (EBIT) | C18: =C17*C9 | D18: =D17*D9 | E18: =E17*E9 | F18: =F17*F9 | G18: =G17*G9 | H18: =H17*H9 | I18: =I17*I9 | J18: =J17*J9 | ... L18: =L17*L9
B19: (-) Impuestos en caja | C19: =-C18*C10 | D19: =-D18*D10 | E19: =-E18*E10 | F19: =-F18*F10 | G19: =-G18*G10 | H19: =-H18*H10 | I19: =-I18*I10 | J19: =-J18*J10 | ... L19: =-L18*L10
B20: NOPAT | C20: =C18+C19 | D20: =D18+D19 | E20: =E18+E19 | F20: =F18+F19 | G20: =G18+G19 | H20: =H18+H19 | I20: =I18+I19 | J20: =J18+J19 | ... L20: =L18+L19
B21: (+) Amortizaciones no de contenido | C21: =C17*C11 | D21: =D17*D11 | E21: =E17*E11 | F21: =F17*F11 | G21: =G17*G11 | H21: =H17*H11 | I21: =I17*I11 | J21: =J17*J11 | ... L21: =L17*L11
B22: (-) Capex | C22: =-C17*C12 | D22: =-D17*D12 | E22: =-E17*E12 | F22: =-F17*F12 | G22: =-G17*G12 | H22: =-H17*H12 | I22: =-I17*I12 | J22: =-J17*J12 | ... L22: =-L17*L12
B23: (-) Inversión neta en contenido | C23: =-C17*C13 | D23: =-D17*D13 | E23: =-E17*E13 | F23: =-F17*F13 | G23: =-G17*G13 | H23: =-H17*H13 | I23: =-I17*I13 | J23: =-J17*J13 | ... L23: =-L17*L13
B24: (-) Retribución en acciones | C24: =-C17*C14 | D24: =-D17*D14 | E24: =-E17*E14 | F24: =-F17*F14 | G24: =-G17*G14 | H24: =-H17*H14 | I24: =-I17*I14 | J24: =-J17*J14 | ... L24: =-L17*L14
B25: (+/-) Fondo de maniobra | C25: =(C17-Supuestos!$C$15)*Supuestos!$C$20 | D25: =(D17-C17)*Supuestos!$C$20 | E25: =(E17-D17)*Supuestos!$C$20 | F25: =(F17-E17)*Supuestos!$C$20 | G25: =(G17-F17)*Supuestos!$C$20 | H25: =(H17-G17)*Supuestos!$C$20 | I25: =(I17-H17)*Supuestos!$C$20 | J25: =(J17-I17)*Supuestos!$C$20 | K25: =(K17-J17)*Supuestos!$C$20 | L25: =(L17-K17)*Supuestos!$C$20
B26: FLUJO DE CAJA LIBRE PARA LA FIRMA (FCFF) | C26: =C20+C21+C22+C23+C24+C25 | D26: =D20+D21+D22+D23+D24+D25 | E26: =E20+E21+E22+E23+E24+E25 | F26: =F20+F21+F22+F23+F24+F25 | G26: =G20+G21+G22+G23+G24+G25 | H26: =H20+H21+H22+H23+H24+H25 | I26: =I20+I21+I22+I23+I24+I25 | J26: =J20+J21+J22+J23+J24+J25 | ... L26: =L20+L21+L22+L23+L24+L25
B27: Factor de descuento | C27: =1/(1+$C$5)^1 | D27: =1/(1+$C$5)^2 | E27: =1/(1+$C$5)^3 | F27: =1/(1+$C$5)^4 | G27: =1/(1+$C$5)^5 | H27: =1/(1+$C$5)^6 | I27: =1/(1+$C$5)^7 | J27: =1/(1+$C$5)^8 | K27: =1/(1+$C$5)^9 | L27: =1/(1+$C$5)^10
B28: Valor actual del flujo | C28: =C26*C27 | D28: =D26*D27 | E28: =E26*E27 | F28: =F26*F27 | G28: =G26*G27 | H28: =H26*H27 | I28: =I26*I27 | J28: =J26*J27 | ... L28: =L26*L27
B30: Suma del valor actual de los flujos explícitos | C30: =SUM(C28:L28)
B31: Valor terminal (Gordon) | C31: =L26*(1+$E$5)/($C$5-$E$5)
B32: Valor actual del valor terminal | C32: =C31*L27
B33: VALOR DE EMPRESA (EV) | C33: =C30+C32
B34: Peso del valor terminal sobre el EV | C34: =C32/C33
B35: (-) Deuda neta | C35: =-Supuestos!$C$25
B36: VALOR DE LOS FONDOS PROPIOS | C36: =C33+C35
B37: VALOR POR ACCIÓN — HOY (USD) | C37: =C36/Supuestos!$C$12
B38: Recorrido sobre el precio actual | C38: =C37/Supuestos!$C$8-1
B39: EV rodado a cierre de 2027 | C39: =(C33*(1+$C$5)-C26)*(1+$C$5)-D26
B40: VALOR POR ACCIÓN — RODADO 24 MESES (USD) | C40: =(C39-Supuestos!$C$25)/Supuestos!$C$12 | D40: Sobre las mismas 4.200 M acciones. A 24 meses la recompra habrá retirado en torno a un 5-6% del capital, de modo que esta cifra está conservadoramente infravalorada en esa magnitud. No se ajusta para no introducir un supuesto de precio medio de recompra.
B41: Recorrido rodado sobre la entrada de 75,50 | C41: =C40/Supuestos!$C$9-1

Sheet Sensibilidad
B2: Sensibilidad del caso base — WACC frente a crecimiento terminal (calculada, no introducida)
B5: WACC \ g | C5: 0.02 | D5: 0.025 | E5: 0.03 | F5: 0.035 | G5: 0.04
B6: 0.09 | C6: =(SUMPRODUCT(Base!$C$26:$L$26/(1+$B6)^(COLUMN(Base!$C$26:$L$26)-2))+Base!$L$26*(1+C$5)/($B6-C$5)/(1+$B6)^10-Supuestos!$C$25)/Supuestos!$C$12 | D6: =(SUMPRODUCT(Base!$C$26:$L$26/(1+$B6)^(COLUMN(Base!$C$26:$L$26)-2))+Base!$L$26*(1+D$5)/($B6-D$5)/(1+$B6)^10-Supuestos!$C$25)/Supuestos!$C$12 | E6: =(SUMPRODUCT(Base!$C$26:$L$26/(1+$B6)^(COLUMN(Base!$C$26:$L$26)-2))+Base!$L$26*(1+E$5)/($B6-E$5)/(1+$B6)^10-Supuestos!$C$25)/Supuestos!$C$12 | F6: =(SUMPRODUCT(Base!$C$26:$L$26/(1+$B6)^(COLUMN(Base!$C$26:$L$26)-2))+Base!$L$26*(1+F$5)/($B6-F$5)/(1+$B6)^10-Supuestos!$C$25)/Supuestos!$C$12 | G6: =(SUMPRODUCT(Base!$C$26:$L$26/(1+$B6)^(COLUMN(Base!$C$26:$L$26)-2))+Base!$L$26*(1+G$5)/($B6-G$5)/(1+$B6)^10-Supuestos!$C$25)/Supuestos!$C$12
B7: 0.095 | C7: =(SUMPRODUCT(Base!$C$26:$L$26/(1+$B7)^(COLUMN(Base!$C$26:$L$26)-2))+Base!$L$26*(1+C$5)/($B7-C$5)/(1+$B7)^10-Supuestos!$C$25)/Supuestos!$C$12 | D7: =(SUMPRODUCT(Base!$C$26:$L$26/(1+$B7)^(COLUMN(Base!$C$26:$L$26)-2))+Base!$L$26*(1+D$5)/($B7-D$5)/(1+$B7)^10-Supuestos!$C$25)/Supuestos!$C$12 | E7: =(SUMPRODUCT(Base!$C$26:$L$26/(1+$B7)^(COLUMN(Base!$C$26:$L$26)-2))+Base!$L$26*(1+E$5)/($B7-E$5)/(1+$B7)^10-Supuestos!$C$25)/Supuestos!$C$12 | F7: =(SUMPRODUCT(Base!$C$26:$L$26/(1+$B7)^(COLUMN(Base!$C$26:$L$26)-2))+Base!$L$26*(1+F$5)/($B7-F$5)/(1+$B7)^10-Supuestos!$C$25)/Supuestos!$C$12 | G7: =(SUMPRODUCT(Base!$C$26:$L$26/(1+$B7)^(COLUMN(Base!$C$26:$L$26)-2))+Base!$L$26*(1+G$5)/($B7-G$5)/(1+$B7)^10-Supuestos!$C$25)/Supuestos!$C$12
B8: 0.1 | C8: =(SUMPRODUCT(Base!$C$26:$L$26/(1+$B8)^(COLUMN(Base!$C$26:$L$26)-2))+Base!$L$26*(1+C$5)/($B8-C$5)/(1+$B8)^10-Supuestos!$C$25)/Supuestos!$C$12 | D8: =(SUMPRODUCT(Base!$C$26:$L$26/(1+$B8)^(COLUMN(Base!$C$26:$L$26)-2))+Base!$L$26*(1+D$5)/($B8-D$5)/(1+$B8)^10-Supuestos!$C$25)/Supuestos!$C$12 | E8: =(SUMPRODUCT(Base!$C$26:$L$26/(1+$B8)^(COLUMN(Base!$C$26:$L$26)-2))+Base!$L$26*(1+E$5)/($B8-E$5)/(1+$B8)^10-Supuestos!$C$25)/Supuestos!$C$12 | F8: =(SUMPRODUCT(Base!$C$26:$L$26/(1+$B8)^(COLUMN(Base!$C$26:$L$26)-2))+Base!$L$26*(1+F$5)/($B8-F$5)/(1+$B8)^10-Supuestos!$C$25)/Supuestos!$C$12 | G8: =(SUMPRODUCT(Base!$C$26:$L$26/(1+$B8)^(COLUMN(Base!$C$26:$L$26)-2))+Base!$L$26*(1+G$5)/($B8-G$5)/(1+$B8)^10-Supuestos!$C$25)/Supuestos!$C$12
B9: 0.105 | C9: =(SUMPRODUCT(Base!$C$26:$L$26/(1+$B9)^(COLUMN(Base!$C$26:$L$26)-2))+Base!$L$26*(1+C$5)/($B9-C$5)/(1+$B9)^10-Supuestos!$C$25)/Supuestos!$C$12 | D9: =(SUMPRODUCT(Base!$C$26:$L$26/(1+$B9)^(COLUMN(Base!$C$26:$L$26)-2))+Base!$L$26*(1+D$5)/($B9-D$5)/(1+$B9)^10-Supuestos!$C$25)/Supuestos!$C$12 | E9: =(SUMPRODUCT(Base!$C$26:$L$26/(1+$B9)^(COLUMN(Base!$C$26:$L$26)-2))+Base!$L$26*(1+E$5)/($B9-E$5)/(1+$B9)^10-Supuestos!$C$25)/Supuestos!$C$12 | F9: =(SUMPRODUCT(Base!$C$26:$L$26/(1+$B9)^(COLUMN(Base!$C$26:$L$26)-2))+Base!$L$26*(1+F$5)/($B9-F$5)/(1+$B9)^10-Supuestos!$C$25)/Supuestos!$C$12 | G9: =(SUMPRODUCT(Base!$C$26:$L$26/(1+$B9)^(COLUMN(Base!$C$26:$L$26)-2))+Base!$L$26*(1+G$5)/($B9-G$5)/(1+$B9)^10-Supuestos!$C$25)/Supuestos!$C$12
B10: 0.11 | C10: =(SUMPRODUCT(Base!$C$26:$L$26/(1+$B10)^(COLUMN(Base!$C$26:$L$26)-2))+Base!$L$26*(1+C$5)/($B10-C$5)/(1+$B10)^10-Supuestos!$C$25)/Supuestos!$C$12 | D10: =(SUMPRODUCT(Base!$C$26:$L$26/(1+$B10)^(COLUMN(Base!$C$26:$L$26)-2))+Base!$L$26*(1+D$5)/($B10-D$5)/(1+$B10)^10-Supuestos!$C$25)/Supuestos!$C$12 | E10: =(SUMPRODUCT(Base!$C$26:$L$26/(1+$B10)^(COLUMN(Base!$C$26:$L$26)-2))+Base!$L$26*(1+E$5)/($B10-E$5)/(1+$B10)^10-Supuestos!$C$25)/Supuestos!$C$12 | F10: =(SUMPRODUCT(Base!$C$26:$L$26/(1+$B10)^(COLUMN(Base!$C$26:$L$26)-2))+Base!$L$26*(1+F$5)/($B10-F$5)/(1+$B10)^10-Supuestos!$C$25)/Supuestos!$C$12 | G10: =(SUMPRODUCT(Base!$C$26:$L$26/(1+$B10)^(COLUMN(Base!$C$26:$L$26)-2))+Base!$L$26*(1+G$5)/($B10-G$5)/(1+$B10)^10-Supuestos!$C$25)/Supuestos!$C$12
B12: Precio de mercado | C12: =Supuestos!$C$8
B13: Precio de entrada del inversor | C13: =Supuestos!$C$9
B14: Valor mínimo de la matriz | C14: =MIN(C6:G10)
B15: Valor máximo de la matriz | C15: =MAX(C6:G10)
B16: Celdas de la matriz por encima de la entrada | C16: =COUNTIF(C6:G10,">"&Supuestos!$C$9)&" de 25"
B18: Cada celda descuenta la serie de FCFF del caso base con el WACC de su fila y capitaliza el flujo de 2035 al crecimiento terminal de su columna. Depende del caso base: si se cambian sus supuestos operativos, la matriz se mueve con ellos.
B19: Comprobación: la celda WACC 9,50% / g 3,25% debe coincidir con Base!C37.
B20: Caso base (Base!C37) | C20: =Base!$C$37

Sheet Reverse DCF
B2: Reverse DCF — Crecimiento implícito en cada nivel de precio
B5: Parámetro | C5: Valor
B6: Crecimiento constante de FCFF (entrada) | C6: 0.1594 | D6: Crecimiento constante que iguala el valor por acción al cierre del 14/09/2026 (80,32 USD). Recalibrado al actualizar el precio.
B7: FCFF de partida 2026E (M USD) | C7: =Base!C26
B8: WACC | C8: =Base!$C$5
B9: Crecimiento terminal | C9: =Base!$E$5
B12: Año | C12: 2026E | D12: 2027E | E12: 2028E | F12: 2029E | G12: 2030E | H12: 2031E | I12: 2032E | J12: 2033E | K12: 2034E | L12: 2035E
B13: FCFF proyectado | C13: =$C$7 | D13: =C13*(1+$C$6) | E13: =D13*(1+$C$6) | F13: =E13*(1+$C$6) | G13: =F13*(1+$C$6) | H13: =G13*(1+$C$6) | I13: =H13*(1+$C$6) | J13: =I13*(1+$C$6) | K13: =J13*(1+$C$6) | L13: =K13*(1+$C$6)
B14: Valor actual | C14: =C13/(1+$C$8)^1 | D14: =D13/(1+$C$8)^2 | E14: =E13/(1+$C$8)^3 | F14: =F13/(1+$C$8)^4 | G14: =G13/(1+$C$8)^5 | H14: =H13/(1+$C$8)^6 | I14: =I13/(1+$C$8)^7 | J14: =J13/(1+$C$8)^8 | K14: =K13/(1+$C$8)^9 | L14: =L13/(1+$C$8)^10
B16: Suma del valor actual de los flujos | C16: =SUM(C14:L14)
B17: Valor terminal | C17: =L13*(1+$C$9)/($C$8-$C$9)
B18: Valor actual del valor terminal | C18: =C17/(1+$C$8)^10
B19: Valor de empresa implícito | C19: =C16+C18
B20: Valor de los fondos propios | C20: =C19-Supuestos!$C$25
B21: Valor por acción implícito | C21: =C20/Supuestos!$C$12
B22: Precio de mercado | C22: =Supuestos!$C$8
B23: Diferencia | C23: =C21-C22
B25: El crecimiento implícito es constante durante diez años; el caso base usa una senda decreciente. Para compararlos hay que usar el CAGR del FCFF del caso base (14,21%), no sus tasas anuales.
