Workbook

Sheet 00 Panel del Analista
A1: PANEL DEL ANALISTA — TODOS LOS INPUTS DEL MODELO EN UN SOLO SITIO
A2: Rellena las celdas AZULES sobre fondo blanco y las AMARILLAS (hipótesis críticas). El resto del libro se recalcula solo. Para valorar OTRA compañía: sustituye la identificación, los tres estados históricos y los drivers; no hace falta tocar ninguna otra hoja.
A3: Las filas marcadas «calculado» no se rellenan: son totales que el libro deriva. Al terminar, comprueba el semáforo del final de esta hoja y la hoja '13 Checks'.
B5: Input | C5: Unidad | D5: Hist. −2 | E5: Hist. −1 | F5: Hist. base | G5: Año 1 | H5: Año 2 | I5: Año 3 | J5: Año 4 | K5: Año 5 | L5: Año 6 | M5: Año 7 | N5: Año 8 | O5: Año 9 | P5: Año 10
B7: 1. IDENTIFICACIÓN Y MERCADO
B8: Compañía | C8: Oracle Corporation
B9: Ticker y mercado | C9: ORCL — NYSE
B10: Moneda y unidades | C10: USD millones
B11: Fecha de valoración | C11: 22/09/2026
B12: Último ejercicio auditado | C12: FY2026A (cerrado 31/05/2026)
B13: PRECIO DE MERCADO ACTUAL (el único dato que el libro no puede deducir) | C13: 0
B14: Etiquetas de los ejercicios (se propagan a las cabeceras de todas las hojas) | C14: texto | D14: FY2024A | E14: FY2025A | F14: FY2026A | G14: FY2027E | H14: FY2028E | I14: FY2029E | J14: FY2030E | K14: FY2031E | L14: FY2032E | M14: FY2033E | N14: FY2034E | O14: FY2035E | P14: FY2036E
B16: 2. CUENTA DE RESULTADOS HISTÓRICA
B18: Cloud | C18: $M | D18: 19774 | E18: 24506 | F18: 33989
B19: Software (licencias y soporte) | C19: $M | D19: 24690 | E19: 24724 | F19: 24541
B20: Hardware | C20: $M | D20: 3066 | E20: 2936 | F20: 3084
B21: Servicios | C21: $M | D21: 5431 | E21: 5233 | F21: 5743
B22: Ingresos totales | C22: $M | D22: calculado
B24: Coste de cloud y software | C24: $M | D24: 9427 | E24: 11569 | F24: 17597
B25: Coste de hardware | C25: $M | D25: 891 | E25: 782 | F25: 868
B26: Coste de servicios | C26: $M | D26: 4825 | E26: 4576 | F26: 4556
B27: Coste total de los ingresos | C27: $M | D27: calculado
B28: Margen bruto (Gross Profit) | C28: $M | D28: calculado
B29: Gross Margin | C29: % | D29: calculado
B31: Ventas y marketing | C31: $M | D31: 8274 | E31: 8651 | F31: 8331
B32: Investigación y desarrollo | C32: $M | D32: 8915 | E32: 9860 | F32: 10272
B33: Generales y administración | C33: $M | D33: 1548 | E33: 1602 | F33: 1618
B34: Amortización de intangibles | C34: $M | D34: 3010 | E34: 2307 | F34: 1671
B35: Reestructuración y otros | C35: $M | D35: 718 | E35: 374 | F35: 1838
B36: Gastos operativos totales | C36: $M | D36: calculado
B37: EBIT (resultado operativo) reportado | C37: $M | D37: calculado
B38: EBIT Margin reportado | C38: % | D38: calculado
B40: Gasto por intereses | C40: $M | D40: 3514 | E40: 3578 | F40: 4599
B41: Resultado no operativo, neto | C41: $M | D41: -98 | E41: 60 | F41: 3547
B42: Beneficio antes de impuestos | C42: $M | D42: calculado
B43: Impuesto sobre sociedades | C43: $M | D43: 1274 | E43: 1717 | F43: 2467
B44: Tipo impositivo efectivo | C44: % | D44: calculado
B45: Beneficio neto | C45: $M | D45: calculado
B46: Dividendos de acciones preferentes | C46: $M | D46: 0 | E46: 0 | F46: 103
B47: Beneficio neto atribuible a ordinarias | C47: $M | D47: calculado
B48: BPA básico | C48: $/acc | D48: 3.82 | E48: 4.46 | F48: 5.94
B49: BPA diluido | C49: $/acc | D49: 3.71 | E49: 4.34 | F49: 5.83
B50: Acciones medias básicas | C50: M acc | D50: 2744 | E50: 2789 | F50: 2860
B51: Acciones medias diluidas | C51: M acc | D51: 2823 | E51: 2866 | F51: 2914
B52: 3. BALANCE HISTÓRICO (a cierre de ejercicio)
B54: Caja y equivalentes | C54: $M | E54: 10786 | F54: 31289
B55: Valores negociables | C55: $M | E55: 417 | F55: 605
B56: Clientes, neto | C56: $M | E56: 8558 | F56: 10385
B57: Gastos anticipados y otros activos corrientes | C57: $M | E57: 4818 | F57: 4288
B58: Total activo corriente | C58: $M | D58: calculado
B59: Inmovilizado material (PP&E), neto | C59: $M | E59: 43522 | F59: 99957
B60: Activos por derecho de uso — leases operativos | C60: $M | E60: 13145 | F60: 29690
B61: Fondo de comercio | C61: $M | E61: 62207 | F61: 62261
B62: Activos por impuesto diferido | C62: $M | E62: 11877 | F62: 11541
B63: Otros activos no corrientes | C63: $M | E63: 13031 | F63: 11743
B64: Total activo no corriente | C64: $M | D64: calculado
B65: TOTAL ACTIVO | C65: $M | D65: calculado
B67: Deuda financiera corriente | C67: $M | E67: 7271 | F67: 7199
B68: Proveedores | C68: $M | E68: 5113 | F68: 10977
B69: Remuneraciones y cargas pendientes | C69: $M | E69: 2243 | F69: 2225
B70: Ingresos diferidos corrientes | C70: $M | E70: 9387 | F70: 9916
B71: Otros pasivos corrientes | C71: $M | E71: 8629 | F71: 11447
B72: Total pasivo corriente | C72: $M | D72: calculado
B73: Deuda financiera no corriente | C73: $M | E73: 85297 | F73: 122342
B74: Impuestos a pagar no corrientes | C74: $M | E74: 10269 | F74: 11771
B75: Pasivo por leases operativos no corriente | C75: $M | E75: 11536 | F75: 26648
B76: Otros pasivos no corrientes | C76: $M | E76: 7647 | F76: 16178
B77: Total pasivo no corriente | C77: $M | D77: calculado
B78: Acciones preferentes convertibles obligatorias (Serie D 6,50%) | C78: $M | E78: 0 | F78: 4954
B79: Capital social y prima de emisión | C79: $M | E79: 37107 | F79: 43243
B80: Resultados acumulados (déficit) | C80: $M | E80: -15481 | F80: -4309
B81: Otro resultado global acumulado | C81: $M | E81: -1175 | F81: -1380
B82: Patrimonio atribuible a Oracle | C82: $M | D82: calculado
B83: Intereses minoritarios | C83: $M | E83: 518 | F83: 548
B88: 4. ESTADO DE FLUJOS DE CAJA HISTÓRICO
B90: Depreciación | C90: $M | D90: 3129 | E90: 3867 | F90: 7623
B91: Amortización de intangibles | C91: $M | D91: calculado
B92: Impuestos diferidos | C92: $M | D92: -2139 | E92: -1637 | F92: -917
B93: Retribución basada en acciones (SBC) | C93: $M | D93: 3974 | E93: 4674 | F93: 4811
B94: Resultados de inversiones y otros, neto | C94: $M | D94: -720 | E94: -667 | F94: 2433
B95: Variación de circulante y otras partidas operativas (derivado) | C95: $M | D95: calculado
B96: FLUJO DE CAJA OPERATIVO (CFO) — reportado | C96: $M | D96: 18673 | E96: 20821 | F96: 31977
B98: Capex (adquisición de inmovilizado) | C98: $M | D98: -6866 | E98: -21215 | F98: -55663
B99: Compras de inversiones y adquisiciones | C99: $M | D99: -1066 | E99: -1272 | F99: -2039
B100: Cobros por ventas y vencimientos de inversiones | C100: $M | D100: 572 | E100: 776 | F100: 5848
B101: Otros de inversión (derivado) | C101: $M | D101: calculado
B102: FLUJO DE CAJA DE INVERSIÓN (CFI) — reportado | C102: $M | D102: -7360 | E102: -21711 | F102: -51854
B104: Emisión de acciones ordinarias | C104: $M | D104: 742 | E104: 653 | F104: 1449
B105: Recompra de acciones ordinarias | C105: $M | D105: -1202 | E105: -600 | F105: -95
B106: Acciones retenidas por impuestos en el vesting | C106: $M | D106: -2040 | E106: -900 | F106: -111
B107: Emisión de preferentes convertibles obligatorias | C107: $M | D107: 0 | E107: 0 | F107: 4954
B108: Dividendos pagados | C108: $M | D108: -4391 | E108: -4743 | F108: -5787
B109: Papel comercial, neto | C109: $M | D109: -167 | E109: 1889 | F109: -2285
B110: Financiación a corto plazo ligada a capex, neto | C110: $M | D110: 0 | E110: 1422 | F110: 3345
B111: Emisión de deuda a largo plazo y préstamos | C111: $M | D111: 0 | E111: 19548 | F111: 46093
B112: Repago de deuda | C112: $M | D112: -3500 | E112: -15841 | F112: -6942
B113: Otros de financiación, neto | C113: $M | D113: 4 | E113: -330 | F113: -337
B114: FLUJO DE CAJA DE FINANCIACIÓN (CFF) — calculado | C114: $M | D114: calculado
B115: CFF reportado en el 10-K | C115: $M | E115: 1098 | F115: 40284
B119: 5. MEMORIA: DEUDA, ARRENDAMIENTOS Y BACKLOG
...

Sheet 01 Summary
A1: ORACLE CORPORATION (ORCL) — RESUMEN DE VALORACIÓN DCF
A2: Valoración condicional: el resultado depende íntegramente de las hipótesis explícitas de '02 Assumptions'. No es una predicción.
B3: ⚠ PULSA Ctrl+Alt+F9 AL ABRIR ESTE LIBRO. Estas zonas se escribieron con el motor de cálculo del complemento bloqueado y mostrarán CEROS hasta que se fuerce un recálculo completo: (1) hojas 09a/09b/09c de escenarios; (2) las 25 celdas de las rejillas de '08 Sensibilidad' D6:H46; (3) en esta hoja, la tabla de escenarios F16:H24, el bloque de Múltiplos y el bloque de Precio objetivo; (4) en '13 Checks', los contadores D5:D7 y los controles 70-78. Las fórmulas están escritas y verificadas sintácticamente; lo que falta es que Excel las evalúe. TRAS EL RECÁLCULO comprueba el control 73 de '13 Checks': si está en OK, la réplica del escenario Base coincide con el DCF y los tres escenarios son fiables.
B4: IDENTIFICACIÓN | E4: CÓMO USAR ESTE LIBRO
B5: Compañía | C5: ='00 Panel del Analista'!C8 -> 0 | E5: 1 | F5: Introducir el precio de mercado actual en C10. Es el ÚNICO dato que el libro no puede obtener por sí mismo. Hasta entonces el upside, el margen de seguridad y el Reverse DCF quedan en blanco por diseño.
B6: Ticker / mercado | C6: ='00 Panel del Analista'!C9 -> 0 | E6: 2 | F6: Actualizar y documentar los inputs de mercado del WACC en '07 WACC': tipo libre de riesgo, prima de riesgo, beta y coste marginal de la deuda. Los valores actuales son inputs del analista, NO datos verificados.
B7: Moneda y unidades | C7: ='00 Panel del Analista'!C10 -> 0 | E7: 3 | F7: Revisar las hipótesis en '02 Assumptions'. Las celdas amarillas son las que mueven el valor. Ninguna otra hoja contiene hipótesis.
B8: Fecha de valoración | C8: ='00 Panel del Analista'!C11 -> 0 | E8: 4 | F8: Cambiar el escenario en '09 Scenarios'!C4 (1=Bear, 2=Base, 3=Bull) y anotar los tres valores para construir el rango.
B9: Último ejercicio auditado | C9: ='00 Panel del Analista'!C12 -> 0 | E9: 5 | F9: Leer '08 Sensitivity' para ver qué variables explican el valor, y '10 Reverse DCF' para ver qué descuenta el precio.
B10: PRECIO DE MERCADO ACTUAL — INTRODUCIR AQUÍ | C10: ='00 Panel del Analista'!C13 -> 0 | E10: 6 | F10: Ejecutar la auditoría de '13 Checks' ANTES de usar cualquier resultado. Si algún control falla, el número no es utilizable.
E11: 7 | F11: Leer '11 Cross Check': un DCF aislado no es una conclusión. Y leer 'M4 Manual Errores' antes de defender el modelo ante otro analista.
B12: RESULTADO DE LA VALORACIÓN | E12: Si esta tabla o el bloque de Precio objetivo muestran ceros: Ctrl+Alt+F9.
B13: Escenario activo | C13: ='09 Escenarios'!C5 -> BASE | E13: LOS TRES ESCENARIOS, CALCULADOS SIMULTÁNEAMENTE
B14: Enterprise Value | C14: ='06 DCF'!F44 -> 608375.19 | E14: Ya NO es una instantánea: cada columna se calcula en su propia hoja ('09a', '09b', '09c'), independiente del interruptor de '09 Escenarios'!C4. Los deltas de cada escenario están en la matriz de '09 Escenarios' filas 9-17.
B15: (−) Deuda neta y otras reclamaciones | C15: ='06 DCF'!F53-'06 DCF'!F44 -> -111860.35 | E15: Métrica | F15: PESIMISTA | G15: BASE | H15: OPTIMISTA | I15: Unidad
B16: Equity Value | C16: ='06 DCF'!F53 -> 496514.84 | E16: Enterprise Value | F16: ='Escenario Pesimista'!$F$66 -> 0 | G16: ='Escenario Base'!$F$66 -> 0 | H16: ='Escenario Optimista'!$F$66 -> 0 | I16: $M
B17: Acciones diluidas | C17: ='06 DCF'!F54 -> 2934 | E17: Equity Value | F17: ='Escenario Pesimista'!$F$70 -> 0 | G17: ='Escenario Base'!$F$70 -> 0 | H17: ='Escenario Optimista'!$F$70 -> 0 | I17: $M
B18: VALOR INTRÍNSECO POR ACCIÓN | C18: ='06 DCF'!F55 -> 169.22796 | E18: Valor intrínseco por acción | F18: ='Escenario Pesimista'!$F$72 -> 0 | G18: ='Escenario Base'!$F$72 -> 0 | H18: ='Escenario Optimista'!$F$72 -> 0 | I18: $/acc
B19: Upside / (Downside) sobre el precio actual | C19: =IF($C$10<=0,"◄ introducir el precio en C10",'06 DCF'!F57) -> ◄ introducir el precio en C10 | E19: WACC | F19: ='Escenario Pesimista'!$P$52 -> 0 | G19: ='Escenario Base'!$P$52 -> 0 | H19: ='Escenario Optimista'!$P$52 -> 0 | I19: %
B20: Margen de seguridad implícito | C20: =IF($C$10<=0,"◄ introducir el precio en C10",'06 DCF'!F58) -> ◄ introducir el precio en C10 | E20: Crecimiento terminal g | F20: ='Escenario Pesimista'!$P$53 -> 0 | G20: ='Escenario Base'!$P$53 -> 0 | H20: ='Escenario Optimista'!$P$53 -> 0 | I20: %
E21: Valor terminal / EV | F21: ='Escenario Pesimista'!$F$67 -> 0 | G21: ='Escenario Base'!$F$67 -> 0 | H21: ='Escenario Optimista'!$F$67 -> 0 | I21: %
B22: RANGO DE VALORACIÓN POR ESCENARIO | E22: Múltiplo de salida implícito | F22: ='Escenario Pesimista'!$F$68 -> 0 | G22: ='Escenario Base'!$F$68 -> 0 | H22: ='Escenario Optimista'!$F$68 -> 0 | I22: x
B23: Nota | C23: Ver la instantánea de los tres escenarios en E13:I21 → | E23: Ingresos FY2036E | F23: ='Escenario Pesimista'!$F$75 -> 0 | G23: ='Escenario Base'!$F$75 -> 0 | H23: ='Escenario Optimista'!$F$75 -> 0 | I23: $M
E24: Upside / (Downside) | F24: ='Escenario Pesimista'!$F$74 -> 0 | G24: ='Escenario Base'!$F$74 -> 0 | H24: ='Escenario Optimista'!$F$74 -> 0 | I24: %
B25: PARÁMETROS CLAVE | E25: CHECK: el escenario Base debe reproducir '06 DCF' | G25: ='Escenario Base'!$F$82 -> 0
B26: WACC | C26: ='07 WACC'!C38 -> 0.087495 | E26: CHECK: ordenación Pesimista < Base < Optimista | G26: =IF(AND($F$18<$G$18,$G$18<$H$18),"OK","FALLO: los escenarios no están ordenados") -> 0
B27: Crecimiento terminal g | C27: ='06 DCF'!F26 -> 0.03
B28: ROIC terminal | C28: ='06 DCF'!F27 -> 0.24
B29: Margen WACC − g | C29: ='07 WACC'!C43 -> 0.057495
B30: Valor terminal / Enterprise Value | C30: ='06 DCF'!F45 -> 0.66008837
B31: Múltiplo de salida implícito (VT / EBITDA FY2036) | C31: ='06 DCF'!F62 -> 9.5110381
B32: EV / EBITDA FY2026A implícito | C32: ='06 DCF'!F71 -> 19.168668
B33: EV / Ingresos FY2026A implícito | C33: ='06 DCF'!F72 -> 9.0321005
B35: SITUACIÓN DE PARTIDA (FY2026A REPORTADO)
B36: Ingresos | C36: ='03 Historical'!F11 -> 67357
B37: Crecimiento de ingresos | C37: ='03 Historical'!F121 -> 0.17348734
B38: EBIT normalizado | C38: ='03 Historical'!F127 -> 22444
B39: Margen EBIT normalizado | C39: ='03 Historical'!F128 -> 0.33320961
B40: Capex | C40: ='03 Historical'!F129 -> 55663
B41: Capex / Ingresos | C41: ='03 Historical'!F130 -> 0.82638775
B42: Flujo de caja operativo | C42: ='03 Historical'!F85 -> 31977
B43: FCF simple (CFO − Capex) | C43: ='03 Historical'!F132 -> -23686
B44: Deuda neta | C44: ='03 Historical'!F137 -> 105348
B45: Deuda neta / EBITDA | C45: ='03 Historical'!F138 -> 3.3193018
B46: RPO (backlog contratado) | C46: ='03 Historical'!F117 -> 638000
B48: CONTROLES CRÍTICOS
B49: Cuadre del balance histórico | C49: =IF('03 Historical'!F75=0,"OK","FALLO") -> OK
B50: WACC > g | C50: ='06 DCF'!F67 -> OK
B51: El FCFF llega a ser positivo | C51: ='06 DCF'!F75 -> OK
B52: Peso del valor terminal | C52: ='06 DCF'!F70 -> OK
B53: Múltiplo de salida implícito razonable | C53: ='06 DCF'!F69 -> OK
B54: Auditoría completa | C54: ="Ver hoja '13 Checks'" -> Ver hoja '13 Checks'
B56: Valoración por múltiplos
B57: AVISO: los múltiplos de la columna E son INPUTS DEL ANALISTA, no múltiplos de comparables observados. No se han obtenido datos de compañías comparables, por lo que estos múltiplos son marcadores de posición razonables que deben sustituirse por los de un conjunto de peers seleccionado con criterio (modelo de negocio, geografía, crecimiento, márgenes, intensidad de capital, riesgo y tamaño). Un múltiplo inventado no es valoración relativa.
B58: Método | C58: Métrica | D58: Valor de la métrica | E58: Múltiplo (input) | F58: EV implícito | G58: Equity implícito | H58: Valor por acción
B59: EV / Ingresos FY2027E | C59: Ingresos FY2027E | D59: ='04 Operating Model'!G11 -> 0 | E59: ='00 Panel del Analista'!D233 -> 0 | F59: =D59*E59 -> 0 | G59: =F59+SUM('06 DCF'!$F$46:$F$52) -> 0 | H59: =G59/'02 Assumptions'!$C$69 -> 0
B60: EV / EBITDA FY2027E | C60: EBITDA FY2027E | D60: ='04 Operating Model'!G39 -> 0 | E60: ='00 Panel del Analista'!D234 -> 0 | F60: =D60*E60 -> 0 | G60: =F60+SUM('06 DCF'!$F$46:$F$52) -> 0 | H60: =G60/'02 Assumptions'!$C$69 -> 0
B61: EV / EBITDA FY2029E | C61: EBITDA FY2029E | D61: ='04 Operating Model'!I39 -> 0 | E61: ='00 Panel del Analista'!D235 -> 0 | F61: =D61*E61 -> 0 | G61: =F61+SUM('06 DCF'!$F$46:$F$52) -> 0 | H61: =G61/'02 Assumptions'!$C$69 -> 0
B62: EV / EBIT normalizado FY2029E | C62: EBIT norm. FY2029E | D62: ='04 Operating Model'!I29 -> 0 | E62: ='00 Panel del Analista'!D236 -> 0 | F62: =D62*E62 -> 0 | G62: =F62+SUM('06 DCF'!$F$46:$F$52) -> 0 | H62: =G62/'02 Assumptions'!$C$69 -> 0
B63: EV / FCFF FY2031E | C63: FCFF FY2031E | D63: ='06 DCF'!K15 -> 0 | E63: ='00 Panel del Analista'!D237 -> 0 | F63: =D63*E63 -> 0 | G63: =F63+SUM('06 DCF'!$F$46:$F$52) -> 0 | H63: =G63/'02 Assumptions'!$C$69 -> 0
B64: P / E FY2029E (valora el equity directamente, sin puente) | C64: Beneficio neto FY2029E | D64: ='05 Three Statement'!I16 -> 0 | E64: ='00 Panel del Analista'!D238 -> 0 | F64: no aplica | G64: =D64*E64 -> 0 | H64: =G64/'02 Assumptions'!$C$69 -> 0
B66: Media de los métodos de múltiplos | H66: =AVERAGE(H59:H64) -> 0
B67: MEDIANA de los métodos de múltiplos | H67: =MEDIAN(H59:H64) -> 0
B68: Rango de los métodos (mínimo – máximo) | G68: =MIN(H59:H64) -> 0 | H68: =MAX(H59:H64) -> 0
B69: Para comparar: valor por acción del DCF (escenario Base) | H69: ='06 DCF'!$F$55 -> 0
B71: Precio objetivo
B72: Precio objetivo ponderado por método. Los PESOS de la columna D son inputs del analista y deben sumar el 100%. La ponderación no reduce la incertidumbre: sólo hace explícito cuánta confianza se otorga a cada método. Si el rango entre métodos es amplio, el precio objetivo es una media de cosas que no coinciden, y eso es información en sí mismo.
B73: Método | C73: Valor por acción | D73: Peso (input) | E73: Contribución
B74: DCF — escenario Pesimista (Bear) | C74: ='Escenario Pesimista'!$F$72 -> 0 | D74: ='00 Panel del Analista'!D241 -> 0 | E74: =C74*D74 -> 0
B75: DCF — escenario Base | C75: ='Escenario Base'!$F$72 -> 0 | D75: ='00 Panel del Analista'!D242 -> 0 | E75: =C75*D75 -> 0
B76: DCF — escenario Optimista (Bull) | C76: ='Escenario Optimista'!$F$72 -> 0 | D76: ='00 Panel del Analista'!D243 -> 0 | E76: =C76*D76 -> 0
B77: Valoración por múltiplos (mediana) | C77: =$H$67 -> 0 | D77: ='00 Panel del Analista'!D244 -> 0 | E77: =C77*D77 -> 0
B78: Sum-of-the-Parts | C78: ='12 SOTP'!$G$25 -> 0 | D78: ='00 Panel del Analista'!D245 -> 0 | E78: =C78*D78 -> 0
B79: Suma de los pesos | D79: =SUM(D74:D78) -> 0 | E79: =IF(ABS(D79-1)<0.0001,"OK","FALLO: los pesos deben sumar 100%") -> 0
B80: PRECIO OBJETIVO PONDERADO | C80: =IF(ABS($D$79-1)>0.0001,"corregir los pesos",SUMPRODUCT(C74:C78,D74:D78)) -> 0
B81: Precio de mercado actual | C81: =$C$10 -> 0
B82: Upside / (Downside) al precio objetivo | C82: =IF(OR($C$10<=0,NOT(ISNUMBER($C$80))),"introducir precio",$C$80/$C$10-1) -> 0
B83: Margen de seguridad sobre el precio objetivo | C83: =IF(OR($C$10<=0,NOT(ISNUMBER($C$80))),"introducir precio",1-$C$10/$C$80) -> 0
B84: Rango entre el método más bajo y el más alto | C84: =MIN(C74:C78) -> 0 | D84: =MAX(C74:C78) -> 0
B85: Dispersión entre métodos (máx / mín) | C85: =IFERROR(D84/C84,"n/a") -> 0
B86: CHECK: dispersión entre métodos | C86: =IF(NOT(ISNUMBER($C$85)),"n/a",IF($C$85>2.5,"AVISO: los métodos discrepan más de 2,5 veces. El precio objetivo ponderado promedia resultados incompatibles: presentar el RANGO, no el punto.","OK")) -> 0

Sheet 02 Assumptions
A1: HIPÓTESIS CENTRALIZADAS — ORACLE CORPORATION (ORCL)
A2: AZUL = input del analista. NEGRO = fórmula. VERDE = enlace a otra hoja. GRIS = dato histórico reportado. AMARILLO = hipótesis crítica. Ninguna otra hoja debe contener hipótesis: todas viven aquí.
B4: Hipótesis | C4: Unidad | D4: ='00 Panel del Analista'!D14 -> 0 | E4: ='00 Panel del Analista'!E14 -> 0 | F4: ='00 Panel del Analista'!F14 -> 0 | G4: ='00 Panel del Analista'!G14 -> 0 | H4: ='00 Panel del Analista'!H14 -> 0 | I4: ='00 Panel del Analista'!I14 -> 0 | J4: ='00 Panel del Analista'!J14 -> 0 | K4: ='00 Panel del Analista'!K14 -> 0 | ... P4: ='00 Panel del Analista'!P14 -> 0 | Q4: Peso del delta de escenario
B6: PANEL DE CONTROL
B7: Escenario activo (1=Bear, 2=Base, 3=Bull) | C7: ='09 Escenarios'!C4 -> 2
B8: Nombre del escenario activo | C8: ='09 Escenarios'!C5 -> BASE
B9: Fecha de valoración | C9: ='00 Panel del Analista'!C11 -> 0
B10: Moneda y unidades | C10: ='00 Panel del Analista'!C10 -> 0
B11: Años de forecast explícito | C11: ='00 Panel del Analista'!D186 -> 0
B12: Convención de descuento (1=fin de año, 2=mitad de año) | C12: ='00 Panel del Analista'!D187 -> 0
B13: Método de valor terminal (1=Gordon, 2=Múltiplo de salida) | C13: ='00 Panel del Analista'!D188 -> 0
B14: Tratamiento de leases operativos | C14: OPERATIVO — coste en EBIT, pasivo fuera de la deuda neta
B15: Tratamiento del SBC | C15: GASTO REAL — no se readiciona, no se aplica dilución adicional
B16: Año base del forecast | C16: ='00 Panel del Analista'!C12 -> 0
B18: INGRESOS — CRECIMIENTO POR SEGMENTO (driver: conversión del RPO de 638.000 en ingresos)
B19: Cloud — crecimiento (vector Base) | C19: % | G19: ='00 Panel del Analista'!G165 -> 0 | H19: ='00 Panel del Analista'!H165 -> 0 | I19: ='00 Panel del Analista'!I165 -> 0 | J19: ='00 Panel del Analista'!J165 -> 0 | K19: ='00 Panel del Analista'!K165 -> 0 | L19: ='00 Panel del Analista'!L165 -> 0 | M19: ='00 Panel del Analista'!M165 -> 0 | N19: ='00 Panel del Analista'!N165 -> 0 | ... P19: ='00 Panel del Analista'!P165 -> 0
B20: Cloud — crecimiento ACTIVO (Base × multiplicador de escenario) | C20: % | G20: =G19*'09 Escenarios'!$G$9+$C$104 -> 0.5 | H20: =H19*'09 Escenarios'!$G$9+$C$104 -> 0.38 | I20: =I19*'09 Escenarios'!$G$9+$C$104 -> 0.28 | J20: =J19*'09 Escenarios'!$G$9+$C$104 -> 0.21 | K20: =K19*'09 Escenarios'!$G$9+$C$104 -> 0.16 | L20: =L19*'09 Escenarios'!$G$9+$C$104 -> 0.12 | M20: =M19*'09 Escenarios'!$G$9+$C$104 -> 0.09 | N20: =N19*'09 Escenarios'!$G$9+$C$104 -> 0.07 | ... P20: =P19*'09 Escenarios'!$G$9+$C$104 -> 0.04
B21: Software — crecimiento (vector Base) | C21: % | G21: ='00 Panel del Analista'!G166 -> 0 | H21: ='00 Panel del Analista'!H166 -> 0 | I21: ='00 Panel del Analista'!I166 -> 0 | J21: ='00 Panel del Analista'!J166 -> 0 | K21: ='00 Panel del Analista'!K166 -> 0 | L21: ='00 Panel del Analista'!L166 -> 0 | M21: ='00 Panel del Analista'!M166 -> 0 | N21: ='00 Panel del Analista'!N166 -> 0 | ... P21: ='00 Panel del Analista'!P166 -> 0
B22: Software — crecimiento ACTIVO | C22: % | G22: =G21+'09 Escenarios'!$G$10+$C$104 -> 0 | H22: =H21+'09 Escenarios'!$G$10+$C$104 -> -0.01 | I22: =I21+'09 Escenarios'!$G$10+$C$104 -> -0.01 | J22: =J21+'09 Escenarios'!$G$10+$C$104 -> 0 | K22: =K21+'09 Escenarios'!$G$10+$C$104 -> 0 | L22: =L21+'09 Escenarios'!$G$10+$C$104 -> 0.01 | M22: =M21+'09 Escenarios'!$G$10+$C$104 -> 0.01 | N22: =N21+'09 Escenarios'!$G$10+$C$104 -> 0.01 | ... P22: =P21+'09 Escenarios'!$G$10+$C$104 -> 0.01
B23: Hardware — crecimiento (vector Base) | C23: % | G23: ='00 Panel del Analista'!G167 -> 0 | H23: ='00 Panel del Analista'!H167 -> 0 | I23: ='00 Panel del Analista'!I167 -> 0 | J23: ='00 Panel del Analista'!J167 -> 0 | K23: ='00 Panel del Analista'!K167 -> 0 | L23: ='00 Panel del Analista'!L167 -> 0 | M23: ='00 Panel del Analista'!M167 -> 0 | N23: ='00 Panel del Analista'!N167 -> 0 | ... P23: ='00 Panel del Analista'!P167 -> 0
B24: Hardware — crecimiento ACTIVO | C24: % | G24: =G23+'09 Escenarios'!$G$10+$C$104 -> -0.02 | H24: =H23+'09 Escenarios'!$G$10+$C$104 -> -0.02 | I24: =I23+'09 Escenarios'!$G$10+$C$104 -> -0.01 | J24: =J23+'09 Escenarios'!$G$10+$C$104 -> -0.01 | K24: =K23+'09 Escenarios'!$G$10+$C$104 -> 0 | L24: =L23+'09 Escenarios'!$G$10+$C$104 -> 0 | M24: =M23+'09 Escenarios'!$G$10+$C$104 -> 0 | N24: =N23+'09 Escenarios'!$G$10+$C$104 -> 0 | ... P24: =P23+'09 Escenarios'!$G$10+$C$104 -> 0
B25: Servicios — crecimiento (vector Base) | C25: % | G25: ='00 Panel del Analista'!G168 -> 0 | H25: ='00 Panel del Analista'!H168 -> 0 | I25: ='00 Panel del Analista'!I168 -> 0 | J25: ='00 Panel del Analista'!J168 -> 0 | K25: ='00 Panel del Analista'!K168 -> 0 | L25: ='00 Panel del Analista'!L168 -> 0 | M25: ='00 Panel del Analista'!M168 -> 0 | N25: ='00 Panel del Analista'!N168 -> 0 | ... P25: ='00 Panel del Analista'!P168 -> 0
B26: Servicios — crecimiento ACTIVO | C26: % | G26: =G25+'09 Escenarios'!$G$10+$C$104 -> 0.08 | H26: =H25+'09 Escenarios'!$G$10+$C$104 -> 0.07 | I26: =I25+'09 Escenarios'!$G$10+$C$104 -> 0.06 | J26: =J25+'09 Escenarios'!$G$10+$C$104 -> 0.05 | K26: =K25+'09 Escenarios'!$G$10+$C$104 -> 0.04 | L26: =L25+'09 Escenarios'!$G$10+$C$104 -> 0.03 | M26: =M25+'09 Escenarios'!$G$10+$C$104 -> 0.03 | N26: =N25+'09 Escenarios'!$G$10+$C$104 -> 0.03 | ... P26: =P25+'09 Escenarios'!$G$10+$C$104 -> 0.03
B28: MÁRGENES Y ESTRUCTURA DE COSTES
B29: Gross Margin (vector Base) | C29: % | G29: ='00 Panel del Analista'!G169 -> 0 | H29: ='00 Panel del Analista'!H169 -> 0 | I29: ='00 Panel del Analista'!I169 -> 0 | J29: ='00 Panel del Analista'!J169 -> 0 | K29: ='00 Panel del Analista'!K169 -> 0 | L29: ='00 Panel del Analista'!L169 -> 0 | M29: ='00 Panel del Analista'!M169 -> 0 | N29: ='00 Panel del Analista'!N169 -> 0 | ... P29: ='00 Panel del Analista'!P169 -> 0
B30: Gross Margin ACTIVO | C30: % | G30: =G29+'09 Escenarios'!$G$11 -> 0.61 | H30: =H29+'09 Escenarios'!$G$11 -> 0.58 | I30: =I29+'09 Escenarios'!$G$11 -> 0.565 | J30: =J29+'09 Escenarios'!$G$11 -> 0.56 | K30: =K29+'09 Escenarios'!$G$11 -> 0.56 | L30: =L29+'09 Escenarios'!$G$11 -> 0.565 | M30: =M29+'09 Escenarios'!$G$11 -> 0.57 | N30: =N29+'09 Escenarios'!$G$11 -> 0.575 | ... P30: =P29+'09 Escenarios'!$G$11 -> 0.58
B31: Ventas y marketing / Ingresos (Base) | C31: % | G31: ='00 Panel del Analista'!G170 -> 0 | H31: ='00 Panel del Analista'!H170 -> 0 | I31: ='00 Panel del Analista'!I170 -> 0 | J31: ='00 Panel del Analista'!J170 -> 0 | K31: ='00 Panel del Analista'!K170 -> 0 | L31: ='00 Panel del Analista'!L170 -> 0 | M31: ='00 Panel del Analista'!M170 -> 0 | N31: ='00 Panel del Analista'!N170 -> 0 | ... P31: ='00 Panel del Analista'!P170 -> 0
B32: Ventas y marketing / Ingresos ACTIVO | C32: % | G32: =G31+'09 Escenarios'!$G$12*$Q$32 -> 0.12 | H32: =H31+'09 Escenarios'!$G$12*$Q$32 -> 0.113 | I32: =I31+'09 Escenarios'!$G$12*$Q$32 -> 0.108 | J32: =J31+'09 Escenarios'!$G$12*$Q$32 -> 0.104 | K32: =K31+'09 Escenarios'!$G$12*$Q$32 -> 0.101 | L32: =L31+'09 Escenarios'!$G$12*$Q$32 -> 0.099 | M32: =M31+'09 Escenarios'!$G$12*$Q$32 -> 0.098 | N32: =N31+'09 Escenarios'!$G$12*$Q$32 -> 0.097 | ... P32: =P31+'09 Escenarios'!$G$12*$Q$32 -> 0.097 | Q32: ='00 Panel del Analista'!D202 -> 0
B33: I+D / Ingresos (Base) | C33: % | G33: ='00 Panel del Analista'!G171 -> 0 | H33: ='00 Panel del Analista'!H171 -> 0 | I33: ='00 Panel del Analista'!I171 -> 0 | J33: ='00 Panel del Analista'!J171 -> 0 | K33: ='00 Panel del Analista'!K171 -> 0 | L33: ='00 Panel del Analista'!L171 -> 0 | M33: ='00 Panel del Analista'!M171 -> 0 | N33: ='00 Panel del Analista'!N171 -> 0 | ... P33: ='00 Panel del Analista'!P171 -> 0
B34: I+D / Ingresos ACTIVO | C34: % | G34: =G33+'09 Escenarios'!$G$12*$Q$34 -> 0.145 | H34: =H33+'09 Escenarios'!$G$12*$Q$34 -> 0.14 | I34: =I33+'09 Escenarios'!$G$12*$Q$34 -> 0.136 | J34: =J33+'09 Escenarios'!$G$12*$Q$34 -> 0.133 | K34: =K33+'09 Escenarios'!$G$12*$Q$34 -> 0.131 | L34: =L33+'09 Escenarios'!$G$12*$Q$34 -> 0.13 | M34: =M33+'09 Escenarios'!$G$12*$Q$34 -> 0.129 | N34: =N33+'09 Escenarios'!$G$12*$Q$34 -> 0.128 | ... P34: =P33+'09 Escenarios'!$G$12*$Q$34 -> 0.128 | Q34: ='00 Panel del Analista'!D203 -> 0
B35: G&A / Ingresos (Base) | C35: % | G35: ='00 Panel del Analista'!G172 -> 0 | H35: ='00 Panel del Analista'!H172 -> 0 | I35: ='00 Panel del Analista'!I172 -> 0 | J35: ='00 Panel del Analista'!J172 -> 0 | K35: ='00 Panel del Analista'!K172 -> 0 | L35: ='00 Panel del Analista'!L172 -> 0 | M35: ='00 Panel del Analista'!M172 -> 0 | N35: ='00 Panel del Analista'!N172 -> 0 | ... P35: ='00 Panel del Analista'!P172 -> 0
B36: G&A / Ingresos ACTIVO | C36: % | G36: =G35+'09 Escenarios'!$G$12*$Q$36 -> 0.022 | H36: =H35+'09 Escenarios'!$G$12*$Q$36 -> 0.021 | I36: =I35+'09 Escenarios'!$G$12*$Q$36 -> 0.02 | J36: =J35+'09 Escenarios'!$G$12*$Q$36 -> 0.019 | K36: =K35+'09 Escenarios'!$G$12*$Q$36 -> 0.019 | L36: =L35+'09 Escenarios'!$G$12*$Q$36 -> 0.018 | M36: =M35+'09 Escenarios'!$G$12*$Q$36 -> 0.018 | N36: =N35+'09 Escenarios'!$G$12*$Q$36 -> 0.018 | ... P36: =P35+'09 Escenarios'!$G$12*$Q$36 -> 0.018 | Q36: ='00 Panel del Analista'!D204 -> 0
B37: Amortización de intangibles adquiridos (calendario) | C37: $M | G37: ='00 Panel del Analista'!G173 -> 0 | H37: ='00 Panel del Analista'!H173 -> 0 | I37: ='00 Panel del Analista'!I173 -> 0 | J37: ='00 Panel del Analista'!J173 -> 0 | K37: ='00 Panel del Analista'!K173 -> 0 | L37: ='00 Panel del Analista'!L173 -> 0 | M37: ='00 Panel del Analista'!M173 -> 0 | N37: ='00 Panel del Analista'!N173 -> 0 | ... P37: ='00 Panel del Analista'!P173 -> 0
B38: Reestructuración normalizada | C38: $M | G38: ='00 Panel del Analista'!G174 -> 0 | H38: ='00 Panel del Analista'!H174 -> 0 | I38: ='00 Panel del Analista'!I174 -> 0 | J38: ='00 Panel del Analista'!J174 -> 0 | K38: ='00 Panel del Analista'!K174 -> 0 | L38: ='00 Panel del Analista'!L174 -> 0 | M38: ='00 Panel del Analista'!M174 -> 0 | N38: ='00 Panel del Analista'!N174 -> 0 | ... P38: ='00 Panel del Analista'!P174 -> 0
B40: CAPEX Y DEPRECIACIÓN
B41: Capex / Ingresos (vector Base) | C41: % | G41: ='00 Panel del Analista'!G175 -> 0 | H41: ='00 Panel del Analista'!H175 -> 0 | I41: ='00 Panel del Analista'!I175 -> 0 | J41: ='00 Panel del Analista'!J175 -> 0 | K41: ='00 Panel del Analista'!K175 -> 0 | L41: ='00 Panel del Analista'!L175 -> 0 | M41: ='00 Panel del Analista'!M175 -> 0 | N41: ='00 Panel del Analista'!N175 -> 0 | ... P41: ='00 Panel del Analista'!P175 -> 0
B42: Capex / Ingresos ACTIVO | C42: % | G42: =G41*'09 Escenarios'!$G$13 -> 0.6 | H42: =H41*'09 Escenarios'!$G$13 -> 0.4 | I42: =I41*'09 Escenarios'!$G$13 -> 0.28 | J42: =J41*'09 Escenarios'!$G$13 -> 0.21 | K42: =K41*'09 Escenarios'!$G$13 -> 0.16 | L42: =L41*'09 Escenarios'!$G$13 -> 0.14 | M42: =M41*'09 Escenarios'!$G$13 -> 0.13 | N42: =N41*'09 Escenarios'!$G$13 -> 0.125 | ... P42: =P41*'09 Escenarios'!$G$13 -> 0.118
B43: Vida útil media del PP&E | C43: ='00 Panel del Analista'!D189 -> 0
B44: Vida útil implícita en FY2026 (check de calibración) | C44: años | F44: =('03 Historical'!E48+'03 Historical'!F129/2)/'03 Historical'!F79 -> 9.3602912
B46: CIRCULANTE OPERATIVO (drivers, no % de ingresos genérico)
B47: DSO — días de cobro (Base) | C47: días | G47: ='00 Panel del Analista'!G176 -> 0 | H47: ='00 Panel del Analista'!H176 -> 0 | I47: ='00 Panel del Analista'!I176 -> 0 | J47: ='00 Panel del Analista'!J176 -> 0 | K47: ='00 Panel del Analista'!K176 -> 0 | L47: ='00 Panel del Analista'!L176 -> 0 | M47: ='00 Panel del Analista'!M176 -> 0 | N47: ='00 Panel del Analista'!N176 -> 0 | ... P47: ='00 Panel del Analista'!P176 -> 0
B48: DSO ACTIVO | C48: días | G48: =G47+'09 Escenarios'!$G$14 -> 56 | H48: =H47+'09 Escenarios'!$G$14 -> 55 | I48: =I47+'09 Escenarios'!$G$14 -> 54 | J48: =J47+'09 Escenarios'!$G$14 -> 53 | K48: =K47+'09 Escenarios'!$G$14 -> 52 | L48: =L47+'09 Escenarios'!$G$14 -> 52 | M48: =M47+'09 Escenarios'!$G$14 -> 52 | N48: =N47+'09 Escenarios'!$G$14 -> 52 | ... P48: =P47+'09 Escenarios'!$G$14 -> 52
B49: Proveedores / (coste de ingresos + capex) | C49: % | G49: ='00 Panel del Analista'!G177 -> 0 | H49: ='00 Panel del Analista'!H177 -> 0 | I49: ='00 Panel del Analista'!I177 -> 0 | J49: ='00 Panel del Analista'!J177 -> 0 | K49: ='00 Panel del Analista'!K177 -> 0 | L49: ='00 Panel del Analista'!L177 -> 0 | M49: ='00 Panel del Analista'!M177 -> 0 | N49: ='00 Panel del Analista'!N177 -> 0 | ... P49: ='00 Panel del Analista'!P177 -> 0
B50: Ingresos diferidos corrientes / Ingresos | C50: % | G50: ='00 Panel del Analista'!G178 -> 0 | H50: ='00 Panel del Analista'!H178 -> 0 | I50: ='00 Panel del Analista'!I178 -> 0 | J50: ='00 Panel del Analista'!J178 -> 0 | K50: ='00 Panel del Analista'!K178 -> 0 | L50: ='00 Panel del Analista'!L178 -> 0 | M50: ='00 Panel del Analista'!M178 -> 0 | N50: ='00 Panel del Analista'!N178 -> 0 | ... P50: ='00 Panel del Analista'!P178 -> 0
B51: Otros activos corrientes / Ingresos | C51: % | G51: ='00 Panel del Analista'!G179 -> 0 | H51: ='00 Panel del Analista'!H179 -> 0 | I51: ='00 Panel del Analista'!I179 -> 0 | J51: ='00 Panel del Analista'!J179 -> 0 | K51: ='00 Panel del Analista'!K179 -> 0 | L51: ='00 Panel del Analista'!L179 -> 0 | M51: ='00 Panel del Analista'!M179 -> 0 | N51: ='00 Panel del Analista'!N179 -> 0 | ... P51: ='00 Panel del Analista'!P179 -> 0
B52: Remuneraciones pendientes / Ingresos | C52: % | G52: ='00 Panel del Analista'!G180 -> 0 | H52: ='00 Panel del Analista'!H180 -> 0 | I52: ='00 Panel del Analista'!I180 -> 0 | J52: ='00 Panel del Analista'!J180 -> 0 | K52: ='00 Panel del Analista'!K180 -> 0 | L52: ='00 Panel del Analista'!L180 -> 0 | M52: ='00 Panel del Analista'!M180 -> 0 | N52: ='00 Panel del Analista'!N180 -> 0 | ... P52: ='00 Panel del Analista'!P180 -> 0
B53: Otros pasivos corrientes operativos / Ingresos | C53: % | G53: ='00 Panel del Analista'!G181 -> 0 | H53: ='00 Panel del Analista'!H181 -> 0 | I53: ='00 Panel del Analista'!I181 -> 0 | J53: ='00 Panel del Analista'!J181 -> 0 | K53: ='00 Panel del Analista'!K181 -> 0 | L53: ='00 Panel del Analista'!L181 -> 0 | M53: ='00 Panel del Analista'!M181 -> 0 | N53: ='00 Panel del Analista'!N181 -> 0 | ... P53: ='00 Panel del Analista'!P181 -> 0
B55: IMPUESTOS
B56: Tipo impositivo de caja (vector Base) | C56: % | G56: ='00 Panel del Analista'!G182 -> 0 | H56: ='00 Panel del Analista'!H182 -> 0 | I56: ='00 Panel del Analista'!I182 -> 0 | J56: ='00 Panel del Analista'!J182 -> 0 | K56: ='00 Panel del Analista'!K182 -> 0 | L56: ='00 Panel del Analista'!L182 -> 0 | M56: ='00 Panel del Analista'!M182 -> 0 | N56: ='00 Panel del Analista'!N182 -> 0 | ... P56: ='00 Panel del Analista'!P182 -> 0
B57: Tipo impositivo de caja ACTIVO | C57: % | G57: =G56+'09 Escenarios'!$G$15 -> 0.14 | H57: =H56+'09 Escenarios'!$G$15 -> 0.15 | I57: =I56+'09 Escenarios'!$G$15 -> 0.16 | J57: =J56+'09 Escenarios'!$G$15 -> 0.17 | K57: =K56+'09 Escenarios'!$G$15 -> 0.18 | L57: =L56+'09 Escenarios'!$G$15 -> 0.19 | M57: =M56+'09 Escenarios'!$G$15 -> 0.19 | N57: =N56+'09 Escenarios'!$G$15 -> 0.19 | ... P57: =P56+'09 Escenarios'!$G$15 -> 0.19
B58: Tipo marginal para el WACC | C58: ='00 Panel del Analista'!D190 -> 0
B59: Tipo efectivo reportado FY2026 (referencia, NO usado) | C59: % | F59: ='03 Historical'!F33 -> 0.12616344
B61: VALOR TERMINAL
B62: Crecimiento terminal g (Base) | C62: ='00 Panel del Analista'!D191 -> 0
B63: Crecimiento terminal g ACTIVO | C63: =C62+'09 Escenarios'!$G$16 -> 0.03
B64: Múltiplo de salida EV/EBITDA (método alternativo) | C64: ='00 Panel del Analista'!D192 -> 0
B65: Tope de referencia: PIB nominal a largo plazo EEUU | C65: ='00 Panel del Analista'!D193 -> 0
B66: ROIC terminal (disciplina la reinversión terminal: reinv. = g / ROIC) | C66: ='00 Panel del Analista'!D194 -> 0
B67: CAJA, ACCIONES Y PUENTE A EQUITY (a la fecha de valoración)
B68: Caja mínima operativa / Ingresos | C68: ='00 Panel del Analista'!D195 -> 0
B69: Acciones diluidas a la fecha de valoración = en circulación a cierre + equivalentes dilutivos | C69: ='03 Historical'!F118+('03 Historical'!F40-'03 Historical'!F39) -> 2934
B70: Deuda financiera total | C70: ='03 Historical'!F110 -> 129541
B71: Pasivo por leases financieros (debt-like) | C71: ='03 Historical'!F112 -> 7701
B72: Caja y equivalentes | C72: ='03 Historical'!F43 -> 31289
B73: Valores negociables | C73: ='03 Historical'!F44 -> 605
B74: Intereses minoritarios | C74: ='03 Historical'!F72 -> 548
B75: Preferentes convertibles obligatorias | C75: ='03 Historical'!F67 -> 4954
B76: Pasivo por leases operativos (NO en el puente, ver C14) | C76: ='03 Historical'!F113 -> 30190
B79: JUSTIFICACIÓN DE LAS HIPÓTESIS CRÍTICAS (toda hipótesis sin mecanismo económico explicado es una hipótesis indefendible)
B80: Hipótesis | C80: Mecanismo económico y riesgo
B81: Crecimiento Cloud 55% → 5% | C81: No es una extrapolación del CAGR histórico. Es la conversión del RPO: 638.000 de obligaciones de rendimiento pendientes a 31/05/2026 frente a unos ingresos cloud de 33.989. El backlog da visibilidad al tramo inicial; la desaceleración refleja que un backlog finito no sostiene tasas de tres dígitos y que la capacidad instalada se llena progresivamente. CHECK en '13 Checks': los ingresos cloud acumulados del forecast no pueden exceder el RPO más la contratación nueva razonable.
B82: Software plano y Hardware en declive | C82: Soporte de licencias es un negocio de renta madura con erosión por migración a cloud, compensada por subidas de precio de soporte. Hardware es residual y estructuralmente decreciente. Proyectar crecimiento aquí sería contradecir la propia tesis de migración a cloud.
B83: Gross Margin del 65,8% al 56% | C83: ES LA HIPÓTESIS MÁS IMPORTANTE DEL MODELO. La depreciación de los centros de datos va dentro del coste de ingresos. Con PP&E pasando de 43.522 a 99.957 y capex de 55.663, el margen bruto DEBE caer: el IaaS es un negocio de capital intensivo, no de software. El margen histórico del 71% (FY2024) correspondía a un mix dominado por licencias. Mantener el margen histórico mientras se multiplica el capex sería una inconsistencia interna grave.
B84: Apalancamiento operativo en S&M, I+D y G&A | C84: Los gastos por debajo del margen bruto crecen menos que los ingresos porque la fuerza comercial y la plataforma de I+D ya están instaladas. Es la única palanca de margen defendible aquí: no se proyecta expansión de margen bruto, se proyecta dilución de gastos fijos.
B85: Amortización de intangibles en declive a ~90 | C85: Los intangibles adquiridos (principalmente Cerner) tienen vida finita y se agotan. Ya cayó de 3.010 (FY2024) a 1.671 (FY2026). Mantenerla constante a perpetuidad sobreestimaría el gasto; eliminarla de golpe infla el EBIT del año 1.
B86: Capex del 60% al 9,5% de ingresos | C86: Segunda hipótesis más sensible. FY2026 gastó el 82,6% de sus ingresos en capex. El modelo asume que se trata de una ola de construcción concentrada contra contratos ya firmados, no de un nivel permanente. Si el capex NO normaliza, el FCFF nunca se vuelve positivo y la valoración colapsa: por eso el capex está en la matriz de sensibilidad. NO se ha asumido Capex = D&A.
B87: Vida útil del PP&E de 8 años | C87: Calibrada contra FY2026: la vida implícita en la depreciación reportada es de ~9,4 años sobre PP&E neto (celda F44). Se usan 8 años por el mix creciente de servidores y GPU, de vida más corta que los edificios. Efecto neto sobre el valor: más depreciación reduce el EBIT pero aumenta el escudo fiscal.
B88: Tipo de caja del 14% al 19% | C88: NO se usa el tipo efectivo reportado del 12,6%. Ese tipo refleja créditos de I+D, FDII, mix jurisdiccional y beneficios por vesting de acciones que no escalan con el beneficio. Converge al 19%, por debajo del 21% estatutario federal por el mix internacional pero por encima del actual. Usar el 12,6% a perpetuidad sobreestimaría el valor de forma material.
B89: Crecimiento terminal del 3,0% | C89: Justificado como ~1% de crecimiento real de largo plazo más ~2% de inflación. Tope de referencia del 4% (PIB nominal EEUU) en C65. NO se ha elegido el 3% por costumbre: por encima del PIB nominal la empresa acabaría siendo la economía entera. CHECK obligatorio: g < WACC.
B90: Leases operativos como operativos | C90: Bajo ASC 842 el coste del lease operativo es un gasto operativo único ya incluido en el EBIT. Por tanto el pasivo de 30.190 NO se suma a la deuda neta: hacerlo sería doble contabilización. El impacto de la convención contraria está cuantificado en '11 Cross Check'.
B91: SBC como gasto real sin dilución adicional | C91: El SBC (4.811 en FY2026, 7,1% de los ingresos) se mantiene dentro de los gastos operativos y NO se readiciona. En consecuencia no se proyecta dilución adicional por SBC futuro. Readicionar el SBC y además no diluir sería el error más común en valoración de software.
B92: Caja mínima operativa del 1,5% de ingresos | C92: No toda la caja de 31.289 es distribuible. Solo el exceso sobre la caja operativa mínima entra en el puente a Equity Value. Con compromisos de capex plurianuales, asumir el 100% de la caja como distribuible es agresivo.
B94: FINANCIACIÓN Y PARTIDAS NO OPERATIVAS — SOLO PARA EL MODELO DE TRES ESTADOS (no afectan al FCFF ni al DCF)
B95: SBC / Ingresos | C95: % | G95: ='00 Panel del Analista'!G183 -> 0 | H95: ='00 Panel del Analista'!H183 -> 0 | I95: ='00 Panel del Analista'!I183 -> 0 | J95: ='00 Panel del Analista'!J183 -> 0 | K95: ='00 Panel del Analista'!K183 -> 0 | L95: ='00 Panel del Analista'!L183 -> 0 | M95: ='00 Panel del Analista'!M183 -> 0 | N95: ='00 Panel del Analista'!N183 -> 0 | ... P95: ='00 Panel del Analista'!P183 -> 0
B96: Crecimiento anual del dividendo ordinario | C96: ='00 Panel del Analista'!D196 -> 0
B97: % del excedente de caja destinado a repagar deuda | C97: ='00 Panel del Analista'!D197 -> 0
B98: Tipo de interés medio sobre la deuda INICIAL | C98: ='00 Panel del Analista'!D198 -> 0
B99: Tipo contractual del dividendo de preferentes (Serie D) | C99: ='00 Panel del Analista'!D199 -> 0
B100: Recompra neta de acciones | C100: ='00 Panel del Analista'!D200 -> 0
B101: Intangibles adquiridos netos a 31/05/2026 (= suma del calendario) | C101: =SUM(G37:P37) -> 4890
B102: Otros activos no corrientes netos de intangibles a 31/05/2026 | C102: ='03 Historical'!F52-C101 -> 6853
B103: NOTA: el gasto por intereses se calcula sobre la deuda INICIAL del periodo, no sobre la media, para eliminar la circularidad deuda→intereses→beneficio→caja→deuda. Es una simplificación deliberada y conservadora; la alternativa exige cálculo iterativo.
B104: Shock uniforme al crecimiento de ingresos (todos los segmentos, todos los años) | C104: ='00 Panel del Analista'!D201 -> 0
B105: NOTA: este shock existe porque la sensibilidad crecimiento × margen no admite forma cerrada (la depreciación depende de la trayectoria de PP&E). Para esa sensibilidad hay que recorrer C104 manualmente; ver instrucciones en '08 Sensitivity'.
B106: NOTA sobre el número de acciones: NO se usa la media ponderada diluida del ejercicio (2.914), que es una media de doce meses ya pasados. Se usan las acciones en circulación a cierre (2.880, portada del 10-K a 12/06/2026) más los equivalentes dilutivos implícitos en la diferencia entre la media diluida y la media básica (2.914 − 2.860 = 54). No se añaden acciones por la conversión de las preferentes porque su valor se resta del Equity Value: ver regla de no doble contabilización.

Sheet 03 Historical
A1: ESTADOS FINANCIEROS HISTÓRICOS — ORACLE CORPORATION (ORCL)
A2: USD millones salvo indicación. Ejercicio fiscal cerrado el 31 de mayo. Fuente: Form 10-K FY2026 (SEC). Datos reportados sin ajustar.
B4: Partida | C4: Unidad | D4: ='00 Panel del Analista'!D14 -> 0 | E4: ='00 Panel del Analista'!E14 -> 0 | F4: ='00 Panel del Analista'!F14 -> 0 | G4: ='00 Panel del Analista'!G14 -> 0 | H4: ='00 Panel del Analista'!H14 -> 0 | I4: ='00 Panel del Analista'!I14 -> 0 | J4: ='00 Panel del Analista'!J14 -> 0 | K4: ='00 Panel del Analista'!K14 -> 0 | ... P4: ='00 Panel del Analista'!P14 -> 0
B6: CUENTA DE RESULTADOS
B7: Cloud | C7: $M | D7: ='00 Panel del Analista'!D18 -> 0 | E7: ='00 Panel del Analista'!E18 -> 0 | F7: ='00 Panel del Analista'!F18 -> 0
B8: Software (licencias y soporte) | C8: $M | D8: ='00 Panel del Analista'!D19 -> 0 | E8: ='00 Panel del Analista'!E19 -> 0 | F8: ='00 Panel del Analista'!F19 -> 0
B9: Hardware | C9: $M | D9: ='00 Panel del Analista'!D20 -> 0 | E9: ='00 Panel del Analista'!E20 -> 0 | F9: ='00 Panel del Analista'!F20 -> 0
B10: Servicios | C10: $M | D10: ='00 Panel del Analista'!D21 -> 0 | E10: ='00 Panel del Analista'!E21 -> 0 | F10: ='00 Panel del Analista'!F21 -> 0
B11: Ingresos totales | C11: $M | D11: =SUM(D7:D10) -> 52961 | E11: =SUM(E7:E10) -> 57399 | F11: =SUM(F7:F10) -> 67357
B13: Coste de cloud y software | C13: $M | D13: ='00 Panel del Analista'!D24 -> 0 | E13: ='00 Panel del Analista'!E24 -> 0 | F13: ='00 Panel del Analista'!F24 -> 0
B14: Coste de hardware | C14: $M | D14: ='00 Panel del Analista'!D25 -> 0 | E14: ='00 Panel del Analista'!E25 -> 0 | F14: ='00 Panel del Analista'!F25 -> 0
B15: Coste de servicios | C15: $M | D15: ='00 Panel del Analista'!D26 -> 0 | E15: ='00 Panel del Analista'!E26 -> 0 | F15: ='00 Panel del Analista'!F26 -> 0
B16: Coste total de los ingresos | C16: $M | D16: =SUM(D13:D15) -> 15143 | E16: =SUM(E13:E15) -> 16927 | F16: =SUM(F13:F15) -> 23021
B17: Margen bruto (Gross Profit) | C17: $M | D17: =D11-D16 -> 37818 | E17: =E11-E16 -> 40472 | F17: =F11-F16 -> 44336
B18: Gross Margin | C18: % | D18: =D17/D11 -> 0.71407262 | E18: =E17/E11 -> 0.70509939 | F18: =F17/F11 -> 0.65822409
B20: Ventas y marketing | C20: $M | D20: ='00 Panel del Analista'!D31 -> 0 | E20: ='00 Panel del Analista'!E31 -> 0 | F20: ='00 Panel del Analista'!F31 -> 0
B21: Investigación y desarrollo | C21: $M | D21: ='00 Panel del Analista'!D32 -> 0 | E21: ='00 Panel del Analista'!E32 -> 0 | F21: ='00 Panel del Analista'!F32 -> 0
B22: Generales y administración | C22: $M | D22: ='00 Panel del Analista'!D33 -> 0 | E22: ='00 Panel del Analista'!E33 -> 0 | F22: ='00 Panel del Analista'!F33 -> 0
B23: Amortización de intangibles | C23: $M | D23: ='00 Panel del Analista'!D34 -> 0 | E23: ='00 Panel del Analista'!E34 -> 0 | F23: ='00 Panel del Analista'!F34 -> 0
B24: Reestructuración y otros | C24: $M | D24: ='00 Panel del Analista'!D35 -> 0 | E24: ='00 Panel del Analista'!E35 -> 0 | F24: ='00 Panel del Analista'!F35 -> 0
B25: Gastos operativos totales | C25: $M | D25: =D16+SUM(D20:D24) -> 37608 | E25: =E16+SUM(E20:E24) -> 39721 | F25: =F16+SUM(F20:F24) -> 46751
B26: EBIT (resultado operativo) reportado | C26: $M | D26: =D11-D25 -> 15353 | E26: =E11-E25 -> 17678 | F26: =F11-F25 -> 20606
B27: EBIT Margin reportado | C27: % | D27: =D26/D11 -> 0.28989256 | E27: =E26/E11 -> 0.30798446 | F27: =F26/F11 -> 0.30592218
B29: Gasto por intereses | C29: $M | D29: ='00 Panel del Analista'!D40 -> 0 | E29: ='00 Panel del Analista'!E40 -> 0 | F29: ='00 Panel del Analista'!F40 -> 0
B30: Resultado no operativo, neto | C30: $M | D30: ='00 Panel del Analista'!D41 -> 0 | E30: ='00 Panel del Analista'!E41 -> 0 | F30: ='00 Panel del Analista'!F41 -> 0
B31: Beneficio antes de impuestos | C31: $M | D31: =D26-D29+D30 -> 11741 | E31: =E26-E29+E30 -> 14160 | F31: =F26-F29+F30 -> 19554
B32: Impuesto sobre sociedades | C32: $M | D32: ='00 Panel del Analista'!D43 -> 0 | E32: ='00 Panel del Analista'!E43 -> 0 | F32: ='00 Panel del Analista'!F43 -> 0
B33: Tipo impositivo efectivo | C33: % | D33: =D32/D31 -> 0.10850864 | E33: =E32/E31 -> 0.12125706 | F33: =F32/F31 -> 0.12616344
B34: Beneficio neto | C34: $M | D34: =D31-D32 -> 10467 | E34: =E31-E32 -> 12443 | F34: =F31-F32 -> 17087
B35: Dividendos de acciones preferentes | C35: $M | D35: ='00 Panel del Analista'!D46 -> 0 | E35: ='00 Panel del Analista'!E46 -> 0 | F35: ='00 Panel del Analista'!F46 -> 0
B36: Beneficio neto atribuible a ordinarias | C36: $M | D36: =D34-D35 -> 10467 | E36: =E34-E35 -> 12443 | F36: =F34-F35 -> 16984
B37: BPA básico | C37: $/acc | D37: ='00 Panel del Analista'!D48 -> 0 | E37: ='00 Panel del Analista'!E48 -> 0 | F37: ='00 Panel del Analista'!F48 -> 0
B38: BPA diluido | C38: $/acc | D38: ='00 Panel del Analista'!D49 -> 0 | E38: ='00 Panel del Analista'!E49 -> 0 | F38: ='00 Panel del Analista'!F49 -> 0
B39: Acciones medias básicas | C39: M acc | D39: ='00 Panel del Analista'!D50 -> 0 | E39: ='00 Panel del Analista'!E50 -> 0 | F39: ='00 Panel del Analista'!F50 -> 0
B40: Acciones medias diluidas | C40: M acc | D40: ='00 Panel del Analista'!D51 -> 0 | E40: ='00 Panel del Analista'!E51 -> 0 | F40: ='00 Panel del Analista'!F51 -> 0
B42: BALANCE (a cierre de ejercicio)
B43: Caja y equivalentes | C43: $M | E43: ='00 Panel del Analista'!E54 -> 0 | F43: ='00 Panel del Analista'!F54 -> 0
B44: Valores negociables | C44: $M | E44: ='00 Panel del Analista'!E55 -> 0 | F44: ='00 Panel del Analista'!F55 -> 0
B45: Clientes, neto | C45: $M | E45: ='00 Panel del Analista'!E56 -> 0 | F45: ='00 Panel del Analista'!F56 -> 0
B46: Gastos anticipados y otros activos corrientes | C46: $M | E46: ='00 Panel del Analista'!E57 -> 0 | F46: ='00 Panel del Analista'!F57 -> 0
B47: Total activo corriente | C47: $M | E47: =SUM(E43:E46) -> 24579 | F47: =SUM(F43:F46) -> 46567
B48: Inmovilizado material (PP&E), neto | C48: $M | E48: ='00 Panel del Analista'!E59 -> 0 | F48: ='00 Panel del Analista'!F59 -> 0
B49: Activos por derecho de uso — leases operativos | C49: $M | E49: ='00 Panel del Analista'!E60 -> 0 | F49: ='00 Panel del Analista'!F60 -> 0
B50: Fondo de comercio | C50: $M | E50: ='00 Panel del Analista'!E61 -> 0 | F50: ='00 Panel del Analista'!F61 -> 0
B51: Activos por impuesto diferido | C51: $M | E51: ='00 Panel del Analista'!E62 -> 0 | F51: ='00 Panel del Analista'!F62 -> 0
B52: Otros activos no corrientes | C52: $M | E52: ='00 Panel del Analista'!E63 -> 0 | F52: ='00 Panel del Analista'!F63 -> 0
B53: Total activo no corriente | C53: $M | E53: =SUM(E48:E52) -> 143782 | F53: =SUM(F48:F52) -> 215192
B54: TOTAL ACTIVO | C54: $M | E54: =E47+E53 -> 168361 | F54: =F47+F53 -> 261759
B56: Deuda financiera corriente | C56: $M | E56: ='00 Panel del Analista'!E67 -> 0 | F56: ='00 Panel del Analista'!F67 -> 0
B57: Proveedores | C57: $M | E57: ='00 Panel del Analista'!E68 -> 0 | F57: ='00 Panel del Analista'!F68 -> 0
B58: Remuneraciones y cargas pendientes | C58: $M | E58: ='00 Panel del Analista'!E69 -> 0 | F58: ='00 Panel del Analista'!F69 -> 0
B59: Ingresos diferidos corrientes | C59: $M | E59: ='00 Panel del Analista'!E70 -> 0 | F59: ='00 Panel del Analista'!F70 -> 0
B60: Otros pasivos corrientes | C60: $M | E60: ='00 Panel del Analista'!E71 -> 0 | F60: ='00 Panel del Analista'!F71 -> 0
B61: Total pasivo corriente | C61: $M | E61: =SUM(E56:E60) -> 32643 | F61: =SUM(F56:F60) -> 41764
B62: Deuda financiera no corriente | C62: $M | E62: ='00 Panel del Analista'!E73 -> 0 | F62: ='00 Panel del Analista'!F73 -> 0
B63: Impuestos a pagar no corrientes | C63: $M | E63: ='00 Panel del Analista'!E74 -> 0 | F63: ='00 Panel del Analista'!F74 -> 0
B64: Pasivo por leases operativos no corriente | C64: $M | E64: ='00 Panel del Analista'!E75 -> 0 | F64: ='00 Panel del Analista'!F75 -> 0
B65: Otros pasivos no corrientes | C65: $M | E65: ='00 Panel del Analista'!E76 -> 0 | F65: ='00 Panel del Analista'!F76 -> 0
B66: Total pasivo no corriente | C66: $M | E66: =SUM(E62:E65) -> 114749 | F66: =SUM(F62:F65) -> 176939
B67: Acciones preferentes convertibles obligatorias (Serie D 6,50%) | C67: $M | E67: ='00 Panel del Analista'!E78 -> 0 | F67: ='00 Panel del Analista'!F78 -> 0
B68: Capital social y prima de emisión | C68: $M | E68: ='00 Panel del Analista'!E79 -> 0 | F68: ='00 Panel del Analista'!F79 -> 0
B69: Resultados acumulados (déficit) | C69: $M | E69: ='00 Panel del Analista'!E80 -> 0 | F69: ='00 Panel del Analista'!F80 -> 0
B70: Otro resultado global acumulado | C70: $M | E70: ='00 Panel del Analista'!E81 -> 0 | F70: ='00 Panel del Analista'!F81 -> 0
B71: Patrimonio atribuible a Oracle | C71: $M | E71: =SUM(E67:E70) -> 20451 | F71: =SUM(F67:F70) -> 42508
B72: Intereses minoritarios | C72: $M | E72: ='00 Panel del Analista'!E83 -> 0 | F72: ='00 Panel del Analista'!F83 -> 0
B73: Total patrimonio neto | C73: $M | E73: =E71+E72 -> 20969 | F73: =F71+F72 -> 43056
B74: TOTAL PASIVO Y PATRIMONIO | C74: $M | E74: =E61+E66+E73 -> 168361 | F74: =F61+F66+F73 -> 261759
B75: CHECK: Activo − Pasivo y Patrimonio (debe ser 0) | C75: $M | E75: =E54-E74 -> 0 | F75: =F54-F74 -> 0
B77: ESTADO DE FLUJOS DE CAJA
B78: Beneficio neto | C78: $M | D78: =D34 -> 10467 | E78: =E34 -> 12443 | F78: =F34 -> 17087
B79: Depreciación | C79: $M | D79: ='00 Panel del Analista'!D90 -> 0 | E79: ='00 Panel del Analista'!E90 -> 0 | F79: ='00 Panel del Analista'!F90 -> 0
B80: Amortización de intangibles | C80: $M | D80: =D23 -> 3010 | E80: =E23 -> 2307 | F80: =F23 -> 1671
B81: Impuestos diferidos | C81: $M | D81: ='00 Panel del Analista'!D92 -> 0 | E81: ='00 Panel del Analista'!E92 -> 0 | F81: ='00 Panel del Analista'!F92 -> 0
B82: Retribución basada en acciones (SBC) | C82: $M | D82: ='00 Panel del Analista'!D93 -> 0 | E82: ='00 Panel del Analista'!E93 -> 0 | F82: ='00 Panel del Analista'!F93 -> 0
B83: Resultados de inversiones y otros, neto | C83: $M | D83: ='00 Panel del Analista'!D94 -> 0 | E83: ='00 Panel del Analista'!E94 -> 0 | F83: ='00 Panel del Analista'!F94 -> 0
B84: Variación de circulante y otras partidas operativas (derivado) | C84: $M | D84: =D85-SUM(D78:D83) -> 952 | E84: =E85-SUM(E78:E83) -> -166 | F84: =F85-SUM(F78:F83) -> -731
B85: FLUJO DE CAJA OPERATIVO (CFO) — reportado | C85: $M | D85: ='00 Panel del Analista'!D96 -> 0 | E85: ='00 Panel del Analista'!E96 -> 0 | F85: ='00 Panel del Analista'!F96 -> 0
B87: Capex (adquisición de inmovilizado) | C87: $M | D87: ='00 Panel del Analista'!D98 -> 0 | E87: ='00 Panel del Analista'!E98 -> 0 | F87: ='00 Panel del Analista'!F98 -> 0
B88: Compras de inversiones y adquisiciones | C88: $M | D88: ='00 Panel del Analista'!D99 -> 0 | E88: ='00 Panel del Analista'!E99 -> 0 | F88: ='00 Panel del Analista'!F99 -> 0
B89: Cobros por ventas y vencimientos de inversiones | C89: $M | D89: ='00 Panel del Analista'!D100 -> 0 | E89: ='00 Panel del Analista'!E100 -> 0 | F89: ='00 Panel del Analista'!F100 -> 0
B90: Otros de inversión (derivado) | C90: $M | D90: =D91-SUM(D87:D89) -> 0 | E90: =E91-SUM(E87:E89) -> 0 | F90: =F91-SUM(F87:F89) -> 0
B91: FLUJO DE CAJA DE INVERSIÓN (CFI) — reportado | C91: $M | D91: ='00 Panel del Analista'!D102 -> 0 | E91: ='00 Panel del Analista'!E102 -> 0 | F91: ='00 Panel del Analista'!F102 -> 0
B93: Emisión de acciones ordinarias | C93: $M | D93: ='00 Panel del Analista'!D104 -> 0 | E93: ='00 Panel del Analista'!E104 -> 0 | F93: ='00 Panel del Analista'!F104 -> 0
B94: Recompra de acciones ordinarias | C94: $M | D94: ='00 Panel del Analista'!D105 -> 0 | E94: ='00 Panel del Analista'!E105 -> 0 | F94: ='00 Panel del Analista'!F105 -> 0
B95: Acciones retenidas por impuestos en el vesting | C95: $M | D95: ='00 Panel del Analista'!D106 -> 0 | E95: ='00 Panel del Analista'!E106 -> 0 | F95: ='00 Panel del Analista'!F106 -> 0
B96: Emisión de preferentes convertibles obligatorias | C96: $M | D96: ='00 Panel del Analista'!D107 -> 0 | E96: ='00 Panel del Analista'!E107 -> 0 | F96: ='00 Panel del Analista'!F107 -> 0
B97: Dividendos pagados | C97: $M | D97: ='00 Panel del Analista'!D108 -> 0 | E97: ='00 Panel del Analista'!E108 -> 0 | F97: ='00 Panel del Analista'!F108 -> 0
B98: Papel comercial, neto | C98: $M | D98: ='00 Panel del Analista'!D109 -> 0 | E98: ='00 Panel del Analista'!E109 -> 0 | F98: ='00 Panel del Analista'!F109 -> 0
B99: Financiación a corto plazo ligada a capex, neto | C99: $M | D99: ='00 Panel del Analista'!D110 -> 0 | E99: ='00 Panel del Analista'!E110 -> 0 | F99: ='00 Panel del Analista'!F110 -> 0
B100: Emisión de deuda a largo plazo y préstamos | C100: $M | D100: ='00 Panel del Analista'!D111 -> 0 | E100: ='00 Panel del Analista'!E111 -> 0 | F100: ='00 Panel del Analista'!F111 -> 0
B101: Repago de deuda | C101: $M | D101: ='00 Panel del Analista'!D112 -> 0 | E101: ='00 Panel del Analista'!E112 -> 0 | F101: ='00 Panel del Analista'!F112 -> 0
B102: Otros de financiación, neto | C102: $M | D102: ='00 Panel del Analista'!D113 -> 0 | E102: ='00 Panel del Analista'!E113 -> 0 | F102: ='00 Panel del Analista'!F113 -> 0
B103: FLUJO DE CAJA DE FINANCIACIÓN (CFF) — calculado | C103: $M | D103: =SUM(D93:D102) -> -10554 | E103: =SUM(E93:E102) -> 1098 | F103: =SUM(F93:F102) -> 40284
B104: CFF reportado en el 10-K | C104: $M | E104: ='00 Panel del Analista'!E115 -> 0 | F104: ='00 Panel del Analista'!F115 -> 0
B105: CHECK: CFF calculado − CFF reportado (debe ser 0) | C105: $M | E105: =E103-E104 -> 0 | F105: =F103-F104 -> 0
B106: Variación neta de caja (CFO+CFI+CFF) | C106: $M | D106: =D85+D91+D103 -> 759 | E106: =E85+E91+E103 -> 208 | F106: =F85+F91+F103 -> 20407
B107: Efecto tipo de cambio (derivado como diferencia) | C107: $M | F107: =F43-E43-F106 -> 96
B109: MEMORIA — DEUDA, ARRENDAMIENTOS Y BACKLOG
B110: Deuda financiera total (senior notes y otros préstamos) | C110: $M | E110: ='00 Panel del Analista'!E121 -> 0 | F110: ='00 Panel del Analista'!F121 -> 0
B111: CHECK: deuda total − (corriente + no corriente) del balance | C111: $M | E111: =E110-E56-E62 -> 0 | F111: =F110-F56-F62 -> 0
...

Sheet 04 Operating Model
A1: MODELO OPERATIVO FY2027E–FY2036E — ORACLE CORPORATION
A2: USD millones. Toda hipótesis procede de '02 Assumptions'. Esta hoja NO contiene hipótesis propias. Verde = enlace; negro = fórmula.
B4: Partida | C4: Unidad | D4: ='00 Panel del Analista'!D14 -> 0 | E4: ='00 Panel del Analista'!E14 -> 0 | F4: ='00 Panel del Analista'!F14 -> 0 | G4: ='00 Panel del Analista'!G14 -> 0 | H4: ='00 Panel del Analista'!H14 -> 0 | I4: ='00 Panel del Analista'!I14 -> 0 | J4: ='00 Panel del Analista'!J14 -> 0 | K4: ='00 Panel del Analista'!K14 -> 0 | ... P4: ='00 Panel del Analista'!P14 -> 0
B6: INGRESOS POR SEGMENTO
B7: Cloud | C7: $M | D7: ='03 Historical'!D7 -> 19774 | E7: ='03 Historical'!E7 -> 24506 | F7: ='03 Historical'!F7 -> 33989 | G7: =F7*(1+'02 Assumptions'!G20) -> 50983.5 | H7: =G7*(1+'02 Assumptions'!H20) -> 70357.23 | I7: =H7*(1+'02 Assumptions'!I20) -> 90057.254 | J7: =I7*(1+'02 Assumptions'!J20) -> 108969.28 | K7: =J7*(1+'02 Assumptions'!K20) -> 126404.36 | L7: =K7*(1+'02 Assumptions'!L20) -> 141572.89 | M7: =L7*(1+'02 Assumptions'!M20) -> 154314.45 | N7: =M7*(1+'02 Assumptions'!N20) -> 165116.46 | ... P7: =O7*(1+'02 Assumptions'!P20) -> 180307.17
B8: Software (licencias y soporte) | C8: $M | D8: ='03 Historical'!D8 -> 24690 | E8: ='03 Historical'!E8 -> 24724 | F8: ='03 Historical'!F8 -> 24541 | G8: =F8*(1+'02 Assumptions'!G22) -> 24541 | H8: =G8*(1+'02 Assumptions'!H22) -> 24295.59 | I8: =H8*(1+'02 Assumptions'!I22) -> 24052.634 | J8: =I8*(1+'02 Assumptions'!J22) -> 24052.634 | K8: =J8*(1+'02 Assumptions'!K22) -> 24052.634 | L8: =K8*(1+'02 Assumptions'!L22) -> 24293.16 | M8: =L8*(1+'02 Assumptions'!M22) -> 24536.092 | N8: =M8*(1+'02 Assumptions'!N22) -> 24781.453 | ... P8: =O8*(1+'02 Assumptions'!P22) -> 25279.56
B9: Hardware | C9: $M | D9: ='03 Historical'!D9 -> 3066 | E9: ='03 Historical'!E9 -> 2936 | F9: ='03 Historical'!F9 -> 3084 | G9: =F9*(1+'02 Assumptions'!G24) -> 3022.32 | H9: =G9*(1+'02 Assumptions'!H24) -> 2961.8736 | I9: =H9*(1+'02 Assumptions'!I24) -> 2932.2549 | J9: =I9*(1+'02 Assumptions'!J24) -> 2902.9323 | K9: =J9*(1+'02 Assumptions'!K24) -> 2902.9323 | L9: =K9*(1+'02 Assumptions'!L24) -> 2902.9323 | M9: =L9*(1+'02 Assumptions'!M24) -> 2902.9323 | N9: =M9*(1+'02 Assumptions'!N24) -> 2902.9323 | ... P9: =O9*(1+'02 Assumptions'!P24) -> 2902.9323
B10: Servicios | C10: $M | D10: ='03 Historical'!D10 -> 5431 | E10: ='03 Historical'!E10 -> 5233 | F10: ='03 Historical'!F10 -> 5743 | G10: =F10*(1+'02 Assumptions'!G26) -> 6202.44 | H10: =G10*(1+'02 Assumptions'!H26) -> 6636.6108 | I10: =H10*(1+'02 Assumptions'!I26) -> 7034.8074 | J10: =I10*(1+'02 Assumptions'!J26) -> 7386.5478 | K10: =J10*(1+'02 Assumptions'!K26) -> 7682.0097 | L10: =K10*(1+'02 Assumptions'!L26) -> 7912.47 | M10: =L10*(1+'02 Assumptions'!M26) -> 8149.8441 | N10: =M10*(1+'02 Assumptions'!N26) -> 8394.3394 | ... P10: =O10*(1+'02 Assumptions'!P26) -> 8905.5547
B11: INGRESOS TOTALES | C11: $M | D11: =SUM(D7:D10) -> 52961 | E11: =SUM(E7:E10) -> 57399 | F11: =SUM(F7:F10) -> 67357 | G11: =SUM(G7:G10) -> 84749.26 | H11: =SUM(H7:H10) -> 104251.3 | I11: =SUM(I7:I10) -> 124076.95 | J11: =SUM(J7:J10) -> 143311.39 | K11: =SUM(K7:K10) -> 161041.94 | ... P11: =SUM(P7:P10) -> 217395.22
B12: Crecimiento de ingresos | C12: % | E12: =E11/D11-1 -> 0.083797511 | F12: =F11/E11-1 -> 0.17348734 | G12: =G11/F11-1 -> 0.25821013 | H12: =H11/G11-1 -> 0.23011463 | I12: =I11/H11-1 -> 0.19017169 | J12: =J11/I11-1 -> 0.15502026 | K12: =K11/J11-1 -> 0.12372043 | L12: =L11/K11-1 -> 0.097114517 | ... P12: =P11/O11-1 -> 0.035458661
B13: Mix: Cloud / ingresos totales | C13: % | D13: =D7/D11 -> 0.37336908 | E13: =E7/E11 -> 0.42694124 | F13: =F7/F11 -> 0.50460977 | G13: =G7/G11 -> 0.60158047 | H13: =H7/H11 -> 0.67488105 | I13: =I7/I11 -> 0.72581776 | J13: =J7/J11 -> 0.76036717 | K13: =K7/K11 -> 0.7849158 | ... P13: =P7/P11 -> 0.82939805
B15: MARGEN BRUTO
B16: Gross Margin | C16: % | D16: ='03 Historical'!D18 -> 0.71407262 | E16: ='03 Historical'!E18 -> 0.70509939 | F16: ='03 Historical'!F18 -> 0.65822409 | G16: ='02 Assumptions'!G30 -> 0.61 | H16: ='02 Assumptions'!H30 -> 0.58 | I16: ='02 Assumptions'!I30 -> 0.565 | J16: ='02 Assumptions'!J30 -> 0.56 | K16: ='02 Assumptions'!K30 -> 0.56 | L16: ='02 Assumptions'!L30 -> 0.565 | M16: ='02 Assumptions'!M30 -> 0.57 | N16: ='02 Assumptions'!N30 -> 0.575 | ... P16: ='02 Assumptions'!P30 -> 0.58
B17: Margen bruto (Gross Profit) | C17: $M | D17: ='03 Historical'!D17 -> 37818 | E17: ='03 Historical'!E17 -> 40472 | F17: ='03 Historical'!F17 -> 44336 | G17: =G11*G16 -> 51697.049 | H17: =H11*H16 -> 60465.757 | I17: =I11*I16 -> 70103.477 | J17: =J11*J16 -> 80254.38 | K17: =K11*K16 -> 90183.486 | L17: =L11*L16 -> 99825.018 | M17: =M11*M16 -> 108244.89 | N17: =N11*N16 -> 115687.23 | ... P17: =P11*P16 -> 126089.23
B18: Coste de los ingresos | C18: $M | D18: ='03 Historical'!D16 -> 15143 | E18: ='03 Historical'!E16 -> 16927 | F18: ='03 Historical'!F16 -> 23021 | G18: =G11-G17 -> 33052.211 | H18: =H11-H17 -> 43785.548 | I18: =I11-I17 -> 53973.474 | J18: =J11-J17 -> 63057.013 | K18: =K11-K17 -> 70858.453 | L18: =L11-L17 -> 76856.43 | M18: =M11-M17 -> 81658.425 | N18: =N11-N17 -> 85507.952 | ... P18: =P11-P17 -> 91305.992
B20: GASTOS OPERATIVOS (por debajo del margen bruto)
B21: Ventas y marketing | C21: $M | D21: ='03 Historical'!D20 -> 8274 | E21: ='03 Historical'!E20 -> 8651 | F21: ='03 Historical'!F20 -> 8331 | G21: =G11*'02 Assumptions'!G32 -> 10169.911 | H21: =H11*'02 Assumptions'!H32 -> 11780.397 | I21: =I11*'02 Assumptions'!I32 -> 13400.311 | J21: =J11*'02 Assumptions'!J32 -> 14904.385 | K21: =K11*'02 Assumptions'!K32 -> 16265.236 | L21: =L11*'02 Assumptions'!L32 -> 17491.463 | M21: =M11*'02 Assumptions'!M32 -> 18610.525 | N21: =N11*'02 Assumptions'!N32 -> 19515.933 | ... P21: =P11*'02 Assumptions'!P32 -> 21087.336
B22: Investigación y desarrollo | C22: $M | D22: ='03 Historical'!D21 -> 8915 | E22: ='03 Historical'!E21 -> 9860 | F22: ='03 Historical'!F21 -> 10272 | G22: =G11*'02 Assumptions'!G34 -> 12288.643 | H22: =H11*'02 Assumptions'!H34 -> 14595.183 | I22: =I11*'02 Assumptions'!I34 -> 16874.465 | J22: =J11*'02 Assumptions'!J34 -> 19060.415 | K22: =K11*'02 Assumptions'!K34 -> 21096.494 | L22: =L11*'02 Assumptions'!L34 -> 22968.588 | M22: =M11*'02 Assumptions'!M34 -> 24497.527 | N22: =N11*'02 Assumptions'!N34 -> 25752.983 | ... P22: =P11*'02 Assumptions'!P34 -> 27826.588
B23: Generales y administración | C23: $M | D23: ='03 Historical'!D22 -> 1548 | E23: ='03 Historical'!E22 -> 1602 | F23: ='03 Historical'!F22 -> 1618 | G23: =G11*'02 Assumptions'!G36 -> 1864.4837 | H23: =H11*'02 Assumptions'!H36 -> 2189.2774 | I23: =I11*'02 Assumptions'!I36 -> 2481.539 | J23: =J11*'02 Assumptions'!J36 -> 2722.9164 | K23: =K11*'02 Assumptions'!K36 -> 3059.7968 | L23: =L11*'02 Assumptions'!L36 -> 3180.2661 | M23: =M11*'02 Assumptions'!M36 -> 3418.2597 | N23: =N11*'02 Assumptions'!N36 -> 3621.5133 | ... P23: =P11*'02 Assumptions'!P36 -> 3913.1139
B24: Amortización de intangibles adquiridos | C24: $M | D24: ='03 Historical'!D23 -> 3010 | E24: ='03 Historical'!E23 -> 2307 | F24: ='03 Historical'!F23 -> 1671 | G24: ='02 Assumptions'!G37 -> 1300 | H24: ='02 Assumptions'!H37 -> 1000 | I24: ='02 Assumptions'!I37 -> 750 | J24: ='02 Assumptions'!J37 -> 550 | K24: ='02 Assumptions'!K37 -> 400 | L24: ='02 Assumptions'!L37 -> 300 | M24: ='02 Assumptions'!M37 -> 220 | N24: ='02 Assumptions'!N37 -> 160 | ... P24: ='02 Assumptions'!P37 -> 90
B25: Reestructuración (normalizada) | C25: $M | D25: ='03 Historical'!D24 -> 718 | E25: ='03 Historical'!E24 -> 374 | F25: ='03 Historical'!F24 -> 1838 | G25: ='02 Assumptions'!G38 -> 600 | H25: ='02 Assumptions'!H38 -> 450 | I25: ='02 Assumptions'!I38 -> 350 | J25: ='02 Assumptions'!J38 -> 300 | K25: ='02 Assumptions'!K38 -> 250 | L25: ='02 Assumptions'!L38 -> 250 | M25: ='02 Assumptions'!M38 -> 250 | N25: ='02 Assumptions'!N38 -> 250 | ... P25: ='02 Assumptions'!P38 -> 250
B26: Total gastos operativos | C26: $M | D26: =SUM(D21:D25) -> 22465 | E26: =SUM(E21:E25) -> 22794 | F26: =SUM(F21:F25) -> 23730 | G26: =SUM(G21:G25) -> 26223.038 | H26: =SUM(H21:H25) -> 30014.857 | I26: =SUM(I21:I25) -> 33856.315 | J26: =SUM(J21:J25) -> 37537.716 | K26: =SUM(K21:K25) -> 41071.527 | ... P26: =SUM(P21:P25) -> 53167.038
B27: EBIT reportado | C27: $M | D27: =D17-D26 -> 15353 | E27: =E17-E26 -> 17678 | F27: =F17-F26 -> 20606 | G27: =G17-G26 -> 25474.011 | H27: =H17-H26 -> 30450.899 | I27: =I17-I26 -> 36247.162 | J27: =J17-J26 -> 42716.663 | K27: =K17-K26 -> 49111.959 | ... P27: =P17-P26 -> 72922.188
B28: EBIT Margin reportado | C28: % | D28: =D27/D11 -> 0.28989256 | E28: =E27/E11 -> 0.30798446 | F28: =F27/F11 -> 0.30592218 | G28: =G27/G11 -> 0.30058093 | H28: =H27/H11 -> 0.2920913 | I28: =I27/I11 -> 0.29213453 | J28: =J27/J11 -> 0.29806886 | K28: =K27/K11 -> 0.30496378 | ... P28: =P27/P11 -> 0.33543603
B29: EBIT NORMALIZADO (excluye reestructuración) | C29: $M | D29: =D27+D25 -> 16071 | E29: =E27+E25 -> 18052 | F29: =F27+F25 -> 22444 | G29: =G27+G25 -> 26074.011 | H29: =H27+H25 -> 30900.899 | I29: =I27+I25 -> 36597.162 | J29: =J27+J25 -> 43016.663 | K29: =K27+K25 -> 49361.959 | ... P29: =P27+P25 -> 73172.188
B30: Margen EBIT normalizado | C30: % | D30: =D29/D11 -> 0.30344971 | E30: =E29/E11 -> 0.31450025 | F30: =F29/F11 -> 0.33320961 | G30: =G29/G11 -> 0.30766063 | H30: =H29/H11 -> 0.29640779 | I30: =I29/I11 -> 0.29495536 | J30: =J29/J11 -> 0.3001622 | K30: =K29/K11 -> 0.30651617 | ... P30: =P29/P11 -> 0.33658601
B32: CAPEX Y DEPRECIACIÓN — ROLL-FORWARD DE PP&E
B33: PP&E neto inicial | C33: $M | F33: ='03 Historical'!E48 -> 43522 | G33: =F37 -> 99957 | H33: =G37 -> 135133.83 | I33: =H37 -> 157336.34 | J33: =I37 -> 170239.5 | K33: =J37 -> 177173.99 | L33: =K37 -> 179183.53 | M33: =L37 -> 179975.03 | N33: =M37 -> 180622.62 | ... P33: =O37 -> 182539.01
B34: Capex | C34: $M | D34: ='03 Historical'!D129 -> 6866 | E34: ='03 Historical'!E129 -> 21215 | F34: ='03 Historical'!F129 -> 55663 | G34: =G11*'02 Assumptions'!G42 -> 50849.556 | H34: =H11*'02 Assumptions'!H42 -> 41700.522 | I34: =I11*'02 Assumptions'!I42 -> 34741.546 | J34: =J11*'02 Assumptions'!J42 -> 30095.392 | K34: =K11*'02 Assumptions'!K42 -> 25766.71 | L34: =L11*'02 Assumptions'!L42 -> 24735.403 | M34: =M11*'02 Assumptions'!M42 -> 24687.431 | N34: =N11*'02 Assumptions'!N42 -> 25149.398 | ... P34: =P11*'02 Assumptions'!P42 -> 25652.636
B35: Capex / Ingresos | C35: % | D35: =D34/D11 -> 0.12964257 | E35: =E34/E11 -> 0.36960574 | F35: =F34/F11 -> 0.82638775 | G35: =G34/G11 -> 0.6 | H35: =H34/H11 -> 0.4 | I35: =I34/I11 -> 0.28 | J35: =J34/J11 -> 0.21 | K35: =K34/K11 -> 0.16 | ... P35: =P34/P11 -> 0.118
B36: Depreciación = (PP&E inicial + Capex/2) / vida útil | C36: $M | D36: ='03 Historical'!D79 -> 3129 | E36: ='03 Historical'!E79 -> 3867 | F36: ='03 Historical'!F79 -> 7623 | G36: =(G33+G34/2)/'02 Assumptions'!$C$43 -> 15672.722 | H36: =(H33+H34/2)/'02 Assumptions'!$C$43 -> 19498.012 | I36: =(I33+I34/2)/'02 Assumptions'!$C$43 -> 21838.39 | J36: =(J33+J34/2)/'02 Assumptions'!$C$43 -> 23160.9 | K36: =(K33+K34/2)/'02 Assumptions'!$C$43 -> 23757.169 | L36: =(L33+L34/2)/'02 Assumptions'!$C$43 -> 23943.905 | M36: =(M33+M34/2)/'02 Assumptions'!$C$43 -> 24039.844 | N36: =(N33+N34/2)/'02 Assumptions'!$C$43 -> 24149.665 | ... P36: =(P33+P34/2)/'02 Assumptions'!$C$43 -> 24420.666
B37: PP&E neto final | C37: $M | E37: ='03 Historical'!E48 -> 43522 | F37: ='03 Historical'!F48 -> 99957 | G37: =G33+G34-G36 -> 135133.83 | H37: =H33+H34-H36 -> 157336.34 | I37: =I33+I34-I36 -> 170239.5 | J37: =J33+J34-J36 -> 177173.99 | K37: =K33+K34-K36 -> 179183.53 | L37: =L33+L34-L36 -> 179975.03 | M37: =M33+M34-M36 -> 180622.62 | N37: =N33+N34-N36 -> 181622.35 | ... P37: =P33+P34-P36 -> 183770.98
B38: D&A total (depreciación + amortización de intangibles) | C38: $M | D38: =D36+D24 -> 6139 | E38: =E36+E24 -> 6174 | F38: =F36+F24 -> 9294 | G38: =G36+G24 -> 16972.722 | H38: =H36+H24 -> 20498.012 | I38: =I36+I24 -> 22588.39 | J38: =J36+J24 -> 23710.9 | K38: =K36+K24 -> 24157.169 | ... P38: =P36+P24 -> 24510.666
B39: EBITDA (EBIT normalizado + D&A) | C39: $M | D39: =D29+D38 -> 22210 | E39: =E29+E38 -> 24226 | F39: =F29+F38 -> 31738 | G39: =G29+G38 -> 43046.733 | H39: =H29+H38 -> 51398.911 | I39: =I29+I38 -> 59185.552 | J39: =J29+J38 -> 66727.563 | K39: =K29+K38 -> 73519.127 | ... P39: =P29+P38 -> 97682.854
B40: EBITDA Margin | C40: % | D40: =D39/D11 -> 0.41936519 | E40: =E39/E11 -> 0.4220631 | F40: =F39/F11 -> 0.47119082 | G40: =G39/G11 -> 0.50793049 | H40: =H39/H11 -> 0.49302895 | I40: =I39/I11 -> 0.47700682 | J40: =J39/J11 -> 0.46561241 | K40: =K39/K11 -> 0.45652163 | ... P40: =P39/P11 -> 0.44933304
B41: Capex / D&A | C41: x | D41: =D34/D38 -> 1.1184232 | E41: =E34/E38 -> 3.436184 | F41: =F34/F38 -> 5.9891328 | G41: =G34/G38 -> 2.9959576 | H41: =H34/H38 -> 2.0343691 | I41: =I34/I38 -> 1.5380267 | J41: =J34/J38 -> 1.269264 | K41: =K34/K38 -> 1.0666279 | ... P41: =P34/P38 -> 1.0465907
B43: CIRCULANTE OPERATIVO (drivers: DSO, proveedores sobre coste+capex, ingresos diferidos)
B44: Clientes (AR) | C44: $M | E44: ='03 Historical'!E45 -> 8558 | F44: ='03 Historical'!F45 -> 10385 | G44: ='02 Assumptions'!G48/365*G11 -> 13002.626 | H44: ='02 Assumptions'!H48/365*H11 -> 15709.101 | I44: ='02 Assumptions'!I48/365*I11 -> 18356.59 | J44: ='02 Assumptions'!J48/365*J11 -> 20809.599 | K44: ='02 Assumptions'!K48/365*K11 -> 22942.961 | L44: ='02 Assumptions'!L48/365*L11 -> 25171.056 | M44: ='02 Assumptions'!M48/365*M11 -> 27054.719 | N44: ='02 Assumptions'!N48/365*N11 -> 28663.423 | ... P44: ='02 Assumptions'!P48/365*P11 -> 30971.374
B45: Otros activos corrientes | C45: $M | E45: ='03 Historical'!E46 -> 4818 | F45: ='03 Historical'!F46 -> 4288 | G45: =G11*'02 Assumptions'!G51 -> 5254.4541 | H45: =H11*'02 Assumptions'!H51 -> 6255.0783 | I45: =I11*'02 Assumptions'!I51 -> 7320.5401 | J45: =J11*'02 Assumptions'!J51 -> 8312.0607 | K45: =K11*'02 Assumptions'!K51 -> 9340.4324 | L45: =L11*'02 Assumptions'!L51 -> 10247.524 | M45: =M11*'02 Assumptions'!M51 -> 11014.392 | N45: =N11*'02 Assumptions'!N51 -> 11669.321 | ... P45: =P11*'02 Assumptions'!P51 -> 12608.923
B46: Proveedores | C46: $M | E46: ='03 Historical'!E57 -> 5113 | F46: ='03 Historical'!F57 -> 10977 | G46: =(G18+G34)*'02 Assumptions'!G49 -> 11326.739 | H46: =(H18+H34)*'02 Assumptions'!H49 -> 11540.619 | I46: =(I18+I34)*'02 Assumptions'!I49 -> 11976.528 | J46: =(J18+J34)*'02 Assumptions'!J49 -> 12575.575 | K46: =(K18+K34)*'02 Assumptions'!K49 -> 13044.397 | L46: =(L18+L34)*'02 Assumptions'!L49 -> 13714.897 | M46: =(M18+M34)*'02 Assumptions'!M49 -> 14356.691 | N46: =(N18+N34)*'02 Assumptions'!N49 -> 14938.742 | ... P46: =(P18+P34)*'02 Assumptions'!P49 -> 15789.415
B47: Remuneraciones pendientes | C47: $M | E47: ='03 Historical'!E58 -> 2243 | F47: ='03 Historical'!F58 -> 2225 | G47: =G11*'02 Assumptions'!G52 -> 2711.9763 | H47: =H11*'02 Assumptions'!H52 -> 3231.7904 | I47: =I11*'02 Assumptions'!I52 -> 3846.3855 | J47: =J11*'02 Assumptions'!J52 -> 4299.3418 | K47: =K11*'02 Assumptions'!K52 -> 4831.2582 | L47: =L11*'02 Assumptions'!L52 -> 5300.4435 | M47: =M11*'02 Assumptions'!M52 -> 5697.0994 | N47: =N11*'02 Assumptions'!N52 -> 6035.8554 | ... P47: =P11*'02 Assumptions'!P52 -> 6521.8565
B48: Ingresos diferidos corrientes | C48: $M | E48: ='03 Historical'!E59 -> 9387 | F48: ='03 Historical'!F59 -> 9916 | G48: =G11*'02 Assumptions'!G50 -> 12203.893 | H48: =H11*'02 Assumptions'!H50 -> 14595.183 | I48: =I11*'02 Assumptions'!I50 -> 16874.465 | J48: =J11*'02 Assumptions'!J50 -> 18917.104 | K48: =K11*'02 Assumptions'!K50 -> 20613.368 | L48: =L11*'02 Assumptions'!L50 -> 22085.181 | M48: =M11*'02 Assumptions'!M50 -> 23168.204 | N48: =N11*'02 Assumptions'!N50 -> 24143.422 | ... P48: =P11*'02 Assumptions'!P50 -> 26087.426
B49: Otros pasivos corrientes operativos (excl. leases financieros) | C49: $M | E49: ='03 Historical'!E60-'03 Historical'!E119 -> 8372 | F49: ='03 Historical'!F60-'03 Historical'!F119 -> 10827 | G49: =G11*'02 Assumptions'!G53 -> 13559.882 | H49: =H11*'02 Assumptions'!H53 -> 16471.706 | I49: =I11*'02 Assumptions'!I53 -> 19356.004 | J49: =J11*'02 Assumptions'!J53 -> 22069.954 | K49: =K11*'02 Assumptions'!K53 -> 24478.375 | L49: =L11*'02 Assumptions'!L53 -> 26502.217 | M49: =M11*'02 Assumptions'!M53 -> 28485.497 | N49: =N11*'02 Assumptions'!N53 -> 30179.277 | ... P49: =P11*'02 Assumptions'!P53 -> 32609.283
B50: CAPITAL CIRCULANTE NETO (NWC) | C50: $M | E50: =E44+E45-E46-E47-E48-E49 -> -11739 | F50: =F44+F45-F46-F47-F48-F49 -> -19272 | G50: =G44+G45-G46-G47-G48-G49 -> -21545.41 | H50: =H44+H45-H46-H47-H48-H49 -> -23875.12 | I50: =I44+I45-I46-I47-I48-I49 -> -26376.253 | J50: =J44+J45-J46-J47-J48-J49 -> -28740.314 | K50: =K44+K45-K46-K47-K48-K49 -> -30684.004 | L50: =L44+L45-L46-L47-L48-L49 -> -32184.16 | ... P50: =P44+P45-P46-P47-P48-P49 -> -37427.684
B51: Variación del NWC (ΔNWC) — positivo = consume caja | C51: $M | F51: =F50-E50 -> -7533 | G51: =G50-F50 -> -2273.4096 | H51: =H50-G50 -> -2329.71 | I51: =I50-H50 -> -2501.1331 | J51: =J50-I50 -> -2364.0617 | K51: =K50-J50 -> -1943.69 | L51: =L50-K50 -> -1500.1551 | M51: =M50-L50 -> -1454.2209 | ... P51: =P50-O50 -> -1225.0019
B52: NWC / Ingresos | C52: % | E52: =E50/E11 -> -0.20451576 | F52: =F50/F11 -> -0.28611726 | G52: =G50/G11 -> -0.25422534 | H52: =H50/H11 -> -0.22901507 | I52: =I50/I11 -> -0.21257979 | J52: =J50/J11 -> -0.20054452 | K52: =K50/K11 -> -0.19053425 | L52: =L50/L11 -> -0.18215925 | ... P52: =P50/P11 -> -0.17216425
B54: IMPUESTOS SOBRE EL EBIT
B55: Tipo impositivo de caja | C55: % | D55: ='03 Historical'!D33 -> 0.10850864 | E55: ='03 Historical'!E33 -> 0.12125706 | F55: ='03 Historical'!F33 -> 0.12616344 | G55: ='02 Assumptions'!G57 -> 0.14 | H55: ='02 Assumptions'!H57 -> 0.15 | I55: ='02 Assumptions'!I57 -> 0.16 | J55: ='02 Assumptions'!J57 -> 0.17 | K55: ='02 Assumptions'!K57 -> 0.18 | L55: ='02 Assumptions'!L57 -> 0.19 | M55: ='02 Assumptions'!M57 -> 0.19 | N55: ='02 Assumptions'!N57 -> 0.19 | ... P55: ='02 Assumptions'!P57 -> 0.19
B56: Impuestos sobre el EBIT normalizado | C56: $M | D56: =D29*D55 -> 1743.8424 | E56: =E29*E55 -> 2188.9325 | F56: =F29*F55 -> 2831.6124 | G56: =G29*G55 -> 3650.3615 | H56: =H29*H55 -> 4635.1349 | I56: =I29*I55 -> 5855.546 | J56: =J29*J55 -> 7312.8327 | K56: =K29*K55 -> 8885.1526 | ... P56: =P29*P55 -> 13902.716
B57: NOPAT (EBIT normalizado − impuestos) | C57: $M | D57: =D29-D56 -> 14327.158 | E57: =E29-E56 -> 15863.068 | F57: =F29-F56 -> 19612.388 | G57: =G29-G56 -> 22423.649 | H57: =H29-H56 -> 26265.764 | I57: =I29-I56 -> 30741.616 | J57: =J29-J56 -> 35703.83 | K57: =K29-K56 -> 40476.806 | ... P57: =P29-P56 -> 59269.473
B59: COMPROBACIONES DE COHERENCIA INTERNA
B60: Ingresos Cloud acumulados del forecast | C60: $M | G60: =SUM($G$7:G7) -> 50983.5 | H60: =SUM($G$7:H7) -> 121340.73 | I60: =SUM($G$7:I7) -> 211397.98 | J60: =SUM($G$7:J7) -> 320367.26 | K60: =SUM($G$7:K7) -> 446771.62 | L60: =SUM($G$7:L7) -> 588344.51 | M60: =SUM($G$7:M7) -> 742658.96 | N60: =SUM($G$7:N7) -> 907775.41 | ... P60: =SUM($G$7:P7) -> 1261454.9
B61: RPO reportado a 31/05/2026 | C61: $M | F61: ='03 Historical'!F117 -> 638000
B62: Cloud acumulado / RPO — si supera el 100% el crecimiento exige contratación NUEVA | C62: % | G62: =G60/$F$61 -> 0.079911442 | H62: =H60/$F$61 -> 0.19018923 | I62: =I60/$F$61 -> 0.3313448 | J62: =J60/$F$61 -> 0.50214304 | K62: =K60/$F$61 -> 0.700269 | L62: =L60/$F$61 -> 0.92217008 | M62: =M60/$F$61 -> 1.1640423 | N62: =N60/$F$61 -> 1.4228455 | ... P62: =P60/$F$61 -> 1.977202
B63: Capital invertido (PP&E + NWC + fondo de comercio + ROU leases) | C63: $M | E63: ='03 Historical'!E48+E50+'03 Historical'!E50+'03 Historical'!E49 -> 107135 | F63: ='03 Historical'!F48+F50+'03 Historical'!F50+'03 Historical'!F49 -> 172636 | G63: =G37+G50+'03 Historical'!$F$50+'03 Historical'!$F$49 -> 205539.42 | H63: =H37+H50+'03 Historical'!$F$50+'03 Historical'!$F$49 -> 225412.22 | I63: =I37+I50+'03 Historical'!$F$50+'03 Historical'!$F$49 -> 235814.25 | J63: =J37+J50+'03 Historical'!$F$50+'03 Historical'!$F$49 -> 240384.68 | K63: =K37+K50+'03 Historical'!$F$50+'03 Historical'!$F$49 -> 240450.53 | L63: =L37+L50+'03 Historical'!$F$50+'03 Historical'!$F$49 -> 239741.87 | M63: =M37+M50+'03 Historical'!$F$50+'03 Historical'!$F$49 -> 238935.24 | N63: =N37+N50+'03 Historical'!$F$50+'03 Historical'!$F$49 -> 238608.8 | ... P63: =P37+P50+'03 Historical'!$F$50+'03 Historical'!$F$49 -> 238294.29
B64: ROIC (NOPAT / capital invertido medio) | C64: % | F64: =F57/AVERAGE(E63:F63) -> 0.14020315 | G64: =G57/AVERAGE(F63:G63) -> 0.11858861 | H64: =H57/AVERAGE(G63:H63) -> 0.12189657 | I64: =I57/AVERAGE(H63:I63) -> 0.13330378 | J64: =J57/AVERAGE(I63:J63) -> 0.14995343 | K64: =K57/AVERAGE(J63:K63) -> 0.16836041 | L64: =L57/AVERAGE(K63:L63) -> 0.18853529 | M64: =M57/AVERAGE(L63:M63) -> 0.20813131 | ... P64: =P57/AVERAGE(O63:P63) -> 0.24872748
B65: Reinversión neta (Capex + ΔNWC − D&A) | C65: $M | G65: =G34+G51-G38 -> 31603.424 | H65: =H34+H51-H38 -> 18872.8 | I65: =I34+I51-I38 -> 9652.0235 | J65: =J34+J51-J38 -> 4020.4311 | K65: =K34+K51-K38 -> -334.14837 | L65: =L34+L51-L38 -> -1008.6569 | M65: =M34+M51-M38 -> -1026.6336 | N65: =N34+N51-N38 -> -486.43979 | ... P65: =P34+P51-P38 -> -83.031816
B66: Tasa de reinversión (reinversión / NOPAT) | C66: % | G66: =IFERROR(G65/G57,"n/a") -> 1.4093792 | H66: =IFERROR(H65/H57,"n/a") -> 0.7185323 | I66: =IFERROR(I65/I57,"n/a") -> 0.31397255 | J66: =IFERROR(J65/J57,"n/a") -> 0.11260503 | K66: =IFERROR(K65/K57,"n/a") -> -0.0082553046 | L66: =IFERROR(L65/L57,"n/a") -> -0.022282581 | M66: =IFERROR(M65/M57,"n/a") -> -0.020609402 | N66: =IFERROR(N65/N57,"n/a") -> -0.0090121816 | ... P66: =IFERROR(P65/P57,"n/a") -> -0.0014009204
B67: Crecimiento implícito = tasa de reinversión × ROIC | C67: % | G67: =IFERROR(G66*G64,"n/a") -> 0.16713632 | H67: =IFERROR(H66*H64,"n/a") -> 0.087586624 | I67: =IFERROR(I66*I64,"n/a") -> 0.041853728 | J67: =IFERROR(J66*J64,"n/a") -> 0.016885511 | K67: =IFERROR(K66*K64,"n/a") -> -0.0013898665 | L67: =IFERROR(L66*L64,"n/a") -> -0.004201053 | M67: =IFERROR(M66*M64,"n/a") -> -0.0042894619 | N67: =IFERROR(N66*N64,"n/a") -> -0.0020372562 | ... P67: =IFERROR(P66*P64,"n/a") -> -0.00034844741
B68: Crecimiento de ingresos proyectado | C68: % | G68: =G12 -> 0.25821013 | H68: =H12 -> 0.23011463 | I68: =I12 -> 0.19017169 | J68: =J12 -> 0.15502026 | K68: =K12 -> 0.12372043 | L68: =L12 -> 0.097114517 | M68: =M12 -> 0.074834486 | N68: =N12 -> 0.059461139 | ... P68: =P12 -> 0.035458661
B69: Diferencia (implícito − proyectado): brecha de coherencia, en p.p. | C69: % | G69: =IFERROR(G67-G68,"n/a") -> -0.091073815 | H69: =IFERROR(H67-H68,"n/a") -> -0.142528 | I69: =IFERROR(I67-I68,"n/a") -> -0.14831796 | J69: =IFERROR(J67-J68,"n/a") -> -0.13813475 | K69: =IFERROR(K67-K68,"n/a") -> -0.12511029 | L69: =IFERROR(L67-L68,"n/a") -> -0.10131557 | M69: =IFERROR(M67-M68,"n/a") -> -0.079123948 | N69: =IFERROR(N67-N68,"n/a") -> -0.061498396 | ... P69: =IFERROR(P67-P68,"n/a") -> -0.035807109
B70: FCFF (calculado en '06 DCF') | C70: $M | G70: ='06 DCF'!G15 -> -9779.7747 | H70: ='06 DCF'!H15 -> 6942.9643 | I70: ='06 DCF'!I15 -> 20739.593 | J70: ='06 DCF'!J15 -> 31383.399 | K70: ='06 DCF'!K15 -> 40560.955 | L70: ='06 DCF'!L15 -> 46025.264 | M70: ='06 DCF'!M15 -> 50590.481 | N70: ='06 DCF'!N15 -> 54212.248 | ... P70: ='06 DCF'!P15 -> 59102.504
B71: De la cual: variación de proveedores ligada al capex (solape con el capex de caja) | C71: $M | G71: ='02 Assumptions'!G49*(G34-F34) -> -649.81494 | H71: ='02 Assumptions'!H49*(H34-G34) -> -1235.1196 | I71: ='02 Assumptions'!I49*(I34-H34) -> -939.4617 | J71: ='02 Assumptions'!J49*(J34-I34) -> -627.23078 | K71: ='02 Assumptions'!K49*(K34-J34) -> -584.37209 | L71: ='02 Assumptions'!L49*(L34-K34) -> -139.22649 | M71: ='02 Assumptions'!M49*(M34-L34) -> -6.4762174 | N71: ='02 Assumptions'!N49*(N34-M34) -> 62.365526 | ... P71: ='02 Assumptions'!P49*(P34-O34) -> 61.905308
B72: ADVERTENCIA METODOLÓGICA: los proveedores se modelan sobre (coste de ingresos + capex) porque así reproducen el saldo real del balance (10.977 en FY2026, impulsado por equipamiento de centros de datos). Pero el capex del FCFF es capex de CAJA, por lo que la parte de la variación de proveedores atribuible al capex se solapa con él. La fila 71 cuantifica ese solape y el control 68 de '13 Checks' vigila que no supere el 5% del FCFF. Si lo supera, hay que separar proveedores operativos (sobre DPO del coste de ingresos) de proveedores ligados a capex y excluir estos últimos del circulante.

Sheet 05 Three Statement
A1: MODELO DE TRES ESTADOS INTEGRADO FY2027E–FY2036E — ORACLE CORPORATION
A2: Sirve para verificar la CONSISTENCIA CONTABLE del forecast (cuadre de balance y de caja). NO alimenta el DCF: el DCF es un FCFF construido sobre '04 Operating Model'.
B4: Partida | C4: Unidad | D4: ='00 Panel del Analista'!D14 -> 0 | E4: ='00 Panel del Analista'!E14 -> 0 | F4: ='00 Panel del Analista'!F14 -> 0 | G4: ='00 Panel del Analista'!G14 -> 0 | H4: ='00 Panel del Analista'!H14 -> 0 | I4: ='00 Panel del Analista'!I14 -> 0 | J4: ='00 Panel del Analista'!J14 -> 0 | K4: ='00 Panel del Analista'!K14 -> 0 | ... P4: ='00 Panel del Analista'!P14 -> 0
B6: CUENTA DE RESULTADOS
B7: Ingresos | C7: $M | G7: ='04 Operating Model'!G11 -> 84749.26 | H7: ='04 Operating Model'!H11 -> 104251.3 | I7: ='04 Operating Model'!I11 -> 124076.95 | J7: ='04 Operating Model'!J11 -> 143311.39 | K7: ='04 Operating Model'!K11 -> 161041.94 | L7: ='04 Operating Model'!L11 -> 176681.45 | M7: ='04 Operating Model'!M11 -> 189903.31 | N7: ='04 Operating Model'!N11 -> 201195.18 | ... P7: ='04 Operating Model'!P11 -> 217395.22
B8: Coste de los ingresos | C8: $M | G8: ='04 Operating Model'!G18 -> 33052.211 | H8: ='04 Operating Model'!H18 -> 43785.548 | I8: ='04 Operating Model'!I18 -> 53973.474 | J8: ='04 Operating Model'!J18 -> 63057.013 | K8: ='04 Operating Model'!K18 -> 70858.453 | L8: ='04 Operating Model'!L18 -> 76856.43 | M8: ='04 Operating Model'!M18 -> 81658.425 | N8: ='04 Operating Model'!N18 -> 85507.952 | ... P8: ='04 Operating Model'!P18 -> 91305.992
B9: Margen bruto | C9: $M | G9: =G7-G8 -> 51697.049 | H9: =H7-H8 -> 60465.757 | I9: =I7-I8 -> 70103.477 | J9: =J7-J8 -> 80254.38 | K9: =K7-K8 -> 90183.486 | L9: =L7-L8 -> 99825.018 | M9: =M7-M8 -> 108244.89 | N9: =N7-N8 -> 115687.23 | ... P9: =P7-P8 -> 126089.23
B10: Gastos operativos | C10: $M | G10: ='04 Operating Model'!G26 -> 26223.038 | H10: ='04 Operating Model'!H26 -> 30014.857 | I10: ='04 Operating Model'!I26 -> 33856.315 | J10: ='04 Operating Model'!J26 -> 37537.716 | K10: ='04 Operating Model'!K26 -> 41071.527 | L10: ='04 Operating Model'!L26 -> 44190.318 | M10: ='04 Operating Model'!M26 -> 46996.312 | N10: ='04 Operating Model'!N26 -> 49300.429 | ... P10: ='04 Operating Model'!P26 -> 53167.038
B11: EBIT reportado | C11: $M | G11: =G9-G10 -> 25474.011 | H11: =H9-H10 -> 30450.899 | I11: =I9-I10 -> 36247.162 | J11: =J9-J10 -> 42716.663 | K11: =K9-K10 -> 49111.959 | L11: =L9-L10 -> 55634.701 | M11: =M9-M10 -> 61248.577 | N11: =N9-N10 -> 66386.8 | ... P11: =P9-P10 -> 72922.188
B12: (−) Gasto por intereses | C12: $M | G12: =G26 -> 5829.345 | H12: =H26 -> 5499.2874 | I12: =I26 -> 5290.2393 | J12: =J26 -> 4817.0895 | K12: =K26 -> 3957.3876 | L12: =L26 -> 2681.3036 | M12: =M26 -> 1055.9943 | N12: =N26 -> 0 | ... P12: =P26 -> 0
B13: (+) Resultado no operativo, neto (no proyectado) | C13: $M | G13: =0 -> 0 | H13: =0 -> 0 | I13: =0 -> 0 | J13: =0 -> 0 | K13: =0 -> 0 | L13: =0 -> 0 | M13: =0 -> 0 | N13: =0 -> 0 | ... P13: =0 -> 0
B14: Beneficio antes de impuestos | C14: $M | G14: =G11-G12+G13 -> 19644.666 | H14: =H11-H12+H13 -> 24951.612 | I14: =I11-I12+I13 -> 30956.923 | J14: =J11-J12+J13 -> 37899.574 | K14: =K11-K12+K13 -> 45154.571 | L14: =L11-L12+L13 -> 52953.397 | M14: =M11-M12+M13 -> 60192.583 | N14: =N11-N12+N13 -> 66386.8 | ... P14: =P11-P12+P13 -> 72922.188
B15: (−) Impuestos | C15: $M | G15: =G14*'04 Operating Model'!G55 -> 2750.2532 | H15: =H14*'04 Operating Model'!H55 -> 3742.7418 | I15: =I14*'04 Operating Model'!I55 -> 4953.1077 | J15: =J14*'04 Operating Model'!J55 -> 6442.9275 | K15: =K14*'04 Operating Model'!K55 -> 8127.8228 | L15: =L14*'04 Operating Model'!L55 -> 10061.145 | M15: =M14*'04 Operating Model'!M55 -> 11436.591 | N15: =N14*'04 Operating Model'!N55 -> 12613.492 | ... P15: =P14*'04 Operating Model'!P55 -> 13855.216
B16: BENEFICIO NETO | C16: $M | G16: =G14-G15 -> 16894.413 | H16: =H14-H15 -> 21208.87 | I16: =I14-I15 -> 26003.815 | J16: =J14-J15 -> 31456.646 | K16: =K14-K15 -> 37026.749 | L16: =L14-L15 -> 42892.252 | M16: =M14-M15 -> 48755.992 | N16: =N14-N15 -> 53773.308 | ... P16: =P14-P15 -> 59066.973
B17: (−) Dividendos de preferentes | C17: $M | G17: =G93 -> 322.01 | H17: =H93 -> 322.01 | I17: =I93 -> 322.01 | J17: =J93 -> 322.01 | K17: =K93 -> 322.01 | L17: =L93 -> 322.01 | M17: =M93 -> 322.01 | N17: =N93 -> 322.01 | ... P17: =P93 -> 322.01
B18: Beneficio atribuible a ordinarias | C18: $M | G18: =G16-G17 -> 16572.403 | H18: =H16-H17 -> 20886.86 | I18: =I16-I17 -> 25681.805 | J18: =J16-J17 -> 31134.636 | K18: =K16-K17 -> 36704.739 | L18: =L16-L17 -> 42570.242 | M18: =M16-M17 -> 48433.982 | N18: =N16-N17 -> 53451.298 | ... P18: =P16-P17 -> 58744.963
B20: ESQUEMA DE DEUDA (interés sobre deuda inicial: sin circularidad)
B21: Deuda inicial | C21: $M | G21: =F24 -> 129541 | H21: =G24 -> 122206.39 | I21: =H24 -> 117560.87 | J21: =I24 -> 107046.43 | K21: =J24 -> 87941.947 | L21: =K24 -> 59584.524 | M21: =L24 -> 23466.54 | N21: =M24 -> 0 | ... P21: =O24 -> 0
B22: (+) Nueva deuda emitida | C22: $M | G22: =G32 -> 0 | H22: =H32 -> 0 | I22: =I32 -> 0 | J22: =J32 -> 0 | K22: =K32 -> 0 | L22: =L32 -> 0 | M22: =M32 -> 0 | N22: =N32 -> 0 | ... P22: =P32 -> 0
B23: (−) Repago de deuda | C23: $M | G23: =G34 -> 7334.614 | H23: =H34 -> 4645.512 | I23: =I34 -> 10514.44 | J23: =J34 -> 19104.487 | K23: =K34 -> 28357.423 | L23: =L34 -> 36117.984 | M23: =M34 -> 23466.54 | N23: =N34 -> 0 | ... P23: =P34 -> 0
B24: Deuda final | C24: $M | F24: ='02 Assumptions'!$C$70 -> 129541 | G24: =G21+G22-G23 -> 122206.39 | H24: =H21+H22-H23 -> 117560.87 | I24: =I21+I22-I23 -> 107046.43 | J24: =J21+J22-J23 -> 87941.947 | K24: =K21+K22-K23 -> 59584.524 | L24: =L21+L22-L23 -> 23466.54 | M24: =M21+M22-M23 -> 0 | N24: =N21+N22-N23 -> 0 | ... P24: =P21+P22-P23 -> 0
B25: Tipo de interés medio | C25: % | G25: ='02 Assumptions'!$C$98 -> 0.045 | H25: ='02 Assumptions'!$C$98 -> 0.045 | I25: ='02 Assumptions'!$C$98 -> 0.045 | J25: ='02 Assumptions'!$C$98 -> 0.045 | K25: ='02 Assumptions'!$C$98 -> 0.045 | L25: ='02 Assumptions'!$C$98 -> 0.045 | M25: ='02 Assumptions'!$C$98 -> 0.045 | N25: ='02 Assumptions'!$C$98 -> 0.045 | ... P25: ='02 Assumptions'!$C$98 -> 0.045
B26: Gasto por intereses = deuda inicial × tipo | C26: $M | G26: =G21*G25 -> 5829.345 | H26: =H21*H25 -> 5499.2874 | I26: =I21*I25 -> 5290.2393 | J26: =J21*J25 -> 4817.0895 | K26: =K21*K25 -> 3957.3876 | L26: =L21*L25 -> 2681.3036 | M26: =M21*M25 -> 1055.9943 | N26: =N21*N25 -> 0 | ... P26: =P21*P25 -> 0
B28: POLÍTICA DE FINANCIACIÓN (determina caja y deuda)
B29: Caja inicial | C29: $M | G29: =F35 -> 31289 | H29: =G35 -> 8605.8529 | I29: =H35 -> 6209.2815 | J29: =I35 -> 12375.594 | K29: =J35 -> 21254.158 | L29: =K35 -> 30773.052 | M29: =L35 -> 38768.205 | N29: =M35 -> 64719.352 | ... P29: =O35 -> 173644.9
B30: Caja preliminar = inicial + CFO + CFI − dividendos − recompras | C30: $M | G30: =G29+G77+G79-G82-G83-G84 -> 15940.467 | H30: =H29+H77+H79-H82-H83-H84 -> 10854.794 | I30: =I29+I77+I79-I82-I83-I84 -> 22890.035 | J30: =J29+J77+J79-J82-J83-J84 -> 40358.645 | K30: =K29+K77+K79-K82-K83-K84 -> 59130.476 | L30: =L29+L77+L79-L82-L83-L84 -> 74886.189 | M30: =M29+M77+M79-M82-M83-M84 -> 88185.892 | N30: =N29+N77+N79-N82-N83-N84 -> 118005.52 | ... P30: =P29+P77+P79-P82-P83-P84 -> 229761.98
B31: Caja mínima requerida | C31: $M | G31: ='02 Assumptions'!$C$68*G7 -> 1271.2389 | H31: ='02 Assumptions'!$C$68*H7 -> 1563.7696 | I31: ='02 Assumptions'!$C$68*I7 -> 1861.1543 | J31: ='02 Assumptions'!$C$68*J7 -> 2149.6709 | K31: ='02 Assumptions'!$C$68*K7 -> 2415.6291 | L31: ='02 Assumptions'!$C$68*L7 -> 2650.2217 | M31: ='02 Assumptions'!$C$68*M7 -> 2848.5497 | N31: ='02 Assumptions'!$C$68*N7 -> 3017.9277 | ... P31: ='02 Assumptions'!$C$68*P7 -> 3260.9283
B32: Nueva deuda necesaria = MAX(0; mínima − preliminar) | C32: $M | G32: =MAX(0,G31-G30) -> 0 | H32: =MAX(0,H31-H30) -> 0 | I32: =MAX(0,I31-I30) -> 0 | J32: =MAX(0,J31-J30) -> 0 | K32: =MAX(0,K31-K30) -> 0 | L32: =MAX(0,L31-L30) -> 0 | M32: =MAX(0,M31-M30) -> 0 | N32: =MAX(0,N31-N30) -> 0 | ... P32: =MAX(0,P31-P30) -> 0
B33: Excedente sobre la caja mínima | C33: $M | G33: =MAX(0,G30-G31) -> 14669.228 | H33: =MAX(0,H30-H31) -> 9291.0239 | I33: =MAX(0,I30-I31) -> 21028.88 | J33: =MAX(0,J30-J31) -> 38208.974 | K33: =MAX(0,K30-K31) -> 56714.847 | L33: =MAX(0,L30-L31) -> 72235.967 | M33: =MAX(0,M30-M31) -> 85337.342 | N33: =MAX(0,N30-N31) -> 114987.59 | ... P33: =MAX(0,P30-P31) -> 226501.05
B34: Repago efectivo = MIN(deuda inicial; excedente × %) | C34: $M | G34: =MIN(G21,G33*'02 Assumptions'!$C$97) -> 7334.614 | H34: =MIN(H21,H33*'02 Assumptions'!$C$97) -> 4645.512 | I34: =MIN(I21,I33*'02 Assumptions'!$C$97) -> 10514.44 | J34: =MIN(J21,J33*'02 Assumptions'!$C$97) -> 19104.487 | K34: =MIN(K21,K33*'02 Assumptions'!$C$97) -> 28357.423 | L34: =MIN(L21,L33*'02 Assumptions'!$C$97) -> 36117.984 | M34: =MIN(M21,M33*'02 Assumptions'!$C$97) -> 23466.54 | N34: =MIN(N21,N33*'02 Assumptions'!$C$97) -> 0 | ... P34: =MIN(P21,P33*'02 Assumptions'!$C$97) -> 0
B35: Caja final | C35: $M | F35: ='02 Assumptions'!$C$72 -> 31289 | G35: =G30+G32-G34 -> 8605.8529 | H35: =H30+H32-H34 -> 6209.2815 | I35: =I30+I32-I34 -> 12375.594 | J35: =J30+J32-J34 -> 21254.158 | K35: =K30+K32-K34 -> 30773.052 | L35: =L30+L32-L34 -> 38768.205 | M35: =M30+M32-M34 -> 64719.352 | N35: =N30+N32-N34 -> 118005.52 | ... P35: =P30+P32-P34 -> 229761.98
B37: BALANCE
B38: Caja y equivalentes | C38: $M | G38: =G35 -> 8605.8529 | H38: =H35 -> 6209.2815 | I38: =I35 -> 12375.594 | J38: =J35 -> 21254.158 | K38: =K35 -> 30773.052 | L38: =L35 -> 38768.205 | M38: =M35 -> 64719.352 | N38: =N35 -> 118005.52 | ... P38: =P35 -> 229761.98
B39: Valores negociables | C39: $M | G39: ='02 Assumptions'!$C$73 -> 605 | H39: ='02 Assumptions'!$C$73 -> 605 | I39: ='02 Assumptions'!$C$73 -> 605 | J39: ='02 Assumptions'!$C$73 -> 605 | K39: ='02 Assumptions'!$C$73 -> 605 | L39: ='02 Assumptions'!$C$73 -> 605 | M39: ='02 Assumptions'!$C$73 -> 605 | N39: ='02 Assumptions'!$C$73 -> 605 | ... P39: ='02 Assumptions'!$C$73 -> 605
B40: Clientes (AR) | C40: $M | G40: ='04 Operating Model'!G44 -> 13002.626 | H40: ='04 Operating Model'!H44 -> 15709.101 | I40: ='04 Operating Model'!I44 -> 18356.59 | J40: ='04 Operating Model'!J44 -> 20809.599 | K40: ='04 Operating Model'!K44 -> 22942.961 | L40: ='04 Operating Model'!L44 -> 25171.056 | M40: ='04 Operating Model'!M44 -> 27054.719 | N40: ='04 Operating Model'!N44 -> 28663.423 | ... P40: ='04 Operating Model'!P44 -> 30971.374
B41: Otros activos corrientes | C41: $M | G41: ='04 Operating Model'!G45 -> 5254.4541 | H41: ='04 Operating Model'!H45 -> 6255.0783 | I41: ='04 Operating Model'!I45 -> 7320.5401 | J41: ='04 Operating Model'!J45 -> 8312.0607 | K41: ='04 Operating Model'!K45 -> 9340.4324 | L41: ='04 Operating Model'!L45 -> 10247.524 | M41: ='04 Operating Model'!M45 -> 11014.392 | N41: ='04 Operating Model'!N45 -> 11669.321 | ... P41: ='04 Operating Model'!P45 -> 12608.923
B42: PP&E neto | C42: $M | G42: ='04 Operating Model'!G37 -> 135133.83 | H42: ='04 Operating Model'!H37 -> 157336.34 | I42: ='04 Operating Model'!I37 -> 170239.5 | J42: ='04 Operating Model'!J37 -> 177173.99 | K42: ='04 Operating Model'!K37 -> 179183.53 | L42: ='04 Operating Model'!L37 -> 179975.03 | M42: ='04 Operating Model'!M37 -> 180622.62 | N42: ='04 Operating Model'!N37 -> 181622.35 | ... P42: ='04 Operating Model'!P37 -> 183770.98
B43: ROU — leases operativos | C43: $M | G43: ='03 Historical'!$F$49 -> 29690 | H43: ='03 Historical'!$F$49 -> 29690 | I43: ='03 Historical'!$F$49 -> 29690 | J43: ='03 Historical'!$F$49 -> 29690 | K43: ='03 Historical'!$F$49 -> 29690 | L43: ='03 Historical'!$F$49 -> 29690 | M43: ='03 Historical'!$F$49 -> 29690 | N43: ='03 Historical'!$F$49 -> 29690 | ... P43: ='03 Historical'!$F$49 -> 29690
B44: Fondo de comercio | C44: $M | G44: ='03 Historical'!$F$50 -> 62261 | H44: ='03 Historical'!$F$50 -> 62261 | I44: ='03 Historical'!$F$50 -> 62261 | J44: ='03 Historical'!$F$50 -> 62261 | K44: ='03 Historical'!$F$50 -> 62261 | L44: ='03 Historical'!$F$50 -> 62261 | M44: ='03 Historical'!$F$50 -> 62261 | N44: ='03 Historical'!$F$50 -> 62261 | ... P44: ='03 Historical'!$F$50 -> 62261
B45: Intangibles adquiridos, neto | C45: $M | F45: ='02 Assumptions'!$C$101 -> 4890 | G45: =F45-'04 Operating Model'!G24 -> 3590 | H45: =G45-'04 Operating Model'!H24 -> 2590 | I45: =H45-'04 Operating Model'!I24 -> 1840 | J45: =I45-'04 Operating Model'!J24 -> 1290 | K45: =J45-'04 Operating Model'!K24 -> 890 | L45: =K45-'04 Operating Model'!L24 -> 590 | M45: =L45-'04 Operating Model'!M24 -> 370 | N45: =M45-'04 Operating Model'!N24 -> 210 | ... P45: =O45-'04 Operating Model'!P24 -> 0
B46: Activos por impuesto diferido | C46: $M | G46: ='03 Historical'!$F$51 -> 11541 | H46: ='03 Historical'!$F$51 -> 11541 | I46: ='03 Historical'!$F$51 -> 11541 | J46: ='03 Historical'!$F$51 -> 11541 | K46: ='03 Historical'!$F$51 -> 11541 | L46: ='03 Historical'!$F$51 -> 11541 | M46: ='03 Historical'!$F$51 -> 11541 | N46: ='03 Historical'!$F$51 -> 11541 | ... P46: ='03 Historical'!$F$51 -> 11541
B47: Otros activos no corrientes (netos de intangibles) | C47: $M | G47: ='02 Assumptions'!$C$102 -> 6853 | H47: ='02 Assumptions'!$C$102 -> 6853 | I47: ='02 Assumptions'!$C$102 -> 6853 | J47: ='02 Assumptions'!$C$102 -> 6853 | K47: ='02 Assumptions'!$C$102 -> 6853 | L47: ='02 Assumptions'!$C$102 -> 6853 | M47: ='02 Assumptions'!$C$102 -> 6853 | N47: ='02 Assumptions'!$C$102 -> 6853 | ... P47: ='02 Assumptions'!$C$102 -> 6853
B48: TOTAL ACTIVO | C48: $M | G48: =SUM(G38:G47) -> 276536.77 | H48: =SUM(H38:H47) -> 299049.8 | I48: =SUM(I38:I47) -> 321082.22 | J48: =SUM(J38:J47) -> 339789.81 | K48: =SUM(K38:K47) -> 354079.98 | L48: =SUM(L38:L47) -> 365701.82 | M48: =SUM(M38:M47) -> 394731.08 | N48: =SUM(N38:N47) -> 451120.61 | ... P48: =SUM(P38:P47) -> 568063.25
B49: Proveedores | C49: $M | G49: ='04 Operating Model'!G46 -> 11326.739 | H49: ='04 Operating Model'!H46 -> 11540.619 | I49: ='04 Operating Model'!I46 -> 11976.528 | J49: ='04 Operating Model'!J46 -> 12575.575 | K49: ='04 Operating Model'!K46 -> 13044.397 | L49: ='04 Operating Model'!L46 -> 13714.897 | M49: ='04 Operating Model'!M46 -> 14356.691 | N49: ='04 Operating Model'!N46 -> 14938.742 | ... P49: ='04 Operating Model'!P46 -> 15789.415
B50: Remuneraciones pendientes | C50: $M | G50: ='04 Operating Model'!G47 -> 2711.9763 | H50: ='04 Operating Model'!H47 -> 3231.7904 | I50: ='04 Operating Model'!I47 -> 3846.3855 | J50: ='04 Operating Model'!J47 -> 4299.3418 | K50: ='04 Operating Model'!K47 -> 4831.2582 | L50: ='04 Operating Model'!L47 -> 5300.4435 | M50: ='04 Operating Model'!M47 -> 5697.0994 | N50: ='04 Operating Model'!N47 -> 6035.8554 | ... P50: ='04 Operating Model'!P47 -> 6521.8565
B51: Ingresos diferidos corrientes | C51: $M | G51: ='04 Operating Model'!G48 -> 12203.893 | H51: ='04 Operating Model'!H48 -> 14595.183 | I51: ='04 Operating Model'!I48 -> 16874.465 | J51: ='04 Operating Model'!J48 -> 18917.104 | K51: ='04 Operating Model'!K48 -> 20613.368 | L51: ='04 Operating Model'!L48 -> 22085.181 | M51: ='04 Operating Model'!M48 -> 23168.204 | N51: ='04 Operating Model'!N48 -> 24143.422 | ... P51: ='04 Operating Model'!P48 -> 26087.426
B52: Otros pasivos corrientes operativos | C52: $M | G52: ='04 Operating Model'!G49 -> 13559.882 | H52: ='04 Operating Model'!H49 -> 16471.706 | I52: ='04 Operating Model'!I49 -> 19356.004 | J52: ='04 Operating Model'!J49 -> 22069.954 | K52: ='04 Operating Model'!K49 -> 24478.375 | L52: ='04 Operating Model'!L49 -> 26502.217 | M52: ='04 Operating Model'!M49 -> 28485.497 | N52: ='04 Operating Model'!N49 -> 30179.277 | ... P52: ='04 Operating Model'!P49 -> 32609.283
B53: Deuda financiera total | C53: $M | G53: =G24 -> 122206.39 | H53: =H24 -> 117560.87 | I53: =I24 -> 107046.43 | J53: =J24 -> 87941.947 | K53: =K24 -> 59584.524 | L53: =L24 -> 23466.54 | M53: =M24 -> 0 | N53: =N24 -> 0 | ... P53: =P24 -> 0
B54: Leases financieros | C54: $M | G54: ='02 Assumptions'!$C$71 -> 7701 | H54: ='02 Assumptions'!$C$71 -> 7701 | I54: ='02 Assumptions'!$C$71 -> 7701 | J54: ='02 Assumptions'!$C$71 -> 7701 | K54: ='02 Assumptions'!$C$71 -> 7701 | L54: ='02 Assumptions'!$C$71 -> 7701 | M54: ='02 Assumptions'!$C$71 -> 7701 | N54: ='02 Assumptions'!$C$71 -> 7701 | ... P54: ='02 Assumptions'!$C$71 -> 7701
B55: Pasivo por leases operativos — NO corriente (el corriente va en otros pasivos corrientes) | C55: $M | G55: ='03 Historical'!$F$64 -> 26648 | H55: ='03 Historical'!$F$64 -> 26648 | I55: ='03 Historical'!$F$64 -> 26648 | J55: ='03 Historical'!$F$64 -> 26648 | K55: ='03 Historical'!$F$64 -> 26648 | L55: ='03 Historical'!$F$64 -> 26648 | M55: ='03 Historical'!$F$64 -> 26648 | N55: ='03 Historical'!$F$64 -> 26648 | ... P55: ='03 Historical'!$F$64 -> 26648
B56: Impuestos a pagar no corrientes | C56: $M | G56: ='03 Historical'!$F$63 -> 11771 | H56: ='03 Historical'!$F$63 -> 11771 | I56: ='03 Historical'!$F$63 -> 11771 | J56: ='03 Historical'!$F$63 -> 11771 | K56: ='03 Historical'!$F$63 -> 11771 | L56: ='03 Historical'!$F$63 -> 11771 | M56: ='03 Historical'!$F$63 -> 11771 | N56: ='03 Historical'!$F$63 -> 11771 | ... P56: ='03 Historical'!$F$63 -> 11771
B57: Otros pasivos no corrientes (netos del lease financiero no corriente) | C57: $M | G57: ='03 Historical'!$F$65-('03 Historical'!$F$112-'03 Historical'!$F$119) -> 9097 | H57: ='03 Historical'!$F$65-('03 Historical'!$F$112-'03 Historical'!$F$119) -> 9097 | I57: ='03 Historical'!$F$65-('03 Historical'!$F$112-'03 Historical'!$F$119) -> 9097 | J57: ='03 Historical'!$F$65-('03 Historical'!$F$112-'03 Historical'!$F$119) -> 9097 | K57: ='03 Historical'!$F$65-('03 Historical'!$F$112-'03 Historical'!$F$119) -> 9097 | L57: ='03 Historical'!$F$65-('03 Historical'!$F$112-'03 Historical'!$F$119) -> 9097 | M57: ='03 Historical'!$F$65-('03 Historical'!$F$112-'03 Historical'!$F$119) -> 9097 | N57: ='03 Historical'!$F$65-('03 Historical'!$F$112-'03 Historical'!$F$119) -> 9097 | ... P57: ='03 Historical'!$F$65-('03 Historical'!$F$112-'03 Historical'!$F$119) -> 9097
B58: TOTAL PASIVO | C58: $M | G58: =SUM(G49:G57) -> 217225.88 | H58: =SUM(H49:H57) -> 218617.17 | I58: =SUM(I49:I57) -> 214316.82 | J58: =SUM(J49:J57) -> 201020.92 | K58: =SUM(K49:K57) -> 177768.92 | L58: =SUM(L49:L57) -> 146286.28 | M58: =SUM(M49:M57) -> 126924.49 | N58: =SUM(N49:N57) -> 130514.3 | ... P58: =SUM(P49:P57) -> 136224.98
B59: Patrimonio neto total (incluye preferentes y minoritarios) | C59: $M | G59: =G70 -> 59310.891 | H59: =H70 -> 80432.632 | I59: =I70 -> 106765.41 | J59: =J70 -> 138768.89 | K59: =K70 -> 176311.06 | L59: =L70 -> 219415.54 | M59: =M70 -> 267806.59 | N59: =N70 -> 320606.32 | ... P59: =P70 -> 431838.27
B60: TOTAL PASIVO Y PATRIMONIO | C60: $M | G60: =G58+G59 -> 276536.77 | H60: =H58+H59 -> 299049.8 | I60: =I58+I59 -> 321082.22 | J60: =J58+J59 -> 339789.81 | K60: =K58+K59 -> 354079.98 | L60: =L58+L59 -> 365701.82 | M60: =M58+M59 -> 394731.08 | N60: =N58+N59 -> 451120.61 | ... P60: =P58+P59 -> 568063.25
B61: CHECK: Activo − Pasivo y Patrimonio (debe ser 0) | C61: $M | G61: =G48-G60 -> 0 | H61: =H48-H60 -> 0 | I61: =I48-I60 -> 0 | J61: =J48-J60 -> 0 | K61: =K48-K60 -> 0 | L61: =L48-L60 -> 0 | M61: =M48-M60 -> 0 | N61: =N48-N60 -> 0 | ... P61: =P48-P60 -> 0
B63: PATRIMONIO — ROLL-FORWARD
B64: Patrimonio inicial | C64: $M | G64: =F70 -> 43056 | H64: =G70 -> 59310.891 | I64: =H70 -> 80432.632 | J64: =I70 -> 106765.41 | K64: =J70 -> 138768.89 | L64: =K70 -> 176311.06 | M64: =L70 -> 219415.54 | N64: =M70 -> 267806.59 | ... P64: =O70 -> 375804.23
B65: (+) Beneficio neto | C65: $M | G65: =G16 -> 16894.413 | H65: =H16 -> 21208.87 | I65: =I16 -> 26003.815 | J65: =J16 -> 31456.646 | K65: =K16 -> 37026.749 | L65: =L16 -> 42892.252 | M65: =M16 -> 48755.992 | N65: =N16 -> 53773.308 | ... P65: =P16 -> 59066.973
B66: (+) Retribución en acciones (SBC) | C66: $M | G66: =G75 -> 5932.4482 | H66: =H75 -> 6984.8374 | I66: =I75 -> 7940.9249 | J66: =J75 -> 8741.9949 | K66: =K75 -> 9340.4324 | L66: =L75 -> 9717.4797 | M66: =M75 -> 9874.9723 | N66: =N75 -> 10059.759 | ... P66: =P75 -> 9782.7848
B67: (−) Dividendos ordinarios | C67: $M | G67: =G92 -> 6249.96 | H67: =H92 -> 6749.9568 | I67: =I92 -> 7289.9533 | J67: =J92 -> 7873.1496 | K67: =K92 -> 8503.0016 | L67: =L92 -> 9183.2417 | M67: =M92 -> 9917.901 | N67: =N92 -> 10711.333 | ... P67: =P92 -> 12493.699
B68: (−) Dividendos de preferentes | C68: $M | G68: =G93 -> 322.01 | H68: =H93 -> 322.01 | I68: =I93 -> 322.01 | J68: =J93 -> 322.01 | K68: =K93 -> 322.01 | L68: =L93 -> 322.01 | M68: =M93 -> 322.01 | N68: =N93 -> 322.01 | ... P68: =P93 -> 322.01
B69: (−) Recompras netas de acciones | C69: $M | G69: ='02 Assumptions'!$C$100 -> 0 | H69: ='02 Assumptions'!$C$100 -> 0 | I69: ='02 Assumptions'!$C$100 -> 0 | J69: ='02 Assumptions'!$C$100 -> 0 | K69: ='02 Assumptions'!$C$100 -> 0 | L69: ='02 Assumptions'!$C$100 -> 0 | M69: ='02 Assumptions'!$C$100 -> 0 | N69: ='02 Assumptions'!$C$100 -> 0 | ... P69: ='02 Assumptions'!$C$100 -> 0
B70: Patrimonio final | C70: $M | F70: ='03 Historical'!$F$73 -> 43056 | G70: =G64+G65+G66-G67-G68-G69 -> 59310.891 | H70: =H64+H65+H66-H67-H68-H69 -> 80432.632 | I70: =I64+I65+I66-I67-I68-I69 -> 106765.41 | J70: =J64+J65+J66-J67-J68-J69 -> 138768.89 | K70: =K64+K65+K66-K67-K68-K69 -> 176311.06 | L70: =L64+L65+L66-L67-L68-L69 -> 219415.54 | M70: =M64+M65+M66-M67-M68-M69 -> 267806.59 | N70: =N64+N65+N66-N67-N68-N69 -> 320606.32 | ... P70: =P64+P65+P66-P67-P68-P69 -> 431838.27
B72: ESTADO DE FLUJOS DE CAJA
B73: Beneficio neto | C73: $M | G73: =G16 -> 16894.413 | H73: =H16 -> 21208.87 | I73: =I16 -> 26003.815 | J73: =J16 -> 31456.646 | K73: =K16 -> 37026.749 | L73: =L16 -> 42892.252 | M73: =M16 -> 48755.992 | N73: =N16 -> 53773.308 | ... P73: =P16 -> 59066.973
B74: (+) D&A | C74: $M | G74: ='04 Operating Model'!G38 -> 16972.722 | H74: ='04 Operating Model'!H38 -> 20498.012 | I74: ='04 Operating Model'!I38 -> 22588.39 | J74: ='04 Operating Model'!J38 -> 23710.9 | K74: ='04 Operating Model'!K38 -> 24157.169 | L74: ='04 Operating Model'!L38 -> 24243.905 | M74: ='04 Operating Model'!M38 -> 24259.844 | N74: ='04 Operating Model'!N38 -> 24309.665 | ... P74: ='04 Operating Model'!P38 -> 24510.666
B75: (+) SBC | C75: $M | G75: =G7*'02 Assumptions'!G95 -> 5932.4482 | H75: =H7*'02 Assumptions'!H95 -> 6984.8374 | I75: =I7*'02 Assumptions'!I95 -> 7940.9249 | J75: =J7*'02 Assumptions'!J95 -> 8741.9949 | K75: =K7*'02 Assumptions'!K95 -> 9340.4324 | L75: =L7*'02 Assumptions'!L95 -> 9717.4797 | M75: =M7*'02 Assumptions'!M95 -> 9874.9723 | N75: =N7*'02 Assumptions'!N95 -> 10059.759 | ... P75: =P7*'02 Assumptions'!P95 -> 9782.7848
B76: (−) Variación del capital circulante neto | C76: $M | G76: =-'04 Operating Model'!G51 -> 2273.4096 | H76: =-'04 Operating Model'!H51 -> 2329.71 | I76: =-'04 Operating Model'!I51 -> 2501.1331 | J76: =-'04 Operating Model'!J51 -> 2364.0617 | K76: =-'04 Operating Model'!K51 -> 1943.69 | L76: =-'04 Operating Model'!L51 -> 1500.1551 | M76: =-'04 Operating Model'!M51 -> 1454.2209 | N76: =-'04 Operating Model'!N51 -> 1326.1726 | ... P76: =-'04 Operating Model'!P51 -> 1225.0019
B77: FLUJO DE CAJA OPERATIVO (CFO) | C77: $M | G77: =SUM(G73:G76) -> 42072.993 | H77: =SUM(H73:H76) -> 51021.429 | I77: =SUM(I73:I76) -> 59034.263 | J77: =SUM(J73:J76) -> 66273.602 | K77: =SUM(K73:K76) -> 72468.039 | L77: =SUM(L73:L76) -> 78353.791 | M77: =SUM(M73:M76) -> 84345.029 | N77: =SUM(N73:N76) -> 89468.905 | ... P77: =SUM(P73:P76) -> 94585.425
B78: (−) Capex | C78: $M | G78: =-'04 Operating Model'!G34 -> -50849.556 | H78: =-'04 Operating Model'!H34 -> -41700.522 | I78: =-'04 Operating Model'!I34 -> -34741.546 | J78: =-'04 Operating Model'!J34 -> -30095.392 | K78: =-'04 Operating Model'!K34 -> -25766.71 | L78: =-'04 Operating Model'!L34 -> -24735.403 | M78: =-'04 Operating Model'!M34 -> -24687.431 | N78: =-'04 Operating Model'!N34 -> -25149.398 | ... P78: =-'04 Operating Model'!P34 -> -25652.636
B79: FLUJO DE CAJA DE INVERSIÓN (CFI) | C79: $M | G79: =G78 -> -50849.556 | H79: =H78 -> -41700.522 | I79: =I78 -> -34741.546 | J79: =J78 -> -30095.392 | K79: =K78 -> -25766.71 | L79: =L78 -> -24735.403 | M79: =M78 -> -24687.431 | N79: =N78 -> -25149.398 | ... P79: =P78 -> -25652.636
B80: (+) Nueva deuda | C80: $M | G80: =G22 -> 0 | H80: =H22 -> 0 | I80: =I22 -> 0 | J80: =J22 -> 0 | K80: =K22 -> 0 | L80: =L22 -> 0 | M80: =M22 -> 0 | N80: =N22 -> 0 | ... P80: =P22 -> 0
B81: (−) Repago de deuda | C81: $M | G81: =-G23 -> -7334.614 | H81: =-H23 -> -4645.512 | I81: =-I23 -> -10514.44 | J81: =-J23 -> -19104.487 | K81: =-K23 -> -28357.423 | L81: =-L23 -> -36117.984 | M81: =-M23 -> -23466.54 | N81: =-N23 -> 0 | ... P81: =-P23 -> 0
B82: (−) Dividendos ordinarios | C82: $M | G82: =G92 -> 6249.96 | H82: =H92 -> 6749.9568 | I82: =I92 -> 7289.9533 | J82: =J92 -> 7873.1496 | K82: =K92 -> 8503.0016 | L82: =L92 -> 9183.2417 | M82: =M92 -> 9917.901 | N82: =N92 -> 10711.333 | ... P82: =P92 -> 12493.699
B83: (−) Dividendos de preferentes | C83: $M | G83: =G93 -> 322.01 | H83: =H93 -> 322.01 | I83: =I93 -> 322.01 | J83: =J93 -> 322.01 | K83: =K93 -> 322.01 | L83: =L93 -> 322.01 | M83: =M93 -> 322.01 | N83: =N93 -> 322.01 | ... P83: =P93 -> 322.01
B84: (−) Recompras netas | C84: $M | G84: ='02 Assumptions'!$C$100 -> 0 | H84: ='02 Assumptions'!$C$100 -> 0 | I84: ='02 Assumptions'!$C$100 -> 0 | J84: ='02 Assumptions'!$C$100 -> 0 | K84: ='02 Assumptions'!$C$100 -> 0 | L84: ='02 Assumptions'!$C$100 -> 0 | M84: ='02 Assumptions'!$C$100 -> 0 | N84: ='02 Assumptions'!$C$100 -> 0 | ... P84: ='02 Assumptions'!$C$100 -> 0
B85: FLUJO DE CAJA DE FINANCIACIÓN (CFF) | C85: $M | G85: =G80+G81-G82-G83-G84 -> -13906.584 | H85: =H80+H81-H82-H83-H84 -> -11717.479 | I85: =I80+I81-I82-I83-I84 -> -18126.404 | J85: =J80+J81-J82-J83-J84 -> -27299.647 | K85: =K80+K81-K82-K83-K84 -> -37182.435 | L85: =L80+L81-L82-L83-L84 -> -45623.235 | M85: =M80+M81-M82-M83-M84 -> -33706.451 | N85: =N80+N81-N82-N83-N84 -> -11033.343 | ... P85: =P80+P81-P82-P83-P84 -> -12815.709
B86: Variación neta de caja | C86: $M | G86: =G77+G79+G85 -> -22683.147 | H86: =H77+H79+H85 -> -2396.5713 | I86: =I77+I79+I85 -> 6166.3129 | J86: =J77+J79+J85 -> 8878.5634 | K86: =K77+K79+K85 -> 9518.8945 | L86: =L77+L79+L85 -> 7995.1529 | M86: =M77+M79+M85 -> 25951.147 | N86: =N77+N79+N85 -> 53286.164 | ... P86: =P77+P79+P85 -> 56117.08
B87: Caja inicial | C87: $M | G87: =G29 -> 31289 | H87: =H29 -> 8605.8529 | I87: =I29 -> 6209.2815 | J87: =J29 -> 12375.594 | K87: =K29 -> 21254.158 | L87: =L29 -> 30773.052 | M87: =M29 -> 38768.205 | N87: =N29 -> 64719.352 | ... P87: =P29 -> 173644.9
B88: Caja final según el estado de flujos | C88: $M | G88: =G86+G87 -> 8605.8529 | H88: =H86+H87 -> 6209.2815 | I88: =I86+I87 -> 12375.594 | J88: =J86+J87 -> 21254.158 | K88: =K86+K87 -> 30773.052 | L88: =L86+L87 -> 38768.205 | M88: =M86+M87 -> 64719.352 | N88: =N86+N87 -> 118005.52 | ... P88: =P86+P87 -> 229761.98
B89: CHECK: caja del flujo − caja del balance (debe ser 0) | C89: $M | G89: =G88-G38 -> 0 | H89: =H88-H38 -> 0 | I89: =I88-I38 -> 0 | J89: =J88-J38 -> 0 | K89: =K88-K38 -> 0 | L89: =L88-L38 -> 0 | M89: =M88-M38 -> 0 | N89: =N88-N38 -> 0 | ... P89: =P88-P38 -> 0
B91: DIVIDENDOS
B92: Dividendo ordinario pagado | C92: $M | F92: =-'03 Historical'!$F$97 -> 5787 | G92: =F92*(1+'02 Assumptions'!$C$96) -> 6249.96 | H92: =G92*(1+'02 Assumptions'!$C$96) -> 6749.9568 | I92: =H92*(1+'02 Assumptions'!$C$96) -> 7289.9533 | J92: =I92*(1+'02 Assumptions'!$C$96) -> 7873.1496 | K92: =J92*(1+'02 Assumptions'!$C$96) -> 8503.0016 | L92: =K92*(1+'02 Assumptions'!$C$96) -> 9183.2417 | M92: =L92*(1+'02 Assumptions'!$C$96) -> 9917.901 | N92: =M92*(1+'02 Assumptions'!$C$96) -> 10711.333 | ... P92: =O92*(1+'02 Assumptions'!$C$96) -> 12493.699
B93: Dividendo de preferentes | C93: $M | G93: ='02 Assumptions'!$C$99*'02 Assumptions'!$C$75 -> 322.01 | H93: ='02 Assumptions'!$C$99*'02 Assumptions'!$C$75 -> 322.01 | I93: ='02 Assumptions'!$C$99*'02 Assumptions'!$C$75 -> 322.01 | J93: ='02 Assumptions'!$C$99*'02 Assumptions'!$C$75 -> 322.01 | K93: ='02 Assumptions'!$C$99*'02 Assumptions'!$C$75 -> 322.01 | L93: ='02 Assumptions'!$C$99*'02 Assumptions'!$C$75 -> 322.01 | M93: ='02 Assumptions'!$C$99*'02 Assumptions'!$C$75 -> 322.01 | N93: ='02 Assumptions'!$C$99*'02 Assumptions'!$C$75 -> 322.01 | ... P93: ='02 Assumptions'!$C$99*'02 Assumptions'!$C$75 -> 322.01
B94: Payout sobre beneficio neto | C94: % | G94: =G92/G16 -> 0.36994242 | H94: =H92/H16 -> 0.31826103 | I94: =I92/I16 -> 0.28034168 | J94: =J92/J16 -> 0.25028573 | K94: =K92/K16 -> 0.22964484 | L94: =L92/L16 -> 0.21410025 | M94: =M92/M16 -> 0.20341912 | N94: =N92/N16 -> 0.19919424 | ... P94: =P92/P16 -> 0.21151751

Sheet 06 DCF
A1: DCF — FREE CASH FLOW TO FIRM — ORACLE CORPORATION (ORCL) | R1: =1+1 -> 0
A2: USD millones. FCFF descontado al WACC. Ningún resultado está introducido a mano: todo se calcula desde '02 Assumptions', '04 Operating Model' y '07 WACC'.
B4: Partida | C4: Unidad | D4: ='00 Panel del Analista'!D14 -> 0 | E4: ='00 Panel del Analista'!E14 -> 0 | F4: ='00 Panel del Analista'!F14 -> 0 | G4: ='00 Panel del Analista'!G14 -> 0 | H4: ='00 Panel del Analista'!H14 -> 0 | I4: ='00 Panel del Analista'!I14 -> 0 | J4: ='00 Panel del Analista'!J14 -> 0 | K4: ='00 Panel del Analista'!K14 -> 0 | ... P4: ='00 Panel del Analista'!P14 -> 0
B6: CÁLCULO DEL FREE CASH FLOW TO FIRM (FCFF)
B7: EBIT normalizado | C7: $M | D7: ='04 Operating Model'!D29 -> 16071 | E7: ='04 Operating Model'!E29 -> 18052 | F7: ='04 Operating Model'!F29 -> 22444 | G7: ='04 Operating Model'!G29 -> 26074.011 | H7: ='04 Operating Model'!H29 -> 30900.899 | I7: ='04 Operating Model'!I29 -> 36597.162 | J7: ='04 Operating Model'!J29 -> 43016.663 | K7: ='04 Operating Model'!K29 -> 49361.959 | ... P7: ='04 Operating Model'!P29 -> 73172.188
B8: Tipo impositivo de caja | C8: % | G8: ='04 Operating Model'!G55 -> 0.14 | H8: ='04 Operating Model'!H55 -> 0.15 | I8: ='04 Operating Model'!I55 -> 0.16 | J8: ='04 Operating Model'!J55 -> 0.17 | K8: ='04 Operating Model'!K55 -> 0.18 | L8: ='04 Operating Model'!L55 -> 0.19 | M8: ='04 Operating Model'!M55 -> 0.19 | N8: ='04 Operating Model'!N55 -> 0.19 | ... P8: ='04 Operating Model'!P55 -> 0.19
B9: (−) Impuestos sobre el EBIT normalizado | C9: $M | G9: =-G7*G8 -> -3650.3615 | H9: =-H7*H8 -> -4635.1349 | I9: =-I7*I8 -> -5855.546 | J9: =-J7*J8 -> -7312.8327 | K9: =-K7*K8 -> -8885.1526 | L9: =-L7*L8 -> -10618.093 | M9: =-M7*M8 -> -11684.73 | N9: =-N7*N8 -> -12660.992 | ... P9: =-P7*P8 -> -13902.716
B10: NOPAT | C10: $M | G10: =G7+G9 -> 22423.649 | H10: =H7+H9 -> 26265.764 | I10: =I7+I9 -> 30741.616 | J10: =J7+J9 -> 35703.83 | K10: =K7+K9 -> 40476.806 | L10: =L7+L9 -> 45266.608 | M10: =M7+M9 -> 49813.847 | N10: =N7+N9 -> 53975.808 | ... P10: =P7+P9 -> 59269.473
B11: (+) D&A | C11: $M | G11: ='04 Operating Model'!G38 -> 16972.722 | H11: ='04 Operating Model'!H38 -> 20498.012 | I11: ='04 Operating Model'!I38 -> 22588.39 | J11: ='04 Operating Model'!J38 -> 23710.9 | K11: ='04 Operating Model'!K38 -> 24157.169 | L11: ='04 Operating Model'!L38 -> 24243.905 | M11: ='04 Operating Model'!M38 -> 24259.844 | N11: ='04 Operating Model'!N38 -> 24309.665 | ... P11: ='04 Operating Model'!P38 -> 24510.666
B12: (−) Capex | C12: $M | G12: =-'04 Operating Model'!G34 -> -50849.556 | H12: =-'04 Operating Model'!H34 -> -41700.522 | I12: =-'04 Operating Model'!I34 -> -34741.546 | J12: =-'04 Operating Model'!J34 -> -30095.392 | K12: =-'04 Operating Model'!K34 -> -25766.71 | L12: =-'04 Operating Model'!L34 -> -24735.403 | M12: =-'04 Operating Model'!M34 -> -24687.431 | N12: =-'04 Operating Model'!N34 -> -25149.398 | ... P12: =-'04 Operating Model'!P34 -> -25652.636
B13: (−) Variación del capital circulante neto | C13: $M | G13: =-'04 Operating Model'!G51 -> 2273.4096 | H13: =-'04 Operating Model'!H51 -> 2329.71 | I13: =-'04 Operating Model'!I51 -> 2501.1331 | J13: =-'04 Operating Model'!J51 -> 2364.0617 | K13: =-'04 Operating Model'!K51 -> 1943.69 | L13: =-'04 Operating Model'!L51 -> 1500.1551 | M13: =-'04 Operating Model'!M51 -> 1454.2209 | N13: =-'04 Operating Model'!N51 -> 1326.1726 | ... P13: =-'04 Operating Model'!P51 -> 1225.0019
B14: (−) Coste en caja de reestructuración (readido al EBIT normalizado) | C14: $M | G14: =-'02 Assumptions'!G38 -> -600 | H14: =-'02 Assumptions'!H38 -> -450 | I14: =-'02 Assumptions'!I38 -> -350 | J14: =-'02 Assumptions'!J38 -> -300 | K14: =-'02 Assumptions'!K38 -> -250 | L14: =-'02 Assumptions'!L38 -> -250 | M14: =-'02 Assumptions'!M38 -> -250 | N14: =-'02 Assumptions'!N38 -> -250 | ... P14: =-'02 Assumptions'!P38 -> -250
B15: FCFF | C15: $M | G15: =SUM(G10:G14) -> -9779.7747 | H15: =SUM(H10:H14) -> 6942.9643 | I15: =SUM(I10:I14) -> 20739.593 | J15: =SUM(J10:J14) -> 31383.399 | K15: =SUM(K10:K14) -> 40560.955 | L15: =SUM(L10:L14) -> 46025.264 | M15: =SUM(M10:M14) -> 50590.481 | N15: =SUM(N10:N14) -> 54212.248 | ... P15: =SUM(P10:P14) -> 59102.504
B16: Margen FCFF sobre ingresos | C16: % | G16: =G15/'04 Operating Model'!G11 -> -0.11539658 | H16: =H15/'04 Operating Model'!H11 -> 0.066598345 | I16: =I15/'04 Operating Model'!I11 -> 0.16715105 | J16: =J15/'04 Operating Model'!J11 -> 0.21898747 | K16: =K15/'04 Operating Model'!K11 -> 0.25186579 | L16: =L15/'04 Operating Model'!L11 -> 0.26049857 | M16: =M15/'04 Operating Model'!M11 -> 0.26640125 | N16: =N15/'04 Operating Model'!N11 -> 0.26945103 | ... P16: =P15/'04 Operating Model'!P11 -> 0.27186663
B17: Conversión FCFF / EBITDA | C17: % | G17: =G15/'04 Operating Model'!G39 -> -0.22718971 | H17: =H15/'04 Operating Model'!H39 -> 0.13507999 | I17: =I15/'04 Operating Model'!I39 -> 0.35041648 | J17: =J15/'04 Operating Model'!J39 -> 0.47032138 | K17: =K15/'04 Operating Model'!K39 -> 0.55170615 | L17: =L15/'04 Operating Model'!L39 -> 0.57439243 | M17: =M15/'04 Operating Model'!M39 -> 0.58991853 | N17: =N15/'04 Operating Model'!N39 -> 0.59608967 | ... P17: =P15/'04 Operating Model'!P39 -> 0.60504482
B19: DESCUENTO
B20: Periodo de descuento t (convención de '02 Assumptions'!C12) | C20: años | G20: =COLUMNS($G20:G20)-IF('02 Assumptions'!$C$12=2,0.5,0) -> 0.5 | H20: =COLUMNS($G20:H20)-IF('02 Assumptions'!$C$12=2,0.5,0) -> 1.5 | I20: =COLUMNS($G20:I20)-IF('02 Assumptions'!$C$12=2,0.5,0) -> 2.5 | J20: =COLUMNS($G20:J20)-IF('02 Assumptions'!$C$12=2,0.5,0) -> 3.5 | K20: =COLUMNS($G20:K20)-IF('02 Assumptions'!$C$12=2,0.5,0) -> 4.5 | L20: =COLUMNS($G20:L20)-IF('02 Assumptions'!$C$12=2,0.5,0) -> 5.5 | M20: =COLUMNS($G20:M20)-IF('02 Assumptions'!$C$12=2,0.5,0) -> 6.5 | N20: =COLUMNS($G20:N20)-IF('02 Assumptions'!$C$12=2,0.5,0) -> 7.5 | ... P20: =COLUMNS($G20:P20)-IF('02 Assumptions'!$C$12=2,0.5,0) -> 9.5
B21: WACC | C21: % | G21: ='07 WACC'!$C$38 -> 0.087495 | H21: ='07 WACC'!$C$38 -> 0.087495 | I21: ='07 WACC'!$C$38 -> 0.087495 | J21: ='07 WACC'!$C$38 -> 0.087495 | K21: ='07 WACC'!$C$38 -> 0.087495 | L21: ='07 WACC'!$C$38 -> 0.087495 | M21: ='07 WACC'!$C$38 -> 0.087495 | N21: ='07 WACC'!$C$38 -> 0.087495 | ... P21: ='07 WACC'!$C$38 -> 0.087495
B22: Factor de descuento = 1 / (1 + WACC)^t | C22: x | G22: =1/(1+G21)^G20 -> 0.95892881 | H22: =1/(1+H21)^H20 -> 0.88177767 | I22: =1/(1+I21)^I20 -> 0.81083377 | J22: =1/(1+J21)^J20 -> 0.7455977 | K22: =1/(1+K21)^K20 -> 0.68561023 | L22: =1/(1+L21)^L20 -> 0.63044909 | M22: =1/(1+M21)^M20 -> 0.57972597 | N22: =1/(1+N21)^N20 -> 0.5330838 | ... P22: =1/(1+P21)^P20 -> 0.45075541
B23: Valor presente del FCFF | C23: $M | G23: =G15*G22 -> -9378.1077 | H23: =H15*H22 -> 6122.1509 | I23: =I15*I22 -> 16816.362 | J23: =J15*J22 -> 23399.39 | K23: =K15*K22 -> 27809.006 | L23: =L15*L22 -> 29016.586 | M23: =M15*M22 -> 29328.615 | N23: =N15*N22 -> 28899.671 | ... P23: =P15*P22 -> 26640.773
B25: VALOR TERMINAL
B26: Crecimiento terminal g | C26: % | F26: ='02 Assumptions'!C63 -> 0.03
B27: ROIC terminal | C27: % | F27: ='02 Assumptions'!C66 -> 0.24
B28: Tasa de reinversión terminal = g / ROIC terminal | C28: % | F28: =F26/F27 -> 0.125
B29: NOPAT terminal = NOPAT FY2036 × (1 + g) | C29: $M | F29: =P10*(1+F26) -> 61047.557
B30: FCFF terminal = NOPAT terminal × (1 − tasa de reinversión) | C30: $M | F30: =F29*(1-F28) -> 53416.612
B31: Valor terminal — Gordon = FCFF terminal / (WACC − g) | C31: $M | F31: =IF(P21<=F26,"FALLO: WACC<=g",F30/(P21-F26)) -> 929065.35
B32: Valor terminal — múltiplo de salida = EBITDA FY2036 × múltiplo | C32: $M | F32: ='04 Operating Model'!P39*'02 Assumptions'!C64 -> 1367560
B33: Método seleccionado ('02 Assumptions'!C13) | F33: =IF('02 Assumptions'!C13=1,"Gordon (crecimiento perpetuo)","Múltiplo de salida EV/EBITDA") -> Gordon (crecimiento perpetuo)
B34: VALOR TERMINAL UTILIZADO | C34: $M | F34: =IF('02 Assumptions'!C13=1,F31,F32) -> 929065.35
B35: Factor de descuento del VT = 1/(1+WACC)^n (año completo, no mitad de año) | C35: x | F35: =1/(1+P21)^'02 Assumptions'!C11 -> 0.43224235
B36: Valor presente del valor terminal | C36: $M | F36: =F34*F35 -> 401581.39
B37: Referencia — FCFF terminal ingenuo = FCFF FY2036 × (1+g) | C37: $M | F37: =P15*(1+F26) -> 60875.58
B38: Referencia — valor terminal ingenuo (sin disciplina de reinversión) | C38: $M | F38: =IF(P21<=F26,"n/a",F37/(P21-F26)) -> 1058797.8
B39: Diferencia: disciplinado − ingenuo | C39: $M | F39: =IFERROR(F34-F38,"n/a") -> -129732.45
B41: PUENTE: ENTERPRISE VALUE → EQUITY VALUE → VALOR POR ACCIÓN
B42: Valor presente del FCFF del periodo explícito | C42: $M | F42: =SUM(G23:P23) -> 206793.81
B43: Valor presente del valor terminal | C43: $M | F43: =F36 -> 401581.39
B44: ENTERPRISE VALUE | C44: $M | F44: =F42+F43 -> 608375.19
B45: Valor terminal / Enterprise Value | C45: % | F45: =F43/F44 -> 0.66008837
B46: (−) Deuda financiera (senior notes y otros préstamos) | C46: $M | F46: =-'02 Assumptions'!C70 -> -129541
B47: (−) Pasivo por leases financieros | C47: $M | F47: =-'02 Assumptions'!C71 -> -7701
B48: (+) Caja y equivalentes | C48: $M | F48: ='02 Assumptions'!C72 -> 31289
B49: (−) Caja mínima operativa (no distribuible) | C49: $M | F49: =-'02 Assumptions'!C68*'03 Historical'!F11 -> -1010.355
B50: (+) Valores negociables | C50: $M | F50: ='02 Assumptions'!C73 -> 605
B51: (−) Intereses minoritarios | C51: $M | F51: =-'02 Assumptions'!C74 -> -548
B52: (−) Preferentes convertibles obligatorias | C52: $M | F52: =-'02 Assumptions'!C75 -> -4954
B53: EQUITY VALUE | C53: $M | F53: =F44+SUM(F46:F52) -> 496514.84
B54: Acciones diluidas | C54: M acc | F54: ='02 Assumptions'!C69 -> 2934
B55: VALOR INTRÍNSECO POR ACCIÓN | C55: $/acc | F55: =F53/F54 -> 169.22796
B56: Precio de mercado actual (input en '01 Summary'!C10) | C56: $/acc | F56: ='01 Summary'!$C$10 -> 0
B57: Upside / (Downside) | C57: % | F57: =IF(F56<=0,"introducir precio",F55/F56-1) -> introducir precio
B58: Margen de seguridad implícito = 1 − precio / valor | C58: % | F58: =IF(F56<=0,"introducir precio",1-F56/F55) -> introducir precio
B60: CONTROLES DE CALIDAD DEL VALOR TERMINAL Y MÚLTIPLOS IMPLÍCITOS
B61: EBITDA FY2036E | C61: $M | F61: ='04 Operating Model'!P39 -> 97682.854
B62: Múltiplo de salida IMPLÍCITO (VT / EBITDA FY2036) | C62: x | F62: =IFERROR(F34/F61,"n/a") -> 9.5110381
B63: Margen EBIT normalizado terminal | C63: % | F63: ='04 Operating Model'!P30 -> 0.33658601
B64: Capex terminal / ingresos | C64: % | F64: ='04 Operating Model'!P35 -> 0.118
B65: D&A terminal / ingresos | C65: % | F65: ='04 Operating Model'!P38/'04 Operating Model'!P11 -> 0.11274703
B66: Capex / D&A terminal | C66: x | F66: ='04 Operating Model'!P41 -> 1.0465907
B67: CHECK: g < WACC | F67: =IF(P21>F26,"OK","FALLO") -> OK
B68: CHECK: g ≤ PIB nominal de referencia | F68: =IF(F26<='02 Assumptions'!C65,"OK","FALLO: g por encima del PIB nominal") -> OK
B69: CHECK: múltiplo de salida implícito en rango razonable (8x–25x) | F69: =IF(AND(F62>=8,F62<=25),"OK","AVISO: múltiplo implícito fuera de rango — revisar g, ROIC terminal o WACC") -> OK
B70: CHECK: peso del valor terminal sobre el EV | F70: =IF(F45>0.75,"AVISO: el valor depende mayoritariamente de las hipótesis terminales","OK") -> OK
B71: EV / EBITDA FY2026A implícito | C71: x | F71: =F44/'03 Historical'!F125 -> 19.168668
B72: EV / Ingresos FY2026A implícito | C72: x | F72: =F44/'03 Historical'!F11 -> 9.0321005
B73: FCFF acumulado del periodo explícito | C73: $M | F73: =SUM(G15:P15) -> 357182.14
B74: Años con FCFF negativo en el periodo explícito | C74: años | F74: =COUNTIF(G15:P15,"<0") -> 1
B75: CHECK: el FCFF llega a ser positivo dentro del horizonte | F75: =IF(P15>0,"OK","FALLO: FCFF negativo al final del horizonte — el FCFF DCF no es la metodología adecuada") -> OK

Sheet 07 WACC
A1: COSTE MEDIO PONDERADO DEL CAPITAL (WACC) — ORACLE CORPORATION
A2: AMARILLO = input de mercado que DEBE actualizarse y fecharse en cada revisión. El WACC se calcula sobre estructura de capital OBJETIVO, no sobre el precio del día.
B4: COSTE DE LOS RECURSOS PROPIOS (Ke) — CAPM
B5: Tipo libre de riesgo (bono EEUU 10 años) | C5: ='00 Panel del Analista'!D207 -> 0 | D5: %
B6: Prima de riesgo de mercado (ERP) | C6: ='00 Panel del Analista'!D208 -> 0 | D6: %
B7: Beta utilizada (reapalancada, ver bloque inferior) | C7: =C19 -> 1.2 | D7: x
B8: Prima adicional por riesgo país / tamaño | C8: ='00 Panel del Analista'!D209 -> 0 | D8: %
B9: Ke = Rf + Beta × ERP + prima adicional | C9: =C5+C7*C6+C8 -> 0.099 | D9: %
B11: DESAPALANCAMIENTO Y REAPALANCAMIENTO DE BETA
B12: Beta apalancada observada (regresión a 5 años, mensual) | C12: ='00 Panel del Analista'!D210 -> 0 | D12: x
B13: D/E de mercado correspondiente a la beta observada | C13: ='00 Panel del Analista'!D211 -> 0 | D13: x
B14: Tipo impositivo marginal | C14: ='02 Assumptions'!C58 -> 0.21 | D14: %
B15: Beta desapalancada = Beta apalancada / (1 + (1−T) × D/E) | C15: =C12/(1+(1-C14)*C13) -> 1.0020877 | D15: x
B16: D/E objetivo = peso deuda / peso equity | C16: =C31/C32 -> 0.25 | D16: x
B17: Beta reapalancada = Beta desapalancada × (1 + (1−T) × D/E objetivo) | C17: =C15*(1+(1-C14)*C16) -> 1.2 | D17: x
B19: BETA UTILIZADA EN EL Ke | C19: =C17 -> 1.2 | D19: x
B21: COSTE DE LA DEUDA (Kd)
B22: Gasto por intereses FY2026 (reportado) | C22: ='03 Historical'!F29 -> 4599 | D22: $M
B23: Deuda media FY2025–FY2026 (senior notes + leases financieros) | C23: =AVERAGE('03 Historical'!E110+'03 Historical'!E112,'03 Historical'!F110+'03 Historical'!F112) -> 116372 | D23: $M
B24: Kd implícito histórico = intereses / deuda media | C24: =C22/C23 -> 0.039519816 | D24: %
B25: Kd MARGINAL utilizado (coste de la deuda nueva) | C25: ='00 Panel del Analista'!D212 -> 0 | D25: %
B26: Kd después de impuestos = Kd × (1 − T) | C26: =C25*(1-C14) -> 0.041475 | D26: %
B28: ESTRUCTURA DE CAPITAL
B29: Capitalización de mercado (precio × acciones diluidas) | C29: =IF('01 Summary'!$C$10<=0,0,'01 Summary'!$C$10*'02 Assumptions'!C69) -> 0 | D29: $M
B30: Deuda total (senior notes + leases financieros) | C30: ='02 Assumptions'!C70+'02 Assumptions'!C71 -> 137242 | D30: $M
B31: PESO OBJETIVO DE LA DEUDA D/(D+E) | C31: ='00 Panel del Analista'!D213 -> 0 | D31: %
B32: Peso de los recursos propios E/(D+E) | C32: =1-C31 -> 0.8 | D32: %
B33: Peso de deuda implícito por mercado (cross-check; requiere precio) | C33: =IF(C29<=0,"introducir precio en Summary!C10",C30/(C30+C29)) -> introducir precio en Summary!C10 | D33: %
B35: WACC
B36: WACC base = E/(D+E)×Ke + D/(D+E)×Kd×(1−T) | C36: =C32*C9+C31*C26 -> 0.087495 | D36: %
B37: Delta de escenario | C37: ='09 Escenarios'!$G$17 -> 0 | D37: pp
B38: WACC ACTIVO | C38: =C36+C37 -> 0.087495 | D38: %
B40: CONTROLES OBLIGATORIOS
B41: Crecimiento terminal g | C41: ='02 Assumptions'!C63 -> 0.03 | D41: %
B42: CHECK: WACC > g | C42: =IF(C38>C41,"OK","FALLO — g debe ser menor que el WACC") -> OK
B43: Margen WACC − g | C43: =C38-C41 -> 0.057495 | D43: pp
B44: CHECK: Kd marginal ≥ Kd implícito histórico | C44: =IF(C25>=C24,"OK","REVISAR — el coste marginal de la deuda nueva no debería ser inferior al histórico") -> OK
B45: CHECK: Ke > Kd (coherencia de prelación de riesgo) | C45: =IF(C9>C25,"OK","FALLO") -> OK
B47: DOCUMENTACIÓN DE LOS INPUTS DE MERCADO (obligatorio rellenar en cada revisión)
B48: Input | C48: Valor usado | D48: Fuente que DEBE documentar el analista | E48: Riesgo si es incorrecto
B49: Tipo libre de riesgo | C49: =C5 -> 0.042 | D49: Rendimiento del bono del Tesoro EEUU a 10 años a la fecha de valoración. Fuente oficial: Treasury.gov / FRED. NO verificado por Claude. | E49: Afecta linealmente al Ke y por tanto al WACC. 100 pb de error mueven el valor de forma material por la duración del flujo.
B50: Prima de riesgo de mercado | C50: =C6 -> 0.0475 | D50: Prima implícita o histórica. Debe ser consistente con el tipo libre de riesgo usado (no mezclar ERP histórica con Rf actual sin criterio). | E50: Segundo input más sensible del WACC.
B51: Beta apalancada observada | C51: =C12 -> 1.2 | D51: Regresión del rendimiento de ORCL contra el índice, 5 años mensual, o media de comparables. NO verificado por Claude. | E51: La beta de Oracle ha cambiado estructuralmente con el apalancamiento y el giro a IaaS: una beta histórica de hace 5 años ya no describe el riesgo actual del negocio.
B52: Kd marginal | C52: =C25 -> 0.0525 | D52: Rendimiento al vencimiento de la deuda cotizada de Oracle a largo plazo, o el diferencial de crédito sobre el Rf para su rating actual. | E52: Con 129.541 de deuda y 46.093 de emisión nueva en FY2026, el coste marginal de la deuda es un input de primer orden, no un residuo.
B53: Peso objetivo de la deuda | C53: =C31 -> 0.2 | D53: Estructura objetivo declarada por la dirección o la media del sector. Se usa objetivo y no la del día para evitar que el WACC oscile con la cotización. | E53: Usar la estructura contable (deuda/patrimonio contable ≈ 3x) produciría un WACC absurdamente bajo. Usar la de mercado del día introduce circularidad precio → WACC → valor.
B54: Estructura objetivo vs actual | D54: Oracle ha pasado de 92.568 a 129.541 de deuda en un año para financiar capex. El 20% objetivo asume desapalancamiento a medida que el capex normaliza. | E54: Si el apalancamiento NO baja, el WACC real es superior y el valor menor. Está recogido en el escenario Bear (+100 pb).
B56: FECHA DE ÚLTIMA ACTUALIZACIÓN DE LOS INPUTS DE MERCADO (introducir dd/mm/aaaa) | C56: ='00 Panel del Analista'!D214 -> 0
B57: Mientras esta celda esté vacía, el control 66 de '13 Checks' permanecerá en AVISO: el WACC no es defendible sin fuente y fecha.

Sheet Sensibilidad
A1: ANÁLISIS DE SENSIBILIDAD — VALOR INTRÍNSECO POR ACCIÓN ($)
A2: Rejillas 5×5 con el caso base en el CENTRO (celda amarilla). Recalculadas en forma cerrada sobre el flujo de '06 DCF': el FCFF no depende del WACC ni de g, por lo que la revaloración es exacta salvo donde se indique.
B4: REJILLA A — WACC × CRECIMIENTO TERMINAL g (exacta) | M4: 123.45
B5: WACC ↓ / g → | D5: ='06 DCF'!$F$26+-0.01 -> 0.02 | E5: ='06 DCF'!$F$26+-0.005 -> 0.025 | F5: ='06 DCF'!$F$26+0 -> 0.03 | G5: ='06 DCF'!$F$26+0.005 -> 0.035 | H5: ='06 DCF'!$F$26+0.01 -> 0.04
C6: ='07 WACC'!$C$38+-0.01 -> 0.077495 | D6: {=(SUMPRODUCT('06 DCF'!$G$15:$P$15,1/(1+$C6)^'06 DCF'!$G$20:$P$20)+'06 DCF'!$P$10*(1+D$5)*(1-D$5/'06 DCF'!$F$27)/($C6-D$5)/(1+$C6)^'02 Assumptions'!$C$11+SUM('06 DCF'!$F$46:$F$52))/'06 DCF'!$F$54} -> 0 | E6: {=(SUMPRODUCT('06 DCF'!$G$15:$P$15,1/(1+$C6)^'06 DCF'!$G$20:$P$20)+'06 DCF'!$P$10*(1+E$5)*(1-E$5/'06 DCF'!$F$27)/($C6-E$5)/(1+$C6)^'02 Assumptions'!$C$11+SUM('06 DCF'!$F$46:$F$52))/'06 DCF'!$F$54} -> 0 | F6: {=(SUMPRODUCT('06 DCF'!$G$15:$P$15,1/(1+$C6)^'06 DCF'!$G$20:$P$20)+'06 DCF'!$P$10*(1+F$5)*(1-F$5/'06 DCF'!$F$27)/($C6-F$5)/(1+$C6)^'02 Assumptions'!$C$11+SUM('06 DCF'!$F$46:$F$52))/'06 DCF'!$F$54} -> 0 | G6: {=(SUMPRODUCT('06 DCF'!$G$15:$P$15,1/(1+$C6)^'06 DCF'!$G$20:$P$20)+'06 DCF'!$P$10*(1+G$5)*(1-G$5/'06 DCF'!$F$27)/($C6-G$5)/(1+$C6)^'02 Assumptions'!$C$11+SUM('06 DCF'!$F$46:$F$52))/'06 DCF'!$F$54} -> 0 | H6: {=(SUMPRODUCT('06 DCF'!$G$15:$P$15,1/(1+$C6)^'06 DCF'!$G$20:$P$20)+'06 DCF'!$P$10*(1+H$5)*(1-H$5/'06 DCF'!$F$27)/($C6-H$5)/(1+$C6)^'02 Assumptions'!$C$11+SUM('06 DCF'!$F$46:$F$52))/'06 DCF'!$F$54} -> 0
C7: ='07 WACC'!$C$38+-0.005 -> 0.082495 | D7: {=(SUMPRODUCT('06 DCF'!$G$15:$P$15,1/(1+$C7)^'06 DCF'!$G$20:$P$20)+'06 DCF'!$P$10*(1+D$5)*(1-D$5/'06 DCF'!$F$27)/($C7-D$5)/(1+$C7)^'02 Assumptions'!$C$11+SUM('06 DCF'!$F$46:$F$52))/'06 DCF'!$F$54} -> 0 | E7: {=(SUMPRODUCT('06 DCF'!$G$15:$P$15,1/(1+$C7)^'06 DCF'!$G$20:$P$20)+'06 DCF'!$P$10*(1+E$5)*(1-E$5/'06 DCF'!$F$27)/($C7-E$5)/(1+$C7)^'02 Assumptions'!$C$11+SUM('06 DCF'!$F$46:$F$52))/'06 DCF'!$F$54} -> 0 | F7: {=(SUMPRODUCT('06 DCF'!$G$15:$P$15,1/(1+$C7)^'06 DCF'!$G$20:$P$20)+'06 DCF'!$P$10*(1+F$5)*(1-F$5/'06 DCF'!$F$27)/($C7-F$5)/(1+$C7)^'02 Assumptions'!$C$11+SUM('06 DCF'!$F$46:$F$52))/'06 DCF'!$F$54} -> 0 | G7: {=(SUMPRODUCT('06 DCF'!$G$15:$P$15,1/(1+$C7)^'06 DCF'!$G$20:$P$20)+'06 DCF'!$P$10*(1+G$5)*(1-G$5/'06 DCF'!$F$27)/($C7-G$5)/(1+$C7)^'02 Assumptions'!$C$11+SUM('06 DCF'!$F$46:$F$52))/'06 DCF'!$F$54} -> 0 | H7: {=(SUMPRODUCT('06 DCF'!$G$15:$P$15,1/(1+$C7)^'06 DCF'!$G$20:$P$20)+'06 DCF'!$P$10*(1+H$5)*(1-H$5/'06 DCF'!$F$27)/($C7-H$5)/(1+$C7)^'02 Assumptions'!$C$11+SUM('06 DCF'!$F$46:$F$52))/'06 DCF'!$F$54} -> 0
C8: ='07 WACC'!$C$38+0 -> 0.087495 | D8: {=(SUMPRODUCT('06 DCF'!$G$15:$P$15,1/(1+$C8)^'06 DCF'!$G$20:$P$20)+'06 DCF'!$P$10*(1+D$5)*(1-D$5/'06 DCF'!$F$27)/($C8-D$5)/(1+$C8)^'02 Assumptions'!$C$11+SUM('06 DCF'!$F$46:$F$52))/'06 DCF'!$F$54} -> 0 | E8: {=(SUMPRODUCT('06 DCF'!$G$15:$P$15,1/(1+$C8)^'06 DCF'!$G$20:$P$20)+'06 DCF'!$P$10*(1+E$5)*(1-E$5/'06 DCF'!$F$27)/($C8-E$5)/(1+$C8)^'02 Assumptions'!$C$11+SUM('06 DCF'!$F$46:$F$52))/'06 DCF'!$F$54} -> 0 | F8: {=(SUMPRODUCT('06 DCF'!$G$15:$P$15,1/(1+$C8)^'06 DCF'!$G$20:$P$20)+'06 DCF'!$P$10*(1+F$5)*(1-F$5/'06 DCF'!$F$27)/($C8-F$5)/(1+$C8)^'02 Assumptions'!$C$11+SUM('06 DCF'!$F$46:$F$52))/'06 DCF'!$F$54} -> 0 | G8: {=(SUMPRODUCT('06 DCF'!$G$15:$P$15,1/(1+$C8)^'06 DCF'!$G$20:$P$20)+'06 DCF'!$P$10*(1+G$5)*(1-G$5/'06 DCF'!$F$27)/($C8-G$5)/(1+$C8)^'02 Assumptions'!$C$11+SUM('06 DCF'!$F$46:$F$52))/'06 DCF'!$F$54} -> 0 | H8: {=(SUMPRODUCT('06 DCF'!$G$15:$P$15,1/(1+$C8)^'06 DCF'!$G$20:$P$20)+'06 DCF'!$P$10*(1+H$5)*(1-H$5/'06 DCF'!$F$27)/($C8-H$5)/(1+$C8)^'02 Assumptions'!$C$11+SUM('06 DCF'!$F$46:$F$52))/'06 DCF'!$F$54} -> 0
C9: ='07 WACC'!$C$38+0.005 -> 0.092495 | D9: {=(SUMPRODUCT('06 DCF'!$G$15:$P$15,1/(1+$C9)^'06 DCF'!$G$20:$P$20)+'06 DCF'!$P$10*(1+D$5)*(1-D$5/'06 DCF'!$F$27)/($C9-D$5)/(1+$C9)^'02 Assumptions'!$C$11+SUM('06 DCF'!$F$46:$F$52))/'06 DCF'!$F$54} -> 0 | E9: {=(SUMPRODUCT('06 DCF'!$G$15:$P$15,1/(1+$C9)^'06 DCF'!$G$20:$P$20)+'06 DCF'!$P$10*(1+E$5)*(1-E$5/'06 DCF'!$F$27)/($C9-E$5)/(1+$C9)^'02 Assumptions'!$C$11+SUM('06 DCF'!$F$46:$F$52))/'06 DCF'!$F$54} -> 0 | F9: {=(SUMPRODUCT('06 DCF'!$G$15:$P$15,1/(1+$C9)^'06 DCF'!$G$20:$P$20)+'06 DCF'!$P$10*(1+F$5)*(1-F$5/'06 DCF'!$F$27)/($C9-F$5)/(1+$C9)^'02 Assumptions'!$C$11+SUM('06 DCF'!$F$46:$F$52))/'06 DCF'!$F$54} -> 0 | G9: {=(SUMPRODUCT('06 DCF'!$G$15:$P$15,1/(1+$C9)^'06 DCF'!$G$20:$P$20)+'06 DCF'!$P$10*(1+G$5)*(1-G$5/'06 DCF'!$F$27)/($C9-G$5)/(1+$C9)^'02 Assumptions'!$C$11+SUM('06 DCF'!$F$46:$F$52))/'06 DCF'!$F$54} -> 0 | H9: {=(SUMPRODUCT('06 DCF'!$G$15:$P$15,1/(1+$C9)^'06 DCF'!$G$20:$P$20)+'06 DCF'!$P$10*(1+H$5)*(1-H$5/'06 DCF'!$F$27)/($C9-H$5)/(1+$C9)^'02 Assumptions'!$C$11+SUM('06 DCF'!$F$46:$F$52))/'06 DCF'!$F$54} -> 0
C10: ='07 WACC'!$C$38+0.01 -> 0.097495 | D10: {=(SUMPRODUCT('06 DCF'!$G$15:$P$15,1/(1+$C10)^'06 DCF'!$G$20:$P$20)+'06 DCF'!$P$10*(1+D$5)*(1-D$5/'06 DCF'!$F$27)/($C10-D$5)/(1+$C10)^'02 Assumptions'!$C$11+SUM('06 DCF'!$F$46:$F$52))/'06 DCF'!$F$54} -> 0 | E10: {=(SUMPRODUCT('06 DCF'!$G$15:$P$15,1/(1+$C10)^'06 DCF'!$G$20:$P$20)+'06 DCF'!$P$10*(1+E$5)*(1-E$5/'06 DCF'!$F$27)/($C10-E$5)/(1+$C10)^'02 Assumptions'!$C$11+SUM('06 DCF'!$F$46:$F$52))/'06 DCF'!$F$54} -> 0 | F10: {=(SUMPRODUCT('06 DCF'!$G$15:$P$15,1/(1+$C10)^'06 DCF'!$G$20:$P$20)+'06 DCF'!$P$10*(1+F$5)*(1-F$5/'06 DCF'!$F$27)/($C10-F$5)/(1+$C10)^'02 Assumptions'!$C$11+SUM('06 DCF'!$F$46:$F$52))/'06 DCF'!$F$54} -> 0 | G10: {=(SUMPRODUCT('06 DCF'!$G$15:$P$15,1/(1+$C10)^'06 DCF'!$G$20:$P$20)+'06 DCF'!$P$10*(1+G$5)*(1-G$5/'06 DCF'!$F$27)/($C10-G$5)/(1+$C10)^'02 Assumptions'!$C$11+SUM('06 DCF'!$F$46:$F$52))/'06 DCF'!$F$54} -> 0 | H10: {=(SUMPRODUCT('06 DCF'!$G$15:$P$15,1/(1+$C10)^'06 DCF'!$G$20:$P$20)+'06 DCF'!$P$10*(1+H$5)*(1-H$5/'06 DCF'!$F$27)/($C10-H$5)/(1+$C10)^'02 Assumptions'!$C$11+SUM('06 DCF'!$F$46:$F$52))/'06 DCF'!$F$54} -> 0
B13: REJILLA B — WACC × MÚLTIPLO DE SALIDA EV/EBITDA (exacta; método alternativo de valor terminal)
B14: WACC ↓ / múltiplo →
C15: ='07 WACC'!$C$38+-0.01 -> 0.077495 | D15: {=(SUMPRODUCT('06 DCF'!$G$15:$P$15,1/(1+$C15)^'06 DCF'!$G$20:$P$20)+'04 Operating Model'!$P$39*D$14/(1+$C15)^'02 Assumptions'!$C$11+SUM('06 DCF'!$F$46:$F$52))/'06 DCF'!$F$54} -> 0 | E15: {=(SUMPRODUCT('06 DCF'!$G$15:$P$15,1/(1+$C15)^'06 DCF'!$G$20:$P$20)+'04 Operating Model'!$P$39*E$14/(1+$C15)^'02 Assumptions'!$C$11+SUM('06 DCF'!$F$46:$F$52))/'06 DCF'!$F$54} -> 0 | F15: {=(SUMPRODUCT('06 DCF'!$G$15:$P$15,1/(1+$C15)^'06 DCF'!$G$20:$P$20)+'04 Operating Model'!$P$39*F$14/(1+$C15)^'02 Assumptions'!$C$11+SUM('06 DCF'!$F$46:$F$52))/'06 DCF'!$F$54} -> 0 | G15: {=(SUMPRODUCT('06 DCF'!$G$15:$P$15,1/(1+$C15)^'06 DCF'!$G$20:$P$20)+'04 Operating Model'!$P$39*G$14/(1+$C15)^'02 Assumptions'!$C$11+SUM('06 DCF'!$F$46:$F$52))/'06 DCF'!$F$54} -> 0 | H15: {=(SUMPRODUCT('06 DCF'!$G$15:$P$15,1/(1+$C15)^'06 DCF'!$G$20:$P$20)+'04 Operating Model'!$P$39*H$14/(1+$C15)^'02 Assumptions'!$C$11+SUM('06 DCF'!$F$46:$F$52))/'06 DCF'!$F$54} -> 0
C16: ='07 WACC'!$C$38+-0.005 -> 0.082495 | D16: {=(SUMPRODUCT('06 DCF'!$G$15:$P$15,1/(1+$C16)^'06 DCF'!$G$20:$P$20)+'04 Operating Model'!$P$39*D$14/(1+$C16)^'02 Assumptions'!$C$11+SUM('06 DCF'!$F$46:$F$52))/'06 DCF'!$F$54} -> 0 | E16: {=(SUMPRODUCT('06 DCF'!$G$15:$P$15,1/(1+$C16)^'06 DCF'!$G$20:$P$20)+'04 Operating Model'!$P$39*E$14/(1+$C16)^'02 Assumptions'!$C$11+SUM('06 DCF'!$F$46:$F$52))/'06 DCF'!$F$54} -> 0 | F16: {=(SUMPRODUCT('06 DCF'!$G$15:$P$15,1/(1+$C16)^'06 DCF'!$G$20:$P$20)+'04 Operating Model'!$P$39*F$14/(1+$C16)^'02 Assumptions'!$C$11+SUM('06 DCF'!$F$46:$F$52))/'06 DCF'!$F$54} -> 0 | G16: {=(SUMPRODUCT('06 DCF'!$G$15:$P$15,1/(1+$C16)^'06 DCF'!$G$20:$P$20)+'04 Operating Model'!$P$39*G$14/(1+$C16)^'02 Assumptions'!$C$11+SUM('06 DCF'!$F$46:$F$52))/'06 DCF'!$F$54} -> 0 | H16: {=(SUMPRODUCT('06 DCF'!$G$15:$P$15,1/(1+$C16)^'06 DCF'!$G$20:$P$20)+'04 Operating Model'!$P$39*H$14/(1+$C16)^'02 Assumptions'!$C$11+SUM('06 DCF'!$F$46:$F$52))/'06 DCF'!$F$54} -> 0
C17: ='07 WACC'!$C$38+0 -> 0.087495 | D17: {=(SUMPRODUCT('06 DCF'!$G$15:$P$15,1/(1+$C17)^'06 DCF'!$G$20:$P$20)+'04 Operating Model'!$P$39*D$14/(1+$C17)^'02 Assumptions'!$C$11+SUM('06 DCF'!$F$46:$F$52))/'06 DCF'!$F$54} -> 0 | E17: {=(SUMPRODUCT('06 DCF'!$G$15:$P$15,1/(1+$C17)^'06 DCF'!$G$20:$P$20)+'04 Operating Model'!$P$39*E$14/(1+$C17)^'02 Assumptions'!$C$11+SUM('06 DCF'!$F$46:$F$52))/'06 DCF'!$F$54} -> 0 | F17: {=(SUMPRODUCT('06 DCF'!$G$15:$P$15,1/(1+$C17)^'06 DCF'!$G$20:$P$20)+'04 Operating Model'!$P$39*F$14/(1+$C17)^'02 Assumptions'!$C$11+SUM('06 DCF'!$F$46:$F$52))/'06 DCF'!$F$54} -> 0 | G17: {=(SUMPRODUCT('06 DCF'!$G$15:$P$15,1/(1+$C17)^'06 DCF'!$G$20:$P$20)+'04 Operating Model'!$P$39*G$14/(1+$C17)^'02 Assumptions'!$C$11+SUM('06 DCF'!$F$46:$F$52))/'06 DCF'!$F$54} -> 0 | H17: {=(SUMPRODUCT('06 DCF'!$G$15:$P$15,1/(1+$C17)^'06 DCF'!$G$20:$P$20)+'04 Operating Model'!$P$39*H$14/(1+$C17)^'02 Assumptions'!$C$11+SUM('06 DCF'!$F$46:$F$52))/'06 DCF'!$F$54} -> 0
C18: ='07 WACC'!$C$38+0.005 -> 0.092495 | D18: {=(SUMPRODUCT('06 DCF'!$G$15:$P$15,1/(1+$C18)^'06 DCF'!$G$20:$P$20)+'04 Operating Model'!$P$39*D$14/(1+$C18)^'02 Assumptions'!$C$11+SUM('06 DCF'!$F$46:$F$52))/'06 DCF'!$F$54} -> 0 | E18: {=(SUMPRODUCT('06 DCF'!$G$15:$P$15,1/(1+$C18)^'06 DCF'!$G$20:$P$20)+'04 Operating Model'!$P$39*E$14/(1+$C18)^'02 Assumptions'!$C$11+SUM('06 DCF'!$F$46:$F$52))/'06 DCF'!$F$54} -> 0 | F18: {=(SUMPRODUCT('06 DCF'!$G$15:$P$15,1/(1+$C18)^'06 DCF'!$G$20:$P$20)+'04 Operating Model'!$P$39*F$14/(1+$C18)^'02 Assumptions'!$C$11+SUM('06 DCF'!$F$46:$F$52))/'06 DCF'!$F$54} -> 0 | G18: {=(SUMPRODUCT('06 DCF'!$G$15:$P$15,1/(1+$C18)^'06 DCF'!$G$20:$P$20)+'04 Operating Model'!$P$39*G$14/(1+$C18)^'02 Assumptions'!$C$11+SUM('06 DCF'!$F$46:$F$52))/'06 DCF'!$F$54} -> 0 | H18: {=(SUMPRODUCT('06 DCF'!$G$15:$P$15,1/(1+$C18)^'06 DCF'!$G$20:$P$20)+'04 Operating Model'!$P$39*H$14/(1+$C18)^'02 Assumptions'!$C$11+SUM('06 DCF'!$F$46:$F$52))/'06 DCF'!$F$54} -> 0
C19: ='07 WACC'!$C$38+0.01 -> 0.097495 | D19: {=(SUMPRODUCT('06 DCF'!$G$15:$P$15,1/(1+$C19)^'06 DCF'!$G$20:$P$20)+'04 Operating Model'!$P$39*D$14/(1+$C19)^'02 Assumptions'!$C$11+SUM('06 DCF'!$F$46:$F$52))/'06 DCF'!$F$54} -> 0 | E19: {=(SUMPRODUCT('06 DCF'!$G$15:$P$15,1/(1+$C19)^'06 DCF'!$G$20:$P$20)+'04 Operating Model'!$P$39*E$14/(1+$C19)^'02 Assumptions'!$C$11+SUM('06 DCF'!$F$46:$F$52))/'06 DCF'!$F$54} -> 0 | F19: {=(SUMPRODUCT('06 DCF'!$G$15:$P$15,1/(1+$C19)^'06 DCF'!$G$20:$P$20)+'04 Operating Model'!$P$39*F$14/(1+$C19)^'02 Assumptions'!$C$11+SUM('06 DCF'!$F$46:$F$52))/'06 DCF'!$F$54} -> 0 | G19: {=(SUMPRODUCT('06 DCF'!$G$15:$P$15,1/(1+$C19)^'06 DCF'!$G$20:$P$20)+'04 Operating Model'!$P$39*G$14/(1+$C19)^'02 Assumptions'!$C$11+SUM('06 DCF'!$F$46:$F$52))/'06 DCF'!$F$54} -> 0 | H19: {=(SUMPRODUCT('06 DCF'!$G$15:$P$15,1/(1+$C19)^'06 DCF'!$G$20:$P$20)+'04 Operating Model'!$P$39*H$14/(1+$C19)^'02 Assumptions'!$C$11+SUM('06 DCF'!$F$46:$F$52))/'06 DCF'!$F$54} -> 0
B22: REJILLA C — WACC × DESPLAZAMIENTO DEL MARGEN EBIT (pp) (exacta)
B23: WACC ↓ / Δ margen EBIT (p.p.) →
C24: ='07 WACC'!$C$38+-0.01 -> 0.077495 | D24: {=(SUMPRODUCT('06 DCF'!$G$15:$P$15+D$23*'04 Operating Model'!$G$11:$P$11*(1-'04 Operating Model'!$G$55:$P$55),1/(1+$C24)^'06 DCF'!$G$20:$P$20)+('06 DCF'!$P$10+D$23*'04 Operating Model'!$P$11*(1-'04 Operating Model'!$P$55))*(1+'06 DCF'!$F$26)*(1-'06 DCF'!$F$26/'06 DCF'!$F$27)/($C24-'06 DCF'!$F$26)/(1+$C24)^'02 Assumptions'!$C$11+SUM('06 DCF'!$F$46:$F$52))/'06 DCF'!$F$54} -> 0 | E24: {=(SUMPRODUCT('06 DCF'!$G$15:$P$15+E$23*'04 Operating Model'!$G$11:$P$11*(1-'04 Operating Model'!$G$55:$P$55),1/(1+$C24)^'06 DCF'!$G$20:$P$20)+('06 DCF'!$P$10+E$23*'04 Operating Model'!$P$11*(1-'04 Operating Model'!$P$55))*(1+'06 DCF'!$F$26)*(1-'06 DCF'!$F$26/'06 DCF'!$F$27)/($C24-'06 DCF'!$F$26)/(1+$C24)^'02 Assumptions'!$C$11+SUM('06 DCF'!$F$46:$F$52))/'06 DCF'!$F$54} -> 0 | F24: {=(SUMPRODUCT('06 DCF'!$G$15:$P$15+F$23*'04 Operating Model'!$G$11:$P$11*(1-'04 Operating Model'!$G$55:$P$55),1/(1+$C24)^'06 DCF'!$G$20:$P$20)+('06 DCF'!$P$10+F$23*'04 Operating Model'!$P$11*(1-'04 Operating Model'!$P$55))*(1+'06 DCF'!$F$26)*(1-'06 DCF'!$F$26/'06 DCF'!$F$27)/($C24-'06 DCF'!$F$26)/(1+$C24)^'02 Assumptions'!$C$11+SUM('06 DCF'!$F$46:$F$52))/'06 DCF'!$F$54} -> 0 | G24: {=(SUMPRODUCT('06 DCF'!$G$15:$P$15+G$23*'04 Operating Model'!$G$11:$P$11*(1-'04 Operating Model'!$G$55:$P$55),1/(1+$C24)^'06 DCF'!$G$20:$P$20)+('06 DCF'!$P$10+G$23*'04 Operating Model'!$P$11*(1-'04 Operating Model'!$P$55))*(1+'06 DCF'!$F$26)*(1-'06 DCF'!$F$26/'06 DCF'!$F$27)/($C24-'06 DCF'!$F$26)/(1+$C24)^'02 Assumptions'!$C$11+SUM('06 DCF'!$F$46:$F$52))/'06 DCF'!$F$54} -> 0 | H24: {=(SUMPRODUCT('06 DCF'!$G$15:$P$15+H$23*'04 Operating Model'!$G$11:$P$11*(1-'04 Operating Model'!$G$55:$P$55),1/(1+$C24)^'06 DCF'!$G$20:$P$20)+('06 DCF'!$P$10+H$23*'04 Operating Model'!$P$11*(1-'04 Operating Model'!$P$55))*(1+'06 DCF'!$F$26)*(1-'06 DCF'!$F$26/'06 DCF'!$F$27)/($C24-'06 DCF'!$F$26)/(1+$C24)^'02 Assumptions'!$C$11+SUM('06 DCF'!$F$46:$F$52))/'06 DCF'!$F$54} -> 0
C25: ='07 WACC'!$C$38+-0.005 -> 0.082495 | D25: {=(SUMPRODUCT('06 DCF'!$G$15:$P$15+D$23*'04 Operating Model'!$G$11:$P$11*(1-'04 Operating Model'!$G$55:$P$55),1/(1+$C25)^'06 DCF'!$G$20:$P$20)+('06 DCF'!$P$10+D$23*'04 Operating Model'!$P$11*(1-'04 Operating Model'!$P$55))*(1+'06 DCF'!$F$26)*(1-'06 DCF'!$F$26/'06 DCF'!$F$27)/($C25-'06 DCF'!$F$26)/(1+$C25)^'02 Assumptions'!$C$11+SUM('06 DCF'!$F$46:$F$52))/'06 DCF'!$F$54} -> 0 | E25: {=(SUMPRODUCT('06 DCF'!$G$15:$P$15+E$23*'04 Operating Model'!$G$11:$P$11*(1-'04 Operating Model'!$G$55:$P$55),1/(1+$C25)^'06 DCF'!$G$20:$P$20)+('06 DCF'!$P$10+E$23*'04 Operating Model'!$P$11*(1-'04 Operating Model'!$P$55))*(1+'06 DCF'!$F$26)*(1-'06 DCF'!$F$26/'06 DCF'!$F$27)/($C25-'06 DCF'!$F$26)/(1+$C25)^'02 Assumptions'!$C$11+SUM('06 DCF'!$F$46:$F$52))/'06 DCF'!$F$54} -> 0 | F25: {=(SUMPRODUCT('06 DCF'!$G$15:$P$15+F$23*'04 Operating Model'!$G$11:$P$11*(1-'04 Operating Model'!$G$55:$P$55),1/(1+$C25)^'06 DCF'!$G$20:$P$20)+('06 DCF'!$P$10+F$23*'04 Operating Model'!$P$11*(1-'04 Operating Model'!$P$55))*(1+'06 DCF'!$F$26)*(1-'06 DCF'!$F$26/'06 DCF'!$F$27)/($C25-'06 DCF'!$F$26)/(1+$C25)^'02 Assumptions'!$C$11+SUM('06 DCF'!$F$46:$F$52))/'06 DCF'!$F$54} -> 0 | G25: {=(SUMPRODUCT('06 DCF'!$G$15:$P$15+G$23*'04 Operating Model'!$G$11:$P$11*(1-'04 Operating Model'!$G$55:$P$55),1/(1+$C25)^'06 DCF'!$G$20:$P$20)+('06 DCF'!$P$10+G$23*'04 Operating Model'!$P$11*(1-'04 Operating Model'!$P$55))*(1+'06 DCF'!$F$26)*(1-'06 DCF'!$F$26/'06 DCF'!$F$27)/($C25-'06 DCF'!$F$26)/(1+$C25)^'02 Assumptions'!$C$11+SUM('06 DCF'!$F$46:$F$52))/'06 DCF'!$F$54} -> 0 | H25: {=(SUMPRODUCT('06 DCF'!$G$15:$P$15+H$23*'04 Operating Model'!$G$11:$P$11*(1-'04 Operating Model'!$G$55:$P$55),1/(1+$C25)^'06 DCF'!$G$20:$P$20)+('06 DCF'!$P$10+H$23*'04 Operating Model'!$P$11*(1-'04 Operating Model'!$P$55))*(1+'06 DCF'!$F$26)*(1-'06 DCF'!$F$26/'06 DCF'!$F$27)/($C25-'06 DCF'!$F$26)/(1+$C25)^'02 Assumptions'!$C$11+SUM('06 DCF'!$F$46:$F$52))/'06 DCF'!$F$54} -> 0
C26: ='07 WACC'!$C$38+0 -> 0.087495 | D26: {=(SUMPRODUCT('06 DCF'!$G$15:$P$15+D$23*'04 Operating Model'!$G$11:$P$11*(1-'04 Operating Model'!$G$55:$P$55),1/(1+$C26)^'06 DCF'!$G$20:$P$20)+('06 DCF'!$P$10+D$23*'04 Operating Model'!$P$11*(1-'04 Operating Model'!$P$55))*(1+'06 DCF'!$F$26)*(1-'06 DCF'!$F$26/'06 DCF'!$F$27)/($C26-'06 DCF'!$F$26)/(1+$C26)^'02 Assumptions'!$C$11+SUM('06 DCF'!$F$46:$F$52))/'06 DCF'!$F$54} -> 0 | E26: {=(SUMPRODUCT('06 DCF'!$G$15:$P$15+E$23*'04 Operating Model'!$G$11:$P$11*(1-'04 Operating Model'!$G$55:$P$55),1/(1+$C26)^'06 DCF'!$G$20:$P$20)+('06 DCF'!$P$10+E$23*'04 Operating Model'!$P$11*(1-'04 Operating Model'!$P$55))*(1+'06 DCF'!$F$26)*(1-'06 DCF'!$F$26/'06 DCF'!$F$27)/($C26-'06 DCF'!$F$26)/(1+$C26)^'02 Assumptions'!$C$11+SUM('06 DCF'!$F$46:$F$52))/'06 DCF'!$F$54} -> 0 | F26: {=(SUMPRODUCT('06 DCF'!$G$15:$P$15+F$23*'04 Operating Model'!$G$11:$P$11*(1-'04 Operating Model'!$G$55:$P$55),1/(1+$C26)^'06 DCF'!$G$20:$P$20)+('06 DCF'!$P$10+F$23*'04 Operating Model'!$P$11*(1-'04 Operating Model'!$P$55))*(1+'06 DCF'!$F$26)*(1-'06 DCF'!$F$26/'06 DCF'!$F$27)/($C26-'06 DCF'!$F$26)/(1+$C26)^'02 Assumptions'!$C$11+SUM('06 DCF'!$F$46:$F$52))/'06 DCF'!$F$54} -> 0 | G26: {=(SUMPRODUCT('06 DCF'!$G$15:$P$15+G$23*'04 Operating Model'!$G$11:$P$11*(1-'04 Operating Model'!$G$55:$P$55),1/(1+$C26)^'06 DCF'!$G$20:$P$20)+('06 DCF'!$P$10+G$23*'04 Operating Model'!$P$11*(1-'04 Operating Model'!$P$55))*(1+'06 DCF'!$F$26)*(1-'06 DCF'!$F$26/'06 DCF'!$F$27)/($C26-'06 DCF'!$F$26)/(1+$C26)^'02 Assumptions'!$C$11+SUM('06 DCF'!$F$46:$F$52))/'06 DCF'!$F$54} -> 0 | H26: {=(SUMPRODUCT('06 DCF'!$G$15:$P$15+H$23*'04 Operating Model'!$G$11:$P$11*(1-'04 Operating Model'!$G$55:$P$55),1/(1+$C26)^'06 DCF'!$G$20:$P$20)+('06 DCF'!$P$10+H$23*'04 Operating Model'!$P$11*(1-'04 Operating Model'!$P$55))*(1+'06 DCF'!$F$26)*(1-'06 DCF'!$F$26/'06 DCF'!$F$27)/($C26-'06 DCF'!$F$26)/(1+$C26)^'02 Assumptions'!$C$11+SUM('06 DCF'!$F$46:$F$52))/'06 DCF'!$F$54} -> 0
C27: ='07 WACC'!$C$38+0.005 -> 0.092495 | D27: {=(SUMPRODUCT('06 DCF'!$G$15:$P$15+D$23*'04 Operating Model'!$G$11:$P$11*(1-'04 Operating Model'!$G$55:$P$55),1/(1+$C27)^'06 DCF'!$G$20:$P$20)+('06 DCF'!$P$10+D$23*'04 Operating Model'!$P$11*(1-'04 Operating Model'!$P$55))*(1+'06 DCF'!$F$26)*(1-'06 DCF'!$F$26/'06 DCF'!$F$27)/($C27-'06 DCF'!$F$26)/(1+$C27)^'02 Assumptions'!$C$11+SUM('06 DCF'!$F$46:$F$52))/'06 DCF'!$F$54} -> 0 | E27: {=(SUMPRODUCT('06 DCF'!$G$15:$P$15+E$23*'04 Operating Model'!$G$11:$P$11*(1-'04 Operating Model'!$G$55:$P$55),1/(1+$C27)^'06 DCF'!$G$20:$P$20)+('06 DCF'!$P$10+E$23*'04 Operating Model'!$P$11*(1-'04 Operating Model'!$P$55))*(1+'06 DCF'!$F$26)*(1-'06 DCF'!$F$26/'06 DCF'!$F$27)/($C27-'06 DCF'!$F$26)/(1+$C27)^'02 Assumptions'!$C$11+SUM('06 DCF'!$F$46:$F$52))/'06 DCF'!$F$54} -> 0 | F27: {=(SUMPRODUCT('06 DCF'!$G$15:$P$15+F$23*'04 Operating Model'!$G$11:$P$11*(1-'04 Operating Model'!$G$55:$P$55),1/(1+$C27)^'06 DCF'!$G$20:$P$20)+('06 DCF'!$P$10+F$23*'04 Operating Model'!$P$11*(1-'04 Operating Model'!$P$55))*(1+'06 DCF'!$F$26)*(1-'06 DCF'!$F$26/'06 DCF'!$F$27)/($C27-'06 DCF'!$F$26)/(1+$C27)^'02 Assumptions'!$C$11+SUM('06 DCF'!$F$46:$F$52))/'06 DCF'!$F$54} -> 0 | G27: {=(SUMPRODUCT('06 DCF'!$G$15:$P$15+G$23*'04 Operating Model'!$G$11:$P$11*(1-'04 Operating Model'!$G$55:$P$55),1/(1+$C27)^'06 DCF'!$G$20:$P$20)+('06 DCF'!$P$10+G$23*'04 Operating Model'!$P$11*(1-'04 Operating Model'!$P$55))*(1+'06 DCF'!$F$26)*(1-'06 DCF'!$F$26/'06 DCF'!$F$27)/($C27-'06 DCF'!$F$26)/(1+$C27)^'02 Assumptions'!$C$11+SUM('06 DCF'!$F$46:$F$52))/'06 DCF'!$F$54} -> 0 | H27: {=(SUMPRODUCT('06 DCF'!$G$15:$P$15+H$23*'04 Operating Model'!$G$11:$P$11*(1-'04 Operating Model'!$G$55:$P$55),1/(1+$C27)^'06 DCF'!$G$20:$P$20)+('06 DCF'!$P$10+H$23*'04 Operating Model'!$P$11*(1-'04 Operating Model'!$P$55))*(1+'06 DCF'!$F$26)*(1-'06 DCF'!$F$26/'06 DCF'!$F$27)/($C27-'06 DCF'!$F$26)/(1+$C27)^'02 Assumptions'!$C$11+SUM('06 DCF'!$F$46:$F$52))/'06 DCF'!$F$54} -> 0
C28: ='07 WACC'!$C$38+0.01 -> 0.097495 | D28: {=(SUMPRODUCT('06 DCF'!$G$15:$P$15+D$23*'04 Operating Model'!$G$11:$P$11*(1-'04 Operating Model'!$G$55:$P$55),1/(1+$C28)^'06 DCF'!$G$20:$P$20)+('06 DCF'!$P$10+D$23*'04 Operating Model'!$P$11*(1-'04 Operating Model'!$P$55))*(1+'06 DCF'!$F$26)*(1-'06 DCF'!$F$26/'06 DCF'!$F$27)/($C28-'06 DCF'!$F$26)/(1+$C28)^'02 Assumptions'!$C$11+SUM('06 DCF'!$F$46:$F$52))/'06 DCF'!$F$54} -> 0 | E28: {=(SUMPRODUCT('06 DCF'!$G$15:$P$15+E$23*'04 Operating Model'!$G$11:$P$11*(1-'04 Operating Model'!$G$55:$P$55),1/(1+$C28)^'06 DCF'!$G$20:$P$20)+('06 DCF'!$P$10+E$23*'04 Operating Model'!$P$11*(1-'04 Operating Model'!$P$55))*(1+'06 DCF'!$F$26)*(1-'06 DCF'!$F$26/'06 DCF'!$F$27)/($C28-'06 DCF'!$F$26)/(1+$C28)^'02 Assumptions'!$C$11+SUM('06 DCF'!$F$46:$F$52))/'06 DCF'!$F$54} -> 0 | F28: {=(SUMPRODUCT('06 DCF'!$G$15:$P$15+F$23*'04 Operating Model'!$G$11:$P$11*(1-'04 Operating Model'!$G$55:$P$55),1/(1+$C28)^'06 DCF'!$G$20:$P$20)+('06 DCF'!$P$10+F$23*'04 Operating Model'!$P$11*(1-'04 Operating Model'!$P$55))*(1+'06 DCF'!$F$26)*(1-'06 DCF'!$F$26/'06 DCF'!$F$27)/($C28-'06 DCF'!$F$26)/(1+$C28)^'02 Assumptions'!$C$11+SUM('06 DCF'!$F$46:$F$52))/'06 DCF'!$F$54} -> 0 | G28: {=(SUMPRODUCT('06 DCF'!$G$15:$P$15+G$23*'04 Operating Model'!$G$11:$P$11*(1-'04 Operating Model'!$G$55:$P$55),1/(1+$C28)^'06 DCF'!$G$20:$P$20)+('06 DCF'!$P$10+G$23*'04 Operating Model'!$P$11*(1-'04 Operating Model'!$P$55))*(1+'06 DCF'!$F$26)*(1-'06 DCF'!$F$26/'06 DCF'!$F$27)/($C28-'06 DCF'!$F$26)/(1+$C28)^'02 Assumptions'!$C$11+SUM('06 DCF'!$F$46:$F$52))/'06 DCF'!$F$54} -> 0 | H28: {=(SUMPRODUCT('06 DCF'!$G$15:$P$15+H$23*'04 Operating Model'!$G$11:$P$11*(1-'04 Operating Model'!$G$55:$P$55),1/(1+$C28)^'06 DCF'!$G$20:$P$20)+('06 DCF'!$P$10+H$23*'04 Operating Model'!$P$11*(1-'04 Operating Model'!$P$55))*(1+'06 DCF'!$F$26)*(1-'06 DCF'!$F$26/'06 DCF'!$F$27)/($C28-'06 DCF'!$F$26)/(1+$C28)^'02 Assumptions'!$C$11+SUM('06 DCF'!$F$46:$F$52))/'06 DCF'!$F$54} -> 0
B31: REJILLA D — WACC × DESPLAZAMIENTO DE CAPEX SOBRE INGRESOS (pp) (primer orden: NO recoge el escudo fiscal de la depreciación asociada)
B32: WACC ↓ / Δ capex sobre ingresos (p.p.) →
C33: ='07 WACC'!$C$38+-0.01 -> 0.077495 | D33: {=(SUMPRODUCT('06 DCF'!$G$15:$P$15-D$32*'04 Operating Model'!$G$11:$P$11,1/(1+$C33)^'06 DCF'!$G$20:$P$20)+'06 DCF'!$P$10*(1+'06 DCF'!$F$26)*(1-'06 DCF'!$F$26/'06 DCF'!$F$27)/($C33-'06 DCF'!$F$26)/(1+$C33)^'02 Assumptions'!$C$11+SUM('06 DCF'!$F$46:$F$52))/'06 DCF'!$F$54} -> 0 | E33: {=(SUMPRODUCT('06 DCF'!$G$15:$P$15-E$32*'04 Operating Model'!$G$11:$P$11,1/(1+$C33)^'06 DCF'!$G$20:$P$20)+'06 DCF'!$P$10*(1+'06 DCF'!$F$26)*(1-'06 DCF'!$F$26/'06 DCF'!$F$27)/($C33-'06 DCF'!$F$26)/(1+$C33)^'02 Assumptions'!$C$11+SUM('06 DCF'!$F$46:$F$52))/'06 DCF'!$F$54} -> 0 | F33: {=(SUMPRODUCT('06 DCF'!$G$15:$P$15-F$32*'04 Operating Model'!$G$11:$P$11,1/(1+$C33)^'06 DCF'!$G$20:$P$20)+'06 DCF'!$P$10*(1+'06 DCF'!$F$26)*(1-'06 DCF'!$F$26/'06 DCF'!$F$27)/($C33-'06 DCF'!$F$26)/(1+$C33)^'02 Assumptions'!$C$11+SUM('06 DCF'!$F$46:$F$52))/'06 DCF'!$F$54} -> 0 | G33: {=(SUMPRODUCT('06 DCF'!$G$15:$P$15-G$32*'04 Operating Model'!$G$11:$P$11,1/(1+$C33)^'06 DCF'!$G$20:$P$20)+'06 DCF'!$P$10*(1+'06 DCF'!$F$26)*(1-'06 DCF'!$F$26/'06 DCF'!$F$27)/($C33-'06 DCF'!$F$26)/(1+$C33)^'02 Assumptions'!$C$11+SUM('06 DCF'!$F$46:$F$52))/'06 DCF'!$F$54} -> 0 | H33: {=(SUMPRODUCT('06 DCF'!$G$15:$P$15-H$32*'04 Operating Model'!$G$11:$P$11,1/(1+$C33)^'06 DCF'!$G$20:$P$20)+'06 DCF'!$P$10*(1+'06 DCF'!$F$26)*(1-'06 DCF'!$F$26/'06 DCF'!$F$27)/($C33-'06 DCF'!$F$26)/(1+$C33)^'02 Assumptions'!$C$11+SUM('06 DCF'!$F$46:$F$52))/'06 DCF'!$F$54} -> 0
C34: ='07 WACC'!$C$38+-0.005 -> 0.082495 | D34: {=(SUMPRODUCT('06 DCF'!$G$15:$P$15-D$32*'04 Operating Model'!$G$11:$P$11,1/(1+$C34)^'06 DCF'!$G$20:$P$20)+'06 DCF'!$P$10*(1+'06 DCF'!$F$26)*(1-'06 DCF'!$F$26/'06 DCF'!$F$27)/($C34-'06 DCF'!$F$26)/(1+$C34)^'02 Assumptions'!$C$11+SUM('06 DCF'!$F$46:$F$52))/'06 DCF'!$F$54} -> 0 | E34: {=(SUMPRODUCT('06 DCF'!$G$15:$P$15-E$32*'04 Operating Model'!$G$11:$P$11,1/(1+$C34)^'06 DCF'!$G$20:$P$20)+'06 DCF'!$P$10*(1+'06 DCF'!$F$26)*(1-'06 DCF'!$F$26/'06 DCF'!$F$27)/($C34-'06 DCF'!$F$26)/(1+$C34)^'02 Assumptions'!$C$11+SUM('06 DCF'!$F$46:$F$52))/'06 DCF'!$F$54} -> 0 | F34: {=(SUMPRODUCT('06 DCF'!$G$15:$P$15-F$32*'04 Operating Model'!$G$11:$P$11,1/(1+$C34)^'06 DCF'!$G$20:$P$20)+'06 DCF'!$P$10*(1+'06 DCF'!$F$26)*(1-'06 DCF'!$F$26/'06 DCF'!$F$27)/($C34-'06 DCF'!$F$26)/(1+$C34)^'02 Assumptions'!$C$11+SUM('06 DCF'!$F$46:$F$52))/'06 DCF'!$F$54} -> 0 | G34: {=(SUMPRODUCT('06 DCF'!$G$15:$P$15-G$32*'04 Operating Model'!$G$11:$P$11,1/(1+$C34)^'06 DCF'!$G$20:$P$20)+'06 DCF'!$P$10*(1+'06 DCF'!$F$26)*(1-'06 DCF'!$F$26/'06 DCF'!$F$27)/($C34-'06 DCF'!$F$26)/(1+$C34)^'02 Assumptions'!$C$11+SUM('06 DCF'!$F$46:$F$52))/'06 DCF'!$F$54} -> 0 | H34: {=(SUMPRODUCT('06 DCF'!$G$15:$P$15-H$32*'04 Operating Model'!$G$11:$P$11,1/(1+$C34)^'06 DCF'!$G$20:$P$20)+'06 DCF'!$P$10*(1+'06 DCF'!$F$26)*(1-'06 DCF'!$F$26/'06 DCF'!$F$27)/($C34-'06 DCF'!$F$26)/(1+$C34)^'02 Assumptions'!$C$11+SUM('06 DCF'!$F$46:$F$52))/'06 DCF'!$F$54} -> 0
C35: ='07 WACC'!$C$38+0 -> 0.087495 | D35: {=(SUMPRODUCT('06 DCF'!$G$15:$P$15-D$32*'04 Operating Model'!$G$11:$P$11,1/(1+$C35)^'06 DCF'!$G$20:$P$20)+'06 DCF'!$P$10*(1+'06 DCF'!$F$26)*(1-'06 DCF'!$F$26/'06 DCF'!$F$27)/($C35-'06 DCF'!$F$26)/(1+$C35)^'02 Assumptions'!$C$11+SUM('06 DCF'!$F$46:$F$52))/'06 DCF'!$F$54} -> 0 | E35: {=(SUMPRODUCT('06 DCF'!$G$15:$P$15-E$32*'04 Operating Model'!$G$11:$P$11,1/(1+$C35)^'06 DCF'!$G$20:$P$20)+'06 DCF'!$P$10*(1+'06 DCF'!$F$26)*(1-'06 DCF'!$F$26/'06 DCF'!$F$27)/($C35-'06 DCF'!$F$26)/(1+$C35)^'02 Assumptions'!$C$11+SUM('06 DCF'!$F$46:$F$52))/'06 DCF'!$F$54} -> 0 | F35: {=(SUMPRODUCT('06 DCF'!$G$15:$P$15-F$32*'04 Operating Model'!$G$11:$P$11,1/(1+$C35)^'06 DCF'!$G$20:$P$20)+'06 DCF'!$P$10*(1+'06 DCF'!$F$26)*(1-'06 DCF'!$F$26/'06 DCF'!$F$27)/($C35-'06 DCF'!$F$26)/(1+$C35)^'02 Assumptions'!$C$11+SUM('06 DCF'!$F$46:$F$52))/'06 DCF'!$F$54} -> 0 | G35: {=(SUMPRODUCT('06 DCF'!$G$15:$P$15-G$32*'04 Operating Model'!$G$11:$P$11,1/(1+$C35)^'06 DCF'!$G$20:$P$20)+'06 DCF'!$P$10*(1+'06 DCF'!$F$26)*(1-'06 DCF'!$F$26/'06 DCF'!$F$27)/($C35-'06 DCF'!$F$26)/(1+$C35)^'02 Assumptions'!$C$11+SUM('06 DCF'!$F$46:$F$52))/'06 DCF'!$F$54} -> 0 | H35: {=(SUMPRODUCT('06 DCF'!$G$15:$P$15-H$32*'04 Operating Model'!$G$11:$P$11,1/(1+$C35)^'06 DCF'!$G$20:$P$20)+'06 DCF'!$P$10*(1+'06 DCF'!$F$26)*(1-'06 DCF'!$F$26/'06 DCF'!$F$27)/($C35-'06 DCF'!$F$26)/(1+$C35)^'02 Assumptions'!$C$11+SUM('06 DCF'!$F$46:$F$52))/'06 DCF'!$F$54} -> 0
C36: ='07 WACC'!$C$38+0.005 -> 0.092495 | D36: {=(SUMPRODUCT('06 DCF'!$G$15:$P$15-D$32*'04 Operating Model'!$G$11:$P$11,1/(1+$C36)^'06 DCF'!$G$20:$P$20)+'06 DCF'!$P$10*(1+'06 DCF'!$F$26)*(1-'06 DCF'!$F$26/'06 DCF'!$F$27)/($C36-'06 DCF'!$F$26)/(1+$C36)^'02 Assumptions'!$C$11+SUM('06 DCF'!$F$46:$F$52))/'06 DCF'!$F$54} -> 0 | E36: {=(SUMPRODUCT('06 DCF'!$G$15:$P$15-E$32*'04 Operating Model'!$G$11:$P$11,1/(1+$C36)^'06 DCF'!$G$20:$P$20)+'06 DCF'!$P$10*(1+'06 DCF'!$F$26)*(1-'06 DCF'!$F$26/'06 DCF'!$F$27)/($C36-'06 DCF'!$F$26)/(1+$C36)^'02 Assumptions'!$C$11+SUM('06 DCF'!$F$46:$F$52))/'06 DCF'!$F$54} -> 0 | F36: {=(SUMPRODUCT('06 DCF'!$G$15:$P$15-F$32*'04 Operating Model'!$G$11:$P$11,1/(1+$C36)^'06 DCF'!$G$20:$P$20)+'06 DCF'!$P$10*(1+'06 DCF'!$F$26)*(1-'06 DCF'!$F$26/'06 DCF'!$F$27)/($C36-'06 DCF'!$F$26)/(1+$C36)^'02 Assumptions'!$C$11+SUM('06 DCF'!$F$46:$F$52))/'06 DCF'!$F$54} -> 0 | G36: {=(SUMPRODUCT('06 DCF'!$G$15:$P$15-G$32*'04 Operating Model'!$G$11:$P$11,1/(1+$C36)^'06 DCF'!$G$20:$P$20)+'06 DCF'!$P$10*(1+'06 DCF'!$F$26)*(1-'06 DCF'!$F$26/'06 DCF'!$F$27)/($C36-'06 DCF'!$F$26)/(1+$C36)^'02 Assumptions'!$C$11+SUM('06 DCF'!$F$46:$F$52))/'06 DCF'!$F$54} -> 0 | H36: {=(SUMPRODUCT('06 DCF'!$G$15:$P$15-H$32*'04 Operating Model'!$G$11:$P$11,1/(1+$C36)^'06 DCF'!$G$20:$P$20)+'06 DCF'!$P$10*(1+'06 DCF'!$F$26)*(1-'06 DCF'!$F$26/'06 DCF'!$F$27)/($C36-'06 DCF'!$F$26)/(1+$C36)^'02 Assumptions'!$C$11+SUM('06 DCF'!$F$46:$F$52))/'06 DCF'!$F$54} -> 0
C37: ='07 WACC'!$C$38+0.01 -> 0.097495 | D37: {=(SUMPRODUCT('06 DCF'!$G$15:$P$15-D$32*'04 Operating Model'!$G$11:$P$11,1/(1+$C37)^'06 DCF'!$G$20:$P$20)+'06 DCF'!$P$10*(1+'06 DCF'!$F$26)*(1-'06 DCF'!$F$26/'06 DCF'!$F$27)/($C37-'06 DCF'!$F$26)/(1+$C37)^'02 Assumptions'!$C$11+SUM('06 DCF'!$F$46:$F$52))/'06 DCF'!$F$54} -> 0 | E37: {=(SUMPRODUCT('06 DCF'!$G$15:$P$15-E$32*'04 Operating Model'!$G$11:$P$11,1/(1+$C37)^'06 DCF'!$G$20:$P$20)+'06 DCF'!$P$10*(1+'06 DCF'!$F$26)*(1-'06 DCF'!$F$26/'06 DCF'!$F$27)/($C37-'06 DCF'!$F$26)/(1+$C37)^'02 Assumptions'!$C$11+SUM('06 DCF'!$F$46:$F$52))/'06 DCF'!$F$54} -> 0 | F37: {=(SUMPRODUCT('06 DCF'!$G$15:$P$15-F$32*'04 Operating Model'!$G$11:$P$11,1/(1+$C37)^'06 DCF'!$G$20:$P$20)+'06 DCF'!$P$10*(1+'06 DCF'!$F$26)*(1-'06 DCF'!$F$26/'06 DCF'!$F$27)/($C37-'06 DCF'!$F$26)/(1+$C37)^'02 Assumptions'!$C$11+SUM('06 DCF'!$F$46:$F$52))/'06 DCF'!$F$54} -> 0 | G37: {=(SUMPRODUCT('06 DCF'!$G$15:$P$15-G$32*'04 Operating Model'!$G$11:$P$11,1/(1+$C37)^'06 DCF'!$G$20:$P$20)+'06 DCF'!$P$10*(1+'06 DCF'!$F$26)*(1-'06 DCF'!$F$26/'06 DCF'!$F$27)/($C37-'06 DCF'!$F$26)/(1+$C37)^'02 Assumptions'!$C$11+SUM('06 DCF'!$F$46:$F$52))/'06 DCF'!$F$54} -> 0 | H37: {=(SUMPRODUCT('06 DCF'!$G$15:$P$15-H$32*'04 Operating Model'!$G$11:$P$11,1/(1+$C37)^'06 DCF'!$G$20:$P$20)+'06 DCF'!$P$10*(1+'06 DCF'!$F$26)*(1-'06 DCF'!$F$26/'06 DCF'!$F$27)/($C37-'06 DCF'!$F$26)/(1+$C37)^'02 Assumptions'!$C$11+SUM('06 DCF'!$F$46:$F$52))/'06 DCF'!$F$54} -> 0
B40: REJILLA E — WACC × DESPLAZAMIENTO DEL TIPO IMPOSITIVO DE CAJA (pp) (exacta)
B41: WACC ↓ / Δ tipo de caja (p.p.) →
C42: ='07 WACC'!$C$38+-0.01 -> 0.077495 | D42: {=(SUMPRODUCT('06 DCF'!$G$15:$P$15-D$41*'06 DCF'!$G$7:$P$7,1/(1+$C42)^'06 DCF'!$G$20:$P$20)+('06 DCF'!$P$10-D$41*'06 DCF'!$P$7)*(1+'06 DCF'!$F$26)*(1-'06 DCF'!$F$26/'06 DCF'!$F$27)/($C42-'06 DCF'!$F$26)/(1+$C42)^'02 Assumptions'!$C$11+SUM('06 DCF'!$F$46:$F$52))/'06 DCF'!$F$54} -> 0 | E42: {=(SUMPRODUCT('06 DCF'!$G$15:$P$15-E$41*'06 DCF'!$G$7:$P$7,1/(1+$C42)^'06 DCF'!$G$20:$P$20)+('06 DCF'!$P$10-E$41*'06 DCF'!$P$7)*(1+'06 DCF'!$F$26)*(1-'06 DCF'!$F$26/'06 DCF'!$F$27)/($C42-'06 DCF'!$F$26)/(1+$C42)^'02 Assumptions'!$C$11+SUM('06 DCF'!$F$46:$F$52))/'06 DCF'!$F$54} -> 0 | F42: {=(SUMPRODUCT('06 DCF'!$G$15:$P$15-F$41*'06 DCF'!$G$7:$P$7,1/(1+$C42)^'06 DCF'!$G$20:$P$20)+('06 DCF'!$P$10-F$41*'06 DCF'!$P$7)*(1+'06 DCF'!$F$26)*(1-'06 DCF'!$F$26/'06 DCF'!$F$27)/($C42-'06 DCF'!$F$26)/(1+$C42)^'02 Assumptions'!$C$11+SUM('06 DCF'!$F$46:$F$52))/'06 DCF'!$F$54} -> 0 | G42: {=(SUMPRODUCT('06 DCF'!$G$15:$P$15-G$41*'06 DCF'!$G$7:$P$7,1/(1+$C42)^'06 DCF'!$G$20:$P$20)+('06 DCF'!$P$10-G$41*'06 DCF'!$P$7)*(1+'06 DCF'!$F$26)*(1-'06 DCF'!$F$26/'06 DCF'!$F$27)/($C42-'06 DCF'!$F$26)/(1+$C42)^'02 Assumptions'!$C$11+SUM('06 DCF'!$F$46:$F$52))/'06 DCF'!$F$54} -> 0 | H42: {=(SUMPRODUCT('06 DCF'!$G$15:$P$15-H$41*'06 DCF'!$G$7:$P$7,1/(1+$C42)^'06 DCF'!$G$20:$P$20)+('06 DCF'!$P$10-H$41*'06 DCF'!$P$7)*(1+'06 DCF'!$F$26)*(1-'06 DCF'!$F$26/'06 DCF'!$F$27)/($C42-'06 DCF'!$F$26)/(1+$C42)^'02 Assumptions'!$C$11+SUM('06 DCF'!$F$46:$F$52))/'06 DCF'!$F$54} -> 0
C43: ='07 WACC'!$C$38+-0.005 -> 0.082495 | D43: {=(SUMPRODUCT('06 DCF'!$G$15:$P$15-D$41*'06 DCF'!$G$7:$P$7,1/(1+$C43)^'06 DCF'!$G$20:$P$20)+('06 DCF'!$P$10-D$41*'06 DCF'!$P$7)*(1+'06 DCF'!$F$26)*(1-'06 DCF'!$F$26/'06 DCF'!$F$27)/($C43-'06 DCF'!$F$26)/(1+$C43)^'02 Assumptions'!$C$11+SUM('06 DCF'!$F$46:$F$52))/'06 DCF'!$F$54} -> 0 | E43: {=(SUMPRODUCT('06 DCF'!$G$15:$P$15-E$41*'06 DCF'!$G$7:$P$7,1/(1+$C43)^'06 DCF'!$G$20:$P$20)+('06 DCF'!$P$10-E$41*'06 DCF'!$P$7)*(1+'06 DCF'!$F$26)*(1-'06 DCF'!$F$26/'06 DCF'!$F$27)/($C43-'06 DCF'!$F$26)/(1+$C43)^'02 Assumptions'!$C$11+SUM('06 DCF'!$F$46:$F$52))/'06 DCF'!$F$54} -> 0 | F43: {=(SUMPRODUCT('06 DCF'!$G$15:$P$15-F$41*'06 DCF'!$G$7:$P$7,1/(1+$C43)^'06 DCF'!$G$20:$P$20)+('06 DCF'!$P$10-F$41*'06 DCF'!$P$7)*(1+'06 DCF'!$F$26)*(1-'06 DCF'!$F$26/'06 DCF'!$F$27)/($C43-'06 DCF'!$F$26)/(1+$C43)^'02 Assumptions'!$C$11+SUM('06 DCF'!$F$46:$F$52))/'06 DCF'!$F$54} -> 0 | G43: {=(SUMPRODUCT('06 DCF'!$G$15:$P$15-G$41*'06 DCF'!$G$7:$P$7,1/(1+$C43)^'06 DCF'!$G$20:$P$20)+('06 DCF'!$P$10-G$41*'06 DCF'!$P$7)*(1+'06 DCF'!$F$26)*(1-'06 DCF'!$F$26/'06 DCF'!$F$27)/($C43-'06 DCF'!$F$26)/(1+$C43)^'02 Assumptions'!$C$11+SUM('06 DCF'!$F$46:$F$52))/'06 DCF'!$F$54} -> 0 | H43: {=(SUMPRODUCT('06 DCF'!$G$15:$P$15-H$41*'06 DCF'!$G$7:$P$7,1/(1+$C43)^'06 DCF'!$G$20:$P$20)+('06 DCF'!$P$10-H$41*'06 DCF'!$P$7)*(1+'06 DCF'!$F$26)*(1-'06 DCF'!$F$26/'06 DCF'!$F$27)/($C43-'06 DCF'!$F$26)/(1+$C43)^'02 Assumptions'!$C$11+SUM('06 DCF'!$F$46:$F$52))/'06 DCF'!$F$54} -> 0
C44: ='07 WACC'!$C$38+0 -> 0.087495 | D44: {=(SUMPRODUCT('06 DCF'!$G$15:$P$15-D$41*'06 DCF'!$G$7:$P$7,1/(1+$C44)^'06 DCF'!$G$20:$P$20)+('06 DCF'!$P$10-D$41*'06 DCF'!$P$7)*(1+'06 DCF'!$F$26)*(1-'06 DCF'!$F$26/'06 DCF'!$F$27)/($C44-'06 DCF'!$F$26)/(1+$C44)^'02 Assumptions'!$C$11+SUM('06 DCF'!$F$46:$F$52))/'06 DCF'!$F$54} -> 0 | E44: {=(SUMPRODUCT('06 DCF'!$G$15:$P$15-E$41*'06 DCF'!$G$7:$P$7,1/(1+$C44)^'06 DCF'!$G$20:$P$20)+('06 DCF'!$P$10-E$41*'06 DCF'!$P$7)*(1+'06 DCF'!$F$26)*(1-'06 DCF'!$F$26/'06 DCF'!$F$27)/($C44-'06 DCF'!$F$26)/(1+$C44)^'02 Assumptions'!$C$11+SUM('06 DCF'!$F$46:$F$52))/'06 DCF'!$F$54} -> 0 | F44: {=(SUMPRODUCT('06 DCF'!$G$15:$P$15-F$41*'06 DCF'!$G$7:$P$7,1/(1+$C44)^'06 DCF'!$G$20:$P$20)+('06 DCF'!$P$10-F$41*'06 DCF'!$P$7)*(1+'06 DCF'!$F$26)*(1-'06 DCF'!$F$26/'06 DCF'!$F$27)/($C44-'06 DCF'!$F$26)/(1+$C44)^'02 Assumptions'!$C$11+SUM('06 DCF'!$F$46:$F$52))/'06 DCF'!$F$54} -> 0 | G44: {=(SUMPRODUCT('06 DCF'!$G$15:$P$15-G$41*'06 DCF'!$G$7:$P$7,1/(1+$C44)^'06 DCF'!$G$20:$P$20)+('06 DCF'!$P$10-G$41*'06 DCF'!$P$7)*(1+'06 DCF'!$F$26)*(1-'06 DCF'!$F$26/'06 DCF'!$F$27)/($C44-'06 DCF'!$F$26)/(1+$C44)^'02 Assumptions'!$C$11+SUM('06 DCF'!$F$46:$F$52))/'06 DCF'!$F$54} -> 0 | H44: {=(SUMPRODUCT('06 DCF'!$G$15:$P$15-H$41*'06 DCF'!$G$7:$P$7,1/(1+$C44)^'06 DCF'!$G$20:$P$20)+('06 DCF'!$P$10-H$41*'06 DCF'!$P$7)*(1+'06 DCF'!$F$26)*(1-'06 DCF'!$F$26/'06 DCF'!$F$27)/($C44-'06 DCF'!$F$26)/(1+$C44)^'02 Assumptions'!$C$11+SUM('06 DCF'!$F$46:$F$52))/'06 DCF'!$F$54} -> 0
C45: ='07 WACC'!$C$38+0.005 -> 0.092495 | D45: {=(SUMPRODUCT('06 DCF'!$G$15:$P$15-D$41*'06 DCF'!$G$7:$P$7,1/(1+$C45)^'06 DCF'!$G$20:$P$20)+('06 DCF'!$P$10-D$41*'06 DCF'!$P$7)*(1+'06 DCF'!$F$26)*(1-'06 DCF'!$F$26/'06 DCF'!$F$27)/($C45-'06 DCF'!$F$26)/(1+$C45)^'02 Assumptions'!$C$11+SUM('06 DCF'!$F$46:$F$52))/'06 DCF'!$F$54} -> 0 | E45: {=(SUMPRODUCT('06 DCF'!$G$15:$P$15-E$41*'06 DCF'!$G$7:$P$7,1/(1+$C45)^'06 DCF'!$G$20:$P$20)+('06 DCF'!$P$10-E$41*'06 DCF'!$P$7)*(1+'06 DCF'!$F$26)*(1-'06 DCF'!$F$26/'06 DCF'!$F$27)/($C45-'06 DCF'!$F$26)/(1+$C45)^'02 Assumptions'!$C$11+SUM('06 DCF'!$F$46:$F$52))/'06 DCF'!$F$54} -> 0 | F45: {=(SUMPRODUCT('06 DCF'!$G$15:$P$15-F$41*'06 DCF'!$G$7:$P$7,1/(1+$C45)^'06 DCF'!$G$20:$P$20)+('06 DCF'!$P$10-F$41*'06 DCF'!$P$7)*(1+'06 DCF'!$F$26)*(1-'06 DCF'!$F$26/'06 DCF'!$F$27)/($C45-'06 DCF'!$F$26)/(1+$C45)^'02 Assumptions'!$C$11+SUM('06 DCF'!$F$46:$F$52))/'06 DCF'!$F$54} -> 0 | G45: {=(SUMPRODUCT('06 DCF'!$G$15:$P$15-G$41*'06 DCF'!$G$7:$P$7,1/(1+$C45)^'06 DCF'!$G$20:$P$20)+('06 DCF'!$P$10-G$41*'06 DCF'!$P$7)*(1+'06 DCF'!$F$26)*(1-'06 DCF'!$F$26/'06 DCF'!$F$27)/($C45-'06 DCF'!$F$26)/(1+$C45)^'02 Assumptions'!$C$11+SUM('06 DCF'!$F$46:$F$52))/'06 DCF'!$F$54} -> 0 | H45: {=(SUMPRODUCT('06 DCF'!$G$15:$P$15-H$41*'06 DCF'!$G$7:$P$7,1/(1+$C45)^'06 DCF'!$G$20:$P$20)+('06 DCF'!$P$10-H$41*'06 DCF'!$P$7)*(1+'06 DCF'!$F$26)*(1-'06 DCF'!$F$26/'06 DCF'!$F$27)/($C45-'06 DCF'!$F$26)/(1+$C45)^'02 Assumptions'!$C$11+SUM('06 DCF'!$F$46:$F$52))/'06 DCF'!$F$54} -> 0
C46: ='07 WACC'!$C$38+0.01 -> 0.097495 | D46: {=(SUMPRODUCT('06 DCF'!$G$15:$P$15-D$41*'06 DCF'!$G$7:$P$7,1/(1+$C46)^'06 DCF'!$G$20:$P$20)+('06 DCF'!$P$10-D$41*'06 DCF'!$P$7)*(1+'06 DCF'!$F$26)*(1-'06 DCF'!$F$26/'06 DCF'!$F$27)/($C46-'06 DCF'!$F$26)/(1+$C46)^'02 Assumptions'!$C$11+SUM('06 DCF'!$F$46:$F$52))/'06 DCF'!$F$54} -> 0 | E46: {=(SUMPRODUCT('06 DCF'!$G$15:$P$15-E$41*'06 DCF'!$G$7:$P$7,1/(1+$C46)^'06 DCF'!$G$20:$P$20)+('06 DCF'!$P$10-E$41*'06 DCF'!$P$7)*(1+'06 DCF'!$F$26)*(1-'06 DCF'!$F$26/'06 DCF'!$F$27)/($C46-'06 DCF'!$F$26)/(1+$C46)^'02 Assumptions'!$C$11+SUM('06 DCF'!$F$46:$F$52))/'06 DCF'!$F$54} -> 0 | F46: {=(SUMPRODUCT('06 DCF'!$G$15:$P$15-F$41*'06 DCF'!$G$7:$P$7,1/(1+$C46)^'06 DCF'!$G$20:$P$20)+('06 DCF'!$P$10-F$41*'06 DCF'!$P$7)*(1+'06 DCF'!$F$26)*(1-'06 DCF'!$F$26/'06 DCF'!$F$27)/($C46-'06 DCF'!$F$26)/(1+$C46)^'02 Assumptions'!$C$11+SUM('06 DCF'!$F$46:$F$52))/'06 DCF'!$F$54} -> 0 | G46: {=(SUMPRODUCT('06 DCF'!$G$15:$P$15-G$41*'06 DCF'!$G$7:$P$7,1/(1+$C46)^'06 DCF'!$G$20:$P$20)+('06 DCF'!$P$10-G$41*'06 DCF'!$P$7)*(1+'06 DCF'!$F$26)*(1-'06 DCF'!$F$26/'06 DCF'!$F$27)/($C46-'06 DCF'!$F$26)/(1+$C46)^'02 Assumptions'!$C$11+SUM('06 DCF'!$F$46:$F$52))/'06 DCF'!$F$54} -> 0 | H46: {=(SUMPRODUCT('06 DCF'!$G$15:$P$15-H$41*'06 DCF'!$G$7:$P$7,1/(1+$C46)^'06 DCF'!$G$20:$P$20)+('06 DCF'!$P$10-H$41*'06 DCF'!$P$7)*(1+'06 DCF'!$F$26)*(1-'06 DCF'!$F$26/'06 DCF'!$F$27)/($C46-'06 DCF'!$F$26)/(1+$C46)^'02 Assumptions'!$C$11+SUM('06 DCF'!$F$46:$F$52))/'06 DCF'!$F$54} -> 0
B49: JERARQUÍA DE DRIVERS DEL VALOR (rango de valor por acción a WACC base, entre los extremos de cada eje)
B50: Driver | C50: Valor mínimo | D50: Valor máximo | E50: Rango ($/acc) | F50: Clasificación
B51: Crecimiento terminal g (±100 pb) | C51: =MIN(D8:H8) -> 153.31535 | D51: =MAX(D8:H8) -> 191.68812 | E51: =D51-C51 -> 38.372777 | F51: =IF(E51>=LARGE($E$51:$E$56,2),"PRIMARIO",IF(E51>=LARGE($E$51:$E$56,4),"SECUNDARIO","BAJO IMPACTO")) -> SECUNDARIO
B52: WACC (±100 pb) | C52: =MIN(D6:D10) -> 124.52367 | D52: =MAX(D6:D10) -> 192.36591 | E52: =D52-C52 -> 67.842248 | F52: =IF(E52>=LARGE($E$51:$E$56,2),"PRIMARIO",IF(E52>=LARGE($E$51:$E$56,4),"SECUNDARIO","BAJO IMPACTO")) -> PRIMARIO
B53: Margen EBIT (±300 pb) | C53: =MIN(D26:H26) -> 148.43169 | D53: =MAX(D26:H26) -> 190.02423 | E53: =D53-C53 -> 41.592547 | F53: =IF(E53>=LARGE($E$51:$E$56,2),"PRIMARIO",IF(E53>=LARGE($E$51:$E$56,4),"SECUNDARIO","BAJO IMPACTO")) -> SECUNDARIO
B54: Tipo impositivo de caja (±300 pb) | C54: =MIN(D44:H44) -> 160.86768 | D54: =MAX(D44:H44) -> 177.58824 | E54: =D54-C54 -> 16.720559 | F54: =IF(E54>=LARGE($E$51:$E$56,2),"PRIMARIO",IF(E54>=LARGE($E$51:$E$56,4),"SECUNDARIO","BAJO IMPACTO")) -> BAJO IMPACTO
B55: Capex sobre ingresos (±200 pb) | C55: =MIN(D35:H35) -> 162.27017 | D55: =MAX(D35:H35) -> 176.18576 | E55: =D55-C55 -> 13.91559 | F55: =IF(E55>=LARGE($E$51:$E$56,2),"PRIMARIO",IF(E55>=LARGE($E$51:$E$56,4),"SECUNDARIO","BAJO IMPACTO")) -> BAJO IMPACTO
B56: Múltiplo de salida (±4x) | C56: =MIN(D17:H17) -> 176.26452 | D56: =MAX(D17:H17) -> 291.39108 | E56: =D56-C56 -> 115.12656 | F56: =IF(E56>=LARGE($E$51:$E$56,2),"PRIMARIO",IF(E56>=LARGE($E$51:$E$56,4),"SECUNDARIO","BAJO IMPACTO")) -> PRIMARIO
B58: SENSIBILIDAD CRECIMIENTO DE INGRESOS × MARGEN: NO admite forma cerrada
B59: La depreciación depende de la trayectoria acumulada de PP&E, por lo que un shock de crecimiento no se puede revalorar analíticamente sin re-ejecutar el modelo. Excel resolvería esto con una Tabla de Datos (Datos → Análisis de hipótesis), que no se puede crear por programación. Procedimiento manual:
B60: Paso 1 | C60: Ir a '02 Assumptions'!C104 (shock uniforme al crecimiento de ingresos, en pp).
B61: Paso 2 | C61: Introducir sucesivamente −3,0pp / −1,5pp / 0 / +1,5pp / +3,0pp y anotar '01 Summary'!C18 en la tabla inferior.
B62: Paso 3 | C62: Repetir para cada desplazamiento de margen usando la REJILLA C, que sí es exacta y ya recoge el efecto margen.
B63: Paso 4 | C63: Devolver C104 a 0 al terminar. Si se deja distinto de 0 TODO el libro queda desplazado.
B64: Aviso | C64: Un shock de crecimiento arrastra capex y circulante porque están definidos como porcentaje de ingresos: el efecto neto sobre el valor es MUCHO menor que el efecto sobre los ingresos. Esa es precisamente la razón por la que el crecimiento no es automáticamente el driver principal.
B65: Tabla manual | C65: Δ crecimiento (pp) → valor por acción: −3,0pp: ____ −1,5pp: ____ 0: (ver Summary) +1,5pp: ____ +3,0pp: ____

Sheet 09 Escenarios
A1: PANEL DE ESCENARIOS — BEAR / BASE / BULL
A2: Este panel gobierna TODO el modelo. Cambiar C4 recalcula operativo, tres estados, DCF, valor terminal y valor por acción.
B4: ESCENARIO ACTIVO (1 = Bear, 2 = Base, 3 = Bull) | C4: ='00 Panel del Analista'!D228 -> 0
B5: Escenario activo (nombre) | C5: =CHOOSE($C$4,"BEAR","BASE","BULL") -> BASE
B7: DESPLAZAMIENTOS POR ESCENARIO — se aplican sobre el vector Base de '02 Assumptions'
B8: Driver | C8: Unidad | D8: Bear | E8: Base | F8: Bull | G8: Activo
B9: Multiplicador del crecimiento de ingresos Cloud | C9: x | D9: ='00 Panel del Analista'!D218 -> 0 | E9: ='00 Panel del Analista'!E218 -> 0 | F9: ='00 Panel del Analista'!F218 -> 0 | G9: =CHOOSE($C$4,D9,E9,F9) -> 1
B10: Delta al crecimiento del resto de ingresos | C10: % | D10: ='00 Panel del Analista'!D219 -> 0 | E10: ='00 Panel del Analista'!E219 -> 0 | F10: ='00 Panel del Analista'!F219 -> 0 | G10: =CHOOSE($C$4,D10,E10,F10) -> 0
B11: Delta al Gross Margin | C11: % | D11: ='00 Panel del Analista'!D220 -> 0 | E11: ='00 Panel del Analista'!E220 -> 0 | F11: ='00 Panel del Analista'!F220 -> 0 | G11: =CHOOSE($C$4,D11,E11,F11) -> 0
B12: Delta a los gastos operativos sobre ingresos | C12: % | D12: ='00 Panel del Analista'!D221 -> 0 | E12: ='00 Panel del Analista'!E221 -> 0 | F12: ='00 Panel del Analista'!F221 -> 0 | G12: =CHOOSE($C$4,D12,E12,F12) -> 0
B13: Multiplicador de Capex / Ingresos | C13: x | D13: ='00 Panel del Analista'!D222 -> 0 | E13: ='00 Panel del Analista'!E222 -> 0 | F13: ='00 Panel del Analista'!F222 -> 0 | G13: =CHOOSE($C$4,D13,E13,F13) -> 1
B14: Delta a los días de cobro (DSO) | C14: días | D14: ='00 Panel del Analista'!D223 -> 0 | E14: ='00 Panel del Analista'!E223 -> 0 | F14: ='00 Panel del Analista'!F223 -> 0 | G14: =CHOOSE($C$4,D14,E14,F14) -> 0
B15: Delta al tipo impositivo de caja | C15: % | D15: ='00 Panel del Analista'!D224 -> 0 | E15: ='00 Panel del Analista'!E224 -> 0 | F15: ='00 Panel del Analista'!F224 -> 0 | G15: =CHOOSE($C$4,D15,E15,F15) -> 0
B16: Delta al crecimiento terminal | C16: % | D16: ='00 Panel del Analista'!D225 -> 0 | E16: ='00 Panel del Analista'!E225 -> 0 | F16: ='00 Panel del Analista'!F225 -> 0 | G16: =CHOOSE($C$4,D16,E16,F16) -> 0
B17: Delta al WACC | C17: % | D17: ='00 Panel del Analista'!D226 -> 0 | E17: ='00 Panel del Analista'!E226 -> 0 | F17: ='00 Panel del Analista'!F226 -> 0 | G17: =CHOOSE($C$4,D17,E17,F17) -> 0
B19: COHERENCIA INTERNA DE LOS ESCENARIOS (regla: ningún escenario mejora todos los drivers a la vez)
B20: Bear | C20: Menos crecimiento y menos margen, pero MÁS capex por unidad de ingreso (capacidad ya comprometida que no se llena), peor circulante, más impuestos, menor crecimiento terminal y mayor coste de capital.
B21: Base | C21: Los vectores de '02 Assumptions' tal cual: conversión del RPO en ingresos con desaceleración progresiva y normalización del capex hacia mantenimiento.
B22: Bull | C22: Más crecimiento y más margen con MENOS capex por unidad de ingreso (mejor utilización de la capacidad instalada), mejor circulante, menos impuestos, algo más de crecimiento terminal y menor coste de capital.
B23: Regla | C23: El apalancamiento operativo es lo que conecta ingresos y márgenes: en Bear la caída de ingresos sobre una base de costes fijos y depreciación ya comprometida comprime el margen más que proporcionalmente. Por eso el delta de margen y el de crecimiento van en el mismo sentido.
B24: Regla | C24: El crecimiento Cloud se ajusta como MULTIPLICADOR y no como desplazamiento en puntos porcentuales. Razón: un delta plano de −8 p.p. aplicado a un vector que termina en el 4% produciría decrecimiento en el año 10 mientras el valor terminal asume crecimiento perpetuo positivo. Eso sería una incoherencia interna. El multiplicador preserva la FORMA de la curva de desaceleración y solo cambia su intensidad. El resto de los segmentos sí usa desplazamiento en p.p. porque sus tasas base están próximas a cero y un multiplicador no tendría efecto.
B25: RESULTADO POR ESCENARIO (se actualiza al cambiar C4; para comparar los tres hay que recorrer 1, 2 y 3)
B26: Métrica | C26: Valor del escenario activo
B27: Enterprise Value ($M) | C27: ='06 DCF'!$F$44 -> 608375.19
B28: Equity Value ($M) | C28: ='06 DCF'!$F$53 -> 496514.84
B29: Valor intrínseco por acción ($) | C29: ='06 DCF'!$F$55 -> 169.22796
B30: Precio actual ($) | C30: ='01 Summary'!$C$10 -> 0
B31: Upside / (Downside) | C31: =IF(C30<=0,"introducir precio",C29/C30-1) -> introducir precio
B32: Valor terminal / EV | C32: ='06 DCF'!$F$45 -> 0.66008837

Sheet Escenario Pesimista
A1: ESCENARIO PESIMISTA (BEAR) — MODELO COMPLETO E INDEPENDIENTE
A2: No depende del interruptor '09 Escenarios'!C4. Lee los vectores Base de '02 Assumptions' y aplica los deltas de la COLUMNA D de '09 Escenarios'. Los tres escenarios se calculan simultáneamente.
B4: Partida | C4: Unidad | D4: ='00 Panel del Analista'!D14 -> 0 | E4: ='00 Panel del Analista'!E14 -> 0 | F4: ='00 Panel del Analista'!F14 -> 0 | G4: ='00 Panel del Analista'!G14 -> 0 | H4: ='00 Panel del Analista'!H14 -> 0 | I4: ='00 Panel del Analista'!I14 -> 0 | J4: ='00 Panel del Analista'!J14 -> 0 | K4: ='00 Panel del Analista'!K14 -> 0 | ... P4: ='00 Panel del Analista'!P14 -> 0
B6: INGRESOS
B7: Cloud | C7: $M | F7: ='03 Historical'!F7 -> 0 | G7: =F7*(1+'02 Assumptions'!G19*'09 Escenarios'!$D$9) -> 0 | H7: =G7*(1+'02 Assumptions'!H19*'09 Escenarios'!$D$9) -> 0 | I7: =H7*(1+'02 Assumptions'!I19*'09 Escenarios'!$D$9) -> 0 | J7: =I7*(1+'02 Assumptions'!J19*'09 Escenarios'!$D$9) -> 0 | K7: =J7*(1+'02 Assumptions'!K19*'09 Escenarios'!$D$9) -> 0 | L7: =K7*(1+'02 Assumptions'!L19*'09 Escenarios'!$D$9) -> 0 | M7: =L7*(1+'02 Assumptions'!M19*'09 Escenarios'!$D$9) -> 0 | N7: =M7*(1+'02 Assumptions'!N19*'09 Escenarios'!$D$9) -> 0 | ... P7: =O7*(1+'02 Assumptions'!P19*'09 Escenarios'!$D$9) -> 0
B8: Software | C8: $M | F8: ='03 Historical'!F8 -> 0 | G8: =F8*(1+'02 Assumptions'!G21+'09 Escenarios'!$D$10) -> 0 | H8: =G8*(1+'02 Assumptions'!H21+'09 Escenarios'!$D$10) -> 0 | I8: =H8*(1+'02 Assumptions'!I21+'09 Escenarios'!$D$10) -> 0 | J8: =I8*(1+'02 Assumptions'!J21+'09 Escenarios'!$D$10) -> 0 | K8: =J8*(1+'02 Assumptions'!K21+'09 Escenarios'!$D$10) -> 0 | L8: =K8*(1+'02 Assumptions'!L21+'09 Escenarios'!$D$10) -> 0 | M8: =L8*(1+'02 Assumptions'!M21+'09 Escenarios'!$D$10) -> 0 | N8: =M8*(1+'02 Assumptions'!N21+'09 Escenarios'!$D$10) -> 0 | ... P8: =O8*(1+'02 Assumptions'!P21+'09 Escenarios'!$D$10) -> 0
B9: Hardware | C9: $M | F9: ='03 Historical'!F9 -> 0 | G9: =F9*(1+'02 Assumptions'!G23+'09 Escenarios'!$D$10) -> 0 | H9: =G9*(1+'02 Assumptions'!H23+'09 Escenarios'!$D$10) -> 0 | I9: =H9*(1+'02 Assumptions'!I23+'09 Escenarios'!$D$10) -> 0 | J9: =I9*(1+'02 Assumptions'!J23+'09 Escenarios'!$D$10) -> 0 | K9: =J9*(1+'02 Assumptions'!K23+'09 Escenarios'!$D$10) -> 0 | L9: =K9*(1+'02 Assumptions'!L23+'09 Escenarios'!$D$10) -> 0 | M9: =L9*(1+'02 Assumptions'!M23+'09 Escenarios'!$D$10) -> 0 | N9: =M9*(1+'02 Assumptions'!N23+'09 Escenarios'!$D$10) -> 0 | ... P9: =O9*(1+'02 Assumptions'!P23+'09 Escenarios'!$D$10) -> 0
B10: Servicios | C10: $M | F10: ='03 Historical'!F10 -> 0 | G10: =F10*(1+'02 Assumptions'!G25+'09 Escenarios'!$D$10) -> 0 | H10: =G10*(1+'02 Assumptions'!H25+'09 Escenarios'!$D$10) -> 0 | I10: =H10*(1+'02 Assumptions'!I25+'09 Escenarios'!$D$10) -> 0 | J10: =I10*(1+'02 Assumptions'!J25+'09 Escenarios'!$D$10) -> 0 | K10: =J10*(1+'02 Assumptions'!K25+'09 Escenarios'!$D$10) -> 0 | L10: =K10*(1+'02 Assumptions'!L25+'09 Escenarios'!$D$10) -> 0 | M10: =L10*(1+'02 Assumptions'!M25+'09 Escenarios'!$D$10) -> 0 | N10: =M10*(1+'02 Assumptions'!N25+'09 Escenarios'!$D$10) -> 0 | ... P10: =O10*(1+'02 Assumptions'!P25+'09 Escenarios'!$D$10) -> 0
B11: INGRESOS TOTALES | C11: $M | F11: =SUM(F7:F10) -> 0 | G11: =SUM(G7:G10) -> 0 | H11: =SUM(H7:H10) -> 0 | I11: =SUM(I7:I10) -> 0 | J11: =SUM(J7:J10) -> 0 | K11: =SUM(K7:K10) -> 0 | L11: =SUM(L7:L10) -> 0 | M11: =SUM(M7:M10) -> 0 | ... P11: =SUM(P7:P10) -> 0
B12: Crecimiento | C12: % | G12: =G11/F11-1 -> 0 | H12: =H11/G11-1 -> 0 | I12: =I11/H11-1 -> 0 | J12: =J11/I11-1 -> 0 | K12: =K11/J11-1 -> 0 | L12: =L11/K11-1 -> 0 | M12: =M11/L11-1 -> 0 | N12: =N11/M11-1 -> 0 | ... P12: =P11/O11-1 -> 0
B13: MÁRGENES Y GASTOS
B14: Gross Margin | C14: % | G14: ='02 Assumptions'!G29+'09 Escenarios'!$D$11 -> 0 | H14: ='02 Assumptions'!H29+'09 Escenarios'!$D$11 -> 0 | I14: ='02 Assumptions'!I29+'09 Escenarios'!$D$11 -> 0 | J14: ='02 Assumptions'!J29+'09 Escenarios'!$D$11 -> 0 | K14: ='02 Assumptions'!K29+'09 Escenarios'!$D$11 -> 0 | L14: ='02 Assumptions'!L29+'09 Escenarios'!$D$11 -> 0 | M14: ='02 Assumptions'!M29+'09 Escenarios'!$D$11 -> 0 | N14: ='02 Assumptions'!N29+'09 Escenarios'!$D$11 -> 0 | ... P14: ='02 Assumptions'!P29+'09 Escenarios'!$D$11 -> 0
B15: Margen bruto | C15: $M | G15: =G11*G14 -> 0 | H15: =H11*H14 -> 0 | I15: =I11*I14 -> 0 | J15: =J11*J14 -> 0 | K15: =K11*K14 -> 0 | L15: =L11*L14 -> 0 | M15: =M11*M14 -> 0 | N15: =N11*N14 -> 0 | ... P15: =P11*P14 -> 0
B16: Coste de los ingresos | C16: $M | G16: =G11-G15 -> 0 | H16: =H11-H15 -> 0 | I16: =I11-I15 -> 0 | J16: =J11-J15 -> 0 | K16: =K11-K15 -> 0 | L16: =L11-L15 -> 0 | M16: =M11-M15 -> 0 | N16: =N11-N15 -> 0 | ... P16: =P11-P15 -> 0
B17: Ventas y marketing | C17: $M | G17: =G11*('02 Assumptions'!G31+'09 Escenarios'!$D$12*'02 Assumptions'!$Q$32) -> 0 | H17: =H11*('02 Assumptions'!H31+'09 Escenarios'!$D$12*'02 Assumptions'!$Q$32) -> 0 | I17: =I11*('02 Assumptions'!I31+'09 Escenarios'!$D$12*'02 Assumptions'!$Q$32) -> 0 | J17: =J11*('02 Assumptions'!J31+'09 Escenarios'!$D$12*'02 Assumptions'!$Q$32) -> 0 | K17: =K11*('02 Assumptions'!K31+'09 Escenarios'!$D$12*'02 Assumptions'!$Q$32) -> 0 | L17: =L11*('02 Assumptions'!L31+'09 Escenarios'!$D$12*'02 Assumptions'!$Q$32) -> 0 | M17: =M11*('02 Assumptions'!M31+'09 Escenarios'!$D$12*'02 Assumptions'!$Q$32) -> 0 | N17: =N11*('02 Assumptions'!N31+'09 Escenarios'!$D$12*'02 Assumptions'!$Q$32) -> 0 | ... P17: =P11*('02 Assumptions'!P31+'09 Escenarios'!$D$12*'02 Assumptions'!$Q$32) -> 0
B18: I+D | C18: $M | G18: =G11*('02 Assumptions'!G33+'09 Escenarios'!$D$12*'02 Assumptions'!$Q$34) -> 0 | H18: =H11*('02 Assumptions'!H33+'09 Escenarios'!$D$12*'02 Assumptions'!$Q$34) -> 0 | I18: =I11*('02 Assumptions'!I33+'09 Escenarios'!$D$12*'02 Assumptions'!$Q$34) -> 0 | J18: =J11*('02 Assumptions'!J33+'09 Escenarios'!$D$12*'02 Assumptions'!$Q$34) -> 0 | K18: =K11*('02 Assumptions'!K33+'09 Escenarios'!$D$12*'02 Assumptions'!$Q$34) -> 0 | L18: =L11*('02 Assumptions'!L33+'09 Escenarios'!$D$12*'02 Assumptions'!$Q$34) -> 0 | M18: =M11*('02 Assumptions'!M33+'09 Escenarios'!$D$12*'02 Assumptions'!$Q$34) -> 0 | N18: =N11*('02 Assumptions'!N33+'09 Escenarios'!$D$12*'02 Assumptions'!$Q$34) -> 0 | ... P18: =P11*('02 Assumptions'!P33+'09 Escenarios'!$D$12*'02 Assumptions'!$Q$34) -> 0
B19: G&A | C19: $M | G19: =G11*('02 Assumptions'!G35+'09 Escenarios'!$D$12*'02 Assumptions'!$Q$36) -> 0 | H19: =H11*('02 Assumptions'!H35+'09 Escenarios'!$D$12*'02 Assumptions'!$Q$36) -> 0 | I19: =I11*('02 Assumptions'!I35+'09 Escenarios'!$D$12*'02 Assumptions'!$Q$36) -> 0 | J19: =J11*('02 Assumptions'!J35+'09 Escenarios'!$D$12*'02 Assumptions'!$Q$36) -> 0 | K19: =K11*('02 Assumptions'!K35+'09 Escenarios'!$D$12*'02 Assumptions'!$Q$36) -> 0 | L19: =L11*('02 Assumptions'!L35+'09 Escenarios'!$D$12*'02 Assumptions'!$Q$36) -> 0 | M19: =M11*('02 Assumptions'!M35+'09 Escenarios'!$D$12*'02 Assumptions'!$Q$36) -> 0 | N19: =N11*('02 Assumptions'!N35+'09 Escenarios'!$D$12*'02 Assumptions'!$Q$36) -> 0 | ... P19: =P11*('02 Assumptions'!P35+'09 Escenarios'!$D$12*'02 Assumptions'!$Q$36) -> 0
B20: Amortización de intangibles | C20: $M | G20: ='02 Assumptions'!G37 -> 0 | H20: ='02 Assumptions'!H37 -> 0 | I20: ='02 Assumptions'!I37 -> 0 | J20: ='02 Assumptions'!J37 -> 0 | K20: ='02 Assumptions'!K37 -> 0 | L20: ='02 Assumptions'!L37 -> 0 | M20: ='02 Assumptions'!M37 -> 0 | N20: ='02 Assumptions'!N37 -> 0 | ... P20: ='02 Assumptions'!P37 -> 0
B21: Reestructuración normalizada | C21: $M | G21: ='02 Assumptions'!G38 -> 0 | H21: ='02 Assumptions'!H38 -> 0 | I21: ='02 Assumptions'!I38 -> 0 | J21: ='02 Assumptions'!J38 -> 0 | K21: ='02 Assumptions'!K38 -> 0 | L21: ='02 Assumptions'!L38 -> 0 | M21: ='02 Assumptions'!M38 -> 0 | N21: ='02 Assumptions'!N38 -> 0 | ... P21: ='02 Assumptions'!P38 -> 0
B22: Total gastos operativos | C22: $M | G22: =SUM(G17:G21) -> 0 | H22: =SUM(H17:H21) -> 0 | I22: =SUM(I17:I21) -> 0 | J22: =SUM(J17:J21) -> 0 | K22: =SUM(K17:K21) -> 0 | L22: =SUM(L17:L21) -> 0 | M22: =SUM(M17:M21) -> 0 | N22: =SUM(N17:N21) -> 0 | ... P22: =SUM(P17:P21) -> 0
B23: EBIT reportado | C23: $M | G23: =G15-G22 -> 0 | H23: =H15-H22 -> 0 | I23: =I15-I22 -> 0 | J23: =J15-J22 -> 0 | K23: =K15-K22 -> 0 | L23: =L15-L22 -> 0 | M23: =M15-M22 -> 0 | N23: =N15-N22 -> 0 | ... P23: =P15-P22 -> 0
B24: EBIT NORMALIZADO | C24: $M | G24: =G23+G21 -> 0 | H24: =H23+H21 -> 0 | I24: =I23+I21 -> 0 | J24: =J23+J21 -> 0 | K24: =K23+K21 -> 0 | L24: =L23+L21 -> 0 | M24: =M23+M21 -> 0 | N24: =N23+N21 -> 0 | ... P24: =P23+P21 -> 0
B25: Margen EBIT normalizado | C25: % | G25: =G24/G11 -> 0 | H25: =H24/H11 -> 0 | I25: =I24/I11 -> 0 | J25: =J24/J11 -> 0 | K25: =K24/K11 -> 0 | L25: =L24/L11 -> 0 | M25: =M24/M11 -> 0 | N25: =N24/N11 -> 0 | ... P25: =P24/P11 -> 0
B26: CAPEX Y DEPRECIACIÓN
B27: PP&E neto inicial | C27: $M | G27: =F30 -> 0 | H27: =G30 -> 0 | I27: =H30 -> 0 | J27: =I30 -> 0 | K27: =J30 -> 0 | L27: =K30 -> 0 | M27: =L30 -> 0 | N27: =M30 -> 0 | ... P27: =O30 -> 0
B28: Capex | C28: $M | G28: =G11*'02 Assumptions'!G41*'09 Escenarios'!$D$13 -> 0 | H28: =H11*'02 Assumptions'!H41*'09 Escenarios'!$D$13 -> 0 | I28: =I11*'02 Assumptions'!I41*'09 Escenarios'!$D$13 -> 0 | J28: =J11*'02 Assumptions'!J41*'09 Escenarios'!$D$13 -> 0 | K28: =K11*'02 Assumptions'!K41*'09 Escenarios'!$D$13 -> 0 | L28: =L11*'02 Assumptions'!L41*'09 Escenarios'!$D$13 -> 0 | M28: =M11*'02 Assumptions'!M41*'09 Escenarios'!$D$13 -> 0 | N28: =N11*'02 Assumptions'!N41*'09 Escenarios'!$D$13 -> 0 | ... P28: =P11*'02 Assumptions'!P41*'09 Escenarios'!$D$13 -> 0
B29: Depreciación | C29: $M | G29: =(G27+G28/2)/'02 Assumptions'!$C$43 -> 0 | H29: =(H27+H28/2)/'02 Assumptions'!$C$43 -> 0 | I29: =(I27+I28/2)/'02 Assumptions'!$C$43 -> 0 | J29: =(J27+J28/2)/'02 Assumptions'!$C$43 -> 0 | K29: =(K27+K28/2)/'02 Assumptions'!$C$43 -> 0 | L29: =(L27+L28/2)/'02 Assumptions'!$C$43 -> 0 | M29: =(M27+M28/2)/'02 Assumptions'!$C$43 -> 0 | N29: =(N27+N28/2)/'02 Assumptions'!$C$43 -> 0 | ... P29: =(P27+P28/2)/'02 Assumptions'!$C$43 -> 0
B30: PP&E neto final | C30: $M | F30: ='03 Historical'!F48 -> 0 | G30: =G27+G28-G29 -> 0 | H30: =H27+H28-H29 -> 0 | I30: =I27+I28-I29 -> 0 | J30: =J27+J28-J29 -> 0 | K30: =K27+K28-K29 -> 0 | L30: =L27+L28-L29 -> 0 | M30: =M27+M28-M29 -> 0 | N30: =N27+N28-N29 -> 0 | ... P30: =P27+P28-P29 -> 0
B31: D&A total | C31: $M | G31: =G29+G20 -> 0 | H31: =H29+H20 -> 0 | I31: =I29+I20 -> 0 | J31: =J29+J20 -> 0 | K31: =K29+K20 -> 0 | L31: =L29+L20 -> 0 | M31: =M29+M20 -> 0 | N31: =N29+N20 -> 0 | ... P31: =P29+P20 -> 0
B32: EBITDA | C32: $M | G32: =G24+G31 -> 0 | H32: =H24+H31 -> 0 | I32: =I24+I31 -> 0 | J32: =J24+J31 -> 0 | K32: =K24+K31 -> 0 | L32: =L24+L31 -> 0 | M32: =M24+M31 -> 0 | N32: =N24+N31 -> 0 | ... P32: =P24+P31 -> 0
B33: CIRCULANTE
B34: Clientes | C34: $M | G34: =('02 Assumptions'!G47+'09 Escenarios'!$D$14)/365*G11 -> 0 | H34: =('02 Assumptions'!H47+'09 Escenarios'!$D$14)/365*H11 -> 0 | I34: =('02 Assumptions'!I47+'09 Escenarios'!$D$14)/365*I11 -> 0 | J34: =('02 Assumptions'!J47+'09 Escenarios'!$D$14)/365*J11 -> 0 | K34: =('02 Assumptions'!K47+'09 Escenarios'!$D$14)/365*K11 -> 0 | L34: =('02 Assumptions'!L47+'09 Escenarios'!$D$14)/365*L11 -> 0 | M34: =('02 Assumptions'!M47+'09 Escenarios'!$D$14)/365*M11 -> 0 | N34: =('02 Assumptions'!N47+'09 Escenarios'!$D$14)/365*N11 -> 0 | ... P34: =('02 Assumptions'!P47+'09 Escenarios'!$D$14)/365*P11 -> 0
B35: Otros activos corrientes | C35: $M | G35: =G11*'02 Assumptions'!G51 -> 0 | H35: =H11*'02 Assumptions'!H51 -> 0 | I35: =I11*'02 Assumptions'!I51 -> 0 | J35: =J11*'02 Assumptions'!J51 -> 0 | K35: =K11*'02 Assumptions'!K51 -> 0 | L35: =L11*'02 Assumptions'!L51 -> 0 | M35: =M11*'02 Assumptions'!M51 -> 0 | N35: =N11*'02 Assumptions'!N51 -> 0 | ... P35: =P11*'02 Assumptions'!P51 -> 0
B36: Proveedores | C36: $M | G36: =(G16+G28)*'02 Assumptions'!G49 -> 0 | H36: =(H16+H28)*'02 Assumptions'!H49 -> 0 | I36: =(I16+I28)*'02 Assumptions'!I49 -> 0 | J36: =(J16+J28)*'02 Assumptions'!J49 -> 0 | K36: =(K16+K28)*'02 Assumptions'!K49 -> 0 | L36: =(L16+L28)*'02 Assumptions'!L49 -> 0 | M36: =(M16+M28)*'02 Assumptions'!M49 -> 0 | N36: =(N16+N28)*'02 Assumptions'!N49 -> 0 | ... P36: =(P16+P28)*'02 Assumptions'!P49 -> 0
B37: Remuneraciones pendientes | C37: $M | G37: =G11*'02 Assumptions'!G52 -> 0 | H37: =H11*'02 Assumptions'!H52 -> 0 | I37: =I11*'02 Assumptions'!I52 -> 0 | J37: =J11*'02 Assumptions'!J52 -> 0 | K37: =K11*'02 Assumptions'!K52 -> 0 | L37: =L11*'02 Assumptions'!L52 -> 0 | M37: =M11*'02 Assumptions'!M52 -> 0 | N37: =N11*'02 Assumptions'!N52 -> 0 | ... P37: =P11*'02 Assumptions'!P52 -> 0
B38: Ingresos diferidos corrientes | C38: $M | G38: =G11*'02 Assumptions'!G50 -> 0 | H38: =H11*'02 Assumptions'!H50 -> 0 | I38: =I11*'02 Assumptions'!I50 -> 0 | J38: =J11*'02 Assumptions'!J50 -> 0 | K38: =K11*'02 Assumptions'!K50 -> 0 | L38: =L11*'02 Assumptions'!L50 -> 0 | M38: =M11*'02 Assumptions'!M50 -> 0 | N38: =N11*'02 Assumptions'!N50 -> 0 | ... P38: =P11*'02 Assumptions'!P50 -> 0
B39: Otros pasivos corrientes | C39: $M | G39: =G11*'02 Assumptions'!G53 -> 0 | H39: =H11*'02 Assumptions'!H53 -> 0 | I39: =I11*'02 Assumptions'!I53 -> 0 | J39: =J11*'02 Assumptions'!J53 -> 0 | K39: =K11*'02 Assumptions'!K53 -> 0 | L39: =L11*'02 Assumptions'!L53 -> 0 | M39: =M11*'02 Assumptions'!M53 -> 0 | N39: =N11*'02 Assumptions'!N53 -> 0 | ... P39: =P11*'02 Assumptions'!P53 -> 0
B40: CAPITAL CIRCULANTE NETO | C40: $M | F40: ='04 Operating Model'!F50 -> 0 | G40: =G34+G35-G36-G37-G38-G39 -> 0 | H40: =H34+H35-H36-H37-H38-H39 -> 0 | I40: =I34+I35-I36-I37-I38-I39 -> 0 | J40: =J34+J35-J36-J37-J38-J39 -> 0 | K40: =K34+K35-K36-K37-K38-K39 -> 0 | L40: =L34+L35-L36-L37-L38-L39 -> 0 | M40: =M34+M35-M36-M37-M38-M39 -> 0 | N40: =N34+N35-N36-N37-N38-N39 -> 0 | ... P40: =P34+P35-P36-P37-P38-P39 -> 0
B41: Variación del NWC | C41: $M | G41: =G40-F40 -> 0 | H41: =H40-G40 -> 0 | I41: =I40-H40 -> 0 | J41: =J40-I40 -> 0 | K41: =K40-J40 -> 0 | L41: =L40-K40 -> 0 | M41: =M40-L40 -> 0 | N41: =N40-M40 -> 0 | ... P41: =P40-O40 -> 0
B42: FCFF
B43: Tipo impositivo de caja | C43: % | G43: ='02 Assumptions'!G56+'09 Escenarios'!$D$15 -> 0 | H43: ='02 Assumptions'!H56+'09 Escenarios'!$D$15 -> 0 | I43: ='02 Assumptions'!I56+'09 Escenarios'!$D$15 -> 0 | J43: ='02 Assumptions'!J56+'09 Escenarios'!$D$15 -> 0 | K43: ='02 Assumptions'!K56+'09 Escenarios'!$D$15 -> 0 | L43: ='02 Assumptions'!L56+'09 Escenarios'!$D$15 -> 0 | M43: ='02 Assumptions'!M56+'09 Escenarios'!$D$15 -> 0 | N43: ='02 Assumptions'!N56+'09 Escenarios'!$D$15 -> 0 | ... P43: ='02 Assumptions'!P56+'09 Escenarios'!$D$15 -> 0
B44: (−) Impuestos sobre el EBIT normalizado | C44: $M | G44: =-G24*G43 -> 0 | H44: =-H24*H43 -> 0 | I44: =-I24*I43 -> 0 | J44: =-J24*J43 -> 0 | K44: =-K24*K43 -> 0 | L44: =-L24*L43 -> 0 | M44: =-M24*M43 -> 0 | N44: =-N24*N43 -> 0 | ... P44: =-P24*P43 -> 0
B45: NOPAT | C45: $M | G45: =G24+G44 -> 0 | H45: =H24+H44 -> 0 | I45: =I24+I44 -> 0 | J45: =J24+J44 -> 0 | K45: =K24+K44 -> 0 | L45: =L24+L44 -> 0 | M45: =M24+M44 -> 0 | N45: =N24+N44 -> 0 | ... P45: =P24+P44 -> 0
B46: (+) D&A | C46: $M | G46: =G31 -> 0 | H46: =H31 -> 0 | I46: =I31 -> 0 | J46: =J31 -> 0 | K46: =K31 -> 0 | L46: =L31 -> 0 | M46: =M31 -> 0 | N46: =N31 -> 0 | ... P46: =P31 -> 0
B47: (−) Capex | C47: $M | G47: =-G28 -> 0 | H47: =-H28 -> 0 | I47: =-I28 -> 0 | J47: =-J28 -> 0 | K47: =-K28 -> 0 | L47: =-L28 -> 0 | M47: =-M28 -> 0 | N47: =-N28 -> 0 | ... P47: =-P28 -> 0
B48: (−) Variación del NWC | C48: $M | G48: =-G41 -> 0 | H48: =-H41 -> 0 | I48: =-I41 -> 0 | J48: =-J41 -> 0 | K48: =-K41 -> 0 | L48: =-L41 -> 0 | M48: =-M41 -> 0 | N48: =-N41 -> 0 | ... P48: =-P41 -> 0
B49: (−) Coste en caja de reestructuración | C49: $M | G49: =-G21 -> 0 | H49: =-H21 -> 0 | I49: =-I21 -> 0 | J49: =-J21 -> 0 | K49: =-K21 -> 0 | L49: =-L21 -> 0 | M49: =-M21 -> 0 | N49: =-N21 -> 0 | ... P49: =-P21 -> 0
B50: FCFF | C50: $M | G50: =SUM(G45:G49) -> 0 | H50: =SUM(H45:H49) -> 0 | I50: =SUM(I45:I49) -> 0 | J50: =SUM(J45:J49) -> 0 | K50: =SUM(K45:K49) -> 0 | L50: =SUM(L45:L49) -> 0 | M50: =SUM(M45:M49) -> 0 | N50: =SUM(N45:N49) -> 0 | ... P50: =SUM(P45:P49) -> 0
B51: DESCUENTO Y VALOR TERMINAL
B52: WACC (base + delta del escenario) | C52: % | G52: ='07 WACC'!$C$36+'09 Escenarios'!$D$17 -> 0 | H52: ='07 WACC'!$C$36+'09 Escenarios'!$D$17 -> 0 | I52: ='07 WACC'!$C$36+'09 Escenarios'!$D$17 -> 0 | J52: ='07 WACC'!$C$36+'09 Escenarios'!$D$17 -> 0 | K52: ='07 WACC'!$C$36+'09 Escenarios'!$D$17 -> 0 | L52: ='07 WACC'!$C$36+'09 Escenarios'!$D$17 -> 0 | M52: ='07 WACC'!$C$36+'09 Escenarios'!$D$17 -> 0 | N52: ='07 WACC'!$C$36+'09 Escenarios'!$D$17 -> 0 | ... P52: ='07 WACC'!$C$36+'09 Escenarios'!$D$17 -> 0
B53: Crecimiento terminal g | C53: % | G53: ='02 Assumptions'!$C$62+'09 Escenarios'!$D$16 -> 0 | H53: ='02 Assumptions'!$C$62+'09 Escenarios'!$D$16 -> 0 | I53: ='02 Assumptions'!$C$62+'09 Escenarios'!$D$16 -> 0 | J53: ='02 Assumptions'!$C$62+'09 Escenarios'!$D$16 -> 0 | K53: ='02 Assumptions'!$C$62+'09 Escenarios'!$D$16 -> 0 | L53: ='02 Assumptions'!$C$62+'09 Escenarios'!$D$16 -> 0 | M53: ='02 Assumptions'!$C$62+'09 Escenarios'!$D$16 -> 0 | N53: ='02 Assumptions'!$C$62+'09 Escenarios'!$D$16 -> 0 | ... P53: ='02 Assumptions'!$C$62+'09 Escenarios'!$D$16 -> 0
B54: ROIC terminal | C54: % | G54: ='02 Assumptions'!$C$66 -> 0 | H54: ='02 Assumptions'!$C$66 -> 0 | I54: ='02 Assumptions'!$C$66 -> 0 | J54: ='02 Assumptions'!$C$66 -> 0 | K54: ='02 Assumptions'!$C$66 -> 0 | L54: ='02 Assumptions'!$C$66 -> 0 | M54: ='02 Assumptions'!$C$66 -> 0 | N54: ='02 Assumptions'!$C$66 -> 0 | ... P54: ='02 Assumptions'!$C$66 -> 0
B55: Periodo de descuento t | C55: años | G55: =COLUMNS($G55:G55)-IF('02 Assumptions'!$C$12=2,0.5,0) -> 0 | H55: =COLUMNS($G55:H55)-IF('02 Assumptions'!$C$12=2,0.5,0) -> 0 | I55: =COLUMNS($G55:I55)-IF('02 Assumptions'!$C$12=2,0.5,0) -> 0 | J55: =COLUMNS($G55:J55)-IF('02 Assumptions'!$C$12=2,0.5,0) -> 0 | K55: =COLUMNS($G55:K55)-IF('02 Assumptions'!$C$12=2,0.5,0) -> 0 | L55: =COLUMNS($G55:L55)-IF('02 Assumptions'!$C$12=2,0.5,0) -> 0 | M55: =COLUMNS($G55:M55)-IF('02 Assumptions'!$C$12=2,0.5,0) -> 0 | N55: =COLUMNS($G55:N55)-IF('02 Assumptions'!$C$12=2,0.5,0) -> 0 | ... P55: =COLUMNS($G55:P55)-IF('02 Assumptions'!$C$12=2,0.5,0) -> 0
B56: Factor de descuento | C56: x | G56: =1/(1+G52)^G55 -> 0 | H56: =1/(1+H52)^H55 -> 0 | I56: =1/(1+I52)^I55 -> 0 | J56: =1/(1+J52)^J55 -> 0 | K56: =1/(1+K52)^K55 -> 0 | L56: =1/(1+L52)^L55 -> 0 | M56: =1/(1+M52)^M55 -> 0 | N56: =1/(1+N52)^N55 -> 0 | ... P56: =1/(1+P52)^P55 -> 0
B57: Valor presente del FCFF | C57: $M | G57: =G50*G56 -> 0 | H57: =H50*H56 -> 0 | I57: =I50*I56 -> 0 | J57: =J50*J56 -> 0 | K57: =K50*K56 -> 0 | L57: =L50*L56 -> 0 | M57: =M50*M56 -> 0 | N57: =N50*N56 -> 0 | ... P57: =P50*P56 -> 0
B59: Valor presente del FCFF explícito | C59: $M | F59: =SUM(G57:P57) -> 0
B60: Tasa de reinversión terminal = g / ROIC | C60: % | F60: =P53/P54 -> 0
B61: NOPAT terminal | C61: $M | F61: =P45*(1+P53) -> 0
B62: FCFF terminal | C62: $M | F62: =F61*(1-F60) -> 0
B63: Valor terminal | C63: $M | F63: =IF(P52<=P53,"FALLO: WACC<=g",F62/(P52-P53)) -> 0
B64: Factor de descuento del valor terminal | C64: x | F64: =1/(1+P52)^'02 Assumptions'!$C$11 -> 0
B65: Valor presente del valor terminal | C65: $M | F65: =F63*F64 -> 0
B66: ENTERPRISE VALUE | C66: $M | F66: =F59+F65 -> 0
B67: Valor terminal / Enterprise Value | C67: % | F67: =F65/F66 -> 0
B68: Múltiplo de salida implícito (VT / EBITDA FY2036) | C68: x | F68: =IFERROR(F63/P32,"n/a") -> 0
B69: Puente a Equity (idéntico a '06 DCF' filas 46-52) | C69: $M | F69: =SUM('06 DCF'!$F$46:$F$52) -> 0
B70: EQUITY VALUE | C70: $M | F70: =F66+F69 -> 0
B71: Acciones diluidas | C71: M acc | F71: ='02 Assumptions'!$C$69 -> 0
B72: VALOR INTRÍNSECO POR ACCIÓN | C72: $/acc | F72: =F70/F71 -> 0
B73: Precio de mercado actual | C73: $/acc | F73: ='01 Summary'!$C$10 -> 0
B74: Upside / (Downside) | C74: % | F74: =IF(F73<=0,"introducir precio",F72/F73-1) -> 0
B75: Ingresos FY2036E | C75: $M | F75: =P11 -> 0
B77: CONTROLES DE ESTE ESCENARIO
B78: CHECK: WACC > g | F78: =IF(P52>P53,"OK","FALLO") -> 0
B79: CHECK: FCFF positivo al final del horizonte | F79: =IF(P50>0,"OK","FALLO") -> 0
B80: CHECK: crecimiento del año 10 ≥ g | F80: =IF(P12>=P53,"OK","AVISO: el último año explícito crece menos que la perpetuidad") -> 0
B81: CHECK: sin errores de fórmula en la hoja | F81: {=IF(SUMPRODUCT(--ISERROR($G$7:$P$57))=0,"OK","FALLO")} -> 0
B82: CHECK: reproduce '06 DCF' (sólo debe cumplirse en el escenario BASE) | F82: no aplica

Sheet Escenario Base
A1: ESCENARIO BASE — MODELO COMPLETO E INDEPENDIENTE
A2: No depende del interruptor '09 Escenarios'!C4. Lee los vectores Base de '02 Assumptions' y aplica los deltas de la COLUMNA E de '09 Escenarios'. Los tres escenarios se calculan simultáneamente.
B4: Partida | C4: Unidad | D4: ='00 Panel del Analista'!D14 -> 0 | E4: ='00 Panel del Analista'!E14 -> 0 | F4: ='00 Panel del Analista'!F14 -> 0 | G4: ='00 Panel del Analista'!G14 -> 0 | H4: ='00 Panel del Analista'!H14 -> 0 | I4: ='00 Panel del Analista'!I14 -> 0 | J4: ='00 Panel del Analista'!J14 -> 0 | K4: ='00 Panel del Analista'!K14 -> 0 | ... P4: ='00 Panel del Analista'!P14 -> 0
B6: INGRESOS
B7: Cloud | C7: $M | F7: ='03 Historical'!F7 -> 0 | G7: =F7*(1+'02 Assumptions'!G19*'09 Escenarios'!$E$9) -> 0 | H7: =G7*(1+'02 Assumptions'!H19*'09 Escenarios'!$E$9) -> 0 | I7: =H7*(1+'02 Assumptions'!I19*'09 Escenarios'!$E$9) -> 0 | J7: =I7*(1+'02 Assumptions'!J19*'09 Escenarios'!$E$9) -> 0 | K7: =J7*(1+'02 Assumptions'!K19*'09 Escenarios'!$E$9) -> 0 | L7: =K7*(1+'02 Assumptions'!L19*'09 Escenarios'!$E$9) -> 0 | M7: =L7*(1+'02 Assumptions'!M19*'09 Escenarios'!$E$9) -> 0 | N7: =M7*(1+'02 Assumptions'!N19*'09 Escenarios'!$E$9) -> 0 | ... P7: =O7*(1+'02 Assumptions'!P19*'09 Escenarios'!$E$9) -> 0
B8: Software | C8: $M | F8: ='03 Historical'!F8 -> 0 | G8: =F8*(1+'02 Assumptions'!G21+'09 Escenarios'!$E$10) -> 0 | H8: =G8*(1+'02 Assumptions'!H21+'09 Escenarios'!$E$10) -> 0 | I8: =H8*(1+'02 Assumptions'!I21+'09 Escenarios'!$E$10) -> 0 | J8: =I8*(1+'02 Assumptions'!J21+'09 Escenarios'!$E$10) -> 0 | K8: =J8*(1+'02 Assumptions'!K21+'09 Escenarios'!$E$10) -> 0 | L8: =K8*(1+'02 Assumptions'!L21+'09 Escenarios'!$E$10) -> 0 | M8: =L8*(1+'02 Assumptions'!M21+'09 Escenarios'!$E$10) -> 0 | N8: =M8*(1+'02 Assumptions'!N21+'09 Escenarios'!$E$10) -> 0 | ... P8: =O8*(1+'02 Assumptions'!P21+'09 Escenarios'!$E$10) -> 0
B9: Hardware | C9: $M | F9: ='03 Historical'!F9 -> 0 | G9: =F9*(1+'02 Assumptions'!G23+'09 Escenarios'!$E$10) -> 0 | H9: =G9*(1+'02 Assumptions'!H23+'09 Escenarios'!$E$10) -> 0 | I9: =H9*(1+'02 Assumptions'!I23+'09 Escenarios'!$E$10) -> 0 | J9: =I9*(1+'02 Assumptions'!J23+'09 Escenarios'!$E$10) -> 0 | K9: =J9*(1+'02 Assumptions'!K23+'09 Escenarios'!$E$10) -> 0 | L9: =K9*(1+'02 Assumptions'!L23+'09 Escenarios'!$E$10) -> 0 | M9: =L9*(1+'02 Assumptions'!M23+'09 Escenarios'!$E$10) -> 0 | N9: =M9*(1+'02 Assumptions'!N23+'09 Escenarios'!$E$10) -> 0 | ... P9: =O9*(1+'02 Assumptions'!P23+'09 Escenarios'!$E$10) -> 0
B10: Servicios | C10: $M | F10: ='03 Historical'!F10 -> 0 | G10: =F10*(1+'02 Assumptions'!G25+'09 Escenarios'!$E$10) -> 0 | H10: =G10*(1+'02 Assumptions'!H25+'09 Escenarios'!$E$10) -> 0 | I10: =H10*(1+'02 Assumptions'!I25+'09 Escenarios'!$E$10) -> 0 | J10: =I10*(1+'02 Assumptions'!J25+'09 Escenarios'!$E$10) -> 0 | K10: =J10*(1+'02 Assumptions'!K25+'09 Escenarios'!$E$10) -> 0 | L10: =K10*(1+'02 Assumptions'!L25+'09 Escenarios'!$E$10) -> 0 | M10: =L10*(1+'02 Assumptions'!M25+'09 Escenarios'!$E$10) -> 0 | N10: =M10*(1+'02 Assumptions'!N25+'09 Escenarios'!$E$10) -> 0 | ... P10: =O10*(1+'02 Assumptions'!P25+'09 Escenarios'!$E$10) -> 0
B11: INGRESOS TOTALES | C11: $M | F11: =SUM(F7:F10) -> 0 | G11: =SUM(G7:G10) -> 0 | H11: =SUM(H7:H10) -> 0 | I11: =SUM(I7:I10) -> 0 | J11: =SUM(J7:J10) -> 0 | K11: =SUM(K7:K10) -> 0 | L11: =SUM(L7:L10) -> 0 | M11: =SUM(M7:M10) -> 0 | ... P11: =SUM(P7:P10) -> 0
B12: Crecimiento | C12: % | G12: =G11/F11-1 -> 0 | H12: =H11/G11-1 -> 0 | I12: =I11/H11-1 -> 0 | J12: =J11/I11-1 -> 0 | K12: =K11/J11-1 -> 0 | L12: =L11/K11-1 -> 0 | M12: =M11/L11-1 -> 0 | N12: =N11/M11-1 -> 0 | ... P12: =P11/O11-1 -> 0
B13: MÁRGENES Y GASTOS
B14: Gross Margin | C14: % | G14: ='02 Assumptions'!G29+'09 Escenarios'!$E$11 -> 0 | H14: ='02 Assumptions'!H29+'09 Escenarios'!$E$11 -> 0 | I14: ='02 Assumptions'!I29+'09 Escenarios'!$E$11 -> 0 | J14: ='02 Assumptions'!J29+'09 Escenarios'!$E$11 -> 0 | K14: ='02 Assumptions'!K29+'09 Escenarios'!$E$11 -> 0 | L14: ='02 Assumptions'!L29+'09 Escenarios'!$E$11 -> 0 | M14: ='02 Assumptions'!M29+'09 Escenarios'!$E$11 -> 0 | N14: ='02 Assumptions'!N29+'09 Escenarios'!$E$11 -> 0 | ... P14: ='02 Assumptions'!P29+'09 Escenarios'!$E$11 -> 0
B15: Margen bruto | C15: $M | G15: =G11*G14 -> 0 | H15: =H11*H14 -> 0 | I15: =I11*I14 -> 0 | J15: =J11*J14 -> 0 | K15: =K11*K14 -> 0 | L15: =L11*L14 -> 0 | M15: =M11*M14 -> 0 | N15: =N11*N14 -> 0 | ... P15: =P11*P14 -> 0
B16: Coste de los ingresos | C16: $M | G16: =G11-G15 -> 0 | H16: =H11-H15 -> 0 | I16: =I11-I15 -> 0 | J16: =J11-J15 -> 0 | K16: =K11-K15 -> 0 | L16: =L11-L15 -> 0 | M16: =M11-M15 -> 0 | N16: =N11-N15 -> 0 | ... P16: =P11-P15 -> 0
B17: Ventas y marketing | C17: $M | G17: =G11*('02 Assumptions'!G31+'09 Escenarios'!$E$12*'02 Assumptions'!$Q$32) -> 0 | H17: =H11*('02 Assumptions'!H31+'09 Escenarios'!$E$12*'02 Assumptions'!$Q$32) -> 0 | I17: =I11*('02 Assumptions'!I31+'09 Escenarios'!$E$12*'02 Assumptions'!$Q$32) -> 0 | J17: =J11*('02 Assumptions'!J31+'09 Escenarios'!$E$12*'02 Assumptions'!$Q$32) -> 0 | K17: =K11*('02 Assumptions'!K31+'09 Escenarios'!$E$12*'02 Assumptions'!$Q$32) -> 0 | L17: =L11*('02 Assumptions'!L31+'09 Escenarios'!$E$12*'02 Assumptions'!$Q$32) -> 0 | M17: =M11*('02 Assumptions'!M31+'09 Escenarios'!$E$12*'02 Assumptions'!$Q$32) -> 0 | N17: =N11*('02 Assumptions'!N31+'09 Escenarios'!$E$12*'02 Assumptions'!$Q$32) -> 0 | ... P17: =P11*('02 Assumptions'!P31+'09 Escenarios'!$E$12*'02 Assumptions'!$Q$32) -> 0
B18: I+D | C18: $M | G18: =G11*('02 Assumptions'!G33+'09 Escenarios'!$E$12*'02 Assumptions'!$Q$34) -> 0 | H18: =H11*('02 Assumptions'!H33+'09 Escenarios'!$E$12*'02 Assumptions'!$Q$34) -> 0 | I18: =I11*('02 Assumptions'!I33+'09 Escenarios'!$E$12*'02 Assumptions'!$Q$34) -> 0 | J18: =J11*('02 Assumptions'!J33+'09 Escenarios'!$E$12*'02 Assumptions'!$Q$34) -> 0 | K18: =K11*('02 Assumptions'!K33+'09 Escenarios'!$E$12*'02 Assumptions'!$Q$34) -> 0 | L18: =L11*('02 Assumptions'!L33+'09 Escenarios'!$E$12*'02 Assumptions'!$Q$34) -> 0 | M18: =M11*('02 Assumptions'!M33+'09 Escenarios'!$E$12*'02 Assumptions'!$Q$34) -> 0 | N18: =N11*('02 Assumptions'!N33+'09 Escenarios'!$E$12*'02 Assumptions'!$Q$34) -> 0 | ... P18: =P11*('02 Assumptions'!P33+'09 Escenarios'!$E$12*'02 Assumptions'!$Q$34) -> 0
B19: G&A | C19: $M | G19: =G11*('02 Assumptions'!G35+'09 Escenarios'!$E$12*'02 Assumptions'!$Q$36) -> 0 | H19: =H11*('02 Assumptions'!H35+'09 Escenarios'!$E$12*'02 Assumptions'!$Q$36) -> 0 | I19: =I11*('02 Assumptions'!I35+'09 Escenarios'!$E$12*'02 Assumptions'!$Q$36) -> 0 | J19: =J11*('02 Assumptions'!J35+'09 Escenarios'!$E$12*'02 Assumptions'!$Q$36) -> 0 | K19: =K11*('02 Assumptions'!K35+'09 Escenarios'!$E$12*'02 Assumptions'!$Q$36) -> 0 | L19: =L11*('02 Assumptions'!L35+'09 Escenarios'!$E$12*'02 Assumptions'!$Q$36) -> 0 | M19: =M11*('02 Assumptions'!M35+'09 Escenarios'!$E$12*'02 Assumptions'!$Q$36) -> 0 | N19: =N11*('02 Assumptions'!N35+'09 Escenarios'!$E$12*'02 Assumptions'!$Q$36) -> 0 | ... P19: =P11*('02 Assumptions'!P35+'09 Escenarios'!$E$12*'02 Assumptions'!$Q$36) -> 0
B20: Amortización de intangibles | C20: $M | G20: ='02 Assumptions'!G37 -> 0 | H20: ='02 Assumptions'!H37 -> 0 | I20: ='02 Assumptions'!I37 -> 0 | J20: ='02 Assumptions'!J37 -> 0 | K20: ='02 Assumptions'!K37 -> 0 | L20: ='02 Assumptions'!L37 -> 0 | M20: ='02 Assumptions'!M37 -> 0 | N20: ='02 Assumptions'!N37 -> 0 | ... P20: ='02 Assumptions'!P37 -> 0
B21: Reestructuración normalizada | C21: $M | G21: ='02 Assumptions'!G38 -> 0 | H21: ='02 Assumptions'!H38 -> 0 | I21: ='02 Assumptions'!I38 -> 0 | J21: ='02 Assumptions'!J38 -> 0 | K21: ='02 Assumptions'!K38 -> 0 | L21: ='02 Assumptions'!L38 -> 0 | M21: ='02 Assumptions'!M38 -> 0 | N21: ='02 Assumptions'!N38 -> 0 | ... P21: ='02 Assumptions'!P38 -> 0
B22: Total gastos operativos | C22: $M | G22: =SUM(G17:G21) -> 0 | H22: =SUM(H17:H21) -> 0 | I22: =SUM(I17:I21) -> 0 | J22: =SUM(J17:J21) -> 0 | K22: =SUM(K17:K21) -> 0 | L22: =SUM(L17:L21) -> 0 | M22: =SUM(M17:M21) -> 0 | N22: =SUM(N17:N21) -> 0 | ... P22: =SUM(P17:P21) -> 0
B23: EBIT reportado | C23: $M | G23: =G15-G22 -> 0 | H23: =H15-H22 -> 0 | I23: =I15-I22 -> 0 | J23: =J15-J22 -> 0 | K23: =K15-K22 -> 0 | L23: =L15-L22 -> 0 | M23: =M15-M22 -> 0 | N23: =N15-N22 -> 0 | ... P23: =P15-P22 -> 0
B24: EBIT NORMALIZADO | C24: $M | G24: =G23+G21 -> 0 | H24: =H23+H21 -> 0 | I24: =I23+I21 -> 0 | J24: =J23+J21 -> 0 | K24: =K23+K21 -> 0 | L24: =L23+L21 -> 0 | M24: =M23+M21 -> 0 | N24: =N23+N21 -> 0 | ... P24: =P23+P21 -> 0
B25: Margen EBIT normalizado | C25: % | G25: =G24/G11 -> 0 | H25: =H24/H11 -> 0 | I25: =I24/I11 -> 0 | J25: =J24/J11 -> 0 | K25: =K24/K11 -> 0 | L25: =L24/L11 -> 0 | M25: =M24/M11 -> 0 | N25: =N24/N11 -> 0 | ... P25: =P24/P11 -> 0
B26: CAPEX Y DEPRECIACIÓN
B27: PP&E neto inicial | C27: $M | G27: =F30 -> 0 | H27: =G30 -> 0 | I27: =H30 -> 0 | J27: =I30 -> 0 | K27: =J30 -> 0 | L27: =K30 -> 0 | M27: =L30 -> 0 | N27: =M30 -> 0 | ... P27: =O30 -> 0
