Workbook

Sheet 00 Panel del Analista
A1: PANEL DEL ANALISTA — TODOS LOS INPUTS DEL MODELO EN UN SOLO SITIO
A2: Rellena las celdas AZULES sobre fondo blanco y las AMARILLAS (hipótesis críticas). El resto del libro se recalcula solo. Para valorar OTRA compañía: sustituye la identificación, los tres estados históricos y los drivers; no hace falta tocar ninguna otra hoja.
A3: Las filas marcadas «calculado» no se rellenan: son totales que el libro deriva. Al terminar, comprueba el semáforo del final de esta hoja y la hoja '13 Checks'.
B5: Input | C5: Unidad | D5: Hist. −2 | E5: Hist. −1 | F5: Hist. base | G5: Año 1 | H5: Año 2 | I5: Año 3 | J5: Año 4 | K5: Año 5 | L5: Año 6 | M5: Año 7 | N5: Año 8 | O5: Año 9 | P5: Año 10
B7: 1. IDENTIFICACIÓN Y MERCADO
B8: Compañía | C8: QUALCOMM Incorporated
B9: Ticker y mercado | C9: QCOM — Nasdaq
B10: Moneda y unidades | C10: USD millones
B11: Fecha de valoración | C11: =DATE(2026,9,23) -> 46288
B12: Último ejercicio auditado | C12: FY2025A auditado (cerrado 28/09/2025); base del forecast FY2026E = 9M real + guía Q4
B13: PRECIO DE MERCADO ACTUAL (el único dato que el libro no puede deducir) | C13: 198.27
B14: Etiquetas de los ejercicios (se propagan a las cabeceras de todas las hojas) | C14: texto | D14: FY2024A | E14: FY2025A | F14: FY2026E | G14: FY2027E | H14: FY2028E | I14: FY2029E | J14: FY2030E | K14: FY2031E | L14: FY2032E | M14: FY2033E | N14: FY2034E | O14: FY2035E | P14: FY2036E
B16: 2. CUENTA DE RESULTADOS HISTÓRICA
B18: QCT IoT + Data Center y otros no reportables | C18: $M | D18: 5617 | E18: 6809 | F18: =5244+353+(1806+109) -> 7512
B19: QCT Handsets | C19: $M | D19: 24863 | E19: 27793 | F19: =18934+5200 -> 24134
B20: QTL Licencias (incl. ingresos no asignados) | C20: $M | D20: 5572 | E20: 5725 | F20: =4252+1300 -> 5552
B21: QCT Automoción | C21: $M | D21: 2910 | E21: 3957 | F21: =4015+1685 -> 5700
B22: Ingresos totales | C22: $M | D22: calculado
B24: Coste de los ingresos (excl. amortización de intangibles) | C24: $M | D24: 16749 | E24: 19417 | F24: =(15138+4752)-331 -> 19559
B25: (no aplica — coste único en QCOM) | C25: $M | D25: 0 | E25: 0 | F25: 0
B26: (no aplica — coste único en QCOM) | C26: $M | D26: 0 | E26: 0 | F26: 0
B27: Coste total de los ingresos | C27: $M | D27: calculado
B28: Margen bruto (Gross Profit) | C28: $M | D28: calculado
B29: Gross Margin | C29: % | D29: calculado
B31: Ventas, generales y administración (SG&A) | C31: $M | D31: 2759 | E31: 3110 | F31: =2738+980 -> 3718
B32: Investigación y desarrollo | C32: $M | D32: 8893 | E32: 9042 | F32: =7523+2620 -> 10143
B33: Generales y administración (incluido en SG&A) | C33: $M | D33: 0 | E33: 0 | F33: 0
B34: Amortización de intangibles adquiridos (reclasificada desde coste de ingresos) | C34: $M | D34: 311 | E34: 321 | F34: 331
B35: Otros gastos operativos (reestructuración, deterioros y otros) | C35: $M | D35: 179 | E35: 39 | F35: =97+0 -> 97
B36: Gastos operativos totales | C36: $M | D36: calculado
B37: EBIT (resultado operativo) reportado | C37: $M | D37: calculado
B38: EBIT Margin reportado | C38: % | D38: calculado
B40: Gasto por intereses | C40: $M | D40: 697 | E40: 664 | F40: =519+175 -> 694
B41: Resultado de inversiones y otros, neto (incl. QSI) | C41: $M | D41: 962 | E41: 972 | F41: =1458+85 -> 1543
B42: Beneficio antes de impuestos | C42: $M | D42: calculado
B43: Impuesto sobre sociedades | C43: $M | D43: 226 | E43: 7122 | F43: =-4136+232 -> -3904
B44: Tipo impositivo efectivo | C44: % | D44: calculado
B45: Beneficio neto | C45: $M | D45: calculado
B46: Dividendos de acciones preferentes | C46: $M | D46: 0 | E46: 0 | F46: 0
B47: Beneficio neto atribuible a ordinarias | C47: $M | D47: calculado
B48: BPA básico | C48: $/acc | D48: 9.06 | E48: 5.05 | F48: =(12377+1426)/1065 -> 12.960563
B49: BPA diluido | C49: $/acc | D49: 8.94 | E49: 5.01 | F49: =(12377+1426)/1075 -> 12.84
B50: Acciones medias básicas | C50: M acc | D50: 1116 | E50: 1096 | F50: 1065
B51: Acciones medias diluidas | C51: M acc | D51: 1130 | E51: 1105 | F51: 1075
B52: 3. BALANCE HISTÓRICO (E = 28/09/2025 auditado; F = 28/06/2026, último 10-Q disponible)
B54: Caja y equivalentes (incl. caja restringida) | C54: $M | E54: 7843 | F54: 4533
B55: Valores negociables | C55: $M | E55: 4635 | F55: 3771
B56: Clientes, neto | C56: $M | E56: 4315 | F56: 4668
B57: Inventarios y otros activos corrientes | C57: $M | E57: =6526+2435 -> 8961 | F57: =8379+1653 -> 10032
B58: Total activo corriente | C58: $M | D58: calculado
B59: Inmovilizado material (PP&E), neto | C59: $M | E59: 4690 | F59: 5217
B60: Activos por derecho de uso — leases operativos | C60: $M | E60: 735 | F60: 735
B61: Fondo de comercio | C61: $M | E61: 11358 | F61: 14274
B62: Activos por impuesto diferido | C62: $M | E62: 743 | F62: 5679
B63: Otros activos no corrientes (incl. intangibles; excl. derecho de uso) | C63: $M | E63: =6450-735+1148 -> 6863 | F63: =7683-735+1510 -> 8458
B64: Total activo no corriente | C64: $M | D64: calculado
B65: TOTAL ACTIVO | C65: $M | D65: calculado
B67: Deuda financiera corriente | C67: $M | E67: 0 | F67: 2489
B68: Proveedores | C68: $M | E68: 2791 | F68: 2897
B69: Nóminas y beneficios pendientes | C69: $M | E69: 1839 | F69: 1470
B70: Ingresos diferidos corrientes (unearned revenues) | C70: $M | E70: 358 | F70: 280
B71: Otros pasivos corrientes | C71: $M | E71: 4156 | F71: 4277
B72: Total pasivo corriente | C72: $M | D72: calculado
B73: Deuda financiera no corriente | C73: $M | E73: 14811 | F73: 12781
B74: Impuestos a pagar no corrientes | C74: $M | E74: 0 | F74: 0
B75: Pasivo por leases operativos no corriente | C75: $M | E75: 730 | F75: 730
B76: Otros pasivos no corrientes (incl. ingresos diferidos LP; excl. leases) | C76: $M | E76: =4911-730+71 -> 4252 | F76: =5434-730+81 -> 4785
B77: Total pasivo no corriente | C77: $M | D77: calculado
B78: Acciones preferentes (ninguna emitida) | C78: $M | E78: 0 | F78: 0
B79: Capital social y prima de emisión | C79: $M | E79: 0 | F79: 0
B80: Resultados acumulados (déficit) | C80: $M | E80: 20646 | F80: 27263
B81: Otro resultado global acumulado | C81: $M | E81: 560 | F81: 395
B82: Patrimonio atribuible a Qualcomm | C82: $M | D82: calculado
B83: Intereses minoritarios | C83: $M | E83: 0 | F83: 0
B88: 4. ESTADO DE FLUJOS DE CAJA HISTÓRICO (F = FY2026E: 9M real + Q4E)
B90: Depreciación (D&A reportada − amortización de intangibles) | C90: $M | D90: 1395 | E90: 1281 | F90: =1202*4/3-331 -> 1271.6667
B91: Amortización de intangibles | C91: $M | D91: calculado
B92: Impuestos diferidos (provisión vs. pagos) | C92: $M | D92: -3064 | E92: 3980 | F92: -5550
B93: Retribución basada en acciones (SBC) | C93: $M | D93: 2648 | E93: 2783 | F93: =2579+860 -> 3439
B94: Resultados de inversiones y otros, neto | C94: $M | D94: -330 | E94: -308 | F94: =-933+61-149-52 -> -1073
B95: Variación de circulante y otras partidas operativas (derivado) | C95: $M | D95: calculado
B96: FLUJO DE CAJA OPERATIVO (CFO) — reportado | C96: $M | D96: 12202 | E96: 14012 | F96: =8405+(1426+401+860) -> 11092
B98: Capex (adquisición de inmovilizado) | C98: $M | D98: -1041 | E98: -1192 | F98: =-(1578+526) -> -2104
B99: Compras de inversiones y adquisiciones | C99: $M | D99: -5323 | E99: -5437 | F99: =-(2449+1573) -> -4022
B100: Cobros por ventas y vencimientos de inversiones | C100: $M | D100: 2677 | E100: 5755 | F100: 3896
B101: Otros de inversión (derivado) | C101: $M | D101: calculado
B102: FLUJO DE CAJA DE INVERSIÓN (CFI) — reportado | C102: $M | D102: -3623 | E102: -800 | F102: =-1648-526 -> -2174
B104: Emisión de acciones ordinarias | C104: $M | D104: 383 | E104: 404 | F104: 223
B105: Recompra de acciones ordinarias | C105: $M | D105: -4121 | E105: -8791 | F105: =-(6806+1400) -> -8206
B106: Acciones retenidas por impuestos en el vesting | C106: $M | D106: -932 | E106: -1115 | F106: -888
B107: Emisión de preferentes (no aplica) | C107: $M | D107: 0 | E107: 0 | F107: 0
B108: Dividendos pagados | C108: $M | D108: -3687 | E108: -3805 | F108: =-(2868+937) -> -3805
B109: Deuda a corto plazo / papel comercial, neto | C109: $M | D109: 0 | E109: 0 | F109: =3238-2743 -> 495
B110: (no aplica) | C110: $M | D110: 0 | E110: 0 | F110: 0
B111: Emisión de deuda a largo plazo y préstamos | C111: $M | D111: 0 | E111: 1487 | F111: 0
B112: Repago de deuda | C112: $M | D112: -914 | E112: -1365 | F112: -174
B113: Otros de financiación, neto | C113: $M | D113: 2 | E113: -11 | F113: -28
B114: FLUJO DE CAJA DE FINANCIACIÓN (CFF) — calculado | C114: $M | D114: calculado
B115: CFF reportado en el 10-K | C115: $M | E115: -13196 | F115: =-10046-2337 -> -12383
B119: 5. MEMORIA: DEUDA, ARRENDAMIENTOS, OBJETIVOS Y DILUCIÓN
...

Sheet 01 Summary
A1: QUALCOMM INCORPORATED (QCOM) — RESUMEN DE VALORACIÓN DCF
A2: Valoración condicional: el resultado depende íntegramente de las hipótesis explícitas de '02 Assumptions'. No es una predicción.
B3: ⚠ PULSA Ctrl+Alt+F9 AL ABRIR ESTE LIBRO. Estas zonas se escribieron con el motor de cálculo del complemento bloqueado y mostrarán CEROS hasta que se fuerce un recálculo completo: (1) hojas 09a/09b/09c de escenarios; (2) las 25 celdas de las rejillas de '08 Sensibilidad' D6:H46; (3) en esta hoja, la tabla de escenarios F16:H24, el bloque de Múltiplos y el bloque de Precio objetivo; (4) en '13 Checks', los contadores D5:D7 y los controles 70-78. Las fórmulas están escritas y verificadas sintácticamente; lo que falta es que Excel las evalúe. TRAS EL RECÁLCULO comprueba el control 73 de '13 Checks': si está en OK, la réplica del escenario Base coincide con el DCF y los tres escenarios son fiables.
B4: IDENTIFICACIÓN | E4: CÓMO USAR ESTE LIBRO
B5: Compañía | C5: ='00 Panel del Analista'!C8 -> QUALCOMM Incorporated | E5: 1 | F5: Introducir el precio de mercado actual en C10. Es el ÚNICO dato que el libro no puede obtener por sí mismo. Hasta entonces el upside, el margen de seguridad y el Reverse DCF quedan en blanco por diseño.
B6: Ticker / mercado | C6: ='00 Panel del Analista'!C9 -> QCOM — Nasdaq | E6: 2 | F6: Actualizar y documentar los inputs de mercado del WACC en '07 WACC': tipo libre de riesgo, prima de riesgo, beta y coste marginal de la deuda. Los valores actuales son inputs del analista, NO datos verificados.
B7: Moneda y unidades | C7: ='00 Panel del Analista'!C10 -> USD millones | E7: 3 | F7: Revisar las hipótesis en '02 Assumptions'. Las celdas amarillas son las que mueven el valor. Ninguna otra hoja contiene hipótesis.
B8: Fecha de valoración | C8: ='00 Panel del Analista'!C11 -> 46288 | E8: 4 | F8: Cambiar el escenario en '09 Scenarios'!C4 (1=Bear, 2=Base, 3=Bull) y anotar los tres valores para construir el rango.
B9: Último ejercicio auditado | C9: ='00 Panel del Analista'!C12 -> FY2025A auditado (cerrado 28/09/2025); base del forecast FY2026E = 9M real + guía Q4 | E9: 5 | F9: Leer '08 Sensitivity' para ver qué variables explican el valor, y '10 Reverse DCF' para ver qué descuenta el precio.
B10: PRECIO DE MERCADO ACTUAL — INTRODUCIR AQUÍ | C10: ='00 Panel del Analista'!C13 -> 198.27 | E10: 6 | F10: Ejecutar la auditoría de '13 Checks' ANTES de usar cualquier resultado. Si algún control falla, el número no es utilizable.
E11: 7 | F11: Leer '11 Cross Check': un DCF aislado no es una conclusión. Y leer 'M4 Manual Errores' antes de defender el modelo ante otro analista.
B12: RESULTADO DE LA VALORACIÓN | E12: Si esta tabla o el bloque de Precio objetivo muestran ceros: Ctrl+Alt+F9.
B13: Escenario activo | C13: ='09 Escenarios'!C5 -> BASE | E13: LOS TRES ESCENARIOS, CALCULADOS SIMULTÁNEAMENTE
B14: Enterprise Value | C14: ='06 DCF'!F44 -> 149457.62 | E14: Ya NO es una instantánea: cada columna se calcula en su propia hoja ('09a', '09b', '09c'), independiente del interruptor de '09 Escenarios'!C4. Los deltas de cada escenario están en la matriz de '09 Escenarios' filas 9-17.
B15: (−) Deuda neta y otras reclamaciones | C15: ='06 DCF'!F53-'06 DCF'!F44 -> -6444.96 | E15: Métrica | F15: PESIMISTA | G15: BASE | H15: OPTIMISTA | I15: Unidad
B16: Equity Value | C16: ='06 DCF'!F53 -> 143012.66 | E16: Enterprise Value | F16: ='Escenario Pesimista'!$F$66 -> 95059.825 | G16: ='Escenario Base'!$F$66 -> 149457.62 | H16: ='Escenario Optimista'!$F$66 -> 216184.32 | I16: $M
B17: Acciones diluidas | C17: ='06 DCF'!F54 -> 1085.7 | E17: Equity Value | F17: ='Escenario Pesimista'!$F$70 -> 88614.865 | G17: ='Escenario Base'!$F$70 -> 143012.66 | H17: ='Escenario Optimista'!$F$70 -> 209739.36 | I17: $M
B18: VALOR INTRÍNSECO POR ACCIÓN | C18: ='06 DCF'!F55 -> 131.72392 | E18: Valor intrínseco por acción | F18: ='Escenario Pesimista'!$F$72 -> 81.620029 | G18: ='Escenario Base'!$F$72 -> 131.72392 | H18: ='Escenario Optimista'!$F$72 -> 193.18353 | I18: $/acc
B19: Upside / (Downside) sobre el precio actual | C19: =IF($C$10<=0,"◄ introducir el precio en C10",'06 DCF'!F57) -> -0.33563362 | E19: WACC | F19: ='Escenario Pesimista'!$P$52 -> 0.12540544 | G19: ='Escenario Base'!$P$52 -> 0.11540544 | H19: ='Escenario Optimista'!$P$52 -> 0.11040544 | I19: %
B20: Margen de seguridad implícito | C20: =IF($C$10<=0,"◄ introducir el precio en C10",'06 DCF'!F58) -> -0.50519356 | E20: Crecimiento terminal g | F20: ='Escenario Pesimista'!$P$53 -> 0.0225 | G20: ='Escenario Base'!$P$53 -> 0.03 | H20: ='Escenario Optimista'!$P$53 -> 0.035 | I20: %
E21: Valor terminal / EV | F21: ='Escenario Pesimista'!$F$67 -> 0.38859779 | G21: ='Escenario Base'!$F$67 -> 0.46198292 | H21: ='Escenario Optimista'!$F$67 -> 0.51577143 | I21: %
B22: RANGO DE VALORACIÓN POR ESCENARIO | E22: Múltiplo de salida implícito | F22: ='Escenario Pesimista'!$F$68 -> 6.6289132 | G22: ='Escenario Base'!$F$68 -> 8.2480732 | H22: ='Escenario Optimista'!$F$68 -> 9.4614903 | I22: x
B23: Nota | C23: Ver la instantánea de los tres escenarios en E13:I21 → | E23: Ingresos FY2036E | F23: ='Escenario Pesimista'!$F$75 -> 63665.185 | G23: ='Escenario Base'!$F$75 -> 81883.255 | H23: ='Escenario Optimista'!$F$75 -> 102631.85 | I23: $M
E24: Upside / (Downside) | F24: ='Escenario Pesimista'!$F$74 -> -0.58833898 | G24: ='Escenario Base'!$F$74 -> -0.33563362 | H24: ='Escenario Optimista'!$F$74 -> -0.025654246 | I24: %
B25: PARÁMETROS CLAVE | E25: CHECK: el escenario Base debe reproducir '06 DCF' | G25: ='Escenario Base'!$F$82 -> OK
B26: WACC | C26: ='07 WACC'!C38 -> 0.11540544 | E26: CHECK: ordenación Pesimista < Base < Optimista | G26: =IF(AND($F$18<$G$18,$G$18<$H$18),"OK","FALLO: los escenarios no están ordenados") -> OK
B27: Crecimiento terminal g | C27: ='06 DCF'!F26 -> 0.03
B28: ROIC terminal | C28: ='06 DCF'!F27 -> 0.3
B29: Margen WACC − g | C29: ='07 WACC'!C43 -> 0.085405443
B30: Valor terminal / Enterprise Value | C30: ='06 DCF'!F45 -> 0.46198292
B31: Múltiplo de salida implícito (VT / EBITDA FY2036) | C31: ='06 DCF'!F62 -> 8.2480732
B32: EV / EBITDA FY2026E implícito | C32: ='06 DCF'!F71 -> 13.903466
B33: EV / Ingresos FY2026E implícito | C33: ='06 DCF'!F72 -> 3.4840231
B35: SITUACIÓN DE PARTIDA (FY2026E = 9M REPORTADO + GUÍA Q4)
B36: Ingresos | C36: ='03 Historical'!F11 -> 42898
B37: Crecimiento de ingresos | C37: ='03 Historical'!F121 -> -0.031297986
B38: EBIT normalizado | C38: ='03 Historical'!F127 -> 9147
B39: Margen EBIT normalizado | C39: ='03 Historical'!F128 -> 0.21322672
B40: Capex | C40: ='03 Historical'!F129 -> 2104
B41: Capex / Ingresos | C41: ='03 Historical'!F130 -> 0.049046576
B42: Flujo de caja operativo | C42: ='03 Historical'!F85 -> 11092
B43: FCF simple (CFO − Capex) | C43: ='03 Historical'!F132 -> 8988
B44: Deuda neta | C44: ='03 Historical'!F137 -> 6966
B45: Deuda neta / EBITDA | C45: ='03 Historical'!F138 -> 0.64802009
B46: Objetivo no-handset FY2029 (dirección) | C46: ='03 Historical'!F117 -> 40000
B48: CONTROLES CRÍTICOS
B49: Cuadre del balance histórico | C49: =IF('03 Historical'!F75=0,"OK","FALLO") -> OK
B50: WACC > g | C50: ='06 DCF'!F67 -> OK
B51: El FCFF llega a ser positivo | C51: ='06 DCF'!F75 -> OK
B52: Peso del valor terminal | C52: ='06 DCF'!F70 -> OK
B53: Múltiplo de salida implícito razonable | C53: ='06 DCF'!F69 -> OK
B54: Auditoría completa | C54: ="Ver hoja '13 Checks'" -> Ver hoja '13 Checks'
B56: Valoración por múltiplos
B57: AVISO: los múltiplos de la columna E son INPUTS DEL ANALISTA, no múltiplos de comparables observados. No se han obtenido datos de compañías comparables, por lo que estos múltiplos son marcadores de posición razonables que deben sustituirse por los de un conjunto de peers seleccionado con criterio (modelo de negocio, geografía, crecimiento, márgenes, intensidad de capital, riesgo y tamaño). Un múltiplo inventado no es valoración relativa.
B58: Método | C58: Métrica | D58: Valor de la métrica | E58: Múltiplo (input) | F58: EV implícito | G58: Equity implícito | H58: Valor por acción
B59: EV / Ingresos FY2027E | C59: Ingresos FY2027E | D59: ='04 Operating Model'!G11 -> 44928.06 | E59: ='00 Panel del Analista'!D233 -> 5 | F59: =D59*E59 -> 224640.3 | G59: =F59+SUM('06 DCF'!$F$46:$F$52) -> 218195.34 | H59: =G59/'02 Assumptions'!$C$69 -> 200.97204
B60: EV / EBITDA FY2027E | C60: EBITDA FY2027E | D60: ='04 Operating Model'!G39 -> 11492.787 | E60: ='00 Panel del Analista'!D234 -> 16 | F60: =D60*E60 -> 183884.59 | G60: =F60+SUM('06 DCF'!$F$46:$F$52) -> 177439.63 | H60: =G60/'02 Assumptions'!$C$69 -> 163.43339
B61: EV / EBITDA FY2029E | C61: EBITDA FY2029E | D61: ='04 Operating Model'!I39 -> 16261.08 | E61: ='00 Panel del Analista'!D235 -> 13 | F61: =D61*E61 -> 211394.04 | G61: =F61+SUM('06 DCF'!$F$46:$F$52) -> 204949.08 | H61: =G61/'02 Assumptions'!$C$69 -> 188.77138
B62: EV / EBIT normalizado FY2029E | C62: EBIT norm. FY2029E | D62: ='04 Operating Model'!I29 -> 14380.41 | E62: ='00 Panel del Analista'!D236 -> 16 | F62: =D62*E62 -> 230086.57 | G62: =F62+SUM('06 DCF'!$F$46:$F$52) -> 223641.61 | H62: =G62/'02 Assumptions'!$C$69 -> 205.9884
B63: EV / FCFF FY2031E | C63: FCFF FY2031E | D63: ='06 DCF'!K15 -> 14207.977 | E63: ='00 Panel del Analista'!D237 -> 20 | F63: =D63*E63 -> 284159.53 | G63: =F63+SUM('06 DCF'!$F$46:$F$52) -> 277714.57 | H63: =G63/'02 Assumptions'!$C$69 -> 255.7931
B64: P / E FY2029E (valora el equity directamente, sin puente) | C64: Beneficio neto FY2029E | D64: ='05 Three Statement'!I16 -> 11813.998 | E64: ='00 Panel del Analista'!D238 -> 18 | F64: no aplica | G64: =D64*E64 -> 212651.97 | H64: =G64/'02 Assumptions'!$C$69 -> 195.86623
B66: Media de los métodos de múltiplos | H66: =AVERAGE(H59:H64) -> 201.80409
B67: MEDIANA de los métodos de múltiplos | H67: =MEDIAN(H59:H64) -> 198.41913
B68: Rango de los métodos (mínimo – máximo) | G68: =MIN(H59:H64) -> 163.43339 | H68: =MAX(H59:H64) -> 255.7931
B69: Para comparar: valor por acción del DCF (escenario Base) | H69: ='06 DCF'!$F$55 -> 131.72392
B71: Precio objetivo
B72: Precio objetivo ponderado por método. Los PESOS de la columna D son inputs del analista y deben sumar el 100%. La ponderación no reduce la incertidumbre: sólo hace explícito cuánta confianza se otorga a cada método. Si el rango entre métodos es amplio, el precio objetivo es una media de cosas que no coinciden, y eso es información en sí mismo.
B73: Método | C73: Valor por acción | D73: Peso (input) | E73: Contribución
B74: DCF — escenario Pesimista (Bear) | C74: ='Escenario Pesimista'!$F$72 -> 81.620029 | D74: ='00 Panel del Analista'!D241 -> 0.2 | E74: =C74*D74 -> 16.324006
B75: DCF — escenario Base | C75: ='Escenario Base'!$F$72 -> 131.72392 | D75: ='00 Panel del Analista'!D242 -> 0.45 | E75: =C75*D75 -> 59.275765
B76: DCF — escenario Optimista (Bull) | C76: ='Escenario Optimista'!$F$72 -> 193.18353 | D76: ='00 Panel del Analista'!D243 -> 0.15 | E76: =C76*D76 -> 28.97753
B77: Valoración por múltiplos (mediana) | C77: =$H$67 -> 198.41913 | D77: ='00 Panel del Analista'!D244 -> 0.1 | E77: =C77*D77 -> 19.841913
B78: Sum-of-the-Parts | C78: ='12 SOTP'!$G$25 -> 205.3298 | D78: ='00 Panel del Analista'!D245 -> 0.1 | E78: =C78*D78 -> 20.53298
B79: Suma de los pesos | D79: =SUM(D74:D78) -> 1 | E79: =IF(ABS(D79-1)<0.0001,"OK","FALLO: los pesos deben sumar 100%") -> OK
B80: PRECIO OBJETIVO PONDERADO | C80: =IF(ABS($D$79-1)>0.0001,"corregir los pesos",SUMPRODUCT(C74:C78,D74:D78)) -> 144.95219
B81: Precio de mercado actual | C81: =$C$10 -> 198.27
B82: Upside / (Downside) al precio objetivo | C82: =IF(OR($C$10<=0,NOT(ISNUMBER($C$80))),"introducir precio",$C$80/$C$10-1) -> -0.26891514
B83: Margen de seguridad sobre el precio objetivo | C83: =IF(OR($C$10<=0,NOT(ISNUMBER($C$80))),"introducir precio",1-$C$10/$C$80) -> -0.36783028
B84: Rango entre el método más bajo y el más alto | C84: =MIN(C74:C78) -> 81.620029 | D84: =MAX(C74:C78) -> 205.3298
B85: Dispersión entre métodos (máx / mín) | C85: =IFERROR(D84/C84,"n/a") -> 2.5156791
B86: CHECK: dispersión entre métodos | C86: =IF(NOT(ISNUMBER($C$85)),"n/a",IF($C$85>2.5,"AVISO: los métodos discrepan más de 2,5 veces. El precio objetivo ponderado promedia resultados incompatibles: presentar el RANGO, no el punto.","OK")) -> AVISO: los métodos discrepan más de 2,5 veces. El precio objetivo ponderado promedia resultados incompatibles: presentar el RANGO, no el punto.

Sheet 02 Assumptions
A1: HIPÓTESIS CENTRALIZADAS — QUALCOMM INCORPORATED (QCOM)
A2: AZUL = input del analista. NEGRO = fórmula. VERDE = enlace a otra hoja. GRIS = dato histórico reportado. AMARILLO = hipótesis crítica. Ninguna otra hoja debe contener hipótesis: todas viven aquí.
B4: Hipótesis | C4: Unidad | D4: ='00 Panel del Analista'!D14 -> FY2024A | E4: ='00 Panel del Analista'!E14 -> FY2025A | F4: ='00 Panel del Analista'!F14 -> FY2026E | G4: ='00 Panel del Analista'!G14 -> FY2027E | H4: ='00 Panel del Analista'!H14 -> FY2028E | I4: ='00 Panel del Analista'!I14 -> FY2029E | J4: ='00 Panel del Analista'!J14 -> FY2030E | K4: ='00 Panel del Analista'!K14 -> FY2031E | ... P4: ='00 Panel del Analista'!P14 -> FY2036E | Q4: Peso del delta de escenario
B6: PANEL DE CONTROL
B7: Escenario activo (1=Bear, 2=Base, 3=Bull) | C7: ='09 Escenarios'!C4 -> 2
B8: Nombre del escenario activo | C8: ='09 Escenarios'!C5 -> BASE
B9: Fecha de valoración | C9: ='00 Panel del Analista'!C11 -> 46288
B10: Moneda y unidades | C10: ='00 Panel del Analista'!C10 -> USD millones
B11: Años de forecast explícito | C11: ='00 Panel del Analista'!D186 -> 10
B12: Convención de descuento (1=fin de año, 2=mitad de año) | C12: ='00 Panel del Analista'!D187 -> 2
B13: Método de valor terminal (1=Gordon, 2=Múltiplo de salida) | C13: ='00 Panel del Analista'!D188 -> 1
B14: Tratamiento de leases operativos | C14: OPERATIVO — coste en EBIT, pasivo fuera de la deuda neta
B15: Tratamiento del SBC | C15: GASTO REAL — no se readiciona, no se aplica dilución adicional
B16: Año base del forecast | C16: ='00 Panel del Analista'!C12 -> FY2025A auditado (cerrado 28/09/2025); base del forecast FY2026E = 9M real + guía Q4
B18: INGRESOS — CRECIMIENTO POR SEGMENTO (driver: salida de Apple en Handsets, rampa de Data Center y diversificación en Auto/IoT)
B19: IoT + Data Center — crecimiento (vector Base) | C19: % | G19: ='00 Panel del Analista'!G165 -> 0.6 | H19: ='00 Panel del Analista'!H165 -> 0.33 | I19: ='00 Panel del Analista'!I165 -> 0.22 | J19: ='00 Panel del Analista'!J165 -> 0.15 | K19: ='00 Panel del Analista'!K165 -> 0.12 | L19: ='00 Panel del Analista'!L165 -> 0.1 | M19: ='00 Panel del Analista'!M165 -> 0.08 | N19: ='00 Panel del Analista'!N165 -> 0.06 | ... P19: ='00 Panel del Analista'!P165 -> 0.04
B20: IoT + Data Center — crecimiento ACTIVO (Base × multiplicador de escenario) | C20: % | G20: =G19*'09 Escenarios'!$G$9+$C$104 -> 0.6 | H20: =H19*'09 Escenarios'!$G$9+$C$104 -> 0.33 | I20: =I19*'09 Escenarios'!$G$9+$C$104 -> 0.22 | J20: =J19*'09 Escenarios'!$G$9+$C$104 -> 0.15 | K20: =K19*'09 Escenarios'!$G$9+$C$104 -> 0.12 | L20: =L19*'09 Escenarios'!$G$9+$C$104 -> 0.1 | M20: =M19*'09 Escenarios'!$G$9+$C$104 -> 0.08 | N20: =N19*'09 Escenarios'!$G$9+$C$104 -> 0.06 | ... P20: =P19*'09 Escenarios'!$G$9+$C$104 -> 0.04
B21: QCT Handsets — crecimiento (vector Base) | C21: % | G21: ='00 Panel del Analista'!G166 -> -0.15 | H21: ='00 Panel del Analista'!H166 -> 0.02 | I21: ='00 Panel del Analista'!I166 -> 0.03 | J21: ='00 Panel del Analista'!J166 -> 0.02 | K21: ='00 Panel del Analista'!K166 -> 0.02 | L21: ='00 Panel del Analista'!L166 -> 0.02 | M21: ='00 Panel del Analista'!M166 -> 0.02 | N21: ='00 Panel del Analista'!N166 -> 0.02 | ... P21: ='00 Panel del Analista'!P166 -> 0.025
B22: QCT Handsets — crecimiento ACTIVO | C22: % | G22: =G21+'09 Escenarios'!$G$10+$C$104 -> -0.15 | H22: =H21+'09 Escenarios'!$G$10+$C$104 -> 0.02 | I22: =I21+'09 Escenarios'!$G$10+$C$104 -> 0.03 | J22: =J21+'09 Escenarios'!$G$10+$C$104 -> 0.02 | K22: =K21+'09 Escenarios'!$G$10+$C$104 -> 0.02 | L22: =L21+'09 Escenarios'!$G$10+$C$104 -> 0.02 | M22: =M21+'09 Escenarios'!$G$10+$C$104 -> 0.02 | N22: =N21+'09 Escenarios'!$G$10+$C$104 -> 0.02 | ... P22: =P21+'09 Escenarios'!$G$10+$C$104 -> 0.025
B23: QTL Licencias — crecimiento (vector Base) | C23: % | G23: ='00 Panel del Analista'!G167 -> -0.02 | H23: ='00 Panel del Analista'!H167 -> -0.02 | I23: ='00 Panel del Analista'!I167 -> 0 | J23: ='00 Panel del Analista'!J167 -> 0.01 | K23: ='00 Panel del Analista'!K167 -> 0.01 | L23: ='00 Panel del Analista'!L167 -> 0.01 | M23: ='00 Panel del Analista'!M167 -> 0.015 | N23: ='00 Panel del Analista'!N167 -> 0.015 | ... P23: ='00 Panel del Analista'!P167 -> 0.02
B24: QTL Licencias — crecimiento ACTIVO | C24: % | G24: =G23+'09 Escenarios'!$G$10+$C$104 -> -0.02 | H24: =H23+'09 Escenarios'!$G$10+$C$104 -> -0.02 | I24: =I23+'09 Escenarios'!$G$10+$C$104 -> 0 | J24: =J23+'09 Escenarios'!$G$10+$C$104 -> 0.01 | K24: =K23+'09 Escenarios'!$G$10+$C$104 -> 0.01 | L24: =L23+'09 Escenarios'!$G$10+$C$104 -> 0.01 | M24: =M23+'09 Escenarios'!$G$10+$C$104 -> 0.015 | N24: =N23+'09 Escenarios'!$G$10+$C$104 -> 0.015 | ... P24: =P23+'09 Escenarios'!$G$10+$C$104 -> 0.02
B25: QCT Automoción — crecimiento (vector Base) | C25: % | G25: ='00 Panel del Analista'!G168 -> 0.22 | H25: ='00 Panel del Analista'!H168 -> 0.17 | I25: ='00 Panel del Analista'!I168 -> 0.15 | J25: ='00 Panel del Analista'!J168 -> 0.13 | K25: ='00 Panel del Analista'!K168 -> 0.11 | L25: ='00 Panel del Analista'!L168 -> 0.09 | M25: ='00 Panel del Analista'!M168 -> 0.08 | N25: ='00 Panel del Analista'!N168 -> 0.07 | ... P25: ='00 Panel del Analista'!P168 -> 0.05
B26: QCT Automoción — crecimiento ACTIVO | C26: % | G26: =G25+'09 Escenarios'!$G$10+$C$104 -> 0.22 | H26: =H25+'09 Escenarios'!$G$10+$C$104 -> 0.17 | I26: =I25+'09 Escenarios'!$G$10+$C$104 -> 0.15 | J26: =J25+'09 Escenarios'!$G$10+$C$104 -> 0.13 | K26: =K25+'09 Escenarios'!$G$10+$C$104 -> 0.11 | L26: =L25+'09 Escenarios'!$G$10+$C$104 -> 0.09 | M26: =M25+'09 Escenarios'!$G$10+$C$104 -> 0.08 | N26: =N25+'09 Escenarios'!$G$10+$C$104 -> 0.07 | ... P26: =P25+'09 Escenarios'!$G$10+$C$104 -> 0.05
B28: MÁRGENES Y ESTRUCTURA DE COSTES
B29: Gross Margin (vector Base) | C29: % | G29: ='00 Panel del Analista'!G169 -> 0.545 | H29: ='00 Panel del Analista'!H169 -> 0.55 | I29: ='00 Panel del Analista'!I169 -> 0.555 | J29: ='00 Panel del Analista'!J169 -> 0.555 | K29: ='00 Panel del Analista'!K169 -> 0.555 | L29: ='00 Panel del Analista'!L169 -> 0.555 | M29: ='00 Panel del Analista'!M169 -> 0.555 | N29: ='00 Panel del Analista'!N169 -> 0.555 | ... P29: ='00 Panel del Analista'!P169 -> 0.555
B30: Gross Margin ACTIVO | C30: % | G30: =G29+'09 Escenarios'!$G$11 -> 0.545 | H30: =H29+'09 Escenarios'!$G$11 -> 0.55 | I30: =I29+'09 Escenarios'!$G$11 -> 0.555 | J30: =J29+'09 Escenarios'!$G$11 -> 0.555 | K30: =K29+'09 Escenarios'!$G$11 -> 0.555 | L30: =L29+'09 Escenarios'!$G$11 -> 0.555 | M30: =M29+'09 Escenarios'!$G$11 -> 0.555 | N30: =N29+'09 Escenarios'!$G$11 -> 0.555 | ... P30: =P29+'09 Escenarios'!$G$11 -> 0.555
B31: SG&A / Ingresos (Base) | C31: % | G31: ='00 Panel del Analista'!G170 -> 0.085 | H31: ='00 Panel del Analista'!H170 -> 0.08 | I31: ='00 Panel del Analista'!I170 -> 0.077 | J31: ='00 Panel del Analista'!J170 -> 0.075 | K31: ='00 Panel del Analista'!K170 -> 0.073 | L31: ='00 Panel del Analista'!L170 -> 0.072 | M31: ='00 Panel del Analista'!M170 -> 0.071 | N31: ='00 Panel del Analista'!N170 -> 0.071 | ... P31: ='00 Panel del Analista'!P170 -> 0.071
B32: SG&A / Ingresos ACTIVO | C32: % | G32: =G31+'09 Escenarios'!$G$12*$Q$32 -> 0.085 | H32: =H31+'09 Escenarios'!$G$12*$Q$32 -> 0.08 | I32: =I31+'09 Escenarios'!$G$12*$Q$32 -> 0.077 | J32: =J31+'09 Escenarios'!$G$12*$Q$32 -> 0.075 | K32: =K31+'09 Escenarios'!$G$12*$Q$32 -> 0.073 | L32: =L31+'09 Escenarios'!$G$12*$Q$32 -> 0.072 | M32: =M31+'09 Escenarios'!$G$12*$Q$32 -> 0.071 | N32: =N31+'09 Escenarios'!$G$12*$Q$32 -> 0.071 | ... P32: =P31+'09 Escenarios'!$G$12*$Q$32 -> 0.071 | Q32: ='00 Panel del Analista'!D202 -> 0.4
B33: I+D / Ingresos (Base) | C33: % | G33: ='00 Panel del Analista'!G171 -> 0.235 | H33: ='00 Panel del Analista'!H171 -> 0.225 | I33: ='00 Panel del Analista'!I171 -> 0.215 | J33: ='00 Panel del Analista'!J171 -> 0.21 | K33: ='00 Panel del Analista'!K171 -> 0.207 | L33: ='00 Panel del Analista'!L171 -> 0.205 | M33: ='00 Panel del Analista'!M171 -> 0.205 | N33: ='00 Panel del Analista'!N171 -> 0.205 | ... P33: ='00 Panel del Analista'!P171 -> 0.205
B34: I+D / Ingresos ACTIVO | C34: % | G34: =G33+'09 Escenarios'!$G$12*$Q$34 -> 0.235 | H34: =H33+'09 Escenarios'!$G$12*$Q$34 -> 0.225 | I34: =I33+'09 Escenarios'!$G$12*$Q$34 -> 0.215 | J34: =J33+'09 Escenarios'!$G$12*$Q$34 -> 0.21 | K34: =K33+'09 Escenarios'!$G$12*$Q$34 -> 0.207 | L34: =L33+'09 Escenarios'!$G$12*$Q$34 -> 0.205 | M34: =M33+'09 Escenarios'!$G$12*$Q$34 -> 0.205 | N34: =N33+'09 Escenarios'!$G$12*$Q$34 -> 0.205 | ... P34: =P33+'09 Escenarios'!$G$12*$Q$34 -> 0.205 | Q34: ='00 Panel del Analista'!D203 -> 0.6
B35: G&A / Ingresos (Base) — incluido en SG&A | C35: % | G35: ='00 Panel del Analista'!G172 -> 0 | H35: ='00 Panel del Analista'!H172 -> 0 | I35: ='00 Panel del Analista'!I172 -> 0 | J35: ='00 Panel del Analista'!J172 -> 0 | K35: ='00 Panel del Analista'!K172 -> 0 | L35: ='00 Panel del Analista'!L172 -> 0 | M35: ='00 Panel del Analista'!M172 -> 0 | N35: ='00 Panel del Analista'!N172 -> 0 | ... P35: ='00 Panel del Analista'!P172 -> 0
B36: G&A / Ingresos ACTIVO — incluido en SG&A | C36: % | G36: =G35+'09 Escenarios'!$G$12*$Q$36 -> 0 | H36: =H35+'09 Escenarios'!$G$12*$Q$36 -> 0 | I36: =I35+'09 Escenarios'!$G$12*$Q$36 -> 0 | J36: =J35+'09 Escenarios'!$G$12*$Q$36 -> 0 | K36: =K35+'09 Escenarios'!$G$12*$Q$36 -> 0 | L36: =L35+'09 Escenarios'!$G$12*$Q$36 -> 0 | M36: =M35+'09 Escenarios'!$G$12*$Q$36 -> 0 | N36: =N35+'09 Escenarios'!$G$12*$Q$36 -> 0 | ... P36: =P35+'09 Escenarios'!$G$12*$Q$36 -> 0 | Q36: ='00 Panel del Analista'!D204 -> 0
B37: Amortización de intangibles adquiridos (calendario) | C37: $M | G37: ='00 Panel del Analista'!G173 -> 430 | H37: ='00 Panel del Analista'!H173 -> 350 | I37: ='00 Panel del Analista'!I173 -> 280 | J37: ='00 Panel del Analista'!J173 -> 210 | K37: ='00 Panel del Analista'!K173 -> 140 | L37: ='00 Panel del Analista'!L173 -> 100 | M37: ='00 Panel del Analista'!M173 -> 0 | N37: ='00 Panel del Analista'!N173 -> 0 | ... P37: ='00 Panel del Analista'!P173 -> 0
B38: Otros gastos operativos normalizados (reestructuración, deterioros) | C38: $M | G38: ='00 Panel del Analista'!G174 -> 100 | H38: ='00 Panel del Analista'!H174 -> 100 | I38: ='00 Panel del Analista'!I174 -> 100 | J38: ='00 Panel del Analista'!J174 -> 100 | K38: ='00 Panel del Analista'!K174 -> 100 | L38: ='00 Panel del Analista'!L174 -> 100 | M38: ='00 Panel del Analista'!M174 -> 100 | N38: ='00 Panel del Analista'!N174 -> 100 | ... P38: ='00 Panel del Analista'!P174 -> 100
B40: CAPEX Y DEPRECIACIÓN
B41: Capex / Ingresos (vector Base) | C41: % | G41: ='00 Panel del Analista'!G175 -> 0.045 | H41: ='00 Panel del Analista'!H175 -> 0.038 | I41: ='00 Panel del Analista'!I175 -> 0.034 | J41: ='00 Panel del Analista'!J175 -> 0.03 | K41: ='00 Panel del Analista'!K175 -> 0.03 | L41: ='00 Panel del Analista'!L175 -> 0.03 | M41: ='00 Panel del Analista'!M175 -> 0.03 | N41: ='00 Panel del Analista'!N175 -> 0.03 | ... P41: ='00 Panel del Analista'!P175 -> 0.03
B42: Capex / Ingresos ACTIVO | C42: % | G42: =G41*'09 Escenarios'!$G$13 -> 0.045 | H42: =H41*'09 Escenarios'!$G$13 -> 0.038 | I42: =I41*'09 Escenarios'!$G$13 -> 0.034 | J42: =J41*'09 Escenarios'!$G$13 -> 0.03 | K42: =K41*'09 Escenarios'!$G$13 -> 0.03 | L42: =L41*'09 Escenarios'!$G$13 -> 0.03 | M42: =M41*'09 Escenarios'!$G$13 -> 0.03 | N42: =N41*'09 Escenarios'!$G$13 -> 0.03 | ... P42: =P41*'09 Escenarios'!$G$13 -> 0.03
B43: Vida útil media del PP&E | C43: ='00 Panel del Analista'!D189 -> 4.5
B44: Vida útil implícita en FY2026 (check de calibración) | C44: años | F44: =('03 Historical'!E48+'03 Historical'!F129/2)/'03 Historical'!F79 -> 4.5153342
B46: CIRCULANTE OPERATIVO (drivers, no % de ingresos genérico)
B47: DSO — días de cobro (Base) | C47: días | G47: ='00 Panel del Analista'!G176 -> 38 | H47: ='00 Panel del Analista'!H176 -> 38 | I47: ='00 Panel del Analista'!I176 -> 38 | J47: ='00 Panel del Analista'!J176 -> 38 | K47: ='00 Panel del Analista'!K176 -> 38 | L47: ='00 Panel del Analista'!L176 -> 38 | M47: ='00 Panel del Analista'!M176 -> 38 | N47: ='00 Panel del Analista'!N176 -> 38 | ... P47: ='00 Panel del Analista'!P176 -> 38
B48: DSO ACTIVO | C48: días | G48: =G47+'09 Escenarios'!$G$14 -> 38 | H48: =H47+'09 Escenarios'!$G$14 -> 38 | I48: =I47+'09 Escenarios'!$G$14 -> 38 | J48: =J47+'09 Escenarios'!$G$14 -> 38 | K48: =K47+'09 Escenarios'!$G$14 -> 38 | L48: =L47+'09 Escenarios'!$G$14 -> 38 | M48: =M47+'09 Escenarios'!$G$14 -> 38 | N48: =N47+'09 Escenarios'!$G$14 -> 38 | ... P48: =P47+'09 Escenarios'!$G$14 -> 38
B49: Proveedores / (coste de ingresos + capex) | C49: % | G49: ='00 Panel del Analista'!G177 -> 0.134 | H49: ='00 Panel del Analista'!H177 -> 0.134 | I49: ='00 Panel del Analista'!I177 -> 0.134 | J49: ='00 Panel del Analista'!J177 -> 0.134 | K49: ='00 Panel del Analista'!K177 -> 0.134 | L49: ='00 Panel del Analista'!L177 -> 0.134 | M49: ='00 Panel del Analista'!M177 -> 0.134 | N49: ='00 Panel del Analista'!N177 -> 0.134 | ... P49: ='00 Panel del Analista'!P177 -> 0.134
B50: Ingresos diferidos corrientes / Ingresos | C50: % | G50: ='00 Panel del Analista'!G178 -> 0.007 | H50: ='00 Panel del Analista'!H178 -> 0.007 | I50: ='00 Panel del Analista'!I178 -> 0.007 | J50: ='00 Panel del Analista'!J178 -> 0.007 | K50: ='00 Panel del Analista'!K178 -> 0.007 | L50: ='00 Panel del Analista'!L178 -> 0.007 | M50: ='00 Panel del Analista'!M178 -> 0.007 | N50: ='00 Panel del Analista'!N178 -> 0.007 | ... P50: ='00 Panel del Analista'!P178 -> 0.007
B51: Inventarios y otros activos corrientes / Ingresos | C51: % | G51: ='00 Panel del Analista'!G179 -> 0.21 | H51: ='00 Panel del Analista'!H179 -> 0.2 | I51: ='00 Panel del Analista'!I179 -> 0.2 | J51: ='00 Panel del Analista'!J179 -> 0.2 | K51: ='00 Panel del Analista'!K179 -> 0.2 | L51: ='00 Panel del Analista'!L179 -> 0.2 | M51: ='00 Panel del Analista'!M179 -> 0.2 | N51: ='00 Panel del Analista'!N179 -> 0.2 | ... P51: ='00 Panel del Analista'!P179 -> 0.2
B52: Nóminas y beneficios pendientes / Ingresos | C52: % | G52: ='00 Panel del Analista'!G180 -> 0.038 | H52: ='00 Panel del Analista'!H180 -> 0.038 | I52: ='00 Panel del Analista'!I180 -> 0.038 | J52: ='00 Panel del Analista'!J180 -> 0.038 | K52: ='00 Panel del Analista'!K180 -> 0.038 | L52: ='00 Panel del Analista'!L180 -> 0.038 | M52: ='00 Panel del Analista'!M180 -> 0.038 | N52: ='00 Panel del Analista'!N180 -> 0.038 | ... P52: ='00 Panel del Analista'!P180 -> 0.038
B53: Otros pasivos corrientes operativos / Ingresos | C53: % | G53: ='00 Panel del Analista'!G181 -> 0.097 | H53: ='00 Panel del Analista'!H181 -> 0.097 | I53: ='00 Panel del Analista'!I181 -> 0.097 | J53: ='00 Panel del Analista'!J181 -> 0.097 | K53: ='00 Panel del Analista'!K181 -> 0.097 | L53: ='00 Panel del Analista'!L181 -> 0.097 | M53: ='00 Panel del Analista'!M181 -> 0.097 | N53: ='00 Panel del Analista'!N181 -> 0.097 | ... P53: ='00 Panel del Analista'!P181 -> 0.097
B55: IMPUESTOS
B56: Tipo impositivo de caja (vector Base) | C56: % | G56: ='00 Panel del Analista'!G182 -> 0.14 | H56: ='00 Panel del Analista'!H182 -> 0.145 | I56: ='00 Panel del Analista'!I182 -> 0.15 | J56: ='00 Panel del Analista'!J182 -> 0.155 | K56: ='00 Panel del Analista'!K182 -> 0.16 | L56: ='00 Panel del Analista'!L182 -> 0.165 | M56: ='00 Panel del Analista'!M182 -> 0.17 | N56: ='00 Panel del Analista'!N182 -> 0.17 | ... P56: ='00 Panel del Analista'!P182 -> 0.17
B57: Tipo impositivo de caja ACTIVO | C57: % | G57: =G56+'09 Escenarios'!$G$15 -> 0.14 | H57: =H56+'09 Escenarios'!$G$15 -> 0.145 | I57: =I56+'09 Escenarios'!$G$15 -> 0.15 | J57: =J56+'09 Escenarios'!$G$15 -> 0.155 | K57: =K56+'09 Escenarios'!$G$15 -> 0.16 | L57: =L56+'09 Escenarios'!$G$15 -> 0.165 | M57: =M56+'09 Escenarios'!$G$15 -> 0.17 | N57: =N56+'09 Escenarios'!$G$15 -> 0.17 | ... P57: =P56+'09 Escenarios'!$G$15 -> 0.17
B58: Tipo marginal para el WACC | C58: ='00 Panel del Analista'!D190 -> 0.21
B59: Tipo efectivo non-GAAP FY2026 (guía 13%; referencia, NO usado) | C59: % | F59: ='00 Panel del Analista'!F136 -> 0.13
B61: VALOR TERMINAL
B62: Crecimiento terminal g (Base) | C62: ='00 Panel del Analista'!D191 -> 0.03
B63: Crecimiento terminal g ACTIVO | C63: =C62+'09 Escenarios'!$G$16 -> 0.03
B64: Múltiplo de salida EV/EBITDA (método alternativo) | C64: ='00 Panel del Analista'!D192 -> 14
B65: Tope de referencia: PIB nominal a largo plazo EEUU | C65: ='00 Panel del Analista'!D193 -> 0.04
B66: ROIC terminal (disciplina la reinversión terminal: reinv. = g / ROIC) | C66: ='00 Panel del Analista'!D194 -> 0.3
B67: CAJA, ACCIONES Y PUENTE A EQUITY (a la fecha de valoración)
B68: Caja mínima operativa / Ingresos | C68: ='00 Panel del Analista'!D195 -> 0.02
B69: Acciones diluidas = en circulación a 28/06/2026 + equivalentes dilutivos + warrant Amazon consolidado (autocartera) + acciones emitidas por Modular | C69: ='03 Historical'!F118+('03 Historical'!F40-'03 Historical'!F39)+'00 Panel del Analista'!F137+'00 Panel del Analista'!F138 -> 1085.7
B70: Deuda financiera total | C70: ='03 Historical'!F110 -> 15270
B71: Pasivo por leases financieros (debt-like) | C71: ='03 Historical'!F112 -> 0
B72: Caja y equivalentes | C72: ='03 Historical'!F43 -> 4533
B73: Valores negociables | C73: ='03 Historical'!F44 -> 3771
B74: Intereses minoritarios | C74: ='03 Historical'!F72 -> 0
B75: Preferentes convertibles obligatorias | C75: ='03 Historical'!F67 -> 0
B76: Pasivo por leases operativos (NO en el puente, ver C14) | C76: ='03 Historical'!F113 -> 832
B77: Inversiones estratégicas QSI no cotizadas + participadas (activo no operativo; solo en el puente) | C77: ='00 Panel del Analista'!F135 -> 1379
B79: JUSTIFICACIÓN DE LAS HIPÓTESIS CRÍTICAS (toda hipótesis sin mecanismo económico explicado es una hipótesis indefendible)
B80: Hipótesis | C80: Mecanismo económico y riesgo
B81: Crecimiento IoT + Data Center 60% → 4% | C81: No es una extrapolación del histórico. FY2027 recoge el arranque de los dos contratos de silicio a medida en Data Center (ingresos desde el trimestre de diciembre) y la guía de la dirección de crecimiento no-handset >60%. Se aplica un descuento deliberado frente al plan del Investor Day (Data Center 15.000+ e IoT 14.000+ en FY2029): el Base sitúa este segmento en ~19.500 en FY2029. El riesgo de ejecución (HBC, CPU Dragonfly en 2S 2028, concentración en pocos hiperescaladores) se recoge en el multiplicador de escenario (0,7x / 1,25x). CHECK en '13 Checks' #51: no-handset FY2029 frente al objetivo de 40.000.
B82: Handsets −15% en FY2027 y +2–2,5% después | C82: La caída de FY2027 es la salida de Apple: la dirección espera una cuota materialmente inferior al 20% desde el Q4 FY26 y que el crecimiento no-handset de FY2027 sustituya todos los ingresos de producto de Apple de FY2026. Después, Android crece ~5% anual según la dirección (FY26–29); el Base usa 2–3% por madurez del mercado de smartphones y presión del coste de memoria sobre la gama media.
B83: Margen bruto del 54,4% al 55,5% | C83: FY2026E está deprimido por la inflación de costes de memoria, obleas y empaquetado. La dirección está subiendo precios y espera volver a su modelo operativo. El Base recupera solo hasta el 55,5%, por debajo del 56–57% de FY2024–25, porque el silicio a medida para Data Center suele tener menor margen bruto y QTL (margen ~70%) pierde peso en el mix.
B84: Apalancamiento operativo en I+D y SG&A | C84: La I+D cae del 23,6% al 20,5% de los ingresos y SG&A del 8,7% al 7,1%. La inversión en Data Center (Alphawave, Modular, CPU y aceleradores) se hace antes de la rampa de ingresos; al escalar ingresos, los gastos crecen menos. El margen EBIT normalizado terminal (~28%) queda en el máximo histórico (FY2025), no por encima.
B85: Amortización de intangibles 430 → 0 | C85: Los intangibles netos a 28/06/2026 son 1.510 (incluye Alphawave y Modular). El calendario los agota en seis años; el 10-K prevé 331/241/200/155/118 para FY26–30 antes de las últimas compras. Mantenerla a perpetuidad sobreestimaría el gasto.
B86: Capex del 4,5% al 3,0% de los ingresos | C86: Qualcomm es fabless: el capex histórico es del 2,7% de los ingresos. FY2026E (4,9%) y FY2027E incluyen inversión en Data Center (laboratorios, centros de validación y máscaras). Se normaliza al 3%. NO se ha asumido Capex = D&A: en el terminal el ratio sale de la mecánica de PP&E.
B87: Vida útil del PP&E de 4,5 años | C87: Calibrada contra FY2026E: la vida implícita de la depreciación reportada es de ~4,5 años (celda F44). El PP&E de Qualcomm son sobre todo equipos de prueba, laboratorio e informática, de vida corta.
B88: Tipo de caja del 14% al 17% | C88: NO se usa el tipo GAAP de FY2026 (negativo por la liberación de 5.700 de provisión de valoración) ni el 56% de FY2025 (cargo no recurrente). La guía non-GAAP es del 13% (FDDEI, créditos de I+D, mix internacional). Se converge al 17% por el endurecimiento del FDDEI (OBBB) y el pilar 2 de la OCDE. Usar el 13% a perpetuidad sobreestimaría el valor.
B89: Crecimiento terminal del 3,0% | C89: ~1% de crecimiento real a largo plazo más ~2% de inflación. Tope de referencia del 4% (PIB nominal de EE. UU.) en C65. CHECK obligatorio: g < WACC.
B90: Leases operativos como operativos | C90: Bajo ASC 842 el coste del lease operativo (184 anuales) ya está dentro del EBIT. El pasivo de 832 NO se suma a la deuda neta: sería doble contabilización. Es inmaterial para Qualcomm.
B91: SBC como gasto real sin dilución adicional | C91: El SBC (3.439 en FY2026E, 8,0% de los ingresos) se mantiene dentro de los gastos operativos y NO se readiciona, aunque la dirección lo excluye en sus cifras non-GAAP. En consecuencia no se proyecta dilución adicional por SBC futuro. Las recompras netas compensan la emisión.
B92: Caja mínima operativa del 2% de ingresos | C92: No toda la caja (4.533 más 3.771 de valores negociables) es distribuible. Solo el exceso sobre ~860 entra en el puente. Se usa el 2% por los compromisos de compra plurianuales con fundiciones (15.100 a 28/09/2025).
B94: FINANCIACIÓN Y PARTIDAS NO OPERATIVAS — SOLO PARA EL MODELO DE TRES ESTADOS (no afectan al FCFF ni al DCF)
B95: SBC / Ingresos | C95: % | G95: ='00 Panel del Analista'!G183 -> 0.075 | H95: ='00 Panel del Analista'!H183 -> 0.072 | I95: ='00 Panel del Analista'!I183 -> 0.07 | J95: ='00 Panel del Analista'!J183 -> 0.068 | K95: ='00 Panel del Analista'!K183 -> 0.066 | L95: ='00 Panel del Analista'!L183 -> 0.065 | M95: ='00 Panel del Analista'!M183 -> 0.064 | N95: ='00 Panel del Analista'!N183 -> 0.063 | ... P95: ='00 Panel del Analista'!P183 -> 0.06
B96: Crecimiento anual del dividendo ordinario | C96: ='00 Panel del Analista'!D196 -> 0.05
B97: % del excedente de caja destinado a repagar deuda | C97: ='00 Panel del Analista'!D197 -> 0.5
B98: Tipo de interés medio sobre la deuda INICIAL | C98: ='00 Panel del Analista'!D198 -> 0.045
B99: Tipo del dividendo de preferentes (no aplica: sin preferentes) | C99: ='00 Panel del Analista'!D199 -> 0
B100: Recompra neta de acciones | C100: ='00 Panel del Analista'!D200 -> 5000
B101: Intangibles adquiridos netos a 28/06/2026 (= suma del calendario) | C101: =SUM(G37:P37) -> 1510
B102: Otros activos no corrientes netos de intangibles a 28/06/2026 | C102: ='03 Historical'!F52-C101 -> 6948
B103: NOTA: el gasto por intereses se calcula sobre la deuda INICIAL del periodo, no sobre la media, para eliminar la circularidad deuda→intereses→beneficio→caja→deuda. Es una simplificación deliberada y conservadora; la alternativa exige cálculo iterativo.
B104: Shock uniforme al crecimiento de ingresos (todos los segmentos, todos los años) | C104: ='00 Panel del Analista'!D201 -> 0
B105: NOTA: este shock existe porque la sensibilidad crecimiento × margen no admite forma cerrada (la depreciación depende de la trayectoria de PP&E). Para esa sensibilidad hay que recorrer C104 manualmente; ver instrucciones en '08 Sensitivity'.
B106: NOTA sobre el número de acciones: NO se usa la media ponderada diluida del ejercicio. Se usan las acciones en circulación a 28/06/2026 (1.057, 10-Q) más los equivalentes dilutivos implícitos (media diluida − media básica FY2026E = 10) más el warrant de Amazon consolidado (3,75 M a 161,26 $) por el método de autocartera al precio actual. Las recompras de Q4 FY26 no se descuentan.

Sheet 03 Historical
A1: ESTADOS FINANCIEROS HISTÓRICOS — QUALCOMM INCORPORATED (QCOM)
A2: USD millones salvo indicación. Ejercicio fiscal cerrado el último domingo de septiembre. Fuentes: Form 10-K FY2025 (auditado) y Form 10-Q Q3 FY2026. FY2026E = 9 meses reportados + guía Q4 (estimación). Balance F = 28/06/2026.
B4: Partida | C4: Unidad | D4: ='00 Panel del Analista'!D14 -> FY2024A | E4: ='00 Panel del Analista'!E14 -> FY2025A | F4: ='00 Panel del Analista'!F14 -> FY2026E | G4: ='00 Panel del Analista'!G14 -> FY2027E | H4: ='00 Panel del Analista'!H14 -> FY2028E | I4: ='00 Panel del Analista'!I14 -> FY2029E | J4: ='00 Panel del Analista'!J14 -> FY2030E | K4: ='00 Panel del Analista'!K14 -> FY2031E | ... P4: ='00 Panel del Analista'!P14 -> FY2036E
B6: CUENTA DE RESULTADOS
B7: ='00 Panel del Analista'!B18 -> QCT IoT + Data Center y otros no reportables | C7: $M | D7: ='00 Panel del Analista'!D18 -> 5617 | E7: ='00 Panel del Analista'!E18 -> 6809 | F7: ='00 Panel del Analista'!F18 -> 7512
B8: ='00 Panel del Analista'!B19 -> QCT Handsets | C8: $M | D8: ='00 Panel del Analista'!D19 -> 24863 | E8: ='00 Panel del Analista'!E19 -> 27793 | F8: ='00 Panel del Analista'!F19 -> 24134
B9: ='00 Panel del Analista'!B20 -> QTL Licencias (incl. ingresos no asignados) | C9: $M | D9: ='00 Panel del Analista'!D20 -> 5572 | E9: ='00 Panel del Analista'!E20 -> 5725 | F9: ='00 Panel del Analista'!F20 -> 5552
B10: ='00 Panel del Analista'!B21 -> QCT Automoción | C10: $M | D10: ='00 Panel del Analista'!D21 -> 2910 | E10: ='00 Panel del Analista'!E21 -> 3957 | F10: ='00 Panel del Analista'!F21 -> 5700
B11: Ingresos totales | C11: $M | D11: =SUM(D7:D10) -> 38962 | E11: =SUM(E7:E10) -> 44284 | F11: =SUM(F7:F10) -> 42898
B13: ='00 Panel del Analista'!B24 -> Coste de los ingresos (excl. amortización de intangibles) | C13: $M | D13: ='00 Panel del Analista'!D24 -> 16749 | E13: ='00 Panel del Analista'!E24 -> 19417 | F13: ='00 Panel del Analista'!F24 -> 19559
B14: ='00 Panel del Analista'!B25 -> (no aplica — coste único en QCOM) | C14: $M | D14: ='00 Panel del Analista'!D25 -> 0 | E14: ='00 Panel del Analista'!E25 -> 0 | F14: ='00 Panel del Analista'!F25 -> 0
B15: ='00 Panel del Analista'!B26 -> (no aplica — coste único en QCOM) | C15: $M | D15: ='00 Panel del Analista'!D26 -> 0 | E15: ='00 Panel del Analista'!E26 -> 0 | F15: ='00 Panel del Analista'!F26 -> 0
B16: Coste total de los ingresos | C16: $M | D16: =SUM(D13:D15) -> 16749 | E16: =SUM(E13:E15) -> 19417 | F16: =SUM(F13:F15) -> 19559
B17: Margen bruto (Gross Profit) | C17: $M | D17: =D11-D16 -> 22213 | E17: =E11-E16 -> 24867 | F17: =F11-F16 -> 23339
B18: Gross Margin | C18: % | D18: =D17/D11 -> 0.5701196 | E18: =E17/E11 -> 0.56153464 | F18: =F17/F11 -> 0.544058
B20: ='00 Panel del Analista'!B31 -> Ventas, generales y administración (SG&A) | C20: $M | D20: ='00 Panel del Analista'!D31 -> 2759 | E20: ='00 Panel del Analista'!E31 -> 3110 | F20: ='00 Panel del Analista'!F31 -> 3718
B21: ='00 Panel del Analista'!B32 -> Investigación y desarrollo | C21: $M | D21: ='00 Panel del Analista'!D32 -> 8893 | E21: ='00 Panel del Analista'!E32 -> 9042 | F21: ='00 Panel del Analista'!F32 -> 10143
B22: ='00 Panel del Analista'!B33 -> Generales y administración (incluido en SG&A) | C22: $M | D22: ='00 Panel del Analista'!D33 -> 0 | E22: ='00 Panel del Analista'!E33 -> 0 | F22: ='00 Panel del Analista'!F33 -> 0
B23: ='00 Panel del Analista'!B34 -> Amortización de intangibles adquiridos (reclasificada desde coste de ingresos) | C23: $M | D23: ='00 Panel del Analista'!D34 -> 311 | E23: ='00 Panel del Analista'!E34 -> 321 | F23: ='00 Panel del Analista'!F34 -> 331
B24: ='00 Panel del Analista'!B35 -> Otros gastos operativos (reestructuración, deterioros y otros) | C24: $M | D24: ='00 Panel del Analista'!D35 -> 179 | E24: ='00 Panel del Analista'!E35 -> 39 | F24: ='00 Panel del Analista'!F35 -> 97
B25: Gastos operativos totales | C25: $M | D25: =D16+SUM(D20:D24) -> 28891 | E25: =E16+SUM(E20:E24) -> 31929 | F25: =F16+SUM(F20:F24) -> 33848
B26: EBIT (resultado operativo) reportado | C26: $M | D26: =D11-D25 -> 10071 | E26: =E11-E25 -> 12355 | F26: =F11-F25 -> 9050
B27: EBIT Margin reportado | C27: % | D27: =D26/D11 -> 0.25848262 | E27: =E26/E11 -> 0.27899467 | F27: =F26/F11 -> 0.21096555
B29: Gasto por intereses | C29: $M | D29: ='00 Panel del Analista'!D40 -> 697 | E29: ='00 Panel del Analista'!E40 -> 664 | F29: ='00 Panel del Analista'!F40 -> 694
B30: Resultado no operativo, neto | C30: $M | D30: ='00 Panel del Analista'!D41 -> 962 | E30: ='00 Panel del Analista'!E41 -> 972 | F30: ='00 Panel del Analista'!F41 -> 1543
B31: Beneficio antes de impuestos | C31: $M | D31: =D26-D29+D30 -> 10336 | E31: =E26-E29+E30 -> 12663 | F31: =F26-F29+F30 -> 9899
B32: Impuesto sobre sociedades | C32: $M | D32: ='00 Panel del Analista'!D43 -> 226 | E32: ='00 Panel del Analista'!E43 -> 7122 | F32: ='00 Panel del Analista'!F43 -> -3904
B33: Tipo impositivo efectivo | C33: % | D33: =D32/D31 -> 0.021865325 | E33: =E32/E31 -> 0.56242597 | F33: =F32/F31 -> -0.39438327
B34: Beneficio neto | C34: $M | D34: =D31-D32 -> 10110 | E34: =E31-E32 -> 5541 | F34: =F31-F32 -> 13803
B35: Dividendos de acciones preferentes | C35: $M | D35: ='00 Panel del Analista'!D46 -> 0 | E35: ='00 Panel del Analista'!E46 -> 0 | F35: ='00 Panel del Analista'!F46 -> 0
B36: Beneficio neto atribuible a ordinarias | C36: $M | D36: =D34-D35 -> 10110 | E36: =E34-E35 -> 5541 | F36: =F34-F35 -> 13803
B37: BPA básico | C37: $/acc | D37: ='00 Panel del Analista'!D48 -> 9.06 | E37: ='00 Panel del Analista'!E48 -> 5.05 | F37: ='00 Panel del Analista'!F48 -> 12.960563
B38: BPA diluido | C38: $/acc | D38: ='00 Panel del Analista'!D49 -> 8.94 | E38: ='00 Panel del Analista'!E49 -> 5.01 | F38: ='00 Panel del Analista'!F49 -> 12.84
B39: Acciones medias básicas | C39: M acc | D39: ='00 Panel del Analista'!D50 -> 1116 | E39: ='00 Panel del Analista'!E50 -> 1096 | F39: ='00 Panel del Analista'!F50 -> 1065
B40: Acciones medias diluidas | C40: M acc | D40: ='00 Panel del Analista'!D51 -> 1130 | E40: ='00 Panel del Analista'!E51 -> 1105 | F40: ='00 Panel del Analista'!F51 -> 1075
B42: BALANCE (a cierre de ejercicio)
B43: Caja y equivalentes | C43: $M | E43: ='00 Panel del Analista'!E54 -> 7843 | F43: ='00 Panel del Analista'!F54 -> 4533
B44: Valores negociables | C44: $M | E44: ='00 Panel del Analista'!E55 -> 4635 | F44: ='00 Panel del Analista'!F55 -> 3771
B45: Clientes, neto | C45: $M | E45: ='00 Panel del Analista'!E56 -> 4315 | F45: ='00 Panel del Analista'!F56 -> 4668
B46: Gastos anticipados y otros activos corrientes | C46: $M | E46: ='00 Panel del Analista'!E57 -> 8961 | F46: ='00 Panel del Analista'!F57 -> 10032
B47: Total activo corriente | C47: $M | E47: =SUM(E43:E46) -> 25754 | F47: =SUM(F43:F46) -> 23004
B48: Inmovilizado material (PP&E), neto | C48: $M | E48: ='00 Panel del Analista'!E59 -> 4690 | F48: ='00 Panel del Analista'!F59 -> 5217
B49: Activos por derecho de uso — leases operativos | C49: $M | E49: ='00 Panel del Analista'!E60 -> 735 | F49: ='00 Panel del Analista'!F60 -> 735
B50: Fondo de comercio | C50: $M | E50: ='00 Panel del Analista'!E61 -> 11358 | F50: ='00 Panel del Analista'!F61 -> 14274
B51: Activos por impuesto diferido | C51: $M | E51: ='00 Panel del Analista'!E62 -> 743 | F51: ='00 Panel del Analista'!F62 -> 5679
B52: Otros activos no corrientes | C52: $M | E52: ='00 Panel del Analista'!E63 -> 6863 | F52: ='00 Panel del Analista'!F63 -> 8458
B53: Total activo no corriente | C53: $M | E53: =SUM(E48:E52) -> 24389 | F53: =SUM(F48:F52) -> 34363
B54: TOTAL ACTIVO | C54: $M | E54: =E47+E53 -> 50143 | F54: =F47+F53 -> 57367
B56: Deuda financiera corriente | C56: $M | E56: ='00 Panel del Analista'!E67 -> 0 | F56: ='00 Panel del Analista'!F67 -> 2489
B57: Proveedores | C57: $M | E57: ='00 Panel del Analista'!E68 -> 2791 | F57: ='00 Panel del Analista'!F68 -> 2897
B58: Remuneraciones y cargas pendientes | C58: $M | E58: ='00 Panel del Analista'!E69 -> 1839 | F58: ='00 Panel del Analista'!F69 -> 1470
B59: Ingresos diferidos corrientes | C59: $M | E59: ='00 Panel del Analista'!E70 -> 358 | F59: ='00 Panel del Analista'!F70 -> 280
B60: Otros pasivos corrientes | C60: $M | E60: ='00 Panel del Analista'!E71 -> 4156 | F60: ='00 Panel del Analista'!F71 -> 4277
B61: Total pasivo corriente | C61: $M | E61: =SUM(E56:E60) -> 9144 | F61: =SUM(F56:F60) -> 11413
B62: Deuda financiera no corriente | C62: $M | E62: ='00 Panel del Analista'!E73 -> 14811 | F62: ='00 Panel del Analista'!F73 -> 12781
B63: Impuestos a pagar no corrientes | C63: $M | E63: ='00 Panel del Analista'!E74 -> 0 | F63: ='00 Panel del Analista'!F74 -> 0
B64: Pasivo por leases operativos no corriente | C64: $M | E64: ='00 Panel del Analista'!E75 -> 730 | F64: ='00 Panel del Analista'!F75 -> 730
B65: Otros pasivos no corrientes | C65: $M | E65: ='00 Panel del Analista'!E76 -> 4252 | F65: ='00 Panel del Analista'!F76 -> 4785
B66: Total pasivo no corriente | C66: $M | E66: =SUM(E62:E65) -> 19793 | F66: =SUM(F62:F65) -> 18296
B67: Acciones preferentes (ninguna emitida) | C67: $M | E67: ='00 Panel del Analista'!E78 -> 0 | F67: ='00 Panel del Analista'!F78 -> 0
B68: Capital social y prima de emisión | C68: $M | E68: ='00 Panel del Analista'!E79 -> 0 | F68: ='00 Panel del Analista'!F79 -> 0
B69: Resultados acumulados (déficit) | C69: $M | E69: ='00 Panel del Analista'!E80 -> 20646 | F69: ='00 Panel del Analista'!F80 -> 27263
B70: Otro resultado global acumulado | C70: $M | E70: ='00 Panel del Analista'!E81 -> 560 | F70: ='00 Panel del Analista'!F81 -> 395
B71: Patrimonio atribuible a Qualcomm | C71: $M | E71: =SUM(E67:E70) -> 21206 | F71: =SUM(F67:F70) -> 27658
B72: Intereses minoritarios | C72: $M | E72: ='00 Panel del Analista'!E83 -> 0 | F72: ='00 Panel del Analista'!F83 -> 0
B73: Total patrimonio neto | C73: $M | E73: =E71+E72 -> 21206 | F73: =F71+F72 -> 27658
B74: TOTAL PASIVO Y PATRIMONIO | C74: $M | E74: =E61+E66+E73 -> 50143 | F74: =F61+F66+F73 -> 57367
B75: CHECK: Activo − Pasivo y Patrimonio (debe ser 0) | C75: $M | E75: =E54-E74 -> 0 | F75: =F54-F74 -> 0
B77: ESTADO DE FLUJOS DE CAJA
B78: Beneficio neto | C78: $M | D78: =D34 -> 10110 | E78: =E34 -> 5541 | F78: =F34 -> 13803
B79: Depreciación | C79: $M | D79: ='00 Panel del Analista'!D90 -> 1395 | E79: ='00 Panel del Analista'!E90 -> 1281 | F79: ='00 Panel del Analista'!F90 -> 1271.6667
B80: Amortización de intangibles | C80: $M | D80: =D23 -> 311 | E80: =E23 -> 321 | F80: =F23 -> 331
B81: Impuestos diferidos | C81: $M | D81: ='00 Panel del Analista'!D92 -> -3064 | E81: ='00 Panel del Analista'!E92 -> 3980 | F81: ='00 Panel del Analista'!F92 -> -5550
B82: Retribución basada en acciones (SBC) | C82: $M | D82: ='00 Panel del Analista'!D93 -> 2648 | E82: ='00 Panel del Analista'!E93 -> 2783 | F82: ='00 Panel del Analista'!F93 -> 3439
B83: Resultados de inversiones y otros, neto | C83: $M | D83: ='00 Panel del Analista'!D94 -> -330 | E83: ='00 Panel del Analista'!E94 -> -308 | F83: ='00 Panel del Analista'!F94 -> -1073
B84: Variación de circulante y otras partidas operativas (derivado) | C84: $M | D84: =D85-SUM(D78:D83) -> 1132 | E84: =E85-SUM(E78:E83) -> 414 | F84: =F85-SUM(F78:F83) -> -1129.6667
B85: FLUJO DE CAJA OPERATIVO (CFO) — reportado | C85: $M | D85: ='00 Panel del Analista'!D96 -> 12202 | E85: ='00 Panel del Analista'!E96 -> 14012 | F85: ='00 Panel del Analista'!F96 -> 11092
B87: Capex (adquisición de inmovilizado) | C87: $M | D87: ='00 Panel del Analista'!D98 -> -1041 | E87: ='00 Panel del Analista'!E98 -> -1192 | F87: ='00 Panel del Analista'!F98 -> -2104
B88: Compras de inversiones y adquisiciones | C88: $M | D88: ='00 Panel del Analista'!D99 -> -5323 | E88: ='00 Panel del Analista'!E99 -> -5437 | F88: ='00 Panel del Analista'!F99 -> -4022
B89: Cobros por ventas y vencimientos de inversiones | C89: $M | D89: ='00 Panel del Analista'!D100 -> 2677 | E89: ='00 Panel del Analista'!E100 -> 5755 | F89: ='00 Panel del Analista'!F100 -> 3896
B90: Otros de inversión (derivado) | C90: $M | D90: =D91-SUM(D87:D89) -> 64 | E90: =E91-SUM(E87:E89) -> 74 | F90: =F91-SUM(F87:F89) -> 56
B91: FLUJO DE CAJA DE INVERSIÓN (CFI) — reportado | C91: $M | D91: ='00 Panel del Analista'!D102 -> -3623 | E91: ='00 Panel del Analista'!E102 -> -800 | F91: ='00 Panel del Analista'!F102 -> -2174
B93: Emisión de acciones ordinarias | C93: $M | D93: ='00 Panel del Analista'!D104 -> 383 | E93: ='00 Panel del Analista'!E104 -> 404 | F93: ='00 Panel del Analista'!F104 -> 223
B94: Recompra de acciones ordinarias | C94: $M | D94: ='00 Panel del Analista'!D105 -> -4121 | E94: ='00 Panel del Analista'!E105 -> -8791 | F94: ='00 Panel del Analista'!F105 -> -8206
B95: Acciones retenidas por impuestos en el vesting | C95: $M | D95: ='00 Panel del Analista'!D106 -> -932 | E95: ='00 Panel del Analista'!E106 -> -1115 | F95: ='00 Panel del Analista'!F106 -> -888
B96: Emisión de preferentes (no aplica) | C96: $M | D96: ='00 Panel del Analista'!D107 -> 0 | E96: ='00 Panel del Analista'!E107 -> 0 | F96: ='00 Panel del Analista'!F107 -> 0
B97: Dividendos pagados | C97: $M | D97: ='00 Panel del Analista'!D108 -> -3687 | E97: ='00 Panel del Analista'!E108 -> -3805 | F97: ='00 Panel del Analista'!F108 -> -3805
B98: Papel comercial, neto | C98: $M | D98: ='00 Panel del Analista'!D109 -> 0 | E98: ='00 Panel del Analista'!E109 -> 0 | F98: ='00 Panel del Analista'!F109 -> 495
B99: Financiación a corto plazo ligada a capex, neto | C99: $M | D99: ='00 Panel del Analista'!D110 -> 0 | E99: ='00 Panel del Analista'!E110 -> 0 | F99: ='00 Panel del Analista'!F110 -> 0
B100: Emisión de deuda a largo plazo y préstamos | C100: $M | D100: ='00 Panel del Analista'!D111 -> 0 | E100: ='00 Panel del Analista'!E111 -> 1487 | F100: ='00 Panel del Analista'!F111 -> 0
B101: Repago de deuda | C101: $M | D101: ='00 Panel del Analista'!D112 -> -914 | E101: ='00 Panel del Analista'!E112 -> -1365 | F101: ='00 Panel del Analista'!F112 -> -174
B102: Otros de financiación, neto | C102: $M | D102: ='00 Panel del Analista'!D113 -> 2 | E102: ='00 Panel del Analista'!E113 -> -11 | F102: ='00 Panel del Analista'!F113 -> -28
B103: FLUJO DE CAJA DE FINANCIACIÓN (CFF) — calculado | C103: $M | D103: =SUM(D93:D102) -> -9269 | E103: =SUM(E93:E102) -> -13196 | F103: =SUM(F93:F102) -> -12383
B104: CFF reportado en el 10-K | C104: $M | E104: ='00 Panel del Analista'!E115 -> -13196 | F104: ='00 Panel del Analista'!F115 -> -12383
B105: CHECK: CFF calculado − CFF reportado (debe ser 0) | C105: $M | E105: =E103-E104 -> 0 | F105: =F103-F104 -> 0
B106: Variación neta de caja (CFO+CFI+CFF) | C106: $M | D106: =D85+D91+D103 -> -690 | E106: =E85+E91+E103 -> 16 | F106: =F85+F91+F103 -> -3465
B107: Diferencia no explicada (FX + desfase balance 28/06/2026 vs flujos FY2026E) | C107: $M | F107: =F43-E43-F106 -> 155
B109: MEMORIA — DEUDA, ARRENDAMIENTOS, OBJETIVOS Y DILUCIÓN
B110: Deuda financiera total (senior notes y otros préstamos) | C110: $M | E110: ='00 Panel del Analista'!E121 -> 14811 | F110: ='00 Panel del Analista'!F121 -> 15270
B111: CHECK: deuda total − (corriente + no corriente) del balance | C111: $M | E111: =E110-E56-E62 -> 0 | F111: =F110-F56-F62 -> 0
...

Sheet 04 Operating Model
A1: MODELO OPERATIVO FY2027E–FY2036E — QUALCOMM INCORPORATED
A2: USD millones. Toda hipótesis procede de '02 Assumptions'. Esta hoja NO contiene hipótesis propias. Verde = enlace; negro = fórmula.
B4: Partida | C4: Unidad | D4: ='00 Panel del Analista'!D14 -> FY2024A | E4: ='00 Panel del Analista'!E14 -> FY2025A | F4: ='00 Panel del Analista'!F14 -> FY2026E | G4: ='00 Panel del Analista'!G14 -> FY2027E | H4: ='00 Panel del Analista'!H14 -> FY2028E | I4: ='00 Panel del Analista'!I14 -> FY2029E | J4: ='00 Panel del Analista'!J14 -> FY2030E | K4: ='00 Panel del Analista'!K14 -> FY2031E | ... P4: ='00 Panel del Analista'!P14 -> FY2036E
B6: INGRESOS POR SEGMENTO
B7: ='00 Panel del Analista'!B18 -> QCT IoT + Data Center y otros no reportables | C7: $M | D7: ='03 Historical'!D7 -> 5617 | E7: ='03 Historical'!E7 -> 6809 | F7: ='03 Historical'!F7 -> 7512 | G7: =F7*(1+'02 Assumptions'!G20) -> 12019.2 | H7: =G7*(1+'02 Assumptions'!H20) -> 15985.536 | I7: =H7*(1+'02 Assumptions'!I20) -> 19502.354 | J7: =I7*(1+'02 Assumptions'!J20) -> 22427.707 | K7: =J7*(1+'02 Assumptions'!K20) -> 25119.032 | L7: =K7*(1+'02 Assumptions'!L20) -> 27630.935 | M7: =L7*(1+'02 Assumptions'!M20) -> 29841.41 | N7: =M7*(1+'02 Assumptions'!N20) -> 31631.894 | ... P7: =O7*(1+'02 Assumptions'!P20) -> 34542.029
B8: ='00 Panel del Analista'!B19 -> QCT Handsets | C8: $M | D8: ='03 Historical'!D8 -> 24863 | E8: ='03 Historical'!E8 -> 27793 | F8: ='03 Historical'!F8 -> 24134 | G8: =F8*(1+'02 Assumptions'!G22) -> 20513.9 | H8: =G8*(1+'02 Assumptions'!H22) -> 20924.178 | I8: =H8*(1+'02 Assumptions'!I22) -> 21551.903 | J8: =I8*(1+'02 Assumptions'!J22) -> 21982.941 | K8: =J8*(1+'02 Assumptions'!K22) -> 22422.6 | L8: =K8*(1+'02 Assumptions'!L22) -> 22871.052 | M8: =L8*(1+'02 Assumptions'!M22) -> 23328.473 | N8: =M8*(1+'02 Assumptions'!N22) -> 23795.043 | ... P8: =O8*(1+'02 Assumptions'!P22) -> 24999.667
B9: ='00 Panel del Analista'!B20 -> QTL Licencias (incl. ingresos no asignados) | C9: $M | D9: ='03 Historical'!D9 -> 5572 | E9: ='03 Historical'!E9 -> 5725 | F9: ='03 Historical'!F9 -> 5552 | G9: =F9*(1+'02 Assumptions'!G24) -> 5440.96 | H9: =G9*(1+'02 Assumptions'!H24) -> 5332.1408 | I9: =H9*(1+'02 Assumptions'!I24) -> 5332.1408 | J9: =I9*(1+'02 Assumptions'!J24) -> 5385.4622 | K9: =J9*(1+'02 Assumptions'!K24) -> 5439.3168 | L9: =K9*(1+'02 Assumptions'!L24) -> 5493.71 | M9: =L9*(1+'02 Assumptions'!M24) -> 5576.1156 | N9: =M9*(1+'02 Assumptions'!N24) -> 5659.7574 | ... P9: =O9*(1+'02 Assumptions'!P24) -> 5888.4116
B10: ='00 Panel del Analista'!B21 -> QCT Automoción | C10: $M | D10: ='03 Historical'!D10 -> 2910 | E10: ='03 Historical'!E10 -> 3957 | F10: ='03 Historical'!F10 -> 5700 | G10: =F10*(1+'02 Assumptions'!G26) -> 6954 | H10: =G10*(1+'02 Assumptions'!H26) -> 8136.18 | I10: =H10*(1+'02 Assumptions'!I26) -> 9356.607 | J10: =I10*(1+'02 Assumptions'!J26) -> 10572.966 | K10: =J10*(1+'02 Assumptions'!K26) -> 11735.992 | L10: =K10*(1+'02 Assumptions'!L26) -> 12792.231 | M10: =L10*(1+'02 Assumptions'!M26) -> 13815.61 | N10: =M10*(1+'02 Assumptions'!N26) -> 14782.703 | ... P10: =O10*(1+'02 Assumptions'!P26) -> 16453.148
B11: INGRESOS TOTALES | C11: $M | D11: =SUM(D7:D10) -> 38962 | E11: =SUM(E7:E10) -> 44284 | F11: =SUM(F7:F10) -> 42898 | G11: =SUM(G7:G10) -> 44928.06 | H11: =SUM(H7:H10) -> 50378.035 | I11: =SUM(I7:I10) -> 55743.005 | J11: =SUM(J7:J10) -> 60369.077 | K11: =SUM(K7:K10) -> 64716.941 | ... P11: =SUM(P7:P10) -> 81883.255
B12: Crecimiento de ingresos | C12: % | E12: =E11/D11-1 -> 0.13659463 | F12: =F11/E11-1 -> -0.031297986 | G12: =G11/F11-1 -> 0.047322952 | H12: =H11/G11-1 -> 0.12130448 | I12: =I11/H11-1 -> 0.10649423 | J12: =J11/I11-1 -> 0.082989273 | K12: =K11/J11-1 -> 0.072021386 | L12: =L11/K11-1 -> 0.062904513 | ... P12: =P11/O11-1 -> 0.03589339
B13: Mix: IoT + Data Center / ingresos totales | C13: % | D13: =D7/D11 -> 0.14416611 | E13: =E7/E11 -> 0.15375756 | F13: =F7/F11 -> 0.17511306 | G13: =G7/G11 -> 0.26752101 | H13: =H7/H11 -> 0.31731162 | I13: =I7/I11 -> 0.3498619 | J13: =J7/J11 -> 0.37150986 | K13: =K7/K11 -> 0.38813688 | ... P13: =P7/P11 -> 0.42184484
B15: MARGEN BRUTO
B16: Gross Margin | C16: % | D16: ='03 Historical'!D18 -> 0.5701196 | E16: ='03 Historical'!E18 -> 0.56153464 | F16: ='03 Historical'!F18 -> 0.544058 | G16: ='02 Assumptions'!G30 -> 0.545 | H16: ='02 Assumptions'!H30 -> 0.55 | I16: ='02 Assumptions'!I30 -> 0.555 | J16: ='02 Assumptions'!J30 -> 0.555 | K16: ='02 Assumptions'!K30 -> 0.555 | L16: ='02 Assumptions'!L30 -> 0.555 | M16: ='02 Assumptions'!M30 -> 0.555 | N16: ='02 Assumptions'!N30 -> 0.555 | ... P16: ='02 Assumptions'!P30 -> 0.555
B17: Margen bruto (Gross Profit) | C17: $M | D17: ='03 Historical'!D17 -> 22213 | E17: ='03 Historical'!E17 -> 24867 | F17: ='03 Historical'!F17 -> 23339 | G17: =G11*G16 -> 24485.793 | H17: =H11*H16 -> 27707.919 | I17: =I11*I16 -> 30937.368 | J17: =J11*J16 -> 33504.837 | K17: =K11*K16 -> 35917.902 | L17: =L11*L16 -> 38177.3 | M17: =M11*M16 -> 40271.693 | N17: =N11*N16 -> 42107.515 | ... P17: =P11*P16 -> 45445.207
B18: Coste de los ingresos | C18: $M | D18: ='03 Historical'!D16 -> 16749 | E18: ='03 Historical'!E16 -> 19417 | F18: ='03 Historical'!F16 -> 19559 | G18: =G11-G17 -> 20442.267 | H18: =H11-H17 -> 22670.116 | I18: =I11-I17 -> 24805.637 | J18: =J11-J17 -> 26864.239 | K18: =K11-K17 -> 28799.039 | L18: =L11-L17 -> 30610.628 | M18: =M11-M17 -> 32289.916 | N18: =N11-N17 -> 33761.882 | ... P18: =P11-P17 -> 36438.049
B20: GASTOS OPERATIVOS (por debajo del margen bruto)
B21: ='00 Panel del Analista'!B31 -> Ventas, generales y administración (SG&A) | C21: $M | D21: ='03 Historical'!D20 -> 2759 | E21: ='03 Historical'!E20 -> 3110 | F21: ='03 Historical'!F20 -> 3718 | G21: =G11*'02 Assumptions'!G32 -> 3818.8851 | H21: =H11*'02 Assumptions'!H32 -> 4030.2428 | I21: =I11*'02 Assumptions'!I32 -> 4292.2114 | J21: =J11*'02 Assumptions'!J32 -> 4527.6807 | K21: =K11*'02 Assumptions'!K32 -> 4724.3367 | L21: =L11*'02 Assumptions'!L32 -> 4952.7309 | M21: =M11*'02 Assumptions'!M32 -> 5151.8742 | N21: =N11*'02 Assumptions'!N32 -> 5386.7272 | ... P21: =P11*'02 Assumptions'!P32 -> 5813.7111
B22: ='00 Panel del Analista'!B32 -> Investigación y desarrollo | C22: $M | D22: ='03 Historical'!D21 -> 8893 | E22: ='03 Historical'!E21 -> 9042 | F22: ='03 Historical'!F21 -> 10143 | G22: =G11*'02 Assumptions'!G34 -> 10558.094 | H22: =H11*'02 Assumptions'!H34 -> 11335.058 | I22: =I11*'02 Assumptions'!I34 -> 11984.746 | J22: =J11*'02 Assumptions'!J34 -> 12677.506 | K22: =K11*'02 Assumptions'!K34 -> 13396.407 | L22: =L11*'02 Assumptions'!L34 -> 14101.525 | M22: =M11*'02 Assumptions'!M34 -> 14875.13 | N22: =N11*'02 Assumptions'!N34 -> 15553.226 | ... P22: =P11*'02 Assumptions'!P34 -> 16786.067
B23: ='00 Panel del Analista'!B33 -> Generales y administración (incluido en SG&A) | C23: $M | D23: ='03 Historical'!D22 -> 0 | E23: ='03 Historical'!E22 -> 0 | F23: ='03 Historical'!F22 -> 0 | G23: =G11*'02 Assumptions'!G36 -> 0 | H23: =H11*'02 Assumptions'!H36 -> 0 | I23: =I11*'02 Assumptions'!I36 -> 0 | J23: =J11*'02 Assumptions'!J36 -> 0 | K23: =K11*'02 Assumptions'!K36 -> 0 | L23: =L11*'02 Assumptions'!L36 -> 0 | M23: =M11*'02 Assumptions'!M36 -> 0 | N23: =N11*'02 Assumptions'!N36 -> 0 | ... P23: =P11*'02 Assumptions'!P36 -> 0
B24: ='00 Panel del Analista'!B34 -> Amortización de intangibles adquiridos (reclasificada desde coste de ingresos) | C24: $M | D24: ='03 Historical'!D23 -> 311 | E24: ='03 Historical'!E23 -> 321 | F24: ='03 Historical'!F23 -> 331 | G24: ='02 Assumptions'!G37 -> 430 | H24: ='02 Assumptions'!H37 -> 350 | I24: ='02 Assumptions'!I37 -> 280 | J24: ='02 Assumptions'!J37 -> 210 | K24: ='02 Assumptions'!K37 -> 140 | L24: ='02 Assumptions'!L37 -> 100 | M24: ='02 Assumptions'!M37 -> 0 | N24: ='02 Assumptions'!N37 -> 0 | ... P24: ='02 Assumptions'!P37 -> 0
B25: ='00 Panel del Analista'!B35 -> Otros gastos operativos (reestructuración, deterioros y otros) | C25: $M | D25: ='03 Historical'!D24 -> 179 | E25: ='03 Historical'!E24 -> 39 | F25: ='03 Historical'!F24 -> 97 | G25: ='02 Assumptions'!G38 -> 100 | H25: ='02 Assumptions'!H38 -> 100 | I25: ='02 Assumptions'!I38 -> 100 | J25: ='02 Assumptions'!J38 -> 100 | K25: ='02 Assumptions'!K38 -> 100 | L25: ='02 Assumptions'!L38 -> 100 | M25: ='02 Assumptions'!M38 -> 100 | N25: ='02 Assumptions'!N38 -> 100 | ... P25: ='02 Assumptions'!P38 -> 100
B26: Total gastos operativos | C26: $M | D26: =SUM(D21:D25) -> 12142 | E26: =SUM(E21:E25) -> 12512 | F26: =SUM(F21:F25) -> 14289 | G26: =SUM(G21:G25) -> 14906.979 | H26: =SUM(H21:H25) -> 15815.301 | I26: =SUM(I21:I25) -> 16656.957 | J26: =SUM(J21:J25) -> 17515.187 | K26: =SUM(K21:K25) -> 18360.744 | ... P26: =SUM(P21:P25) -> 22699.778
B27: EBIT reportado | C27: $M | D27: =D17-D26 -> 10071 | E27: =E17-E26 -> 12355 | F27: =F17-F26 -> 9050 | G27: =G17-G26 -> 9578.8135 | H27: =H17-H26 -> 11892.619 | I27: =I17-I26 -> 14280.41 | J27: =J17-J26 -> 15989.651 | K27: =K17-K26 -> 17557.159 | ... P27: =P17-P26 -> 22745.428
B28: EBIT Margin reportado | C28: % | D28: =D27/D11 -> 0.25848262 | E28: =E27/E11 -> 0.27899467 | F28: =F27/F11 -> 0.21096555 | G28: =G27/G11 -> 0.21320336 | H28: =H27/H11 -> 0.23606754 | I28: =I27/I11 -> 0.256183 | J28: =J27/J11 -> 0.26486492 | K28: =K27/K11 -> 0.27129154 | ... P28: =P27/P11 -> 0.27777875
B29: EBIT NORMALIZADO (excluye reestructuración) | C29: $M | D29: =D27+D25 -> 10250 | E29: =E27+E25 -> 12394 | F29: =F27+F25 -> 9147 | G29: =G27+G25 -> 9678.8135 | H29: =H27+H25 -> 11992.619 | I29: =I27+I25 -> 14380.41 | J29: =J27+J25 -> 16089.651 | K29: =K27+K25 -> 17657.159 | ... P29: =P27+P25 -> 22845.428
B30: Margen EBIT normalizado | C30: % | D30: =D29/D11 -> 0.26307684 | E30: =E29/E11 -> 0.27987535 | F30: =F29/F11 -> 0.21322672 | G30: =G29/G11 -> 0.21542914 | H30: =H29/H11 -> 0.23805253 | I30: =I29/I11 -> 0.25797695 | J30: =J29/J11 -> 0.2665214 | K30: =K29/K11 -> 0.27283673 | ... P30: =P29/P11 -> 0.279
B32: CAPEX Y DEPRECIACIÓN — ROLL-FORWARD DE PP&E
B33: PP&E neto inicial | C33: $M | F33: ='03 Historical'!E48 -> 4690 | G33: =F37 -> 5217 | H33: =G37 -> 5854.7891 | I33: =H37 -> 6255.3829 | J33: =I37 -> 6549.9753 | K33: =J37 -> 6704.2673 | L33: =K37 -> 6940.2152 | M33: =L37 -> 7232.2899 | N33: =M37 -> 7560.0906 | ... P33: =O37 -> 8254.8697
B34: Capex | C34: $M | D34: ='03 Historical'!D129 -> 1041 | E34: ='03 Historical'!E129 -> 1192 | F34: ='03 Historical'!F129 -> 2104 | G34: =G11*'02 Assumptions'!G42 -> 2021.7627 | H34: =H11*'02 Assumptions'!H42 -> 1914.3653 | I34: =I11*'02 Assumptions'!I42 -> 1895.2622 | J34: =J11*'02 Assumptions'!J42 -> 1811.0723 | K34: =K11*'02 Assumptions'!K42 -> 1941.5082 | L34: =L11*'02 Assumptions'!L42 -> 2063.6379 | M34: =M11*'02 Assumptions'!M42 -> 2176.8483 | N34: =N11*'02 Assumptions'!N42 -> 2276.0819 | ... P34: =P11*'02 Assumptions'!P42 -> 2456.4977
B35: Capex / Ingresos | C35: % | D35: =D34/D11 -> 0.026718341 | E35: =E34/E11 -> 0.026917171 | F35: =F34/F11 -> 0.049046576 | G35: =G34/G11 -> 0.045 | H35: =H34/H11 -> 0.038 | I35: =I34/I11 -> 0.034 | J35: =J34/J11 -> 0.03 | K35: =K34/K11 -> 0.03 | ... P35: =P34/P11 -> 0.03
B36: Depreciación = (PP&E inicial + Capex/2) / vida útil | C36: $M | D36: ='03 Historical'!D79 -> 1395 | E36: ='03 Historical'!E79 -> 1281 | F36: ='03 Historical'!F79 -> 1271.6667 | G36: =(G33+G34/2)/'02 Assumptions'!$C$43 -> 1383.9736 | H36: =(H33+H34/2)/'02 Assumptions'!$C$43 -> 1513.7715 | I36: =(I33+I34/2)/'02 Assumptions'!$C$43 -> 1600.6698 | J36: =(J33+J34/2)/'02 Assumptions'!$C$43 -> 1656.7803 | K36: =(K33+K34/2)/'02 Assumptions'!$C$43 -> 1705.5603 | L36: =(L33+L34/2)/'02 Assumptions'!$C$43 -> 1771.5631 | M36: =(M33+M34/2)/'02 Assumptions'!$C$43 -> 1849.0476 | N36: =(N33+N34/2)/'02 Assumptions'!$C$43 -> 1932.9181 | ... P36: =(P33+P34/2)/'02 Assumptions'!$C$43 -> 2107.3597
B37: PP&E neto final | C37: $M | E37: ='03 Historical'!E48 -> 4690 | F37: ='03 Historical'!F48 -> 5217 | G37: =G33+G34-G36 -> 5854.7891 | H37: =H33+H34-H36 -> 6255.3829 | I37: =I33+I34-I36 -> 6549.9753 | J37: =J33+J34-J36 -> 6704.2673 | K37: =K33+K34-K36 -> 6940.2152 | L37: =L33+L34-L36 -> 7232.2899 | M37: =M33+M34-M36 -> 7560.0906 | N37: =N33+N34-N36 -> 7903.2544 | ... P37: =P33+P34-P36 -> 8604.0076
B38: D&A total (depreciación + amortización de intangibles) | C38: $M | D38: =D36+D24 -> 1706 | E38: =E36+E24 -> 1602 | F38: =F36+F24 -> 1602.6667 | G38: =G36+G24 -> 1813.9736 | H38: =H36+H24 -> 1863.7715 | I38: =I36+I24 -> 1880.6698 | J38: =J36+J24 -> 1866.7803 | K38: =K36+K24 -> 1845.5603 | ... P38: =P36+P24 -> 2107.3597
B39: EBITDA (EBIT normalizado + D&A) | C39: $M | D39: =D29+D38 -> 11956 | E39: =E29+E38 -> 13996 | F39: =F29+F38 -> 10749.667 | G39: =G29+G38 -> 11492.787 | H39: =H29+H38 -> 13856.39 | I39: =I29+I38 -> 16261.08 | J39: =J29+J38 -> 17956.431 | K39: =K29+K38 -> 19502.719 | ... P39: =P29+P38 -> 24952.788
B40: EBITDA Margin | C40: % | D40: =D39/D11 -> 0.3068631 | E40: =E39/E11 -> 0.31605094 | F40: =F39/F11 -> 0.25058666 | G40: =G39/G11 -> 0.25580422 | H40: =H39/H11 -> 0.27504824 | I40: =I39/I11 -> 0.29171517 | J40: =J39/J11 -> 0.29744419 | K40: =K39/K11 -> 0.30135416 | ... P40: =P39/P11 -> 0.30473615
B41: Capex / D&A | C41: x | D41: =D34/D38 -> 0.6101993 | E41: =E34/E38 -> 0.74406991 | F41: =F34/F38 -> 1.312812 | G41: =G34/G38 -> 1.1145491 | H41: =H34/H38 -> 1.0271459 | I41: =I34/I38 -> 1.0077591 | J41: =J34/J38 -> 0.97015823 | K41: =K34/K38 -> 1.0519885 | ... P41: =P34/P38 -> 1.1656756
B43: CIRCULANTE OPERATIVO (drivers: DSO, proveedores sobre coste+capex, ingresos diferidos)
B44: Clientes (AR) | C44: $M | E44: ='03 Historical'!E45 -> 4315 | F44: ='03 Historical'!F45 -> 4668 | G44: ='02 Assumptions'!G48/365*G11 -> 4677.4419 | H44: ='02 Assumptions'!H48/365*H11 -> 5244.8365 | I44: ='02 Assumptions'!I48/365*I11 -> 5803.3813 | J44: ='02 Assumptions'!J48/365*J11 -> 6284.9997 | K44: ='02 Assumptions'!K48/365*K11 -> 6737.6541 | L44: ='02 Assumptions'!L48/365*L11 -> 7161.483 | M44: ='02 Assumptions'!M48/365*M11 -> 7554.3593 | N44: ='02 Assumptions'!N48/365*N11 -> 7898.7318 | ... P44: ='02 Assumptions'!P48/365*P11 -> 8524.832
B45: Inventarios y otros activos corrientes | C45: $M | E45: ='03 Historical'!E46 -> 8961 | F45: ='03 Historical'!F46 -> 10032 | G45: =G11*'02 Assumptions'!G51 -> 9434.8926 | H45: =H11*'02 Assumptions'!H51 -> 10075.607 | I45: =I11*'02 Assumptions'!I51 -> 11148.601 | J45: =J11*'02 Assumptions'!J51 -> 12073.815 | K45: =K11*'02 Assumptions'!K51 -> 12943.388 | L45: =L11*'02 Assumptions'!L51 -> 13757.586 | M45: =M11*'02 Assumptions'!M51 -> 14512.322 | N45: =N11*'02 Assumptions'!N51 -> 15173.879 | ... P45: =P11*'02 Assumptions'!P51 -> 16376.651
B46: Proveedores | C46: $M | E46: ='03 Historical'!E57 -> 2791 | F46: ='03 Historical'!F57 -> 2897 | G46: =(G18+G34)*'02 Assumptions'!G49 -> 3010.18 | H46: =(H18+H34)*'02 Assumptions'!H49 -> 3294.3205 | I46: =(I18+I34)*'02 Assumptions'!I49 -> 3577.9205 | J46: =(J18+J34)*'02 Assumptions'!J49 -> 3842.4917 | K46: =(K18+K34)*'02 Assumptions'!K49 -> 4119.2333 | L46: =(L18+L34)*'02 Assumptions'!L49 -> 4378.3517 | M46: =(M18+M34)*'02 Assumptions'!M49 -> 4618.5464 | N46: =(N18+N34)*'02 Assumptions'!N49 -> 4829.0871 | ... P46: =(P18+P34)*'02 Assumptions'!P49 -> 5211.8692
B47: Nóminas y beneficios pendientes | C47: $M | E47: ='03 Historical'!E58 -> 1839 | F47: ='03 Historical'!F58 -> 1470 | G47: =G11*'02 Assumptions'!G52 -> 1707.2663 | H47: =H11*'02 Assumptions'!H52 -> 1914.3653 | I47: =I11*'02 Assumptions'!I52 -> 2118.2342 | J47: =J11*'02 Assumptions'!J52 -> 2294.0249 | K47: =K11*'02 Assumptions'!K52 -> 2459.2438 | L47: =L11*'02 Assumptions'!L52 -> 2613.9413 | M47: =M11*'02 Assumptions'!M52 -> 2757.3411 | N47: =N11*'02 Assumptions'!N52 -> 2883.0371 | ... P47: =P11*'02 Assumptions'!P52 -> 3111.5637
B48: Ingresos diferidos corrientes | C48: $M | E48: ='03 Historical'!E59 -> 358 | F48: ='03 Historical'!F59 -> 280 | G48: =G11*'02 Assumptions'!G50 -> 314.49642 | H48: =H11*'02 Assumptions'!H50 -> 352.64624 | I48: =I11*'02 Assumptions'!I50 -> 390.20104 | J48: =J11*'02 Assumptions'!J50 -> 422.58354 | K48: =K11*'02 Assumptions'!K50 -> 453.01859 | L48: =L11*'02 Assumptions'!L50 -> 481.5155 | M48: =M11*'02 Assumptions'!M50 -> 507.93126 | N48: =N11*'02 Assumptions'!N50 -> 531.08578 | ... P48: =P11*'02 Assumptions'!P50 -> 573.18279
B49: Otros pasivos corrientes operativos (excl. leases financieros) | C49: $M | E49: ='03 Historical'!E60-'03 Historical'!E119 -> 4156 | F49: ='03 Historical'!F60-'03 Historical'!F119 -> 4277 | G49: =G11*'02 Assumptions'!G53 -> 4358.0218 | H49: =H11*'02 Assumptions'!H53 -> 4886.6694 | I49: =I11*'02 Assumptions'!I53 -> 5407.0715 | J49: =J11*'02 Assumptions'!J53 -> 5855.8004 | K49: =K11*'02 Assumptions'!K53 -> 6277.5433 | L49: =L11*'02 Assumptions'!L53 -> 6672.4291 | M49: =M11*'02 Assumptions'!M53 -> 7038.476 | N49: =N11*'02 Assumptions'!N53 -> 7359.3315 | ... P49: =P11*'02 Assumptions'!P53 -> 7942.6758
B50: CAPITAL CIRCULANTE NETO (NWC) | C50: $M | E50: =E44+E45-E46-E47-E48-E49 -> 4132 | F50: =F44+F45-F46-F47-F48-F49 -> 5776 | G50: =G44+G45-G46-G47-G48-G49 -> 4722.3699 | H50: =H44+H45-H46-H47-H48-H49 -> 4872.4421 | I50: =I44+I45-I46-I47-I48-I49 -> 5458.5551 | J50: =J44+J45-J46-J47-J48-J49 -> 5943.9145 | K50: =K44+K45-K46-K47-K48-K49 -> 6372.0034 | L50: =L44+L45-L46-L47-L48-L49 -> 6772.8312 | ... P50: =P44+P45-P46-P47-P48-P49 -> 8062.1917
B51: Variación del NWC (ΔNWC) — positivo = consume caja | C51: $M | F51: =F50-E50 -> 1644 | G51: =G50-F50 -> -1053.6301 | H51: =H50-G50 -> 150.07214 | I51: =I50-H50 -> 586.11305 | J51: =J50-I50 -> 485.35935 | K51: =K50-J50 -> 428.08896 | L51: =L50-K50 -> 400.82777 | M51: =M50-L50 -> 371.55498 | ... P51: =P50-O50 -> 279.35248
B52: NWC / Ingresos | C52: % | E52: =E50/E11 -> 0.093306838 | F52: =F50/F11 -> 0.13464497 | G52: =G50/G11 -> 0.10510959 | H52: =H50/H11 -> 0.096717589 | I52: =I50/I11 -> 0.097923589 | J52: =J50/J11 -> 0.098459589 | K52: =K50/K11 -> 0.098459589 | L52: =L50/L11 -> 0.098459589 | ... P52: =P50/P11 -> 0.098459589
B54: IMPUESTOS SOBRE EL EBIT
B55: Tipo impositivo de caja | C55: % | D55: ='03 Historical'!D33 -> 0.021865325 | E55: ='03 Historical'!E33 -> 0.56242597 | F55: ='03 Historical'!F33 -> -0.39438327 | G55: ='02 Assumptions'!G57 -> 0.14 | H55: ='02 Assumptions'!H57 -> 0.145 | I55: ='02 Assumptions'!I57 -> 0.15 | J55: ='02 Assumptions'!J57 -> 0.155 | K55: ='02 Assumptions'!K57 -> 0.16 | L55: ='02 Assumptions'!L57 -> 0.165 | M55: ='02 Assumptions'!M57 -> 0.17 | N55: ='02 Assumptions'!N57 -> 0.17 | ... P55: ='02 Assumptions'!P57 -> 0.17
B56: Impuestos sobre el EBIT normalizado | C56: $M | D56: =D29*D55 -> 224.11958 | E56: =E29*E55 -> 6970.7074 | F56: =F29*F55 -> -3607.4238 | G56: =G29*G55 -> 1355.0339 | H56: =H29*H55 -> 1738.9297 | I56: =I29*I55 -> 2157.0615 | J56: =J29*J55 -> 2493.8959 | K56: =K29*K55 -> 2825.1454 | ... P56: =P29*P55 -> 3883.7228
B57: NOPAT (EBIT normalizado − impuestos) | C57: $M | D57: =D29-D56 -> 10025.88 | E57: =E29-E56 -> 5423.2926 | F57: =F29-F56 -> 12754.424 | G57: =G29-G56 -> 8323.7796 | H57: =H29-H56 -> 10253.689 | I57: =I29-I56 -> 12223.349 | J57: =J29-J56 -> 13595.755 | K57: =K29-K56 -> 14832.013 | ... P57: =P29-P56 -> 18961.705
B59: COMPROBACIONES DE COHERENCIA INTERNA
B60: Ingresos no-handset (IoT + Data Center + Automoción) | C60: $M | G60: =G7+G10 -> 18973.2 | H60: =H7+H10 -> 24121.716 | I60: =I7+I10 -> 28858.961 | J60: =J7+J10 -> 33000.673 | K60: =K7+K10 -> 36855.024 | L60: =L7+L10 -> 40423.166 | M60: =M7+M10 -> 43657.02 | N60: =N7+N10 -> 46414.597 | ... P60: =P7+P10 -> 50995.177
B61: Objetivo de la dirección FY2029 (no-handset) | C61: $M | F61: ='03 Historical'!F117 -> 40000
B62: Ingresos no-handset / objetivo FY2029 de la dirección | C62: % | G62: =G60/$F$61 -> 0.47433 | H62: =H60/$F$61 -> 0.6030429 | I62: =I60/$F$61 -> 0.72147402 | J62: =J60/$F$61 -> 0.82501682 | K62: =K60/$F$61 -> 0.9213756 | L62: =L60/$F$61 -> 1.0105792 | M62: =M60/$F$61 -> 1.0914255 | N62: =N60/$F$61 -> 1.1603649 | ... P62: =P60/$F$61 -> 1.2748794
B63: Capital invertido (PP&E + NWC + fondo de comercio + ROU leases) | C63: $M | E63: ='03 Historical'!E48+E50+'03 Historical'!E50+'03 Historical'!E49 -> 20915 | F63: ='03 Historical'!F48+F50+'03 Historical'!F50+'03 Historical'!F49 -> 26002 | G63: =G37+G50+'03 Historical'!$F$50+'03 Historical'!$F$49 -> 25586.159 | H63: =H37+H50+'03 Historical'!$F$50+'03 Historical'!$F$49 -> 26136.825 | I63: =I37+I50+'03 Historical'!$F$50+'03 Historical'!$F$49 -> 27017.53 | J63: =J37+J50+'03 Historical'!$F$50+'03 Historical'!$F$49 -> 27657.182 | K63: =K37+K50+'03 Historical'!$F$50+'03 Historical'!$F$49 -> 28321.219 | L63: =L37+L50+'03 Historical'!$F$50+'03 Historical'!$F$49 -> 29014.121 | M63: =M37+M50+'03 Historical'!$F$50+'03 Historical'!$F$49 -> 29713.477 | N63: =N37+N50+'03 Historical'!$F$50+'03 Historical'!$F$49 -> 30382.324 | ... P63: =P37+P50+'03 Historical'!$F$50+'03 Historical'!$F$49 -> 31675.199
B64: ROIC (NOPAT / capital invertido medio) | C64: % | F64: =F57/AVERAGE(E63:F63) -> 0.54370159 | G64: =G57/AVERAGE(F63:G63) -> 0.32270117 | H64: =H57/AVERAGE(G63:H63) -> 0.39648481 | I64: =I57/AVERAGE(H63:I63) -> 0.45991899 | J64: =J57/AVERAGE(I63:J63) -> 0.49733247 | K64: =K57/AVERAGE(J63:K63) -> 0.52991916 | L64: =L57/AVERAGE(K63:L63) -> 0.55408207 | M64: =M57/AVERAGE(L63:M63) -> 0.57223835 | ... P64: =P57/AVERAGE(O63:P63) -> 0.60462782
B65: Reinversión neta (Capex + ΔNWC − D&A) | C65: $M | G65: =G34+G51-G38 -> -845.84101 | H65: =H34+H51-H38 -> 200.66597 | I65: =I34+I51-I38 -> 600.70545 | J65: =J34+J51-J38 -> 429.65132 | K65: =K34+K51-K38 -> 524.03688 | L65: =L34+L51-L38 -> 592.90249 | M65: =M34+M51-M38 -> 699.35568 | N65: =N34+N51-N38 -> 668.84729 | ... P65: =P34+P51-P38 -> 628.49047
B66: Tasa de reinversión (reinversión / NOPAT) | C66: % | G66: =IFERROR(G65/G57,"n/a") -> -0.10161742 | H66: =IFERROR(H65/H57,"n/a") -> 0.019570125 | I66: =IFERROR(I65/I57,"n/a") -> 0.049144098 | J66: =IFERROR(J65/J57,"n/a") -> 0.031601873 | K66: =IFERROR(K65/K57,"n/a") -> 0.035331473 | L66: =IFERROR(L65/L57,"n/a") -> 0.037326458 | M66: =IFERROR(M65/M57,"n/a") -> 0.041620655 | N66: =IFERROR(N65/N57,"n/a") -> 0.038069576 | ... P66: =IFERROR(P65/P57,"n/a") -> 0.03314525
B67: Crecimiento implícito = tasa de reinversión × ROIC | C67: % | G67: =IFERROR(G66*G64,"n/a") -> -0.03279206 | H67: =IFERROR(H66*H64,"n/a") -> 0.0077592573 | I67: =IFERROR(I66*I64,"n/a") -> 0.022602304 | J67: =IFERROR(J66*J64,"n/a") -> 0.015716638 | K67: =IFERROR(K66*K64,"n/a") -> 0.018722824 | L67: =IFERROR(L66*L64,"n/a") -> 0.020681921 | M67: =IFERROR(M66*M64,"n/a") -> 0.023816935 | N67: =IFERROR(N66*N64,"n/a") -> 0.022259368 | ... P67: =IFERROR(P66*P64,"n/a") -> 0.020040541
B68: Crecimiento de ingresos proyectado | C68: % | G68: =G12 -> 0.047322952 | H68: =H12 -> 0.12130448 | I68: =I12 -> 0.10649423 | J68: =J12 -> 0.082989273 | K68: =K12 -> 0.072021386 | L68: =L12 -> 0.062904513 | M68: =M12 -> 0.054859626 | N68: =N12 -> 0.045585931 | ... P68: =P12 -> 0.03589339
B69: Diferencia (implícito − proyectado): brecha de coherencia, en p.p. | C69: % | G69: =IFERROR(G67-G68,"n/a") -> -0.080115012 | H69: =IFERROR(H67-H68,"n/a") -> -0.11354522 | I69: =IFERROR(I67-I68,"n/a") -> -0.083891931 | J69: =IFERROR(J67-J68,"n/a") -> -0.067272635 | K69: =IFERROR(K67-K68,"n/a") -> -0.053298561 | L69: =IFERROR(L67-L68,"n/a") -> -0.042222591 | M69: =IFERROR(M67-M68,"n/a") -> -0.031042691 | N69: =IFERROR(N67-N68,"n/a") -> -0.023326563 | ... P69: =IFERROR(P67-P68,"n/a") -> -0.01585285
B70: FCFF (calculado en '06 DCF') | C70: $M | G70: ='06 DCF'!G15 -> 9069.6206 | H70: ='06 DCF'!H15 -> 9953.0229 | I70: ='06 DCF'!I15 -> 11522.643 | J70: ='06 DCF'!J15 -> 13066.103 | K70: ='06 DCF'!K15 -> 14207.977 | L70: ='06 DCF'!L15 -> 15191.339 | M70: ='06 DCF'!M15 -> 16003.736 | N70: ='06 DCF'!N15 -> 16800.229 | ... P70: ='06 DCF'!P15 -> 18233.215
B71: De la cual: variación de proveedores ligada al capex (solape con el capex de caja) | C71: $M | G71: ='02 Assumptions'!G49*(G34-F34) -> -11.019798 | H71: ='02 Assumptions'!H49*(H34-G34) -> -14.391249 | I71: ='02 Assumptions'!I49*(I34-H34) -> -2.5598221 | J71: ='02 Assumptions'!J49*(J34-I34) -> -11.281443 | K71: ='02 Assumptions'!K49*(K34-J34) -> 17.478415 | L71: ='02 Assumptions'!L49*(L34-K34) -> 16.36537 | M71: ='02 Assumptions'!M49*(M34-L34) -> 15.170194 | N71: ='02 Assumptions'!N49*(N34-M34) -> 13.29731 | ... P71: ='02 Assumptions'!P49*(P34-O34) -> 11.405664
B72: ADVERTENCIA METODOLÓGICA: los proveedores se modelan sobre (coste de ingresos + capex) porque así reproducen el saldo real del balance (10.977 en FY2026, impulsado por equipamiento de centros de datos). Pero el capex del FCFF es capex de CAJA, por lo que la parte de la variación de proveedores atribuible al capex se solapa con él. La fila 71 cuantifica ese solape y el control 68 de '13 Checks' vigila que no supere el 5% del FCFF. Si lo supera, hay que separar proveedores operativos (sobre DPO del coste de ingresos) de proveedores ligados a capex y excluir estos últimos del circulante.

Sheet 05 Three Statement
A1: MODELO DE TRES ESTADOS INTEGRADO FY2027E–FY2036E — QUALCOMM INCORPORATED
A2: Sirve para verificar la CONSISTENCIA CONTABLE del forecast (cuadre de balance y de caja). NO alimenta el DCF: el DCF es un FCFF construido sobre '04 Operating Model'.
B4: Partida | C4: Unidad | D4: ='00 Panel del Analista'!D14 -> FY2024A | E4: ='00 Panel del Analista'!E14 -> FY2025A | F4: ='00 Panel del Analista'!F14 -> FY2026E | G4: ='00 Panel del Analista'!G14 -> FY2027E | H4: ='00 Panel del Analista'!H14 -> FY2028E | I4: ='00 Panel del Analista'!I14 -> FY2029E | J4: ='00 Panel del Analista'!J14 -> FY2030E | K4: ='00 Panel del Analista'!K14 -> FY2031E | ... P4: ='00 Panel del Analista'!P14 -> FY2036E
B6: CUENTA DE RESULTADOS
B7: Ingresos | C7: $M | G7: ='04 Operating Model'!G11 -> 44928.06 | H7: ='04 Operating Model'!H11 -> 50378.035 | I7: ='04 Operating Model'!I11 -> 55743.005 | J7: ='04 Operating Model'!J11 -> 60369.077 | K7: ='04 Operating Model'!K11 -> 64716.941 | L7: ='04 Operating Model'!L11 -> 68787.929 | M7: ='04 Operating Model'!M11 -> 72561.609 | N7: ='04 Operating Model'!N11 -> 75869.397 | ... P7: ='04 Operating Model'!P11 -> 81883.255
B8: Coste de los ingresos | C8: $M | G8: ='04 Operating Model'!G18 -> 20442.267 | H8: ='04 Operating Model'!H18 -> 22670.116 | I8: ='04 Operating Model'!I18 -> 24805.637 | J8: ='04 Operating Model'!J18 -> 26864.239 | K8: ='04 Operating Model'!K18 -> 28799.039 | L8: ='04 Operating Model'!L18 -> 30610.628 | M8: ='04 Operating Model'!M18 -> 32289.916 | N8: ='04 Operating Model'!N18 -> 33761.882 | ... P8: ='04 Operating Model'!P18 -> 36438.049
B9: Margen bruto | C9: $M | G9: =G7-G8 -> 24485.793 | H9: =H7-H8 -> 27707.919 | I9: =I7-I8 -> 30937.368 | J9: =J7-J8 -> 33504.837 | K9: =K7-K8 -> 35917.902 | L9: =L7-L8 -> 38177.3 | M9: =M7-M8 -> 40271.693 | N9: =N7-N8 -> 42107.515 | ... P9: =P7-P8 -> 45445.207
B10: Gastos operativos | C10: $M | G10: ='04 Operating Model'!G26 -> 14906.979 | H10: ='04 Operating Model'!H26 -> 15815.301 | I10: ='04 Operating Model'!I26 -> 16656.957 | J10: ='04 Operating Model'!J26 -> 17515.187 | K10: ='04 Operating Model'!K26 -> 18360.744 | L10: ='04 Operating Model'!L26 -> 19254.256 | M10: ='04 Operating Model'!M26 -> 20127.004 | N10: ='04 Operating Model'!N26 -> 21039.954 | ... P10: ='04 Operating Model'!P26 -> 22699.778
B11: EBIT reportado | C11: $M | G11: =G9-G10 -> 9578.8135 | H11: =H9-H10 -> 11892.619 | I11: =I9-I10 -> 14280.41 | J11: =J9-J10 -> 15989.651 | K11: =K9-K10 -> 17557.159 | L11: =L9-L10 -> 18923.044 | M11: =M9-M10 -> 20144.689 | N11: =N9-N10 -> 21067.562 | ... P11: =P9-P10 -> 22745.428
B12: (−) Gasto por intereses | C12: $M | G12: =G26 -> 687.15 | H12: =H26 -> 540.86704 | I12: =I26 -> 381.58908 | J12: =J26 -> 175.87719 | K12: =K26 -> 0 | L12: =L26 -> 0 | M12: =M26 -> 0 | N12: =N26 -> 0 | ... P12: =P26 -> 0
B13: (+) Resultado no operativo, neto (no proyectado) | C13: $M | G13: =0 -> 0 | H13: =0 -> 0 | I13: =0 -> 0 | J13: =0 -> 0 | K13: =0 -> 0 | L13: =0 -> 0 | M13: =0 -> 0 | N13: =0 -> 0 | ... P13: =0 -> 0
B14: Beneficio antes de impuestos | C14: $M | G14: =G11-G12+G13 -> 8891.6635 | H14: =H11-H12+H13 -> 11351.751 | I14: =I11-I12+I13 -> 13898.821 | J14: =J11-J12+J13 -> 15813.773 | K14: =K11-K12+K13 -> 17557.159 | L14: =L11-L12+L13 -> 18923.044 | M14: =M11-M12+M13 -> 20144.689 | N14: =N11-N12+N13 -> 21067.562 | ... P14: =P11-P12+P13 -> 22745.428
B15: (−) Impuestos | C15: $M | G15: =G14*'04 Operating Model'!G55 -> 1244.8329 | H15: =H14*'04 Operating Model'!H55 -> 1646.004 | I15: =I14*'04 Operating Model'!I55 -> 2084.8232 | J15: =J14*'04 Operating Model'!J55 -> 2451.1349 | K15: =K14*'04 Operating Model'!K55 -> 2809.1454 | L15: =L14*'04 Operating Model'!L55 -> 3122.3023 | M15: =M14*'04 Operating Model'!M55 -> 3424.5971 | N15: =N14*'04 Operating Model'!N55 -> 3581.4855 | ... P15: =P14*'04 Operating Model'!P55 -> 3866.7228
B16: BENEFICIO NETO | C16: $M | G16: =G14-G15 -> 7646.8306 | H16: =H14-H15 -> 9705.7475 | I16: =I14-I15 -> 11813.998 | J16: =J14-J15 -> 13362.639 | K16: =K14-K15 -> 14748.013 | L16: =L14-L15 -> 15800.742 | M16: =M14-M15 -> 16720.092 | N16: =N14-N15 -> 17486.076 | ... P16: =P14-P15 -> 18878.705
B17: (−) Dividendos de preferentes | C17: $M | G17: =G93 -> 0 | H17: =H93 -> 0 | I17: =I93 -> 0 | J17: =J93 -> 0 | K17: =K93 -> 0 | L17: =L93 -> 0 | M17: =M93 -> 0 | N17: =N93 -> 0 | ... P17: =P93 -> 0
B18: Beneficio atribuible a ordinarias | C18: $M | G18: =G16-G17 -> 7646.8306 | H18: =H16-H17 -> 9705.7475 | I18: =I16-I17 -> 11813.998 | J18: =J16-J17 -> 13362.639 | K18: =K16-K17 -> 14748.013 | L18: =L16-L17 -> 15800.742 | M18: =M16-M17 -> 16720.092 | N18: =N16-N17 -> 17486.076 | ... P18: =P16-P17 -> 18878.705
B20: ESQUEMA DE DEUDA (interés sobre deuda inicial: sin circularidad)
B21: Deuda inicial | C21: $M | G21: =F24 -> 15270 | H21: =G24 -> 12019.268 | I21: =H24 -> 8479.7573 | J21: =I24 -> 3908.3819 | K21: =J24 -> 0 | L21: =K24 -> 0 | M21: =L24 -> 0 | N21: =M24 -> 0 | ... P21: =O24 -> 0
B22: (+) Nueva deuda emitida | C22: $M | G22: =G32 -> 0 | H22: =H32 -> 0 | I22: =I32 -> 0 | J22: =J32 -> 0 | K22: =K32 -> 0 | L22: =L32 -> 0 | M22: =M32 -> 0 | N22: =N32 -> 0 | ... P22: =P32 -> 0
B23: (−) Repago de deuda | C23: $M | G23: =G34 -> 3250.7325 | H23: =H34 -> 3539.5103 | I23: =I34 -> 4571.3753 | J23: =J34 -> 3908.3819 | K23: =K34 -> 0 | L23: =L34 -> 0 | M23: =M34 -> 0 | N23: =N34 -> 0 | ... P23: =P34 -> 0
B24: Deuda final | C24: $M | F24: ='02 Assumptions'!$C$70 -> 15270 | G24: =G21+G22-G23 -> 12019.268 | H24: =H21+H22-H23 -> 8479.7573 | I24: =I21+I22-I23 -> 3908.3819 | J24: =J21+J22-J23 -> 0 | K24: =K21+K22-K23 -> 0 | L24: =L21+L22-L23 -> 0 | M24: =M21+M22-M23 -> 0 | N24: =N21+N22-N23 -> 0 | ... P24: =P21+P22-P23 -> 0
B25: Tipo de interés medio | C25: % | G25: ='02 Assumptions'!$C$98 -> 0.045 | H25: ='02 Assumptions'!$C$98 -> 0.045 | I25: ='02 Assumptions'!$C$98 -> 0.045 | J25: ='02 Assumptions'!$C$98 -> 0.045 | K25: ='02 Assumptions'!$C$98 -> 0.045 | L25: ='02 Assumptions'!$C$98 -> 0.045 | M25: ='02 Assumptions'!$C$98 -> 0.045 | N25: ='02 Assumptions'!$C$98 -> 0.045 | ... P25: ='02 Assumptions'!$C$98 -> 0.045
B26: Gasto por intereses = deuda inicial × tipo | C26: $M | G26: =G21*G25 -> 687.15 | H26: =H21*H25 -> 540.86704 | I26: =I21*I25 -> 381.58908 | J26: =J21*J25 -> 175.87719 | K26: =K21*K25 -> 0 | L26: =L21*L25 -> 0 | M26: =M21*M25 -> 0 | N26: =N21*N25 -> 0 | ... P26: =P21*P25 -> 0
B28: POLÍTICA DE FINANCIACIÓN (determina caja y deuda)
B29: Caja inicial | C29: $M | G29: =F35 -> 4533 | H29: =G35 -> 4149.2937 | I29: =H35 -> 4547.071 | J29: =I35 -> 5686.2355 | K29: =J35 -> 9190.9367 | L29: =K35 -> 17829.98 | M29: =L35 -> 27409.971 | N29: =M35 -> 37720.633 | ... P29: =O35 -> 60251.269
B30: Caja preliminar = inicial + CFO + CFI − dividendos − recompras | C30: $M | G30: =G29+G77+G79-G82-G83-G84 -> 7400.0261 | H30: =H29+H77+H79-H82-H83-H84 -> 8086.5812 | I30: =I29+I77+I79-I82-I83-I84 -> 10257.611 | J30: =J29+J77+J79-J82-J83-J84 -> 13099.319 | K30: =K29+K77+K79-K82-K83-K84 -> 17829.98 | L30: =L29+L77+L79-L82-L83-L84 -> 27409.971 | M30: =M29+M77+M79-M82-M83-M84 -> 37720.633 | N30: =N29+N77+N79-N82-N83-N84 -> 48695.916 | ... P30: =P29+P77+P79-P82-P83-P84 -> 72216.535
B31: Caja mínima requerida | C31: $M | G31: ='02 Assumptions'!$C$68*G7 -> 898.5612 | H31: ='02 Assumptions'!$C$68*H7 -> 1007.5607 | I31: ='02 Assumptions'!$C$68*I7 -> 1114.8601 | J31: ='02 Assumptions'!$C$68*J7 -> 1207.3815 | K31: ='02 Assumptions'!$C$68*K7 -> 1294.3388 | L31: ='02 Assumptions'!$C$68*L7 -> 1375.7586 | M31: ='02 Assumptions'!$C$68*M7 -> 1451.2322 | N31: ='02 Assumptions'!$C$68*N7 -> 1517.3879 | ... P31: ='02 Assumptions'!$C$68*P7 -> 1637.6651
B32: Nueva deuda necesaria = MAX(0; mínima − preliminar) | C32: $M | G32: =MAX(0,G31-G30) -> 0 | H32: =MAX(0,H31-H30) -> 0 | I32: =MAX(0,I31-I30) -> 0 | J32: =MAX(0,J31-J30) -> 0 | K32: =MAX(0,K31-K30) -> 0 | L32: =MAX(0,L31-L30) -> 0 | M32: =MAX(0,M31-M30) -> 0 | N32: =MAX(0,N31-N30) -> 0 | ... P32: =MAX(0,P31-P30) -> 0
B33: Excedente sobre la caja mínima | C33: $M | G33: =MAX(0,G30-G31) -> 6501.4649 | H33: =MAX(0,H30-H31) -> 7079.0205 | I33: =MAX(0,I30-I31) -> 9142.7507 | J33: =MAX(0,J30-J31) -> 11891.937 | K33: =MAX(0,K30-K31) -> 16535.641 | L33: =MAX(0,L30-L31) -> 26034.212 | M33: =MAX(0,M30-M31) -> 36269.401 | N33: =MAX(0,N30-N31) -> 47178.528 | ... P33: =MAX(0,P30-P31) -> 70578.87
B34: Repago efectivo = MIN(deuda inicial; excedente × %) | C34: $M | G34: =MIN(G21,G33*'02 Assumptions'!$C$97) -> 3250.7325 | H34: =MIN(H21,H33*'02 Assumptions'!$C$97) -> 3539.5103 | I34: =MIN(I21,I33*'02 Assumptions'!$C$97) -> 4571.3753 | J34: =MIN(J21,J33*'02 Assumptions'!$C$97) -> 3908.3819 | K34: =MIN(K21,K33*'02 Assumptions'!$C$97) -> 0 | L34: =MIN(L21,L33*'02 Assumptions'!$C$97) -> 0 | M34: =MIN(M21,M33*'02 Assumptions'!$C$97) -> 0 | N34: =MIN(N21,N33*'02 Assumptions'!$C$97) -> 0 | ... P34: =MIN(P21,P33*'02 Assumptions'!$C$97) -> 0
B35: Caja final | C35: $M | F35: ='02 Assumptions'!$C$72 -> 4533 | G35: =G30+G32-G34 -> 4149.2937 | H35: =H30+H32-H34 -> 4547.071 | I35: =I30+I32-I34 -> 5686.2355 | J35: =J30+J32-J34 -> 9190.9367 | K35: =K30+K32-K34 -> 17829.98 | L35: =L30+L32-L34 -> 27409.971 | M35: =M30+M32-M34 -> 37720.633 | N35: =N30+N32-N34 -> 48695.916 | ... P35: =P30+P32-P34 -> 72216.535
B37: BALANCE
B38: Caja y equivalentes | C38: $M | G38: =G35 -> 4149.2937 | H38: =H35 -> 4547.071 | I38: =I35 -> 5686.2355 | J38: =J35 -> 9190.9367 | K38: =K35 -> 17829.98 | L38: =L35 -> 27409.971 | M38: =M35 -> 37720.633 | N38: =N35 -> 48695.916 | ... P38: =P35 -> 72216.535
B39: Valores negociables | C39: $M | G39: ='02 Assumptions'!$C$73 -> 3771 | H39: ='02 Assumptions'!$C$73 -> 3771 | I39: ='02 Assumptions'!$C$73 -> 3771 | J39: ='02 Assumptions'!$C$73 -> 3771 | K39: ='02 Assumptions'!$C$73 -> 3771 | L39: ='02 Assumptions'!$C$73 -> 3771 | M39: ='02 Assumptions'!$C$73 -> 3771 | N39: ='02 Assumptions'!$C$73 -> 3771 | ... P39: ='02 Assumptions'!$C$73 -> 3771
B40: Clientes (AR) | C40: $M | G40: ='04 Operating Model'!G44 -> 4677.4419 | H40: ='04 Operating Model'!H44 -> 5244.8365 | I40: ='04 Operating Model'!I44 -> 5803.3813 | J40: ='04 Operating Model'!J44 -> 6284.9997 | K40: ='04 Operating Model'!K44 -> 6737.6541 | L40: ='04 Operating Model'!L44 -> 7161.483 | M40: ='04 Operating Model'!M44 -> 7554.3593 | N40: ='04 Operating Model'!N44 -> 7898.7318 | ... P40: ='04 Operating Model'!P44 -> 8524.832
B41: Otros activos corrientes | C41: $M | G41: ='04 Operating Model'!G45 -> 9434.8926 | H41: ='04 Operating Model'!H45 -> 10075.607 | I41: ='04 Operating Model'!I45 -> 11148.601 | J41: ='04 Operating Model'!J45 -> 12073.815 | K41: ='04 Operating Model'!K45 -> 12943.388 | L41: ='04 Operating Model'!L45 -> 13757.586 | M41: ='04 Operating Model'!M45 -> 14512.322 | N41: ='04 Operating Model'!N45 -> 15173.879 | ... P41: ='04 Operating Model'!P45 -> 16376.651
B42: PP&E neto | C42: $M | G42: ='04 Operating Model'!G37 -> 5854.7891 | H42: ='04 Operating Model'!H37 -> 6255.3829 | I42: ='04 Operating Model'!I37 -> 6549.9753 | J42: ='04 Operating Model'!J37 -> 6704.2673 | K42: ='04 Operating Model'!K37 -> 6940.2152 | L42: ='04 Operating Model'!L37 -> 7232.2899 | M42: ='04 Operating Model'!M37 -> 7560.0906 | N42: ='04 Operating Model'!N37 -> 7903.2544 | ... P42: ='04 Operating Model'!P37 -> 8604.0076
B43: ROU — leases operativos | C43: $M | G43: ='03 Historical'!$F$49 -> 735 | H43: ='03 Historical'!$F$49 -> 735 | I43: ='03 Historical'!$F$49 -> 735 | J43: ='03 Historical'!$F$49 -> 735 | K43: ='03 Historical'!$F$49 -> 735 | L43: ='03 Historical'!$F$49 -> 735 | M43: ='03 Historical'!$F$49 -> 735 | N43: ='03 Historical'!$F$49 -> 735 | ... P43: ='03 Historical'!$F$49 -> 735
B44: Fondo de comercio | C44: $M | G44: ='03 Historical'!$F$50 -> 14274 | H44: ='03 Historical'!$F$50 -> 14274 | I44: ='03 Historical'!$F$50 -> 14274 | J44: ='03 Historical'!$F$50 -> 14274 | K44: ='03 Historical'!$F$50 -> 14274 | L44: ='03 Historical'!$F$50 -> 14274 | M44: ='03 Historical'!$F$50 -> 14274 | N44: ='03 Historical'!$F$50 -> 14274 | ... P44: ='03 Historical'!$F$50 -> 14274
B45: Intangibles adquiridos, neto | C45: $M | F45: ='02 Assumptions'!$C$101 -> 1510 | G45: =F45-'04 Operating Model'!G24 -> 1080 | H45: =G45-'04 Operating Model'!H24 -> 730 | I45: =H45-'04 Operating Model'!I24 -> 450 | J45: =I45-'04 Operating Model'!J24 -> 240 | K45: =J45-'04 Operating Model'!K24 -> 100 | L45: =K45-'04 Operating Model'!L24 -> 0 | M45: =L45-'04 Operating Model'!M24 -> 0 | N45: =M45-'04 Operating Model'!N24 -> 0 | ... P45: =O45-'04 Operating Model'!P24 -> 0
B46: Activos por impuesto diferido | C46: $M | G46: ='03 Historical'!$F$51 -> 5679 | H46: ='03 Historical'!$F$51 -> 5679 | I46: ='03 Historical'!$F$51 -> 5679 | J46: ='03 Historical'!$F$51 -> 5679 | K46: ='03 Historical'!$F$51 -> 5679 | L46: ='03 Historical'!$F$51 -> 5679 | M46: ='03 Historical'!$F$51 -> 5679 | N46: ='03 Historical'!$F$51 -> 5679 | ... P46: ='03 Historical'!$F$51 -> 5679
B47: Otros activos no corrientes (netos de intangibles) | C47: $M | G47: ='02 Assumptions'!$C$102 -> 6948 | H47: ='02 Assumptions'!$C$102 -> 6948 | I47: ='02 Assumptions'!$C$102 -> 6948 | J47: ='02 Assumptions'!$C$102 -> 6948 | K47: ='02 Assumptions'!$C$102 -> 6948 | L47: ='02 Assumptions'!$C$102 -> 6948 | M47: ='02 Assumptions'!$C$102 -> 6948 | N47: ='02 Assumptions'!$C$102 -> 6948 | ... P47: ='02 Assumptions'!$C$102 -> 6948
B48: TOTAL ACTIVO | C48: $M | G48: =SUM(G38:G47) -> 56603.417 | H48: =SUM(H38:H47) -> 58259.897 | I48: =SUM(I38:I47) -> 61045.193 | J48: =SUM(J38:J47) -> 65901.019 | K48: =SUM(K38:K47) -> 75958.238 | L48: =SUM(L38:L47) -> 86968.329 | M48: =SUM(M38:M47) -> 98754.404 | N48: =SUM(N38:N47) -> 111078.78 | ... P48: =SUM(P38:P47) -> 137129.03
B49: Proveedores | C49: $M | G49: ='04 Operating Model'!G46 -> 3010.18 | H49: ='04 Operating Model'!H46 -> 3294.3205 | I49: ='04 Operating Model'!I46 -> 3577.9205 | J49: ='04 Operating Model'!J46 -> 3842.4917 | K49: ='04 Operating Model'!K46 -> 4119.2333 | L49: ='04 Operating Model'!L46 -> 4378.3517 | M49: ='04 Operating Model'!M46 -> 4618.5464 | N49: ='04 Operating Model'!N46 -> 4829.0871 | ... P49: ='04 Operating Model'!P46 -> 5211.8692
B50: Remuneraciones pendientes | C50: $M | G50: ='04 Operating Model'!G47 -> 1707.2663 | H50: ='04 Operating Model'!H47 -> 1914.3653 | I50: ='04 Operating Model'!I47 -> 2118.2342 | J50: ='04 Operating Model'!J47 -> 2294.0249 | K50: ='04 Operating Model'!K47 -> 2459.2438 | L50: ='04 Operating Model'!L47 -> 2613.9413 | M50: ='04 Operating Model'!M47 -> 2757.3411 | N50: ='04 Operating Model'!N47 -> 2883.0371 | ... P50: ='04 Operating Model'!P47 -> 3111.5637
B51: Ingresos diferidos corrientes | C51: $M | G51: ='04 Operating Model'!G48 -> 314.49642 | H51: ='04 Operating Model'!H48 -> 352.64624 | I51: ='04 Operating Model'!I48 -> 390.20104 | J51: ='04 Operating Model'!J48 -> 422.58354 | K51: ='04 Operating Model'!K48 -> 453.01859 | L51: ='04 Operating Model'!L48 -> 481.5155 | M51: ='04 Operating Model'!M48 -> 507.93126 | N51: ='04 Operating Model'!N48 -> 531.08578 | ... P51: ='04 Operating Model'!P48 -> 573.18279
B52: Otros pasivos corrientes operativos | C52: $M | G52: ='04 Operating Model'!G49 -> 4358.0218 | H52: ='04 Operating Model'!H49 -> 4886.6694 | I52: ='04 Operating Model'!I49 -> 5407.0715 | J52: ='04 Operating Model'!J49 -> 5855.8004 | K52: ='04 Operating Model'!K49 -> 6277.5433 | L52: ='04 Operating Model'!L49 -> 6672.4291 | M52: ='04 Operating Model'!M49 -> 7038.476 | N52: ='04 Operating Model'!N49 -> 7359.3315 | ... P52: ='04 Operating Model'!P49 -> 7942.6758
B53: Deuda financiera total | C53: $M | G53: =G24 -> 12019.268 | H53: =H24 -> 8479.7573 | I53: =I24 -> 3908.3819 | J53: =J24 -> 0 | K53: =K24 -> 0 | L53: =L24 -> 0 | M53: =M24 -> 0 | N53: =N24 -> 0 | ... P53: =P24 -> 0
B54: Leases financieros | C54: $M | G54: ='02 Assumptions'!$C$71 -> 0 | H54: ='02 Assumptions'!$C$71 -> 0 | I54: ='02 Assumptions'!$C$71 -> 0 | J54: ='02 Assumptions'!$C$71 -> 0 | K54: ='02 Assumptions'!$C$71 -> 0 | L54: ='02 Assumptions'!$C$71 -> 0 | M54: ='02 Assumptions'!$C$71 -> 0 | N54: ='02 Assumptions'!$C$71 -> 0 | ... P54: ='02 Assumptions'!$C$71 -> 0
B55: Pasivo por leases operativos — NO corriente (el corriente va en otros pasivos corrientes) | C55: $M | G55: ='03 Historical'!$F$64 -> 730 | H55: ='03 Historical'!$F$64 -> 730 | I55: ='03 Historical'!$F$64 -> 730 | J55: ='03 Historical'!$F$64 -> 730 | K55: ='03 Historical'!$F$64 -> 730 | L55: ='03 Historical'!$F$64 -> 730 | M55: ='03 Historical'!$F$64 -> 730 | N55: ='03 Historical'!$F$64 -> 730 | ... P55: ='03 Historical'!$F$64 -> 730
B56: Impuestos a pagar no corrientes | C56: $M | G56: ='03 Historical'!$F$63 -> 0 | H56: ='03 Historical'!$F$63 -> 0 | I56: ='03 Historical'!$F$63 -> 0 | J56: ='03 Historical'!$F$63 -> 0 | K56: ='03 Historical'!$F$63 -> 0 | L56: ='03 Historical'!$F$63 -> 0 | M56: ='03 Historical'!$F$63 -> 0 | N56: ='03 Historical'!$F$63 -> 0 | ... P56: ='03 Historical'!$F$63 -> 0
B57: Otros pasivos no corrientes (netos del lease financiero no corriente) | C57: $M | G57: ='03 Historical'!$F$65-('03 Historical'!$F$112-'03 Historical'!$F$119) -> 4785 | H57: ='03 Historical'!$F$65-('03 Historical'!$F$112-'03 Historical'!$F$119) -> 4785 | I57: ='03 Historical'!$F$65-('03 Historical'!$F$112-'03 Historical'!$F$119) -> 4785 | J57: ='03 Historical'!$F$65-('03 Historical'!$F$112-'03 Historical'!$F$119) -> 4785 | K57: ='03 Historical'!$F$65-('03 Historical'!$F$112-'03 Historical'!$F$119) -> 4785 | L57: ='03 Historical'!$F$65-('03 Historical'!$F$112-'03 Historical'!$F$119) -> 4785 | M57: ='03 Historical'!$F$65-('03 Historical'!$F$112-'03 Historical'!$F$119) -> 4785 | N57: ='03 Historical'!$F$65-('03 Historical'!$F$112-'03 Historical'!$F$119) -> 4785 | ... P57: ='03 Historical'!$F$65-('03 Historical'!$F$112-'03 Historical'!$F$119) -> 4785
B58: TOTAL PASIVO | C58: $M | G58: =SUM(G49:G57) -> 26924.232 | H58: =SUM(H49:H57) -> 24442.759 | I58: =SUM(I49:I57) -> 20916.809 | J58: =SUM(J49:J57) -> 17929.901 | K58: =SUM(K49:K57) -> 18824.039 | L58: =SUM(L49:L57) -> 19661.238 | M58: =SUM(M49:M57) -> 20437.295 | N58: =SUM(N49:N57) -> 21117.542 | ... P58: =SUM(P49:P57) -> 22354.291
B59: Patrimonio neto total (incluye preferentes y minoritarios) | C59: $M | G59: =G70 -> 29679.185 | H59: =H70 -> 33817.139 | I59: =I70 -> 40128.384 | J59: =J70 -> 47971.118 | K59: =K70 -> 57134.199 | L59: =L70 -> 67307.092 | M59: =M70 -> 78317.11 | N59: =N70 -> 89961.24 | ... P59: =P70 -> 114774.73
B60: TOTAL PASIVO Y PATRIMONIO | C60: $M | G60: =G58+G59 -> 56603.417 | H60: =H58+H59 -> 58259.897 | I60: =I58+I59 -> 61045.193 | J60: =J58+J59 -> 65901.019 | K60: =K58+K59 -> 75958.238 | L60: =L58+L59 -> 86968.329 | M60: =M58+M59 -> 98754.404 | N60: =N58+N59 -> 111078.78 | ... P60: =P58+P59 -> 137129.03
B61: CHECK: Activo − Pasivo y Patrimonio (debe ser 0) | C61: $M | G61: =G48-G60 -> 0 | H61: =H48-H60 -> 0 | I61: =I48-I60 -> 0 | J61: =J48-J60 -> 0 | K61: =K48-K60 -> 0 | L61: =L48-L60 -> 0 | M61: =M48-M60 -> 0 | N61: =N48-N60 -> 0 | ... P61: =P48-P60 -> 0
B63: PATRIMONIO — ROLL-FORWARD
B64: Patrimonio inicial | C64: $M | G64: =F70 -> 27658 | H64: =G70 -> 29679.185 | I64: =H70 -> 33817.139 | J64: =I70 -> 40128.384 | K64: =J70 -> 47971.118 | L64: =K70 -> 57134.199 | M64: =L70 -> 67307.092 | N64: =M70 -> 78317.11 | ... P64: =O70 -> 102180.98
B65: (+) Beneficio neto | C65: $M | G65: =G16 -> 7646.8306 | H65: =H16 -> 9705.7475 | I65: =I16 -> 11813.998 | J65: =J16 -> 13362.639 | K65: =K16 -> 14748.013 | L65: =L16 -> 15800.742 | M65: =M16 -> 16720.092 | N65: =N16 -> 17486.076 | ... P65: =P16 -> 18878.705
B66: (+) Retribución en acciones (SBC) | C66: $M | G66: =G75 -> 3369.6045 | H66: =H75 -> 3627.2185 | I66: =I75 -> 3902.0104 | J66: =J75 -> 4105.0972 | K66: =K75 -> 4271.3181 | L66: =L75 -> 4471.2154 | M66: =M75 -> 4643.943 | N66: =N75 -> 4779.772 | ... P66: =P75 -> 4912.9953
B67: (−) Dividendos ordinarios | C67: $M | G67: =G92 -> 3995.25 | H67: =H92 -> 4195.0125 | I67: =I92 -> 4404.7631 | J67: =J92 -> 4625.0013 | K67: =K92 -> 4856.2513 | L67: =L92 -> 5099.0639 | M67: =M92 -> 5354.0171 | N67: =N92 -> 5621.718 | ... P67: =P92 -> 6197.9441
B68: (−) Dividendos de preferentes | C68: $M | G68: =G93 -> 0 | H68: =H93 -> 0 | I68: =I93 -> 0 | J68: =J93 -> 0 | K68: =K93 -> 0 | L68: =L93 -> 0 | M68: =M93 -> 0 | N68: =N93 -> 0 | ... P68: =P93 -> 0
B69: (−) Recompras netas de acciones | C69: $M | G69: ='02 Assumptions'!$C$100 -> 5000 | H69: ='02 Assumptions'!$C$100 -> 5000 | I69: ='02 Assumptions'!$C$100 -> 5000 | J69: ='02 Assumptions'!$C$100 -> 5000 | K69: ='02 Assumptions'!$C$100 -> 5000 | L69: ='02 Assumptions'!$C$100 -> 5000 | M69: ='02 Assumptions'!$C$100 -> 5000 | N69: ='02 Assumptions'!$C$100 -> 5000 | ... P69: ='02 Assumptions'!$C$100 -> 5000
B70: Patrimonio final | C70: $M | F70: ='03 Historical'!$F$73 -> 27658 | G70: =G64+G65+G66-G67-G68-G69 -> 29679.185 | H70: =H64+H65+H66-H67-H68-H69 -> 33817.139 | I70: =I64+I65+I66-I67-I68-I69 -> 40128.384 | J70: =J64+J65+J66-J67-J68-J69 -> 47971.118 | K70: =K64+K65+K66-K67-K68-K69 -> 57134.199 | L70: =L64+L65+L66-L67-L68-L69 -> 67307.092 | M70: =M64+M65+M66-M67-M68-M69 -> 78317.11 | N70: =N64+N65+N66-N67-N68-N69 -> 89961.24 | ... P70: =P64+P65+P66-P67-P68-P69 -> 114774.73
B72: ESTADO DE FLUJOS DE CAJA
B73: Beneficio neto | C73: $M | G73: =G16 -> 7646.8306 | H73: =H16 -> 9705.7475 | I73: =I16 -> 11813.998 | J73: =J16 -> 13362.639 | K73: =K16 -> 14748.013 | L73: =L16 -> 15800.742 | M73: =M16 -> 16720.092 | N73: =N16 -> 17486.076 | ... P73: =P16 -> 18878.705
B74: (+) D&A | C74: $M | G74: ='04 Operating Model'!G38 -> 1813.9736 | H74: ='04 Operating Model'!H38 -> 1863.7715 | I74: ='04 Operating Model'!I38 -> 1880.6698 | J74: ='04 Operating Model'!J38 -> 1866.7803 | K74: ='04 Operating Model'!K38 -> 1845.5603 | L74: ='04 Operating Model'!L38 -> 1871.5631 | M74: ='04 Operating Model'!M38 -> 1849.0476 | N74: ='04 Operating Model'!N38 -> 1932.9181 | ... P74: ='04 Operating Model'!P38 -> 2107.3597
B75: (+) SBC | C75: $M | G75: =G7*'02 Assumptions'!G95 -> 3369.6045 | H75: =H7*'02 Assumptions'!H95 -> 3627.2185 | I75: =I7*'02 Assumptions'!I95 -> 3902.0104 | J75: =J7*'02 Assumptions'!J95 -> 4105.0972 | K75: =K7*'02 Assumptions'!K95 -> 4271.3181 | L75: =L7*'02 Assumptions'!L95 -> 4471.2154 | M75: =M7*'02 Assumptions'!M95 -> 4643.943 | N75: =N7*'02 Assumptions'!N95 -> 4779.772 | ... P75: =P7*'02 Assumptions'!P95 -> 4912.9953
B76: (−) Variación del capital circulante neto | C76: $M | G76: =-'04 Operating Model'!G51 -> 1053.6301 | H76: =-'04 Operating Model'!H51 -> -150.07214 | I76: =-'04 Operating Model'!I51 -> -586.11305 | J76: =-'04 Operating Model'!J51 -> -485.35935 | K76: =-'04 Operating Model'!K51 -> -428.08896 | L76: =-'04 Operating Model'!L51 -> -400.82777 | M76: =-'04 Operating Model'!M51 -> -371.55498 | N76: =-'04 Operating Model'!N51 -> -325.6835 | ... P76: =-'04 Operating Model'!P51 -> -279.35248
B77: FLUJO DE CAJA OPERATIVO (CFO) | C77: $M | G77: =SUM(G73:G76) -> 13884.039 | H77: =SUM(H73:H76) -> 15046.665 | I77: =SUM(I73:I76) -> 17010.565 | J77: =SUM(J73:J76) -> 18849.157 | K77: =SUM(K73:K76) -> 20436.803 | L77: =SUM(L73:L76) -> 21742.693 | M77: =SUM(M73:M76) -> 22841.527 | N77: =SUM(N73:N76) -> 23873.083 | ... P77: =SUM(P73:P76) -> 25619.708
B78: (−) Capex | C78: $M | G78: =-'04 Operating Model'!G34 -> -2021.7627 | H78: =-'04 Operating Model'!H34 -> -1914.3653 | I78: =-'04 Operating Model'!I34 -> -1895.2622 | J78: =-'04 Operating Model'!J34 -> -1811.0723 | K78: =-'04 Operating Model'!K34 -> -1941.5082 | L78: =-'04 Operating Model'!L34 -> -2063.6379 | M78: =-'04 Operating Model'!M34 -> -2176.8483 | N78: =-'04 Operating Model'!N34 -> -2276.0819 | ... P78: =-'04 Operating Model'!P34 -> -2456.4977
B79: FLUJO DE CAJA DE INVERSIÓN (CFI) | C79: $M | G79: =G78 -> -2021.7627 | H79: =H78 -> -1914.3653 | I79: =I78 -> -1895.2622 | J79: =J78 -> -1811.0723 | K79: =K78 -> -1941.5082 | L79: =L78 -> -2063.6379 | M79: =M78 -> -2176.8483 | N79: =N78 -> -2276.0819 | ... P79: =P78 -> -2456.4977
B80: (+) Nueva deuda | C80: $M | G80: =G22 -> 0 | H80: =H22 -> 0 | I80: =I22 -> 0 | J80: =J22 -> 0 | K80: =K22 -> 0 | L80: =L22 -> 0 | M80: =M22 -> 0 | N80: =N22 -> 0 | ... P80: =P22 -> 0
B81: (−) Repago de deuda | C81: $M | G81: =-G23 -> -3250.7325 | H81: =-H23 -> -3539.5103 | I81: =-I23 -> -4571.3753 | J81: =-J23 -> -3908.3819 | K81: =-K23 -> 0 | L81: =-L23 -> 0 | M81: =-M23 -> 0 | N81: =-N23 -> 0 | ... P81: =-P23 -> 0
B82: (−) Dividendos ordinarios | C82: $M | G82: =G92 -> 3995.25 | H82: =H92 -> 4195.0125 | I82: =I92 -> 4404.7631 | J82: =J92 -> 4625.0013 | K82: =K92 -> 4856.2513 | L82: =L92 -> 5099.0639 | M82: =M92 -> 5354.0171 | N82: =N92 -> 5621.718 | ... P82: =P92 -> 6197.9441
B83: (−) Dividendos de preferentes | C83: $M | G83: =G93 -> 0 | H83: =H93 -> 0 | I83: =I93 -> 0 | J83: =J93 -> 0 | K83: =K93 -> 0 | L83: =L93 -> 0 | M83: =M93 -> 0 | N83: =N93 -> 0 | ... P83: =P93 -> 0
B84: (−) Recompras netas | C84: $M | G84: ='02 Assumptions'!$C$100 -> 5000 | H84: ='02 Assumptions'!$C$100 -> 5000 | I84: ='02 Assumptions'!$C$100 -> 5000 | J84: ='02 Assumptions'!$C$100 -> 5000 | K84: ='02 Assumptions'!$C$100 -> 5000 | L84: ='02 Assumptions'!$C$100 -> 5000 | M84: ='02 Assumptions'!$C$100 -> 5000 | N84: ='02 Assumptions'!$C$100 -> 5000 | ... P84: ='02 Assumptions'!$C$100 -> 5000
B85: FLUJO DE CAJA DE FINANCIACIÓN (CFF) | C85: $M | G85: =G80+G81-G82-G83-G84 -> -12245.982 | H85: =H80+H81-H82-H83-H84 -> -12734.523 | I85: =I80+I81-I82-I83-I84 -> -13976.138 | J85: =J80+J81-J82-J83-J84 -> -13533.383 | K85: =K80+K81-K82-K83-K84 -> -9856.2513 | L85: =L80+L81-L82-L83-L84 -> -10099.064 | M85: =M80+M81-M82-M83-M84 -> -10354.017 | N85: =N80+N81-N82-N83-N84 -> -10621.718 | ... P85: =P80+P81-P82-P83-P84 -> -11197.944
B86: Variación neta de caja | C86: $M | G86: =G77+G79+G85 -> -383.70634 | H86: =H77+H79+H85 -> 397.7773 | I86: =I77+I79+I85 -> 1139.1645 | J86: =J77+J79+J85 -> 3504.7013 | K86: =K77+K79+K85 -> 8639.0433 | L86: =L77+L79+L85 -> 9579.9909 | M86: =M77+M79+M85 -> 10310.662 | N86: =N77+N79+N85 -> 10975.283 | ... P86: =P77+P79+P85 -> 11965.266
B87: Caja inicial | C87: $M | G87: =G29 -> 4533 | H87: =H29 -> 4149.2937 | I87: =I29 -> 4547.071 | J87: =J29 -> 5686.2355 | K87: =K29 -> 9190.9367 | L87: =L29 -> 17829.98 | M87: =M29 -> 27409.971 | N87: =N29 -> 37720.633 | ... P87: =P29 -> 60251.269
B88: Caja final según el estado de flujos | C88: $M | G88: =G86+G87 -> 4149.2937 | H88: =H86+H87 -> 4547.071 | I88: =I86+I87 -> 5686.2355 | J88: =J86+J87 -> 9190.9367 | K88: =K86+K87 -> 17829.98 | L88: =L86+L87 -> 27409.971 | M88: =M86+M87 -> 37720.633 | N88: =N86+N87 -> 48695.916 | ... P88: =P86+P87 -> 72216.535
B89: CHECK: caja del flujo − caja del balance (debe ser 0) | C89: $M | G89: =G88-G38 -> 0 | H89: =H88-H38 -> 0 | I89: =I88-I38 -> 0 | J89: =J88-J38 -> 0 | K89: =K88-K38 -> 0 | L89: =L88-L38 -> 0 | M89: =M88-M38 -> 0 | N89: =N88-N38 -> 0 | ... P89: =P88-P38 -> 0
B91: DIVIDENDOS
B92: Dividendo ordinario pagado | C92: $M | F92: =-'03 Historical'!$F$97 -> 3805 | G92: =F92*(1+'02 Assumptions'!$C$96) -> 3995.25 | H92: =G92*(1+'02 Assumptions'!$C$96) -> 4195.0125 | I92: =H92*(1+'02 Assumptions'!$C$96) -> 4404.7631 | J92: =I92*(1+'02 Assumptions'!$C$96) -> 4625.0013 | K92: =J92*(1+'02 Assumptions'!$C$96) -> 4856.2513 | L92: =K92*(1+'02 Assumptions'!$C$96) -> 5099.0639 | M92: =L92*(1+'02 Assumptions'!$C$96) -> 5354.0171 | N92: =M92*(1+'02 Assumptions'!$C$96) -> 5621.718 | ... P92: =O92*(1+'02 Assumptions'!$C$96) -> 6197.9441
B93: Dividendo de preferentes | C93: $M | G93: ='02 Assumptions'!$C$99*'02 Assumptions'!$C$75 -> 0 | H93: ='02 Assumptions'!$C$99*'02 Assumptions'!$C$75 -> 0 | I93: ='02 Assumptions'!$C$99*'02 Assumptions'!$C$75 -> 0 | J93: ='02 Assumptions'!$C$99*'02 Assumptions'!$C$75 -> 0 | K93: ='02 Assumptions'!$C$99*'02 Assumptions'!$C$75 -> 0 | L93: ='02 Assumptions'!$C$99*'02 Assumptions'!$C$75 -> 0 | M93: ='02 Assumptions'!$C$99*'02 Assumptions'!$C$75 -> 0 | N93: ='02 Assumptions'!$C$99*'02 Assumptions'!$C$75 -> 0 | ... P93: ='02 Assumptions'!$C$99*'02 Assumptions'!$C$75 -> 0
B94: Payout sobre beneficio neto | C94: % | G94: =G92/G16 -> 0.52247136 | H94: =H92/H16 -> 0.43221941 | I94: =I92/I16 -> 0.37284272 | J94: =J92/J16 -> 0.34611437 | K94: =K92/K16 -> 0.32928173 | L94: =L92/L16 -> 0.32271041 | M94: =M92/M16 -> 0.32021458 | N94: =N92/N16 -> 0.32149682 | ... P94: =P92/P16 -> 0.32830345

Sheet 06 DCF
A1: DCF — FREE CASH FLOW TO FIRM — QUALCOMM INCORPORATED (QCOM) | R1: =1+1 -> 2
A2: USD millones. FCFF descontado al WACC. Ningún resultado está introducido a mano: todo se calcula desde '02 Assumptions', '04 Operating Model' y '07 WACC'.
B4: Partida | C4: Unidad | D4: ='00 Panel del Analista'!D14 -> FY2024A | E4: ='00 Panel del Analista'!E14 -> FY2025A | F4: ='00 Panel del Analista'!F14 -> FY2026E | G4: ='00 Panel del Analista'!G14 -> FY2027E | H4: ='00 Panel del Analista'!H14 -> FY2028E | I4: ='00 Panel del Analista'!I14 -> FY2029E | J4: ='00 Panel del Analista'!J14 -> FY2030E | K4: ='00 Panel del Analista'!K14 -> FY2031E | ... P4: ='00 Panel del Analista'!P14 -> FY2036E
B6: CÁLCULO DEL FREE CASH FLOW TO FIRM (FCFF)
B7: EBIT normalizado | C7: $M | D7: ='04 Operating Model'!D29 -> 10250 | E7: ='04 Operating Model'!E29 -> 12394 | F7: ='04 Operating Model'!F29 -> 9147 | G7: ='04 Operating Model'!G29 -> 9678.8135 | H7: ='04 Operating Model'!H29 -> 11992.619 | I7: ='04 Operating Model'!I29 -> 14380.41 | J7: ='04 Operating Model'!J29 -> 16089.651 | K7: ='04 Operating Model'!K29 -> 17657.159 | ... P7: ='04 Operating Model'!P29 -> 22845.428
B8: Tipo impositivo de caja | C8: % | G8: ='04 Operating Model'!G55 -> 0.14 | H8: ='04 Operating Model'!H55 -> 0.145 | I8: ='04 Operating Model'!I55 -> 0.15 | J8: ='04 Operating Model'!J55 -> 0.155 | K8: ='04 Operating Model'!K55 -> 0.16 | L8: ='04 Operating Model'!L55 -> 0.165 | M8: ='04 Operating Model'!M55 -> 0.17 | N8: ='04 Operating Model'!N55 -> 0.17 | ... P8: ='04 Operating Model'!P55 -> 0.17
B9: (−) Impuestos sobre el EBIT normalizado | C9: $M | G9: =-G7*G8 -> -1355.0339 | H9: =-H7*H8 -> -1738.9297 | I9: =-I7*I8 -> -2157.0615 | J9: =-J7*J8 -> -2493.8959 | K9: =-K7*K8 -> -2825.1454 | L9: =-L7*L8 -> -3138.8023 | M9: =-M7*M8 -> -3441.5971 | N9: =-N7*N8 -> -3598.4855 | ... P9: =-P7*P8 -> -3883.7228
B10: NOPAT | C10: $M | G10: =G7+G9 -> 8323.7796 | H10: =H7+H9 -> 10253.689 | I10: =I7+I9 -> 12223.349 | J10: =J7+J9 -> 13595.755 | K10: =K7+K9 -> 14832.013 | L10: =L7+L9 -> 15884.242 | M10: =M7+M9 -> 16803.092 | N10: =N7+N9 -> 17569.076 | ... P10: =P7+P9 -> 18961.705
B11: (+) D&A | C11: $M | G11: ='04 Operating Model'!G38 -> 1813.9736 | H11: ='04 Operating Model'!H38 -> 1863.7715 | I11: ='04 Operating Model'!I38 -> 1880.6698 | J11: ='04 Operating Model'!J38 -> 1866.7803 | K11: ='04 Operating Model'!K38 -> 1845.5603 | L11: ='04 Operating Model'!L38 -> 1871.5631 | M11: ='04 Operating Model'!M38 -> 1849.0476 | N11: ='04 Operating Model'!N38 -> 1932.9181 | ... P11: ='04 Operating Model'!P38 -> 2107.3597
B12: (−) Capex | C12: $M | G12: =-'04 Operating Model'!G34 -> -2021.7627 | H12: =-'04 Operating Model'!H34 -> -1914.3653 | I12: =-'04 Operating Model'!I34 -> -1895.2622 | J12: =-'04 Operating Model'!J34 -> -1811.0723 | K12: =-'04 Operating Model'!K34 -> -1941.5082 | L12: =-'04 Operating Model'!L34 -> -2063.6379 | M12: =-'04 Operating Model'!M34 -> -2176.8483 | N12: =-'04 Operating Model'!N34 -> -2276.0819 | ... P12: =-'04 Operating Model'!P34 -> -2456.4977
B13: (−) Variación del capital circulante neto | C13: $M | G13: =-'04 Operating Model'!G51 -> 1053.6301 | H13: =-'04 Operating Model'!H51 -> -150.07214 | I13: =-'04 Operating Model'!I51 -> -586.11305 | J13: =-'04 Operating Model'!J51 -> -485.35935 | K13: =-'04 Operating Model'!K51 -> -428.08896 | L13: =-'04 Operating Model'!L51 -> -400.82777 | M13: =-'04 Operating Model'!M51 -> -371.55498 | N13: =-'04 Operating Model'!N51 -> -325.6835 | ... P13: =-'04 Operating Model'!P51 -> -279.35248
B14: (−) Coste en caja de reestructuración (readido al EBIT normalizado) | C14: $M | G14: =-'02 Assumptions'!G38 -> -100 | H14: =-'02 Assumptions'!H38 -> -100 | I14: =-'02 Assumptions'!I38 -> -100 | J14: =-'02 Assumptions'!J38 -> -100 | K14: =-'02 Assumptions'!K38 -> -100 | L14: =-'02 Assumptions'!L38 -> -100 | M14: =-'02 Assumptions'!M38 -> -100 | N14: =-'02 Assumptions'!N38 -> -100 | ... P14: =-'02 Assumptions'!P38 -> -100
B15: FCFF | C15: $M | G15: =SUM(G10:G14) -> 9069.6206 | H15: =SUM(H10:H14) -> 9953.0229 | I15: =SUM(I10:I14) -> 11522.643 | J15: =SUM(J10:J14) -> 13066.103 | K15: =SUM(K10:K14) -> 14207.977 | L15: =SUM(L10:L14) -> 15191.339 | M15: =SUM(M10:M14) -> 16003.736 | N15: =SUM(N10:N14) -> 16800.229 | ... P15: =SUM(P10:P14) -> 18233.215
B16: Margen FCFF sobre ingresos | C16: % | G16: =G15/'04 Operating Model'!G11 -> 0.20186985 | H16: =H15/'04 Operating Model'!H11 -> 0.19756672 | I16: =I15/'04 Operating Model'!I11 -> 0.20671012 | J16: =J15/'04 Operating Model'!J11 -> 0.21643703 | K16: =K15/'04 Operating Model'!K11 -> 0.2195403 | L16: =L15/'04 Operating Model'!L11 -> 0.2208431 | M16: =M15/'04 Operating Model'!M11 -> 0.22055377 | N16: =N15/'04 Operating Model'!N11 -> 0.22143617 | ... P16: =P15/'04 Operating Model'!P11 -> 0.2226733
B17: Conversión FCFF / EBITDA | C17: % | G17: =G15/'04 Operating Model'!G39 -> 0.78915763 | H17: =H15/'04 Operating Model'!H39 -> 0.71829841 | I17: =I15/'04 Operating Model'!I39 -> 0.70860258 | J17: =J15/'04 Operating Model'!J39 -> 0.72765593 | K17: =K15/'04 Operating Model'!K39 -> 0.7285126 | L17: =L15/'04 Operating Model'!L39 -> 0.72704594 | M17: =M15/'04 Operating Model'!M39 -> 0.72435625 | N17: =N15/'04 Operating Model'!N39 -> 0.72726753 | ... P17: =P15/'04 Operating Model'!P39 -> 0.73070853
B19: DESCUENTO
B20: Periodo de descuento t (convención de '02 Assumptions'!C12) | C20: años | G20: =COLUMNS($G20:G20)-IF('02 Assumptions'!$C$12=2,0.5,0) -> 0.5 | H20: =COLUMNS($G20:H20)-IF('02 Assumptions'!$C$12=2,0.5,0) -> 1.5 | I20: =COLUMNS($G20:I20)-IF('02 Assumptions'!$C$12=2,0.5,0) -> 2.5 | J20: =COLUMNS($G20:J20)-IF('02 Assumptions'!$C$12=2,0.5,0) -> 3.5 | K20: =COLUMNS($G20:K20)-IF('02 Assumptions'!$C$12=2,0.5,0) -> 4.5 | L20: =COLUMNS($G20:L20)-IF('02 Assumptions'!$C$12=2,0.5,0) -> 5.5 | M20: =COLUMNS($G20:M20)-IF('02 Assumptions'!$C$12=2,0.5,0) -> 6.5 | N20: =COLUMNS($G20:N20)-IF('02 Assumptions'!$C$12=2,0.5,0) -> 7.5 | ... P20: =COLUMNS($G20:P20)-IF('02 Assumptions'!$C$12=2,0.5,0) -> 9.5
B21: WACC | C21: % | G21: ='07 WACC'!$C$38 -> 0.11540544 | H21: ='07 WACC'!$C$38 -> 0.11540544 | I21: ='07 WACC'!$C$38 -> 0.11540544 | J21: ='07 WACC'!$C$38 -> 0.11540544 | K21: ='07 WACC'!$C$38 -> 0.11540544 | L21: ='07 WACC'!$C$38 -> 0.11540544 | M21: ='07 WACC'!$C$38 -> 0.11540544 | N21: ='07 WACC'!$C$38 -> 0.11540544 | ... P21: ='07 WACC'!$C$38 -> 0.11540544
B22: Factor de descuento = 1 / (1 + WACC)^t | C22: x | G22: =1/(1+G21)^G20 -> 0.94685531 | H22: =1/(1+H21)^H20 -> 0.84888891 | I22: =1/(1+I21)^I20 -> 0.76105861 | J22: =1/(1+J21)^J20 -> 0.68231567 | K22: =1/(1+K21)^K20 -> 0.61171986 | L22: =1/(1+L21)^L20 -> 0.54842826 | M22: =1/(1+M21)^M20 -> 0.49168512 | N22: =1/(1+N21)^N20 -> 0.44081291 | ... P22: =1/(1+P21)^P20 -> 0.35431439
B23: Valor presente del FCFF | C23: $M | G23: =G15*G22 -> 8587.6185 | H23: =H15*H22 -> 8449.0108 | I23: =I15*I22 -> 8769.4069 | J23: =J15*J22 -> 8915.2071 | K23: =K15*K22 -> 8691.3015 | L23: =L15*L22 -> 8331.3598 | M23: =M15*M22 -> 7868.7989 | N23: =N15*N22 -> 7405.7578 | ... P23: =P15*P22 -> 6460.2904
B25: VALOR TERMINAL
B26: Crecimiento terminal g | C26: % | F26: ='02 Assumptions'!C63 -> 0.03
B27: ROIC terminal | C27: % | F27: ='02 Assumptions'!C66 -> 0.3
B28: Tasa de reinversión terminal = g / ROIC terminal | C28: % | F28: =F26/F27 -> 0.1
B29: NOPAT terminal = NOPAT FY2036 × (1 + g) | C29: $M | F29: =P10*(1+F26) -> 19530.557
B30: FCFF terminal = NOPAT terminal × (1 − tasa de reinversión) | C30: $M | F30: =F29*(1-F28) -> 17577.501
B31: Valor terminal — Gordon = FCFF terminal / (WACC − g) | C31: $M | F31: =IF(P21<=F26,"FALLO: WACC<=g",F30/(P21-F26)) -> 205812.42
B32: Valor terminal — múltiplo de salida = EBITDA FY2036 × múltiplo | C32: $M | F32: ='04 Operating Model'!P39*'02 Assumptions'!C64 -> 349339.03
B33: Método seleccionado ('02 Assumptions'!C13) | F33: =IF('02 Assumptions'!C13=1,"Gordon (crecimiento perpetuo)","Múltiplo de salida EV/EBITDA") -> Gordon (crecimiento perpetuo)
B34: VALOR TERMINAL UTILIZADO | C34: $M | F34: =IF('02 Assumptions'!C13=1,F31,F32) -> 205812.42
B35: Factor de descuento del VT = 1/(1+WACC)^n (año completo, no mitad de año) | C35: x | F35: =1/(1+P21)^'02 Assumptions'!C11 -> 0.33548446
B36: Valor presente del valor terminal | C36: $M | F36: =F34*F35 -> 69046.869
B37: Referencia — FCFF terminal ingenuo = FCFF FY2036 × (1+g) | C37: $M | F37: =P15*(1+F26) -> 18780.211
B38: Referencia — valor terminal ingenuo (sin disciplina de reinversión) | C38: $M | F38: =IF(P21<=F26,"n/a",F37/(P21-F26)) -> 219894.78
B39: Diferencia: disciplinado − ingenuo | C39: $M | F39: =IFERROR(F34-F38,"n/a") -> -14082.363
B41: PUENTE: ENTERPRISE VALUE → EQUITY VALUE → VALOR POR ACCIÓN
B42: Valor presente del FCFF del periodo explícito | C42: $M | F42: =SUM(G23:P23) -> 80410.753
B43: Valor presente del valor terminal | C43: $M | F43: =F36 -> 69046.869
B44: ENTERPRISE VALUE | C44: $M | F44: =F42+F43 -> 149457.62
B45: Valor terminal / Enterprise Value | C45: % | F45: =F43/F44 -> 0.46198292
B46: (−) Deuda financiera (senior notes y otros préstamos) | C46: $M | F46: =-'02 Assumptions'!C70 -> -15270
B47: (−) Pasivo por leases financieros | C47: $M | F47: =-'02 Assumptions'!C71 -> 0
B48: (+) Caja y equivalentes | C48: $M | F48: ='02 Assumptions'!C72 -> 4533
B49: (−) Caja mínima operativa (no distribuible) | C49: $M | F49: =-'02 Assumptions'!C68*'03 Historical'!F11 -> -857.96
B50: (+) Valores negociables e inversiones estratégicas QSI | C50: $M | F50: ='02 Assumptions'!C73+'02 Assumptions'!C77 -> 5150
B51: (−) Intereses minoritarios | C51: $M | F51: =-'02 Assumptions'!C74 -> 0
B52: (−) Preferentes convertibles obligatorias | C52: $M | F52: =-'02 Assumptions'!C75 -> 0
B53: EQUITY VALUE | C53: $M | F53: =F44+SUM(F46:F52) -> 143012.66
B54: Acciones diluidas | C54: M acc | F54: ='02 Assumptions'!C69 -> 1085.7
B55: VALOR INTRÍNSECO POR ACCIÓN | C55: $/acc | F55: =F53/F54 -> 131.72392
B56: Precio de mercado actual (input en '01 Summary'!C10) | C56: $/acc | F56: ='01 Summary'!$C$10 -> 198.27
B57: Upside / (Downside) | C57: % | F57: =IF(F56<=0,"introducir precio",F55/F56-1) -> -0.33563362
B58: Margen de seguridad implícito = 1 − precio / valor | C58: % | F58: =IF(F56<=0,"introducir precio",1-F56/F55) -> -0.50519356
B60: CONTROLES DE CALIDAD DEL VALOR TERMINAL Y MÚLTIPLOS IMPLÍCITOS
B61: EBITDA FY2036E | C61: $M | F61: ='04 Operating Model'!P39 -> 24952.788
B62: Múltiplo de salida IMPLÍCITO (VT / EBITDA FY2036) | C62: x | F62: =IFERROR(F34/F61,"n/a") -> 8.2480732
B63: Margen EBIT normalizado terminal | C63: % | F63: ='04 Operating Model'!P30 -> 0.279
B64: Capex terminal / ingresos | C64: % | F64: ='04 Operating Model'!P35 -> 0.03
B65: D&A terminal / ingresos | C65: % | F65: ='04 Operating Model'!P38/'04 Operating Model'!P11 -> 0.025736149
B66: Capex / D&A terminal | C66: x | F66: ='04 Operating Model'!P41 -> 1.1656756
B67: CHECK: g < WACC | F67: =IF(P21>F26,"OK","FALLO") -> OK
B68: CHECK: g ≤ PIB nominal de referencia | F68: =IF(F26<='02 Assumptions'!C65,"OK","FALLO: g por encima del PIB nominal") -> OK
B69: CHECK: múltiplo de salida implícito en rango razonable (8x–25x) | F69: =IF(AND(F62>=8,F62<=25),"OK","AVISO: múltiplo implícito fuera de rango — revisar g, ROIC terminal o WACC") -> OK
B70: CHECK: peso del valor terminal sobre el EV | F70: =IF(F45>0.75,"AVISO: el valor depende mayoritariamente de las hipótesis terminales","OK") -> OK
B71: EV / EBITDA FY2026E implícito | C71: x | F71: =F44/'03 Historical'!F125 -> 13.903466
B72: EV / Ingresos FY2026E implícito | C72: x | F72: =F44/'03 Historical'!F11 -> 3.4840231
B73: FCFF acumulado del periodo explícito | C73: $M | F73: =SUM(G15:P15) -> 141588.19
B74: Años con FCFF negativo en el periodo explícito | C74: años | F74: =COUNTIF(G15:P15,"<0") -> 0
B75: CHECK: el FCFF llega a ser positivo dentro del horizonte | F75: =IF(P15>0,"OK","FALLO: FCFF negativo al final del horizonte — el FCFF DCF no es la metodología adecuada") -> OK

Sheet 07 WACC
A1: COSTE MEDIO PONDERADO DEL CAPITAL (WACC) — QUALCOMM INCORPORATED
A2: AMARILLO = input de mercado que DEBE actualizarse y fecharse en cada revisión. El WACC se calcula sobre estructura de capital OBJETIVO, no sobre el precio del día.
B4: COSTE DE LOS RECURSOS PROPIOS (Ke) — CAPM
B5: Tipo libre de riesgo (bono EEUU 10 años) | C5: ='00 Panel del Analista'!D207 -> 0.0496 | D5: %
B6: Prima de riesgo de mercado (ERP) | C6: ='00 Panel del Analista'!D208 -> 0.0423 | D6: %
B7: Beta utilizada (reapalancada, ver bloque inferior) | C7: =C19 -> 1.6830192 | D7: x
B8: Prima adicional por riesgo país / tamaño | C8: ='00 Panel del Analista'!D209 -> 0 | D8: %
B9: Ke = Rf + Beta × ERP + prima adicional | C9: =C5+C7*C6+C8 -> 0.12079171 | D9: %
B11: DESAPALANCAMIENTO Y REAPALANCAMIENTO DE BETA
B12: Beta apalancada observada (regresión a 5 años, mensual) | C12: ='00 Panel del Analista'!D210 -> 1.68 | D12: x
B13: D/E de mercado correspondiente a la beta observada | C13: ='00 Panel del Analista'!D211 -> 0.072862999 | D13: x
B14: Tipo impositivo marginal | C14: ='02 Assumptions'!C58 -> 0.21 | D14: %
B15: Beta desapalancada = Beta apalancada / (1 + (1−T) × D/E) | C15: =C12/(1+(1-C14)*C13) -> 1.5885597 | D15: x
B16: D/E objetivo = peso deuda / peso equity | C16: =C31/C32 -> 0.075268817 | D16: x
B17: Beta reapalancada = Beta desapalancada × (1 + (1−T) × D/E objetivo) | C17: =C15*(1+(1-C14)*C16) -> 1.6830192 | D17: x
B19: BETA UTILIZADA EN EL Ke | C19: =C17 -> 1.6830192 | D19: x
B21: COSTE DE LA DEUDA (Kd)
B22: Gasto por intereses FY2026 (reportado) | C22: ='03 Historical'!F29 -> 694 | D22: $M
B23: Deuda media FY2025–FY2026 (senior notes + leases financieros) | C23: =AVERAGE('03 Historical'!E110+'03 Historical'!E112,'03 Historical'!F110+'03 Historical'!F112) -> 15040.5 | D23: $M
B24: Kd implícito histórico = intereses / deuda media | C24: =C22/C23 -> 0.046142083 | D24: %
B25: Kd MARGINAL utilizado (coste de la deuda nueva) | C25: ='00 Panel del Analista'!D212 -> 0.0555 | D25: %
B26: Kd después de impuestos = Kd × (1 − T) | C26: =C25*(1-C14) -> 0.043845 | D26: %
B28: ESTRUCTURA DE CAPITAL
B29: Capitalización de mercado (precio × acciones diluidas) | C29: =IF('01 Summary'!$C$10<=0,0,'01 Summary'!$C$10*'02 Assumptions'!C69) -> 215261.74 | D29: $M
B30: Deuda total (senior notes + leases financieros) | C30: ='02 Assumptions'!C70+'02 Assumptions'!C71 -> 15270 | D30: $M
B31: PESO OBJETIVO DE LA DEUDA D/(D+E) | C31: ='00 Panel del Analista'!D213 -> 0.07 | D31: %
B32: Peso de los recursos propios E/(D+E) | C32: =1-C31 -> 0.93 | D32: %
B33: Peso de deuda implícito por mercado (cross-check; requiere precio) | C33: =IF(C29<=0,"introducir precio en Summary!C10",C30/(C30+C29)) -> 0.066238168 | D33: %
B35: WACC
B36: WACC base = E/(D+E)×Ke + D/(D+E)×Kd×(1−T) | C36: =C32*C9+C31*C26 -> 0.11540544 | D36: %
B37: Delta de escenario | C37: ='09 Escenarios'!$G$17 -> 0 | D37: pp
B38: WACC ACTIVO | C38: =C36+C37 -> 0.11540544 | D38: %
B40: CONTROLES OBLIGATORIOS
B41: Crecimiento terminal g | C41: ='02 Assumptions'!C63 -> 0.03 | D41: %
B42: CHECK: WACC > g | C42: =IF(C38>C41,"OK","FALLO — g debe ser menor que el WACC") -> OK
B43: Margen WACC − g | C43: =C38-C41 -> 0.085405443 | D43: pp
B44: CHECK: Kd marginal ≥ Kd implícito histórico | C44: =IF(C25>=C24,"OK","REVISAR — el coste marginal de la deuda nueva no debería ser inferior al histórico") -> OK
B45: CHECK: Ke > Kd (coherencia de prelación de riesgo) | C45: =IF(C9>C25,"OK","FALLO") -> OK
B47: DOCUMENTACIÓN DE LOS INPUTS DE MERCADO (obligatorio rellenar en cada revisión)
B48: Input | C48: Valor usado | D48: Fuente que DEBE documentar el analista | E48: Riesgo si es incorrecto
B49: Tipo libre de riesgo | C49: =C5 -> 0.0496 | D49: Rendimiento del bono del Tesoro EEUU a 10 años a la fecha de valoración. Fuente oficial: Treasury.gov / FRED. NO verificado por Claude. | E49: Afecta linealmente al Ke y por tanto al WACC. 100 pb de error mueven el valor de forma material por la duración del flujo.
B50: Prima de riesgo de mercado | C50: =C6 -> 0.0423 | D50: Prima implícita o histórica. Debe ser consistente con el tipo libre de riesgo usado (no mezclar ERP histórica con Rf actual sin criterio). | E50: Segundo input más sensible del WACC.
B51: Beta apalancada observada | C51: =C12 -> 1.68 | D51: Regresión del rendimiento de QCOM contra el S&P 500, 5 años mensual, o media de comparables de semiconductores. 1,25 = ESTIMACIÓN, NO verificada con terminal. | E51: La beta de Qualcomm puede subir con la entrada en Data Center (negocio más cíclico y concentrado en pocos clientes); una beta histórica no recoge del todo ese cambio de mix.
B52: Kd marginal | C52: =C25 -> 0.0555 | D52: Rendimiento al vencimiento de las senior notes de Qualcomm a largo plazo (rating A), o UST + diferencial de crédito. 5,85% = UST 4,96% + ~90 pb. | E52: Con 15.270 de deuda y una estructura muy poco apalancada, el Kd pesa poco en el WACC: el riesgo real está en el Ke.
B53: Peso objetivo de la deuda | C53: =C31 -> 0.07 | D53: Estructura objetivo: la deuda de mercado actual es ~7% del valor (15.270 frente a ~205.000 de capitalización). | E53: Usar la estructura contable (deuda/patrimonio contable) sobreponderaría la deuda.
B54: Estructura objetivo vs actual | D54: Qualcomm mantiene un apalancamiento bajo y estable (deuda 14.634–15.270 en los últimos 2 años) y financia recompras con caja operativa. El 7% objetivo asume que se mantiene esa política. | E54: Si Qualcomm se endeudara para financiar compras en Data Center, el peso de la deuda subiría y el WACC bajaría ligeramente.
B56: FECHA DE ÚLTIMA ACTUALIZACIÓN DE LOS INPUTS DE MERCADO (introducir dd/mm/aaaa) | C56: ='00 Panel del Analista'!D214 -> 0
B57: Mientras esta celda esté vacía, el control 66 de '13 Checks' permanecerá en AVISO: el WACC no es defendible sin fuente y fecha.

Sheet Sensibilidad
A1: ANÁLISIS DE SENSIBILIDAD — VALOR INTRÍNSECO POR ACCIÓN ($)
A2: Rejillas 5×5 con el caso base en el CENTRO (celda amarilla). Recalculadas en forma cerrada sobre el flujo de '06 DCF': el FCFF no depende del WACC ni de g, por lo que la revaloración es exacta salvo donde se indique.
B4: REJILLA A — WACC × CRECIMIENTO TERMINAL g (exacta) | M4: 123.45
B5: WACC ↓ / g → | D5: ='06 DCF'!$F$26+-0.01 -> 0.02 | E5: ='06 DCF'!$F$26+-0.005 -> 0.025 | F5: ='06 DCF'!$F$26+0 -> 0.03 | G5: ='06 DCF'!$F$26+0.005 -> 0.035 | H5: ='06 DCF'!$F$26+0.01 -> 0.04
C6: ='07 WACC'!$C$38+-0.01 -> 0.10540544 | D6: {=(SUMPRODUCT('06 DCF'!$G$15:$P$15,1/(1+$C6)^'06 DCF'!$G$20:$P$20)+'06 DCF'!$P$10*(1+D$5)*(1-D$5/'06 DCF'!$F$27)/($C6-D$5)/(1+$C6)^'02 Assumptions'!$C$11+SUM('06 DCF'!$F$46:$F$52))/'06 DCF'!$F$54} -> 142.85602 | E6: {=(SUMPRODUCT('06 DCF'!$G$15:$P$15,1/(1+$C6)^'06 DCF'!$G$20:$P$20)+'06 DCF'!$P$10*(1+E$5)*(1-E$5/'06 DCF'!$F$27)/($C6-E$5)/(1+$C6)^'02 Assumptions'!$C$11+SUM('06 DCF'!$F$46:$F$52))/'06 DCF'!$F$54} -> 146.31007 | F6: {=(SUMPRODUCT('06 DCF'!$G$15:$P$15,1/(1+$C6)^'06 DCF'!$G$20:$P$20)+'06 DCF'!$P$10*(1+F$5)*(1-F$5/'06 DCF'!$F$27)/($C6-F$5)/(1+$C6)^'02 Assumptions'!$C$11+SUM('06 DCF'!$F$46:$F$52))/'06 DCF'!$F$54} -> 150.20802 | G6: {=(SUMPRODUCT('06 DCF'!$G$15:$P$15,1/(1+$C6)^'06 DCF'!$G$20:$P$20)+'06 DCF'!$P$10*(1+G$5)*(1-G$5/'06 DCF'!$F$27)/($C6-G$5)/(1+$C6)^'02 Assumptions'!$C$11+SUM('06 DCF'!$F$46:$F$52))/'06 DCF'!$F$54} -> 154.64444 | H6: {=(SUMPRODUCT('06 DCF'!$G$15:$P$15,1/(1+$C6)^'06 DCF'!$G$20:$P$20)+'06 DCF'!$P$10*(1+H$5)*(1-H$5/'06 DCF'!$F$27)/($C6-H$5)/(1+$C6)^'02 Assumptions'!$C$11+SUM('06 DCF'!$F$46:$F$52))/'06 DCF'!$F$54} -> 159.74281
C7: ='07 WACC'!$C$38+-0.005 -> 0.11040544 | D7: {=(SUMPRODUCT('06 DCF'!$G$15:$P$15,1/(1+$C7)^'06 DCF'!$G$20:$P$20)+'06 DCF'!$P$10*(1+D$5)*(1-D$5/'06 DCF'!$F$27)/($C7-D$5)/(1+$C7)^'02 Assumptions'!$C$11+SUM('06 DCF'!$F$46:$F$52))/'06 DCF'!$F$54} -> 134.26591 | E7: {=(SUMPRODUCT('06 DCF'!$G$15:$P$15,1/(1+$C7)^'06 DCF'!$G$20:$P$20)+'06 DCF'!$P$10*(1+E$5)*(1-E$5/'06 DCF'!$F$27)/($C7-E$5)/(1+$C7)^'02 Assumptions'!$C$11+SUM('06 DCF'!$F$46:$F$52))/'06 DCF'!$F$54} -> 137.15307 | F7: {=(SUMPRODUCT('06 DCF'!$G$15:$P$15,1/(1+$C7)^'06 DCF'!$G$20:$P$20)+'06 DCF'!$P$10*(1+F$5)*(1-F$5/'06 DCF'!$F$27)/($C7-F$5)/(1+$C7)^'02 Assumptions'!$C$11+SUM('06 DCF'!$F$46:$F$52))/'06 DCF'!$F$54} -> 140.38659 | G7: {=(SUMPRODUCT('06 DCF'!$G$15:$P$15,1/(1+$C7)^'06 DCF'!$G$20:$P$20)+'06 DCF'!$P$10*(1+G$5)*(1-G$5/'06 DCF'!$F$27)/($C7-G$5)/(1+$C7)^'02 Assumptions'!$C$11+SUM('06 DCF'!$F$46:$F$52))/'06 DCF'!$F$54} -> 144.0354 | H7: {=(SUMPRODUCT('06 DCF'!$G$15:$P$15,1/(1+$C7)^'06 DCF'!$G$20:$P$20)+'06 DCF'!$P$10*(1+H$5)*(1-H$5/'06 DCF'!$F$27)/($C7-H$5)/(1+$C7)^'02 Assumptions'!$C$11+SUM('06 DCF'!$F$46:$F$52))/'06 DCF'!$F$54} -> 148.18795
C8: ='07 WACC'!$C$38+0 -> 0.11540544 | D8: {=(SUMPRODUCT('06 DCF'!$G$15:$P$15,1/(1+$C8)^'06 DCF'!$G$20:$P$20)+'06 DCF'!$P$10*(1+D$5)*(1-D$5/'06 DCF'!$F$27)/($C8-D$5)/(1+$C8)^'02 Assumptions'!$C$11+SUM('06 DCF'!$F$46:$F$52))/'06 DCF'!$F$54} -> 126.59334 | E8: {=(SUMPRODUCT('06 DCF'!$G$15:$P$15,1/(1+$C8)^'06 DCF'!$G$20:$P$20)+'06 DCF'!$P$10*(1+E$5)*(1-E$5/'06 DCF'!$F$27)/($C8-E$5)/(1+$C8)^'02 Assumptions'!$C$11+SUM('06 DCF'!$F$46:$F$52))/'06 DCF'!$F$54} -> 129.02215 | F8: {=(SUMPRODUCT('06 DCF'!$G$15:$P$15,1/(1+$C8)^'06 DCF'!$G$20:$P$20)+'06 DCF'!$P$10*(1+F$5)*(1-F$5/'06 DCF'!$F$27)/($C8-F$5)/(1+$C8)^'02 Assumptions'!$C$11+SUM('06 DCF'!$F$46:$F$52))/'06 DCF'!$F$54} -> 131.72392 | G8: {=(SUMPRODUCT('06 DCF'!$G$15:$P$15,1/(1+$C8)^'06 DCF'!$G$20:$P$20)+'06 DCF'!$P$10*(1+G$5)*(1-G$5/'06 DCF'!$F$27)/($C8-G$5)/(1+$C8)^'02 Assumptions'!$C$11+SUM('06 DCF'!$F$46:$F$52))/'06 DCF'!$F$54} -> 134.74956 | H8: {=(SUMPRODUCT('06 DCF'!$G$15:$P$15,1/(1+$C8)^'06 DCF'!$G$20:$P$20)+'06 DCF'!$P$10*(1+H$5)*(1-H$5/'06 DCF'!$F$27)/($C8-H$5)/(1+$C8)^'02 Assumptions'!$C$11+SUM('06 DCF'!$F$46:$F$52))/'06 DCF'!$F$54} -> 138.16351
C9: ='07 WACC'!$C$38+0.005 -> 0.12040544 | D9: {=(SUMPRODUCT('06 DCF'!$G$15:$P$15,1/(1+$C9)^'06 DCF'!$G$20:$P$20)+'06 DCF'!$P$10*(1+D$5)*(1-D$5/'06 DCF'!$F$27)/($C9-D$5)/(1+$C9)^'02 Assumptions'!$C$11+SUM('06 DCF'!$F$46:$F$52))/'06 DCF'!$F$54} -> 119.70037 | E9: {=(SUMPRODUCT('06 DCF'!$G$15:$P$15,1/(1+$C9)^'06 DCF'!$G$20:$P$20)+'06 DCF'!$P$10*(1+E$5)*(1-E$5/'06 DCF'!$F$27)/($C9-E$5)/(1+$C9)^'02 Assumptions'!$C$11+SUM('06 DCF'!$F$46:$F$52))/'06 DCF'!$F$54} -> 121.75532 | F9: {=(SUMPRODUCT('06 DCF'!$G$15:$P$15,1/(1+$C9)^'06 DCF'!$G$20:$P$20)+'06 DCF'!$P$10*(1+F$5)*(1-F$5/'06 DCF'!$F$27)/($C9-F$5)/(1+$C9)^'02 Assumptions'!$C$11+SUM('06 DCF'!$F$46:$F$52))/'06 DCF'!$F$54} -> 124.02724 | G9: {=(SUMPRODUCT('06 DCF'!$G$15:$P$15,1/(1+$C9)^'06 DCF'!$G$20:$P$20)+'06 DCF'!$P$10*(1+G$5)*(1-G$5/'06 DCF'!$F$27)/($C9-G$5)/(1+$C9)^'02 Assumptions'!$C$11+SUM('06 DCF'!$F$46:$F$52))/'06 DCF'!$F$54} -> 126.55424 | H9: {=(SUMPRODUCT('06 DCF'!$G$15:$P$15,1/(1+$C9)^'06 DCF'!$G$20:$P$20)+'06 DCF'!$P$10*(1+H$5)*(1-H$5/'06 DCF'!$F$27)/($C9-H$5)/(1+$C9)^'02 Assumptions'!$C$11+SUM('06 DCF'!$F$46:$F$52))/'06 DCF'!$F$54} -> 129.38391
C10: ='07 WACC'!$C$38+0.01 -> 0.12540544 | D10: {=(SUMPRODUCT('06 DCF'!$G$15:$P$15,1/(1+$C10)^'06 DCF'!$G$20:$P$20)+'06 DCF'!$P$10*(1+D$5)*(1-D$5/'06 DCF'!$F$27)/($C10-D$5)/(1+$C10)^'02 Assumptions'!$C$11+SUM('06 DCF'!$F$46:$F$52))/'06 DCF'!$F$54} -> 113.47531 | E10: {=(SUMPRODUCT('06 DCF'!$G$15:$P$15,1/(1+$C10)^'06 DCF'!$G$20:$P$20)+'06 DCF'!$P$10*(1+E$5)*(1-E$5/'06 DCF'!$F$27)/($C10-E$5)/(1+$C10)^'02 Assumptions'!$C$11+SUM('06 DCF'!$F$46:$F$52))/'06 DCF'!$F$54} -> 115.22286 | F10: {=(SUMPRODUCT('06 DCF'!$G$15:$P$15,1/(1+$C10)^'06 DCF'!$G$20:$P$20)+'06 DCF'!$P$10*(1+F$5)*(1-F$5/'06 DCF'!$F$27)/($C10-F$5)/(1+$C10)^'02 Assumptions'!$C$11+SUM('06 DCF'!$F$46:$F$52))/'06 DCF'!$F$54} -> 117.14421 | G10: {=(SUMPRODUCT('06 DCF'!$G$15:$P$15,1/(1+$C10)^'06 DCF'!$G$20:$P$20)+'06 DCF'!$P$10*(1+G$5)*(1-G$5/'06 DCF'!$F$27)/($C10-G$5)/(1+$C10)^'02 Assumptions'!$C$11+SUM('06 DCF'!$F$46:$F$52))/'06 DCF'!$F$54} -> 119.26822 | H10: {=(SUMPRODUCT('06 DCF'!$G$15:$P$15,1/(1+$C10)^'06 DCF'!$G$20:$P$20)+'06 DCF'!$P$10*(1+H$5)*(1-H$5/'06 DCF'!$F$27)/($C10-H$5)/(1+$C10)^'02 Assumptions'!$C$11+SUM('06 DCF'!$F$46:$F$52))/'06 DCF'!$F$54} -> 121.63046
B13: REJILLA B — WACC × MÚLTIPLO DE SALIDA EV/EBITDA (exacta; método alternativo de valor terminal)
B14: WACC ↓ / múltiplo →
C15: ='07 WACC'!$C$38+-0.01 -> 0.10540544 | D15: {=(SUMPRODUCT('06 DCF'!$G$15:$P$15,1/(1+$C15)^'06 DCF'!$G$20:$P$20)+'04 Operating Model'!$P$39*D$14/(1+$C15)^'02 Assumptions'!$C$11+SUM('06 DCF'!$F$46:$F$52))/'06 DCF'!$F$54} -> 71.389441 | E15: {=(SUMPRODUCT('06 DCF'!$G$15:$P$15,1/(1+$C15)^'06 DCF'!$G$20:$P$20)+'04 Operating Model'!$P$39*E$14/(1+$C15)^'02 Assumptions'!$C$11+SUM('06 DCF'!$F$46:$F$52))/'06 DCF'!$F$54} -> 71.389441 | F15: {=(SUMPRODUCT('06 DCF'!$G$15:$P$15,1/(1+$C15)^'06 DCF'!$G$20:$P$20)+'04 Operating Model'!$P$39*F$14/(1+$C15)^'02 Assumptions'!$C$11+SUM('06 DCF'!$F$46:$F$52))/'06 DCF'!$F$54} -> 71.389441 | G15: {=(SUMPRODUCT('06 DCF'!$G$15:$P$15,1/(1+$C15)^'06 DCF'!$G$20:$P$20)+'04 Operating Model'!$P$39*G$14/(1+$C15)^'02 Assumptions'!$C$11+SUM('06 DCF'!$F$46:$F$52))/'06 DCF'!$F$54} -> 71.389441 | H15: {=(SUMPRODUCT('06 DCF'!$G$15:$P$15,1/(1+$C15)^'06 DCF'!$G$20:$P$20)+'04 Operating Model'!$P$39*H$14/(1+$C15)^'02 Assumptions'!$C$11+SUM('06 DCF'!$F$46:$F$52))/'06 DCF'!$F$54} -> 71.389441
C16: ='07 WACC'!$C$38+-0.005 -> 0.11040544 | D16: {=(SUMPRODUCT('06 DCF'!$G$15:$P$15,1/(1+$C16)^'06 DCF'!$G$20:$P$20)+'04 Operating Model'!$P$39*D$14/(1+$C16)^'02 Assumptions'!$C$11+SUM('06 DCF'!$F$46:$F$52))/'06 DCF'!$F$54} -> 69.731086 | E16: {=(SUMPRODUCT('06 DCF'!$G$15:$P$15,1/(1+$C16)^'06 DCF'!$G$20:$P$20)+'04 Operating Model'!$P$39*E$14/(1+$C16)^'02 Assumptions'!$C$11+SUM('06 DCF'!$F$46:$F$52))/'06 DCF'!$F$54} -> 69.731086 | F16: {=(SUMPRODUCT('06 DCF'!$G$15:$P$15,1/(1+$C16)^'06 DCF'!$G$20:$P$20)+'04 Operating Model'!$P$39*F$14/(1+$C16)^'02 Assumptions'!$C$11+SUM('06 DCF'!$F$46:$F$52))/'06 DCF'!$F$54} -> 69.731086 | G16: {=(SUMPRODUCT('06 DCF'!$G$15:$P$15,1/(1+$C16)^'06 DCF'!$G$20:$P$20)+'04 Operating Model'!$P$39*G$14/(1+$C16)^'02 Assumptions'!$C$11+SUM('06 DCF'!$F$46:$F$52))/'06 DCF'!$F$54} -> 69.731086 | H16: {=(SUMPRODUCT('06 DCF'!$G$15:$P$15,1/(1+$C16)^'06 DCF'!$G$20:$P$20)+'04 Operating Model'!$P$39*H$14/(1+$C16)^'02 Assumptions'!$C$11+SUM('06 DCF'!$F$46:$F$52))/'06 DCF'!$F$54} -> 69.731086
C17: ='07 WACC'!$C$38+0 -> 0.11540544 | D17: {=(SUMPRODUCT('06 DCF'!$G$15:$P$15,1/(1+$C17)^'06 DCF'!$G$20:$P$20)+'04 Operating Model'!$P$39*D$14/(1+$C17)^'02 Assumptions'!$C$11+SUM('06 DCF'!$F$46:$F$52))/'06 DCF'!$F$54} -> 68.127285 | E17: {=(SUMPRODUCT('06 DCF'!$G$15:$P$15,1/(1+$C17)^'06 DCF'!$G$20:$P$20)+'04 Operating Model'!$P$39*E$14/(1+$C17)^'02 Assumptions'!$C$11+SUM('06 DCF'!$F$46:$F$52))/'06 DCF'!$F$54} -> 68.127285 | F17: {=(SUMPRODUCT('06 DCF'!$G$15:$P$15,1/(1+$C17)^'06 DCF'!$G$20:$P$20)+'04 Operating Model'!$P$39*F$14/(1+$C17)^'02 Assumptions'!$C$11+SUM('06 DCF'!$F$46:$F$52))/'06 DCF'!$F$54} -> 68.127285 | G17: {=(SUMPRODUCT('06 DCF'!$G$15:$P$15,1/(1+$C17)^'06 DCF'!$G$20:$P$20)+'04 Operating Model'!$P$39*G$14/(1+$C17)^'02 Assumptions'!$C$11+SUM('06 DCF'!$F$46:$F$52))/'06 DCF'!$F$54} -> 68.127285 | H17: {=(SUMPRODUCT('06 DCF'!$G$15:$P$15,1/(1+$C17)^'06 DCF'!$G$20:$P$20)+'04 Operating Model'!$P$39*H$14/(1+$C17)^'02 Assumptions'!$C$11+SUM('06 DCF'!$F$46:$F$52))/'06 DCF'!$F$54} -> 68.127285
C18: ='07 WACC'!$C$38+0.005 -> 0.12040544 | D18: {=(SUMPRODUCT('06 DCF'!$G$15:$P$15,1/(1+$C18)^'06 DCF'!$G$20:$P$20)+'04 Operating Model'!$P$39*D$14/(1+$C18)^'02 Assumptions'!$C$11+SUM('06 DCF'!$F$46:$F$52))/'06 DCF'!$F$54} -> 66.575836 | E18: {=(SUMPRODUCT('06 DCF'!$G$15:$P$15,1/(1+$C18)^'06 DCF'!$G$20:$P$20)+'04 Operating Model'!$P$39*E$14/(1+$C18)^'02 Assumptions'!$C$11+SUM('06 DCF'!$F$46:$F$52))/'06 DCF'!$F$54} -> 66.575836 | F18: {=(SUMPRODUCT('06 DCF'!$G$15:$P$15,1/(1+$C18)^'06 DCF'!$G$20:$P$20)+'04 Operating Model'!$P$39*F$14/(1+$C18)^'02 Assumptions'!$C$11+SUM('06 DCF'!$F$46:$F$52))/'06 DCF'!$F$54} -> 66.575836 | G18: {=(SUMPRODUCT('06 DCF'!$G$15:$P$15,1/(1+$C18)^'06 DCF'!$G$20:$P$20)+'04 Operating Model'!$P$39*G$14/(1+$C18)^'02 Assumptions'!$C$11+SUM('06 DCF'!$F$46:$F$52))/'06 DCF'!$F$54} -> 66.575836 | H18: {=(SUMPRODUCT('06 DCF'!$G$15:$P$15,1/(1+$C18)^'06 DCF'!$G$20:$P$20)+'04 Operating Model'!$P$39*H$14/(1+$C18)^'02 Assumptions'!$C$11+SUM('06 DCF'!$F$46:$F$52))/'06 DCF'!$F$54} -> 66.575836
C19: ='07 WACC'!$C$38+0.01 -> 0.12540544 | D19: {=(SUMPRODUCT('06 DCF'!$G$15:$P$15,1/(1+$C19)^'06 DCF'!$G$20:$P$20)+'04 Operating Model'!$P$39*D$14/(1+$C19)^'02 Assumptions'!$C$11+SUM('06 DCF'!$F$46:$F$52))/'06 DCF'!$F$54} -> 65.07464 | E19: {=(SUMPRODUCT('06 DCF'!$G$15:$P$15,1/(1+$C19)^'06 DCF'!$G$20:$P$20)+'04 Operating Model'!$P$39*E$14/(1+$C19)^'02 Assumptions'!$C$11+SUM('06 DCF'!$F$46:$F$52))/'06 DCF'!$F$54} -> 65.07464 | F19: {=(SUMPRODUCT('06 DCF'!$G$15:$P$15,1/(1+$C19)^'06 DCF'!$G$20:$P$20)+'04 Operating Model'!$P$39*F$14/(1+$C19)^'02 Assumptions'!$C$11+SUM('06 DCF'!$F$46:$F$52))/'06 DCF'!$F$54} -> 65.07464 | G19: {=(SUMPRODUCT('06 DCF'!$G$15:$P$15,1/(1+$C19)^'06 DCF'!$G$20:$P$20)+'04 Operating Model'!$P$39*G$14/(1+$C19)^'02 Assumptions'!$C$11+SUM('06 DCF'!$F$46:$F$52))/'06 DCF'!$F$54} -> 65.07464 | H19: {=(SUMPRODUCT('06 DCF'!$G$15:$P$15,1/(1+$C19)^'06 DCF'!$G$20:$P$20)+'04 Operating Model'!$P$39*H$14/(1+$C19)^'02 Assumptions'!$C$11+SUM('06 DCF'!$F$46:$F$52))/'06 DCF'!$F$54} -> 65.07464
B22: REJILLA C — WACC × DESPLAZAMIENTO DEL MARGEN EBIT (pp) (exacta)
B23: WACC ↓ / Δ margen EBIT (p.p.) →
C24: ='07 WACC'!$C$38+-0.01 -> 0.10540544 | D24: {=(SUMPRODUCT('06 DCF'!$G$15:$P$15+D$23*'04 Operating Model'!$G$11:$P$11*(1-'04 Operating Model'!$G$55:$P$55),1/(1+$C24)^'06 DCF'!$G$20:$P$20)+('06 DCF'!$P$10+D$23*'04 Operating Model'!$P$11*(1-'04 Operating Model'!$P$55))*(1+'06 DCF'!$F$26)*(1-'06 DCF'!$F$26/'06 DCF'!$F$27)/($C24-'06 DCF'!$F$26)/(1+$C24)^'02 Assumptions'!$C$11+SUM('06 DCF'!$F$46:$F$52))/'06 DCF'!$F$54} -> 150.20802 | E24: {=(SUMPRODUCT('06 DCF'!$G$15:$P$15+E$23*'04 Operating Model'!$G$11:$P$11*(1-'04 Operating Model'!$G$55:$P$55),1/(1+$C24)^'06 DCF'!$G$20:$P$20)+('06 DCF'!$P$10+E$23*'04 Operating Model'!$P$11*(1-'04 Operating Model'!$P$55))*(1+'06 DCF'!$F$26)*(1-'06 DCF'!$F$26/'06 DCF'!$F$27)/($C24-'06 DCF'!$F$26)/(1+$C24)^'02 Assumptions'!$C$11+SUM('06 DCF'!$F$46:$F$52))/'06 DCF'!$F$54} -> 150.20802 | F24: {=(SUMPRODUCT('06 DCF'!$G$15:$P$15+F$23*'04 Operating Model'!$G$11:$P$11*(1-'04 Operating Model'!$G$55:$P$55),1/(1+$C24)^'06 DCF'!$G$20:$P$20)+('06 DCF'!$P$10+F$23*'04 Operating Model'!$P$11*(1-'04 Operating Model'!$P$55))*(1+'06 DCF'!$F$26)*(1-'06 DCF'!$F$26/'06 DCF'!$F$27)/($C24-'06 DCF'!$F$26)/(1+$C24)^'02 Assumptions'!$C$11+SUM('06 DCF'!$F$46:$F$52))/'06 DCF'!$F$54} -> 150.20802 | G24: {=(SUMPRODUCT('06 DCF'!$G$15:$P$15+G$23*'04 Operating Model'!$G$11:$P$11*(1-'04 Operating Model'!$G$55:$P$55),1/(1+$C24)^'06 DCF'!$G$20:$P$20)+('06 DCF'!$P$10+G$23*'04 Operating Model'!$P$11*(1-'04 Operating Model'!$P$55))*(1+'06 DCF'!$F$26)*(1-'06 DCF'!$F$26/'06 DCF'!$F$27)/($C24-'06 DCF'!$F$26)/(1+$C24)^'02 Assumptions'!$C$11+SUM('06 DCF'!$F$46:$F$52))/'06 DCF'!$F$54} -> 150.20802 | H24: {=(SUMPRODUCT('06 DCF'!$G$15:$P$15+H$23*'04 Operating Model'!$G$11:$P$11*(1-'04 Operating Model'!$G$55:$P$55),1/(1+$C24)^'06 DCF'!$G$20:$P$20)+('06 DCF'!$P$10+H$23*'04 Operating Model'!$P$11*(1-'04 Operating Model'!$P$55))*(1+'06 DCF'!$F$26)*(1-'06 DCF'!$F$26/'06 DCF'!$F$27)/($C24-'06 DCF'!$F$26)/(1+$C24)^'02 Assumptions'!$C$11+SUM('06 DCF'!$F$46:$F$52))/'06 DCF'!$F$54} -> 150.20802
C25: ='07 WACC'!$C$38+-0.005 -> 0.11040544 | D25: {=(SUMPRODUCT('06 DCF'!$G$15:$P$15+D$23*'04 Operating Model'!$G$11:$P$11*(1-'04 Operating Model'!$G$55:$P$55),1/(1+$C25)^'06 DCF'!$G$20:$P$20)+('06 DCF'!$P$10+D$23*'04 Operating Model'!$P$11*(1-'04 Operating Model'!$P$55))*(1+'06 DCF'!$F$26)*(1-'06 DCF'!$F$26/'06 DCF'!$F$27)/($C25-'06 DCF'!$F$26)/(1+$C25)^'02 Assumptions'!$C$11+SUM('06 DCF'!$F$46:$F$52))/'06 DCF'!$F$54} -> 140.38659 | E25: {=(SUMPRODUCT('06 DCF'!$G$15:$P$15+E$23*'04 Operating Model'!$G$11:$P$11*(1-'04 Operating Model'!$G$55:$P$55),1/(1+$C25)^'06 DCF'!$G$20:$P$20)+('06 DCF'!$P$10+E$23*'04 Operating Model'!$P$11*(1-'04 Operating Model'!$P$55))*(1+'06 DCF'!$F$26)*(1-'06 DCF'!$F$26/'06 DCF'!$F$27)/($C25-'06 DCF'!$F$26)/(1+$C25)^'02 Assumptions'!$C$11+SUM('06 DCF'!$F$46:$F$52))/'06 DCF'!$F$54} -> 140.38659 | F25: {=(SUMPRODUCT('06 DCF'!$G$15:$P$15+F$23*'04 Operating Model'!$G$11:$P$11*(1-'04 Operating Model'!$G$55:$P$55),1/(1+$C25)^'06 DCF'!$G$20:$P$20)+('06 DCF'!$P$10+F$23*'04 Operating Model'!$P$11*(1-'04 Operating Model'!$P$55))*(1+'06 DCF'!$F$26)*(1-'06 DCF'!$F$26/'06 DCF'!$F$27)/($C25-'06 DCF'!$F$26)/(1+$C25)^'02 Assumptions'!$C$11+SUM('06 DCF'!$F$46:$F$52))/'06 DCF'!$F$54} -> 140.38659 | G25: {=(SUMPRODUCT('06 DCF'!$G$15:$P$15+G$23*'04 Operating Model'!$G$11:$P$11*(1-'04 Operating Model'!$G$55:$P$55),1/(1+$C25)^'06 DCF'!$G$20:$P$20)+('06 DCF'!$P$10+G$23*'04 Operating Model'!$P$11*(1-'04 Operating Model'!$P$55))*(1+'06 DCF'!$F$26)*(1-'06 DCF'!$F$26/'06 DCF'!$F$27)/($C25-'06 DCF'!$F$26)/(1+$C25)^'02 Assumptions'!$C$11+SUM('06 DCF'!$F$46:$F$52))/'06 DCF'!$F$54} -> 140.38659 | H25: {=(SUMPRODUCT('06 DCF'!$G$15:$P$15+H$23*'04 Operating Model'!$G$11:$P$11*(1-'04 Operating Model'!$G$55:$P$55),1/(1+$C25)^'06 DCF'!$G$20:$P$20)+('06 DCF'!$P$10+H$23*'04 Operating Model'!$P$11*(1-'04 Operating Model'!$P$55))*(1+'06 DCF'!$F$26)*(1-'06 DCF'!$F$26/'06 DCF'!$F$27)/($C25-'06 DCF'!$F$26)/(1+$C25)^'02 Assumptions'!$C$11+SUM('06 DCF'!$F$46:$F$52))/'06 DCF'!$F$54} -> 140.38659
C26: ='07 WACC'!$C$38+0 -> 0.11540544 | D26: {=(SUMPRODUCT('06 DCF'!$G$15:$P$15+D$23*'04 Operating Model'!$G$11:$P$11*(1-'04 Operating Model'!$G$55:$P$55),1/(1+$C26)^'06 DCF'!$G$20:$P$20)+('06 DCF'!$P$10+D$23*'04 Operating Model'!$P$11*(1-'04 Operating Model'!$P$55))*(1+'06 DCF'!$F$26)*(1-'06 DCF'!$F$26/'06 DCF'!$F$27)/($C26-'06 DCF'!$F$26)/(1+$C26)^'02 Assumptions'!$C$11+SUM('06 DCF'!$F$46:$F$52))/'06 DCF'!$F$54} -> 131.72392 | E26: {=(SUMPRODUCT('06 DCF'!$G$15:$P$15+E$23*'04 Operating Model'!$G$11:$P$11*(1-'04 Operating Model'!$G$55:$P$55),1/(1+$C26)^'06 DCF'!$G$20:$P$20)+('06 DCF'!$P$10+E$23*'04 Operating Model'!$P$11*(1-'04 Operating Model'!$P$55))*(1+'06 DCF'!$F$26)*(1-'06 DCF'!$F$26/'06 DCF'!$F$27)/($C26-'06 DCF'!$F$26)/(1+$C26)^'02 Assumptions'!$C$11+SUM('06 DCF'!$F$46:$F$52))/'06 DCF'!$F$54} -> 131.72392 | F26: {=(SUMPRODUCT('06 DCF'!$G$15:$P$15+F$23*'04 Operating Model'!$G$11:$P$11*(1-'04 Operating Model'!$G$55:$P$55),1/(1+$C26)^'06 DCF'!$G$20:$P$20)+('06 DCF'!$P$10+F$23*'04 Operating Model'!$P$11*(1-'04 Operating Model'!$P$55))*(1+'06 DCF'!$F$26)*(1-'06 DCF'!$F$26/'06 DCF'!$F$27)/($C26-'06 DCF'!$F$26)/(1+$C26)^'02 Assumptions'!$C$11+SUM('06 DCF'!$F$46:$F$52))/'06 DCF'!$F$54} -> 131.72392 | G26: {=(SUMPRODUCT('06 DCF'!$G$15:$P$15+G$23*'04 Operating Model'!$G$11:$P$11*(1-'04 Operating Model'!$G$55:$P$55),1/(1+$C26)^'06 DCF'!$G$20:$P$20)+('06 DCF'!$P$10+G$23*'04 Operating Model'!$P$11*(1-'04 Operating Model'!$P$55))*(1+'06 DCF'!$F$26)*(1-'06 DCF'!$F$26/'06 DCF'!$F$27)/($C26-'06 DCF'!$F$26)/(1+$C26)^'02 Assumptions'!$C$11+SUM('06 DCF'!$F$46:$F$52))/'06 DCF'!$F$54} -> 131.72392 | H26: {=(SUMPRODUCT('06 DCF'!$G$15:$P$15+H$23*'04 Operating Model'!$G$11:$P$11*(1-'04 Operating Model'!$G$55:$P$55),1/(1+$C26)^'06 DCF'!$G$20:$P$20)+('06 DCF'!$P$10+H$23*'04 Operating Model'!$P$11*(1-'04 Operating Model'!$P$55))*(1+'06 DCF'!$F$26)*(1-'06 DCF'!$F$26/'06 DCF'!$F$27)/($C26-'06 DCF'!$F$26)/(1+$C26)^'02 Assumptions'!$C$11+SUM('06 DCF'!$F$46:$F$52))/'06 DCF'!$F$54} -> 131.72392
C27: ='07 WACC'!$C$38+0.005 -> 0.12040544 | D27: {=(SUMPRODUCT('06 DCF'!$G$15:$P$15+D$23*'04 Operating Model'!$G$11:$P$11*(1-'04 Operating Model'!$G$55:$P$55),1/(1+$C27)^'06 DCF'!$G$20:$P$20)+('06 DCF'!$P$10+D$23*'04 Operating Model'!$P$11*(1-'04 Operating Model'!$P$55))*(1+'06 DCF'!$F$26)*(1-'06 DCF'!$F$26/'06 DCF'!$F$27)/($C27-'06 DCF'!$F$26)/(1+$C27)^'02 Assumptions'!$C$11+SUM('06 DCF'!$F$46:$F$52))/'06 DCF'!$F$54} -> 124.02724 | E27: {=(SUMPRODUCT('06 DCF'!$G$15:$P$15+E$23*'04 Operating Model'!$G$11:$P$11*(1-'04 Operating Model'!$G$55:$P$55),1/(1+$C27)^'06 DCF'!$G$20:$P$20)+('06 DCF'!$P$10+E$23*'04 Operating Model'!$P$11*(1-'04 Operating Model'!$P$55))*(1+'06 DCF'!$F$26)*(1-'06 DCF'!$F$26/'06 DCF'!$F$27)/($C27-'06 DCF'!$F$26)/(1+$C27)^'02 Assumptions'!$C$11+SUM('06 DCF'!$F$46:$F$52))/'06 DCF'!$F$54} -> 124.02724 | F27: {=(SUMPRODUCT('06 DCF'!$G$15:$P$15+F$23*'04 Operating Model'!$G$11:$P$11*(1-'04 Operating Model'!$G$55:$P$55),1/(1+$C27)^'06 DCF'!$G$20:$P$20)+('06 DCF'!$P$10+F$23*'04 Operating Model'!$P$11*(1-'04 Operating Model'!$P$55))*(1+'06 DCF'!$F$26)*(1-'06 DCF'!$F$26/'06 DCF'!$F$27)/($C27-'06 DCF'!$F$26)/(1+$C27)^'02 Assumptions'!$C$11+SUM('06 DCF'!$F$46:$F$52))/'06 DCF'!$F$54} -> 124.02724 | G27: {=(SUMPRODUCT('06 DCF'!$G$15:$P$15+G$23*'04 Operating Model'!$G$11:$P$11*(1-'04 Operating Model'!$G$55:$P$55),1/(1+$C27)^'06 DCF'!$G$20:$P$20)+('06 DCF'!$P$10+G$23*'04 Operating Model'!$P$11*(1-'04 Operating Model'!$P$55))*(1+'06 DCF'!$F$26)*(1-'06 DCF'!$F$26/'06 DCF'!$F$27)/($C27-'06 DCF'!$F$26)/(1+$C27)^'02 Assumptions'!$C$11+SUM('06 DCF'!$F$46:$F$52))/'06 DCF'!$F$54} -> 124.02724 | H27: {=(SUMPRODUCT('06 DCF'!$G$15:$P$15+H$23*'04 Operating Model'!$G$11:$P$11*(1-'04 Operating Model'!$G$55:$P$55),1/(1+$C27)^'06 DCF'!$G$20:$P$20)+('06 DCF'!$P$10+H$23*'04 Operating Model'!$P$11*(1-'04 Operating Model'!$P$55))*(1+'06 DCF'!$F$26)*(1-'06 DCF'!$F$26/'06 DCF'!$F$27)/($C27-'06 DCF'!$F$26)/(1+$C27)^'02 Assumptions'!$C$11+SUM('06 DCF'!$F$46:$F$52))/'06 DCF'!$F$54} -> 124.02724
C28: ='07 WACC'!$C$38+0.01 -> 0.12540544 | D28: {=(SUMPRODUCT('06 DCF'!$G$15:$P$15+D$23*'04 Operating Model'!$G$11:$P$11*(1-'04 Operating Model'!$G$55:$P$55),1/(1+$C28)^'06 DCF'!$G$20:$P$20)+('06 DCF'!$P$10+D$23*'04 Operating Model'!$P$11*(1-'04 Operating Model'!$P$55))*(1+'06 DCF'!$F$26)*(1-'06 DCF'!$F$26/'06 DCF'!$F$27)/($C28-'06 DCF'!$F$26)/(1+$C28)^'02 Assumptions'!$C$11+SUM('06 DCF'!$F$46:$F$52))/'06 DCF'!$F$54} -> 117.14421 | E28: {=(SUMPRODUCT('06 DCF'!$G$15:$P$15+E$23*'04 Operating Model'!$G$11:$P$11*(1-'04 Operating Model'!$G$55:$P$55),1/(1+$C28)^'06 DCF'!$G$20:$P$20)+('06 DCF'!$P$10+E$23*'04 Operating Model'!$P$11*(1-'04 Operating Model'!$P$55))*(1+'06 DCF'!$F$26)*(1-'06 DCF'!$F$26/'06 DCF'!$F$27)/($C28-'06 DCF'!$F$26)/(1+$C28)^'02 Assumptions'!$C$11+SUM('06 DCF'!$F$46:$F$52))/'06 DCF'!$F$54} -> 117.14421 | F28: {=(SUMPRODUCT('06 DCF'!$G$15:$P$15+F$23*'04 Operating Model'!$G$11:$P$11*(1-'04 Operating Model'!$G$55:$P$55),1/(1+$C28)^'06 DCF'!$G$20:$P$20)+('06 DCF'!$P$10+F$23*'04 Operating Model'!$P$11*(1-'04 Operating Model'!$P$55))*(1+'06 DCF'!$F$26)*(1-'06 DCF'!$F$26/'06 DCF'!$F$27)/($C28-'06 DCF'!$F$26)/(1+$C28)^'02 Assumptions'!$C$11+SUM('06 DCF'!$F$46:$F$52))/'06 DCF'!$F$54} -> 117.14421 | G28: {=(SUMPRODUCT('06 DCF'!$G$15:$P$15+G$23*'04 Operating Model'!$G$11:$P$11*(1-'04 Operating Model'!$G$55:$P$55),1/(1+$C28)^'06 DCF'!$G$20:$P$20)+('06 DCF'!$P$10+G$23*'04 Operating Model'!$P$11*(1-'04 Operating Model'!$P$55))*(1+'06 DCF'!$F$26)*(1-'06 DCF'!$F$26/'06 DCF'!$F$27)/($C28-'06 DCF'!$F$26)/(1+$C28)^'02 Assumptions'!$C$11+SUM('06 DCF'!$F$46:$F$52))/'06 DCF'!$F$54} -> 117.14421 | H28: {=(SUMPRODUCT('06 DCF'!$G$15:$P$15+H$23*'04 Operating Model'!$G$11:$P$11*(1-'04 Operating Model'!$G$55:$P$55),1/(1+$C28)^'06 DCF'!$G$20:$P$20)+('06 DCF'!$P$10+H$23*'04 Operating Model'!$P$11*(1-'04 Operating Model'!$P$55))*(1+'06 DCF'!$F$26)*(1-'06 DCF'!$F$26/'06 DCF'!$F$27)/($C28-'06 DCF'!$F$26)/(1+$C28)^'02 Assumptions'!$C$11+SUM('06 DCF'!$F$46:$F$52))/'06 DCF'!$F$54} -> 117.14421
B31: REJILLA D — WACC × DESPLAZAMIENTO DE CAPEX SOBRE INGRESOS (pp) (primer orden: NO recoge el escudo fiscal de la depreciación asociada)
B32: WACC ↓ / Δ capex sobre ingresos (p.p.) →
C33: ='07 WACC'!$C$38+-0.01 -> 0.10540544 | D33: {=(SUMPRODUCT('06 DCF'!$G$15:$P$15-D$32*'04 Operating Model'!$G$11:$P$11,1/(1+$C33)^'06 DCF'!$G$20:$P$20)+'06 DCF'!$P$10*(1+'06 DCF'!$F$26)*(1-'06 DCF'!$F$26/'06 DCF'!$F$27)/($C33-'06 DCF'!$F$26)/(1+$C33)^'02 Assumptions'!$C$11+SUM('06 DCF'!$F$46:$F$52))/'06 DCF'!$F$54} -> 150.20802 | E33: {=(SUMPRODUCT('06 DCF'!$G$15:$P$15-E$32*'04 Operating Model'!$G$11:$P$11,1/(1+$C33)^'06 DCF'!$G$20:$P$20)+'06 DCF'!$P$10*(1+'06 DCF'!$F$26)*(1-'06 DCF'!$F$26/'06 DCF'!$F$27)/($C33-'06 DCF'!$F$26)/(1+$C33)^'02 Assumptions'!$C$11+SUM('06 DCF'!$F$46:$F$52))/'06 DCF'!$F$54} -> 150.20802 | F33: {=(SUMPRODUCT('06 DCF'!$G$15:$P$15-F$32*'04 Operating Model'!$G$11:$P$11,1/(1+$C33)^'06 DCF'!$G$20:$P$20)+'06 DCF'!$P$10*(1+'06 DCF'!$F$26)*(1-'06 DCF'!$F$26/'06 DCF'!$F$27)/($C33-'06 DCF'!$F$26)/(1+$C33)^'02 Assumptions'!$C$11+SUM('06 DCF'!$F$46:$F$52))/'06 DCF'!$F$54} -> 150.20802 | G33: {=(SUMPRODUCT('06 DCF'!$G$15:$P$15-G$32*'04 Operating Model'!$G$11:$P$11,1/(1+$C33)^'06 DCF'!$G$20:$P$20)+'06 DCF'!$P$10*(1+'06 DCF'!$F$26)*(1-'06 DCF'!$F$26/'06 DCF'!$F$27)/($C33-'06 DCF'!$F$26)/(1+$C33)^'02 Assumptions'!$C$11+SUM('06 DCF'!$F$46:$F$52))/'06 DCF'!$F$54} -> 150.20802 | H33: {=(SUMPRODUCT('06 DCF'!$G$15:$P$15-H$32*'04 Operating Model'!$G$11:$P$11,1/(1+$C33)^'06 DCF'!$G$20:$P$20)+'06 DCF'!$P$10*(1+'06 DCF'!$F$26)*(1-'06 DCF'!$F$26/'06 DCF'!$F$27)/($C33-'06 DCF'!$F$26)/(1+$C33)^'02 Assumptions'!$C$11+SUM('06 DCF'!$F$46:$F$52))/'06 DCF'!$F$54} -> 150.20802
C34: ='07 WACC'!$C$38+-0.005 -> 0.11040544 | D34: {=(SUMPRODUCT('06 DCF'!$G$15:$P$15-D$32*'04 Operating Model'!$G$11:$P$11,1/(1+$C34)^'06 DCF'!$G$20:$P$20)+'06 DCF'!$P$10*(1+'06 DCF'!$F$26)*(1-'06 DCF'!$F$26/'06 DCF'!$F$27)/($C34-'06 DCF'!$F$26)/(1+$C34)^'02 Assumptions'!$C$11+SUM('06 DCF'!$F$46:$F$52))/'06 DCF'!$F$54} -> 140.38659 | E34: {=(SUMPRODUCT('06 DCF'!$G$15:$P$15-E$32*'04 Operating Model'!$G$11:$P$11,1/(1+$C34)^'06 DCF'!$G$20:$P$20)+'06 DCF'!$P$10*(1+'06 DCF'!$F$26)*(1-'06 DCF'!$F$26/'06 DCF'!$F$27)/($C34-'06 DCF'!$F$26)/(1+$C34)^'02 Assumptions'!$C$11+SUM('06 DCF'!$F$46:$F$52))/'06 DCF'!$F$54} -> 140.38659 | F34: {=(SUMPRODUCT('06 DCF'!$G$15:$P$15-F$32*'04 Operating Model'!$G$11:$P$11,1/(1+$C34)^'06 DCF'!$G$20:$P$20)+'06 DCF'!$P$10*(1+'06 DCF'!$F$26)*(1-'06 DCF'!$F$26/'06 DCF'!$F$27)/($C34-'06 DCF'!$F$26)/(1+$C34)^'02 Assumptions'!$C$11+SUM('06 DCF'!$F$46:$F$52))/'06 DCF'!$F$54} -> 140.38659 | G34: {=(SUMPRODUCT('06 DCF'!$G$15:$P$15-G$32*'04 Operating Model'!$G$11:$P$11,1/(1+$C34)^'06 DCF'!$G$20:$P$20)+'06 DCF'!$P$10*(1+'06 DCF'!$F$26)*(1-'06 DCF'!$F$26/'06 DCF'!$F$27)/($C34-'06 DCF'!$F$26)/(1+$C34)^'02 Assumptions'!$C$11+SUM('06 DCF'!$F$46:$F$52))/'06 DCF'!$F$54} -> 140.38659 | H34: {=(SUMPRODUCT('06 DCF'!$G$15:$P$15-H$32*'04 Operating Model'!$G$11:$P$11,1/(1+$C34)^'06 DCF'!$G$20:$P$20)+'06 DCF'!$P$10*(1+'06 DCF'!$F$26)*(1-'06 DCF'!$F$26/'06 DCF'!$F$27)/($C34-'06 DCF'!$F$26)/(1+$C34)^'02 Assumptions'!$C$11+SUM('06 DCF'!$F$46:$F$52))/'06 DCF'!$F$54} -> 140.38659
C35: ='07 WACC'!$C$38+0 -> 0.11540544 | D35: {=(SUMPRODUCT('06 DCF'!$G$15:$P$15-D$32*'04 Operating Model'!$G$11:$P$11,1/(1+$C35)^'06 DCF'!$G$20:$P$20)+'06 DCF'!$P$10*(1+'06 DCF'!$F$26)*(1-'06 DCF'!$F$26/'06 DCF'!$F$27)/($C35-'06 DCF'!$F$26)/(1+$C35)^'02 Assumptions'!$C$11+SUM('06 DCF'!$F$46:$F$52))/'06 DCF'!$F$54} -> 131.72392 | E35: {=(SUMPRODUCT('06 DCF'!$G$15:$P$15-E$32*'04 Operating Model'!$G$11:$P$11,1/(1+$C35)^'06 DCF'!$G$20:$P$20)+'06 DCF'!$P$10*(1+'06 DCF'!$F$26)*(1-'06 DCF'!$F$26/'06 DCF'!$F$27)/($C35-'06 DCF'!$F$26)/(1+$C35)^'02 Assumptions'!$C$11+SUM('06 DCF'!$F$46:$F$52))/'06 DCF'!$F$54} -> 131.72392 | F35: {=(SUMPRODUCT('06 DCF'!$G$15:$P$15-F$32*'04 Operating Model'!$G$11:$P$11,1/(1+$C35)^'06 DCF'!$G$20:$P$20)+'06 DCF'!$P$10*(1+'06 DCF'!$F$26)*(1-'06 DCF'!$F$26/'06 DCF'!$F$27)/($C35-'06 DCF'!$F$26)/(1+$C35)^'02 Assumptions'!$C$11+SUM('06 DCF'!$F$46:$F$52))/'06 DCF'!$F$54} -> 131.72392 | G35: {=(SUMPRODUCT('06 DCF'!$G$15:$P$15-G$32*'04 Operating Model'!$G$11:$P$11,1/(1+$C35)^'06 DCF'!$G$20:$P$20)+'06 DCF'!$P$10*(1+'06 DCF'!$F$26)*(1-'06 DCF'!$F$26/'06 DCF'!$F$27)/($C35-'06 DCF'!$F$26)/(1+$C35)^'02 Assumptions'!$C$11+SUM('06 DCF'!$F$46:$F$52))/'06 DCF'!$F$54} -> 131.72392 | H35: {=(SUMPRODUCT('06 DCF'!$G$15:$P$15-H$32*'04 Operating Model'!$G$11:$P$11,1/(1+$C35)^'06 DCF'!$G$20:$P$20)+'06 DCF'!$P$10*(1+'06 DCF'!$F$26)*(1-'06 DCF'!$F$26/'06 DCF'!$F$27)/($C35-'06 DCF'!$F$26)/(1+$C35)^'02 Assumptions'!$C$11+SUM('06 DCF'!$F$46:$F$52))/'06 DCF'!$F$54} -> 131.72392
C36: ='07 WACC'!$C$38+0.005 -> 0.12040544 | D36: {=(SUMPRODUCT('06 DCF'!$G$15:$P$15-D$32*'04 Operating Model'!$G$11:$P$11,1/(1+$C36)^'06 DCF'!$G$20:$P$20)+'06 DCF'!$P$10*(1+'06 DCF'!$F$26)*(1-'06 DCF'!$F$26/'06 DCF'!$F$27)/($C36-'06 DCF'!$F$26)/(1+$C36)^'02 Assumptions'!$C$11+SUM('06 DCF'!$F$46:$F$52))/'06 DCF'!$F$54} -> 124.02724 | E36: {=(SUMPRODUCT('06 DCF'!$G$15:$P$15-E$32*'04 Operating Model'!$G$11:$P$11,1/(1+$C36)^'06 DCF'!$G$20:$P$20)+'06 DCF'!$P$10*(1+'06 DCF'!$F$26)*(1-'06 DCF'!$F$26/'06 DCF'!$F$27)/($C36-'06 DCF'!$F$26)/(1+$C36)^'02 Assumptions'!$C$11+SUM('06 DCF'!$F$46:$F$52))/'06 DCF'!$F$54} -> 124.02724 | F36: {=(SUMPRODUCT('06 DCF'!$G$15:$P$15-F$32*'04 Operating Model'!$G$11:$P$11,1/(1+$C36)^'06 DCF'!$G$20:$P$20)+'06 DCF'!$P$10*(1+'06 DCF'!$F$26)*(1-'06 DCF'!$F$26/'06 DCF'!$F$27)/($C36-'06 DCF'!$F$26)/(1+$C36)^'02 Assumptions'!$C$11+SUM('06 DCF'!$F$46:$F$52))/'06 DCF'!$F$54} -> 124.02724 | G36: {=(SUMPRODUCT('06 DCF'!$G$15:$P$15-G$32*'04 Operating Model'!$G$11:$P$11,1/(1+$C36)^'06 DCF'!$G$20:$P$20)+'06 DCF'!$P$10*(1+'06 DCF'!$F$26)*(1-'06 DCF'!$F$26/'06 DCF'!$F$27)/($C36-'06 DCF'!$F$26)/(1+$C36)^'02 Assumptions'!$C$11+SUM('06 DCF'!$F$46:$F$52))/'06 DCF'!$F$54} -> 124.02724 | H36: {=(SUMPRODUCT('06 DCF'!$G$15:$P$15-H$32*'04 Operating Model'!$G$11:$P$11,1/(1+$C36)^'06 DCF'!$G$20:$P$20)+'06 DCF'!$P$10*(1+'06 DCF'!$F$26)*(1-'06 DCF'!$F$26/'06 DCF'!$F$27)/($C36-'06 DCF'!$F$26)/(1+$C36)^'02 Assumptions'!$C$11+SUM('06 DCF'!$F$46:$F$52))/'06 DCF'!$F$54} -> 124.02724
C37: ='07 WACC'!$C$38+0.01 -> 0.12540544 | D37: {=(SUMPRODUCT('06 DCF'!$G$15:$P$15-D$32*'04 Operating Model'!$G$11:$P$11,1/(1+$C37)^'06 DCF'!$G$20:$P$20)+'06 DCF'!$P$10*(1+'06 DCF'!$F$26)*(1-'06 DCF'!$F$26/'06 DCF'!$F$27)/($C37-'06 DCF'!$F$26)/(1+$C37)^'02 Assumptions'!$C$11+SUM('06 DCF'!$F$46:$F$52))/'06 DCF'!$F$54} -> 117.14421 | E37: {=(SUMPRODUCT('06 DCF'!$G$15:$P$15-E$32*'04 Operating Model'!$G$11:$P$11,1/(1+$C37)^'06 DCF'!$G$20:$P$20)+'06 DCF'!$P$10*(1+'06 DCF'!$F$26)*(1-'06 DCF'!$F$26/'06 DCF'!$F$27)/($C37-'06 DCF'!$F$26)/(1+$C37)^'02 Assumptions'!$C$11+SUM('06 DCF'!$F$46:$F$52))/'06 DCF'!$F$54} -> 117.14421 | F37: {=(SUMPRODUCT('06 DCF'!$G$15:$P$15-F$32*'04 Operating Model'!$G$11:$P$11,1/(1+$C37)^'06 DCF'!$G$20:$P$20)+'06 DCF'!$P$10*(1+'06 DCF'!$F$26)*(1-'06 DCF'!$F$26/'06 DCF'!$F$27)/($C37-'06 DCF'!$F$26)/(1+$C37)^'02 Assumptions'!$C$11+SUM('06 DCF'!$F$46:$F$52))/'06 DCF'!$F$54} -> 117.14421 | G37: {=(SUMPRODUCT('06 DCF'!$G$15:$P$15-G$32*'04 Operating Model'!$G$11:$P$11,1/(1+$C37)^'06 DCF'!$G$20:$P$20)+'06 DCF'!$P$10*(1+'06 DCF'!$F$26)*(1-'06 DCF'!$F$26/'06 DCF'!$F$27)/($C37-'06 DCF'!$F$26)/(1+$C37)^'02 Assumptions'!$C$11+SUM('06 DCF'!$F$46:$F$52))/'06 DCF'!$F$54} -> 117.14421 | H37: {=(SUMPRODUCT('06 DCF'!$G$15:$P$15-H$32*'04 Operating Model'!$G$11:$P$11,1/(1+$C37)^'06 DCF'!$G$20:$P$20)+'06 DCF'!$P$10*(1+'06 DCF'!$F$26)*(1-'06 DCF'!$F$26/'06 DCF'!$F$27)/($C37-'06 DCF'!$F$26)/(1+$C37)^'02 Assumptions'!$C$11+SUM('06 DCF'!$F$46:$F$52))/'06 DCF'!$F$54} -> 117.14421
B40: REJILLA E — WACC × DESPLAZAMIENTO DEL TIPO IMPOSITIVO DE CAJA (pp) (exacta)
B41: WACC ↓ / Δ tipo de caja (p.p.) →
C42: ='07 WACC'!$C$38+-0.01 -> 0.10540544 | D42: {=(SUMPRODUCT('06 DCF'!$G$15:$P$15-D$41*'06 DCF'!$G$7:$P$7,1/(1+$C42)^'06 DCF'!$G$20:$P$20)+('06 DCF'!$P$10-D$41*'06 DCF'!$P$7)*(1+'06 DCF'!$F$26)*(1-'06 DCF'!$F$26/'06 DCF'!$F$27)/($C42-'06 DCF'!$F$26)/(1+$C42)^'02 Assumptions'!$C$11+SUM('06 DCF'!$F$46:$F$52))/'06 DCF'!$F$54} -> 150.20802 | E42: {=(SUMPRODUCT('06 DCF'!$G$15:$P$15-E$41*'06 DCF'!$G$7:$P$7,1/(1+$C42)^'06 DCF'!$G$20:$P$20)+('06 DCF'!$P$10-E$41*'06 DCF'!$P$7)*(1+'06 DCF'!$F$26)*(1-'06 DCF'!$F$26/'06 DCF'!$F$27)/($C42-'06 DCF'!$F$26)/(1+$C42)^'02 Assumptions'!$C$11+SUM('06 DCF'!$F$46:$F$52))/'06 DCF'!$F$54} -> 150.20802 | F42: {=(SUMPRODUCT('06 DCF'!$G$15:$P$15-F$41*'06 DCF'!$G$7:$P$7,1/(1+$C42)^'06 DCF'!$G$20:$P$20)+('06 DCF'!$P$10-F$41*'06 DCF'!$P$7)*(1+'06 DCF'!$F$26)*(1-'06 DCF'!$F$26/'06 DCF'!$F$27)/($C42-'06 DCF'!$F$26)/(1+$C42)^'02 Assumptions'!$C$11+SUM('06 DCF'!$F$46:$F$52))/'06 DCF'!$F$54} -> 150.20802 | G42: {=(SUMPRODUCT('06 DCF'!$G$15:$P$15-G$41*'06 DCF'!$G$7:$P$7,1/(1+$C42)^'06 DCF'!$G$20:$P$20)+('06 DCF'!$P$10-G$41*'06 DCF'!$P$7)*(1+'06 DCF'!$F$26)*(1-'06 DCF'!$F$26/'06 DCF'!$F$27)/($C42-'06 DCF'!$F$26)/(1+$C42)^'02 Assumptions'!$C$11+SUM('06 DCF'!$F$46:$F$52))/'06 DCF'!$F$54} -> 150.20802 | H42: {=(SUMPRODUCT('06 DCF'!$G$15:$P$15-H$41*'06 DCF'!$G$7:$P$7,1/(1+$C42)^'06 DCF'!$G$20:$P$20)+('06 DCF'!$P$10-H$41*'06 DCF'!$P$7)*(1+'06 DCF'!$F$26)*(1-'06 DCF'!$F$26/'06 DCF'!$F$27)/($C42-'06 DCF'!$F$26)/(1+$C42)^'02 Assumptions'!$C$11+SUM('06 DCF'!$F$46:$F$52))/'06 DCF'!$F$54} -> 150.20802
C43: ='07 WACC'!$C$38+-0.005 -> 0.11040544 | D43: {=(SUMPRODUCT('06 DCF'!$G$15:$P$15-D$41*'06 DCF'!$G$7:$P$7,1/(1+$C43)^'06 DCF'!$G$20:$P$20)+('06 DCF'!$P$10-D$41*'06 DCF'!$P$7)*(1+'06 DCF'!$F$26)*(1-'06 DCF'!$F$26/'06 DCF'!$F$27)/($C43-'06 DCF'!$F$26)/(1+$C43)^'02 Assumptions'!$C$11+SUM('06 DCF'!$F$46:$F$52))/'06 DCF'!$F$54} -> 140.38659 | E43: {=(SUMPRODUCT('06 DCF'!$G$15:$P$15-E$41*'06 DCF'!$G$7:$P$7,1/(1+$C43)^'06 DCF'!$G$20:$P$20)+('06 DCF'!$P$10-E$41*'06 DCF'!$P$7)*(1+'06 DCF'!$F$26)*(1-'06 DCF'!$F$26/'06 DCF'!$F$27)/($C43-'06 DCF'!$F$26)/(1+$C43)^'02 Assumptions'!$C$11+SUM('06 DCF'!$F$46:$F$52))/'06 DCF'!$F$54} -> 140.38659 | F43: {=(SUMPRODUCT('06 DCF'!$G$15:$P$15-F$41*'06 DCF'!$G$7:$P$7,1/(1+$C43)^'06 DCF'!$G$20:$P$20)+('06 DCF'!$P$10-F$41*'06 DCF'!$P$7)*(1+'06 DCF'!$F$26)*(1-'06 DCF'!$F$26/'06 DCF'!$F$27)/($C43-'06 DCF'!$F$26)/(1+$C43)^'02 Assumptions'!$C$11+SUM('06 DCF'!$F$46:$F$52))/'06 DCF'!$F$54} -> 140.38659 | G43: {=(SUMPRODUCT('06 DCF'!$G$15:$P$15-G$41*'06 DCF'!$G$7:$P$7,1/(1+$C43)^'06 DCF'!$G$20:$P$20)+('06 DCF'!$P$10-G$41*'06 DCF'!$P$7)*(1+'06 DCF'!$F$26)*(1-'06 DCF'!$F$26/'06 DCF'!$F$27)/($C43-'06 DCF'!$F$26)/(1+$C43)^'02 Assumptions'!$C$11+SUM('06 DCF'!$F$46:$F$52))/'06 DCF'!$F$54} -> 140.38659 | H43: {=(SUMPRODUCT('06 DCF'!$G$15:$P$15-H$41*'06 DCF'!$G$7:$P$7,1/(1+$C43)^'06 DCF'!$G$20:$P$20)+('06 DCF'!$P$10-H$41*'06 DCF'!$P$7)*(1+'06 DCF'!$F$26)*(1-'06 DCF'!$F$26/'06 DCF'!$F$27)/($C43-'06 DCF'!$F$26)/(1+$C43)^'02 Assumptions'!$C$11+SUM('06 DCF'!$F$46:$F$52))/'06 DCF'!$F$54} -> 140.38659
C44: ='07 WACC'!$C$38+0 -> 0.11540544 | D44: {=(SUMPRODUCT('06 DCF'!$G$15:$P$15-D$41*'06 DCF'!$G$7:$P$7,1/(1+$C44)^'06 DCF'!$G$20:$P$20)+('06 DCF'!$P$10-D$41*'06 DCF'!$P$7)*(1+'06 DCF'!$F$26)*(1-'06 DCF'!$F$26/'06 DCF'!$F$27)/($C44-'06 DCF'!$F$26)/(1+$C44)^'02 Assumptions'!$C$11+SUM('06 DCF'!$F$46:$F$52))/'06 DCF'!$F$54} -> 131.72392 | E44: {=(SUMPRODUCT('06 DCF'!$G$15:$P$15-E$41*'06 DCF'!$G$7:$P$7,1/(1+$C44)^'06 DCF'!$G$20:$P$20)+('06 DCF'!$P$10-E$41*'06 DCF'!$P$7)*(1+'06 DCF'!$F$26)*(1-'06 DCF'!$F$26/'06 DCF'!$F$27)/($C44-'06 DCF'!$F$26)/(1+$C44)^'02 Assumptions'!$C$11+SUM('06 DCF'!$F$46:$F$52))/'06 DCF'!$F$54} -> 131.72392 | F44: {=(SUMPRODUCT('06 DCF'!$G$15:$P$15-F$41*'06 DCF'!$G$7:$P$7,1/(1+$C44)^'06 DCF'!$G$20:$P$20)+('06 DCF'!$P$10-F$41*'06 DCF'!$P$7)*(1+'06 DCF'!$F$26)*(1-'06 DCF'!$F$26/'06 DCF'!$F$27)/($C44-'06 DCF'!$F$26)/(1+$C44)^'02 Assumptions'!$C$11+SUM('06 DCF'!$F$46:$F$52))/'06 DCF'!$F$54} -> 131.72392 | G44: {=(SUMPRODUCT('06 DCF'!$G$15:$P$15-G$41*'06 DCF'!$G$7:$P$7,1/(1+$C44)^'06 DCF'!$G$20:$P$20)+('06 DCF'!$P$10-G$41*'06 DCF'!$P$7)*(1+'06 DCF'!$F$26)*(1-'06 DCF'!$F$26/'06 DCF'!$F$27)/($C44-'06 DCF'!$F$26)/(1+$C44)^'02 Assumptions'!$C$11+SUM('06 DCF'!$F$46:$F$52))/'06 DCF'!$F$54} -> 131.72392 | H44: {=(SUMPRODUCT('06 DCF'!$G$15:$P$15-H$41*'06 DCF'!$G$7:$P$7,1/(1+$C44)^'06 DCF'!$G$20:$P$20)+('06 DCF'!$P$10-H$41*'06 DCF'!$P$7)*(1+'06 DCF'!$F$26)*(1-'06 DCF'!$F$26/'06 DCF'!$F$27)/($C44-'06 DCF'!$F$26)/(1+$C44)^'02 Assumptions'!$C$11+SUM('06 DCF'!$F$46:$F$52))/'06 DCF'!$F$54} -> 131.72392
C45: ='07 WACC'!$C$38+0.005 -> 0.12040544 | D45: {=(SUMPRODUCT('06 DCF'!$G$15:$P$15-D$41*'06 DCF'!$G$7:$P$7,1/(1+$C45)^'06 DCF'!$G$20:$P$20)+('06 DCF'!$P$10-D$41*'06 DCF'!$P$7)*(1+'06 DCF'!$F$26)*(1-'06 DCF'!$F$26/'06 DCF'!$F$27)/($C45-'06 DCF'!$F$26)/(1+$C45)^'02 Assumptions'!$C$11+SUM('06 DCF'!$F$46:$F$52))/'06 DCF'!$F$54} -> 124.02724 | E45: {=(SUMPRODUCT('06 DCF'!$G$15:$P$15-E$41*'06 DCF'!$G$7:$P$7,1/(1+$C45)^'06 DCF'!$G$20:$P$20)+('06 DCF'!$P$10-E$41*'06 DCF'!$P$7)*(1+'06 DCF'!$F$26)*(1-'06 DCF'!$F$26/'06 DCF'!$F$27)/($C45-'06 DCF'!$F$26)/(1+$C45)^'02 Assumptions'!$C$11+SUM('06 DCF'!$F$46:$F$52))/'06 DCF'!$F$54} -> 124.02724 | F45: {=(SUMPRODUCT('06 DCF'!$G$15:$P$15-F$41*'06 DCF'!$G$7:$P$7,1/(1+$C45)^'06 DCF'!$G$20:$P$20)+('06 DCF'!$P$10-F$41*'06 DCF'!$P$7)*(1+'06 DCF'!$F$26)*(1-'06 DCF'!$F$26/'06 DCF'!$F$27)/($C45-'06 DCF'!$F$26)/(1+$C45)^'02 Assumptions'!$C$11+SUM('06 DCF'!$F$46:$F$52))/'06 DCF'!$F$54} -> 124.02724 | G45: {=(SUMPRODUCT('06 DCF'!$G$15:$P$15-G$41*'06 DCF'!$G$7:$P$7,1/(1+$C45)^'06 DCF'!$G$20:$P$20)+('06 DCF'!$P$10-G$41*'06 DCF'!$P$7)*(1+'06 DCF'!$F$26)*(1-'06 DCF'!$F$26/'06 DCF'!$F$27)/($C45-'06 DCF'!$F$26)/(1+$C45)^'02 Assumptions'!$C$11+SUM('06 DCF'!$F$46:$F$52))/'06 DCF'!$F$54} -> 124.02724 | H45: {=(SUMPRODUCT('06 DCF'!$G$15:$P$15-H$41*'06 DCF'!$G$7:$P$7,1/(1+$C45)^'06 DCF'!$G$20:$P$20)+('06 DCF'!$P$10-H$41*'06 DCF'!$P$7)*(1+'06 DCF'!$F$26)*(1-'06 DCF'!$F$26/'06 DCF'!$F$27)/($C45-'06 DCF'!$F$26)/(1+$C45)^'02 Assumptions'!$C$11+SUM('06 DCF'!$F$46:$F$52))/'06 DCF'!$F$54} -> 124.02724
C46: ='07 WACC'!$C$38+0.01 -> 0.12540544 | D46: {=(SUMPRODUCT('06 DCF'!$G$15:$P$15-D$41*'06 DCF'!$G$7:$P$7,1/(1+$C46)^'06 DCF'!$G$20:$P$20)+('06 DCF'!$P$10-D$41*'06 DCF'!$P$7)*(1+'06 DCF'!$F$26)*(1-'06 DCF'!$F$26/'06 DCF'!$F$27)/($C46-'06 DCF'!$F$26)/(1+$C46)^'02 Assumptions'!$C$11+SUM('06 DCF'!$F$46:$F$52))/'06 DCF'!$F$54} -> 117.14421 | E46: {=(SUMPRODUCT('06 DCF'!$G$15:$P$15-E$41*'06 DCF'!$G$7:$P$7,1/(1+$C46)^'06 DCF'!$G$20:$P$20)+('06 DCF'!$P$10-E$41*'06 DCF'!$P$7)*(1+'06 DCF'!$F$26)*(1-'06 DCF'!$F$26/'06 DCF'!$F$27)/($C46-'06 DCF'!$F$26)/(1+$C46)^'02 Assumptions'!$C$11+SUM('06 DCF'!$F$46:$F$52))/'06 DCF'!$F$54} -> 117.14421 | F46: {=(SUMPRODUCT('06 DCF'!$G$15:$P$15-F$41*'06 DCF'!$G$7:$P$7,1/(1+$C46)^'06 DCF'!$G$20:$P$20)+('06 DCF'!$P$10-F$41*'06 DCF'!$P$7)*(1+'06 DCF'!$F$26)*(1-'06 DCF'!$F$26/'06 DCF'!$F$27)/($C46-'06 DCF'!$F$26)/(1+$C46)^'02 Assumptions'!$C$11+SUM('06 DCF'!$F$46:$F$52))/'06 DCF'!$F$54} -> 117.14421 | G46: {=(SUMPRODUCT('06 DCF'!$G$15:$P$15-G$41*'06 DCF'!$G$7:$P$7,1/(1+$C46)^'06 DCF'!$G$20:$P$20)+('06 DCF'!$P$10-G$41*'06 DCF'!$P$7)*(1+'06 DCF'!$F$26)*(1-'06 DCF'!$F$26/'06 DCF'!$F$27)/($C46-'06 DCF'!$F$26)/(1+$C46)^'02 Assumptions'!$C$11+SUM('06 DCF'!$F$46:$F$52))/'06 DCF'!$F$54} -> 117.14421 | H46: {=(SUMPRODUCT('06 DCF'!$G$15:$P$15-H$41*'06 DCF'!$G$7:$P$7,1/(1+$C46)^'06 DCF'!$G$20:$P$20)+('06 DCF'!$P$10-H$41*'06 DCF'!$P$7)*(1+'06 DCF'!$F$26)*(1-'06 DCF'!$F$26/'06 DCF'!$F$27)/($C46-'06 DCF'!$F$26)/(1+$C46)^'02 Assumptions'!$C$11+SUM('06 DCF'!$F$46:$F$52))/'06 DCF'!$F$54} -> 117.14421
B49: JERARQUÍA DE DRIVERS DEL VALOR (rango de valor por acción a WACC base, entre los extremos de cada eje)
B50: Driver | C50: Valor mínimo | D50: Valor máximo | E50: Rango ($/acc) | F50: Clasificación
B51: Crecimiento terminal g (±100 pb) | C51: =MIN(D8:H8) -> 126.59334 | D51: =MAX(D8:H8) -> 138.16351 | E51: =D51-C51 -> 11.57017 | F51: =IF(E51>=LARGE($E$51:$E$56,2),"PRIMARIO",IF(E51>=LARGE($E$51:$E$56,4),"SECUNDARIO","BAJO IMPACTO")) -> PRIMARIO
B52: WACC (±100 pb) | C52: =MIN(D6:D10) -> 113.47531 | D52: =MAX(D6:D10) -> 142.85602 | E52: =D52-C52 -> 29.380708 | F52: =IF(E52>=LARGE($E$51:$E$56,2),"PRIMARIO",IF(E52>=LARGE($E$51:$E$56,4),"SECUNDARIO","BAJO IMPACTO")) -> PRIMARIO
B53: Margen EBIT (±300 pb) | C53: =MIN(D26:H26) -> 131.72392 | D53: =MAX(D26:H26) -> 131.72392 | E53: =D53-C53 -> 0 | F53: =IF(E53>=LARGE($E$51:$E$56,2),"PRIMARIO",IF(E53>=LARGE($E$51:$E$56,4),"SECUNDARIO","BAJO IMPACTO")) -> SECUNDARIO
B54: Tipo impositivo de caja (±300 pb) | C54: =MIN(D44:H44) -> 131.72392 | D54: =MAX(D44:H44) -> 131.72392 | E54: =D54-C54 -> 0 | F54: =IF(E54>=LARGE($E$51:$E$56,2),"PRIMARIO",IF(E54>=LARGE($E$51:$E$56,4),"SECUNDARIO","BAJO IMPACTO")) -> SECUNDARIO
B55: Capex sobre ingresos (±200 pb) | C55: =MIN(D35:H35) -> 131.72392 | D55: =MAX(D35:H35) -> 131.72392 | E55: =D55-C55 -> 0 | F55: =IF(E55>=LARGE($E$51:$E$56,2),"PRIMARIO",IF(E55>=LARGE($E$51:$E$56,4),"SECUNDARIO","BAJO IMPACTO")) -> SECUNDARIO
B56: Múltiplo de salida (±4x) | C56: =MIN(D17:H17) -> 68.127285 | D56: =MAX(D17:H17) -> 68.127285 | E56: =D56-C56 -> 0 | F56: =IF(E56>=LARGE($E$51:$E$56,2),"PRIMARIO",IF(E56>=LARGE($E$51:$E$56,4),"SECUNDARIO","BAJO IMPACTO")) -> SECUNDARIO
B58: SENSIBILIDAD CRECIMIENTO DE INGRESOS × MARGEN: NO admite forma cerrada
B59: La depreciación depende de la trayectoria acumulada de PP&E, por lo que un shock de crecimiento no se puede revalorar analíticamente sin re-ejecutar el modelo. Excel resolvería esto con una Tabla de Datos (Datos → Análisis de hipótesis), que no se puede crear por programación. Procedimiento manual:
B60: Paso 1 | C60: Ir a '02 Assumptions'!C104 (shock uniforme al crecimiento de ingresos, en pp).
B61: Paso 2 | C61: Introducir sucesivamente −3,0pp / −1,5pp / 0 / +1,5pp / +3,0pp y anotar '01 Summary'!C18 en la tabla inferior.
B62: Paso 3 | C62: Repetir para cada desplazamiento de margen usando la REJILLA C, que sí es exacta y ya recoge el efecto margen.
B63: Paso 4 | C63: Devolver C104 a 0 al terminar. Si se deja distinto de 0 TODO el libro queda desplazado.
B64: Aviso | C64: Un shock de crecimiento arrastra capex y circulante porque están definidos como porcentaje de ingresos: el efecto neto sobre el valor es MUCHO menor que el efecto sobre los ingresos. Esa es precisamente la razón por la que el crecimiento no es automáticamente el driver principal.
B65: Tabla manual | C65: Δ crecimiento (pp) → valor por acción: −3,0pp: ____ −1,5pp: ____ 0: (ver Summary) +1,5pp: ____ +3,0pp: ____

Sheet 09 Escenarios
A1: PANEL DE ESCENARIOS — BEAR / BASE / BULL
A2: Este panel gobierna TODO el modelo. Cambiar C4 recalcula operativo, tres estados, DCF, valor terminal y valor por acción.
B4: ESCENARIO ACTIVO (1 = Bear, 2 = Base, 3 = Bull) | C4: ='00 Panel del Analista'!D228 -> 2
B5: Escenario activo (nombre) | C5: =CHOOSE($C$4,"BEAR","BASE","BULL") -> BASE
B7: DESPLAZAMIENTOS POR ESCENARIO — se aplican sobre el vector Base de '02 Assumptions'
B8: Driver | C8: Unidad | D8: Bear | E8: Base | F8: Bull | G8: Activo
B9: Multiplicador del crecimiento de ingresos IoT + Data Center | C9: x | D9: ='00 Panel del Analista'!D218 -> 0.7 | E9: ='00 Panel del Analista'!E218 -> 1 | F9: ='00 Panel del Analista'!F218 -> 1.25 | G9: =CHOOSE($C$4,D9,E9,F9) -> 1
B10: Delta al crecimiento del resto de ingresos | C10: % | D10: ='00 Panel del Analista'!D219 -> -0.015 | E10: ='00 Panel del Analista'!E219 -> 0 | F10: ='00 Panel del Analista'!F219 -> 0.015 | G10: =CHOOSE($C$4,D10,E10,F10) -> 0
B11: Delta al Gross Margin | C11: % | D11: ='00 Panel del Analista'!D220 -> -0.015 | E11: ='00 Panel del Analista'!E220 -> 0 | F11: ='00 Panel del Analista'!F220 -> 0.015 | G11: =CHOOSE($C$4,D11,E11,F11) -> 0
B12: Delta a los gastos operativos sobre ingresos | C12: % | D12: ='00 Panel del Analista'!D221 -> 0.01 | E12: ='00 Panel del Analista'!E221 -> 0 | F12: ='00 Panel del Analista'!F221 -> -0.01 | G12: =CHOOSE($C$4,D12,E12,F12) -> 0
B13: Multiplicador de Capex / Ingresos | C13: x | D13: ='00 Panel del Analista'!D222 -> 1.15 | E13: ='00 Panel del Analista'!E222 -> 1 | F13: ='00 Panel del Analista'!F222 -> 0.95 | G13: =CHOOSE($C$4,D13,E13,F13) -> 1
B14: Delta a los días de cobro (DSO) | C14: días | D14: ='00 Panel del Analista'!D223 -> 5 | E14: ='00 Panel del Analista'!E223 -> 0 | F14: ='00 Panel del Analista'!F223 -> -3 | G14: =CHOOSE($C$4,D14,E14,F14) -> 0
B15: Delta al tipo impositivo de caja | C15: % | D15: ='00 Panel del Analista'!D224 -> 0.02 | E15: ='00 Panel del Analista'!E224 -> 0 | F15: ='00 Panel del Analista'!F224 -> -0.01 | G15: =CHOOSE($C$4,D15,E15,F15) -> 0
B16: Delta al crecimiento terminal | C16: % | D16: ='00 Panel del Analista'!D225 -> -0.0075 | E16: ='00 Panel del Analista'!E225 -> 0 | F16: ='00 Panel del Analista'!F225 -> 0.005 | G16: =CHOOSE($C$4,D16,E16,F16) -> 0
B17: Delta al WACC | C17: % | D17: ='00 Panel del Analista'!D226 -> 0.01 | E17: ='00 Panel del Analista'!E226 -> 0 | F17: ='00 Panel del Analista'!F226 -> -0.005 | G17: =CHOOSE($C$4,D17,E17,F17) -> 0
B19: COHERENCIA INTERNA DE LOS ESCENARIOS (regla: ningún escenario mejora todos los drivers a la vez)
B20: Bear | C20: Menos crecimiento y menos margen, pero MÁS capex por unidad de ingreso (capacidad ya comprometida que no se llena), peor circulante, más impuestos, menor crecimiento terminal y mayor coste de capital.
B21: Base | C21: Los vectores de '02 Assumptions' tal cual: salida de Apple en FY2027, rampa de Data Center por debajo del plan de la dirección, recuperación parcial del margen bruto y capex normalizado al 3%.
B22: Bull | C22: Más crecimiento y más margen con MENOS capex por unidad de ingreso (mejor utilización de la capacidad instalada), mejor circulante, menos impuestos, algo más de crecimiento terminal y menor coste de capital.
B23: Regla | C23: El apalancamiento operativo es lo que conecta ingresos y márgenes: en Bear la caída de ingresos sobre una base de costes fijos y depreciación ya comprometida comprime el margen más que proporcionalmente. Por eso el delta de margen y el de crecimiento van en el mismo sentido.
B24: Regla | C24: El crecimiento IoT + Data Center se ajusta como MULTIPLICADOR y no como desplazamiento en puntos porcentuales. Razón: un delta plano de −8 pp aplicado a un vector que termina en el 4% produciría decrecimiento en el año 10 mientras el valor terminal asume crecimiento perpetuo. El multiplicador (0,7x / 1,25x) escala la rampa de Data Center, que es la variable binaria de la tesis, sin romper la convergencia terminal.
B25: RESULTADO POR ESCENARIO (se actualiza al cambiar C4; para comparar los tres hay que recorrer 1, 2 y 3)
B26: Métrica | C26: Valor del escenario activo
B27: Enterprise Value ($M) | C27: ='06 DCF'!$F$44 -> 149457.62
B28: Equity Value ($M) | C28: ='06 DCF'!$F$53 -> 143012.66
B29: Valor intrínseco por acción ($) | C29: ='06 DCF'!$F$55 -> 131.72392
B30: Precio actual ($) | C30: ='01 Summary'!$C$10 -> 198.27
B31: Upside / (Downside) | C31: =IF(C30<=0,"introducir precio",C29/C30-1) -> -0.33563362
B32: Valor terminal / EV | C32: ='06 DCF'!$F$45 -> 0.46198292

Sheet Escenario Pesimista
A1: ESCENARIO PESIMISTA (BEAR) — MODELO COMPLETO E INDEPENDIENTE
A2: No depende del interruptor '09 Escenarios'!C4. Lee los vectores Base de '02 Assumptions' y aplica los deltas de la COLUMNA D de '09 Escenarios'. Los tres escenarios se calculan simultáneamente.
B4: Partida | C4: Unidad | D4: ='00 Panel del Analista'!D14 -> FY2024A | E4: ='00 Panel del Analista'!E14 -> FY2025A | F4: ='00 Panel del Analista'!F14 -> FY2026E | G4: ='00 Panel del Analista'!G14 -> FY2027E | H4: ='00 Panel del Analista'!H14 -> FY2028E | I4: ='00 Panel del Analista'!I14 -> FY2029E | J4: ='00 Panel del Analista'!J14 -> FY2030E | K4: ='00 Panel del Analista'!K14 -> FY2031E | ... P4: ='00 Panel del Analista'!P14 -> FY2036E
B6: INGRESOS
B7: ='00 Panel del Analista'!B18 -> QCT IoT + Data Center y otros no reportables | C7: $M | F7: ='03 Historical'!F7 -> 7512 | G7: =F7*(1+'02 Assumptions'!G19*'09 Escenarios'!$D$9) -> 10667.04 | H7: =G7*(1+'02 Assumptions'!H19*'09 Escenarios'!$D$9) -> 13131.126 | I7: =H7*(1+'02 Assumptions'!I19*'09 Escenarios'!$D$9) -> 15153.32 | J7: =I7*(1+'02 Assumptions'!J19*'09 Escenarios'!$D$9) -> 16744.418 | K7: =J7*(1+'02 Assumptions'!K19*'09 Escenarios'!$D$9) -> 18150.949 | L7: =K7*(1+'02 Assumptions'!L19*'09 Escenarios'!$D$9) -> 19421.516 | M7: =L7*(1+'02 Assumptions'!M19*'09 Escenarios'!$D$9) -> 20509.121 | N7: =M7*(1+'02 Assumptions'!N19*'09 Escenarios'!$D$9) -> 21370.504 | ... P7: =O7*(1+'02 Assumptions'!P19*'09 Escenarios'!$D$9) -> 22737.789
B8: ='00 Panel del Analista'!B19 -> QCT Handsets | C8: $M | F8: ='03 Historical'!F8 -> 24134 | G8: =F8*(1+'02 Assumptions'!G21+'09 Escenarios'!$D$10) -> 20151.89 | H8: =G8*(1+'02 Assumptions'!H21+'09 Escenarios'!$D$10) -> 20252.649 | I8: =H8*(1+'02 Assumptions'!I21+'09 Escenarios'!$D$10) -> 20556.439 | J8: =I8*(1+'02 Assumptions'!J21+'09 Escenarios'!$D$10) -> 20659.221 | K8: =J8*(1+'02 Assumptions'!K21+'09 Escenarios'!$D$10) -> 20762.517 | L8: =K8*(1+'02 Assumptions'!L21+'09 Escenarios'!$D$10) -> 20866.33 | M8: =L8*(1+'02 Assumptions'!M21+'09 Escenarios'!$D$10) -> 20970.662 | N8: =M8*(1+'02 Assumptions'!N21+'09 Escenarios'!$D$10) -> 21075.515 | ... P8: =O8*(1+'02 Assumptions'!P21+'09 Escenarios'!$D$10) -> 21499.133
B9: ='00 Panel del Analista'!B20 -> QTL Licencias (incl. ingresos no asignados) | C9: $M | F9: ='03 Historical'!F9 -> 5552 | G9: =F9*(1+'02 Assumptions'!G23+'09 Escenarios'!$D$10) -> 5357.68 | H9: =G9*(1+'02 Assumptions'!H23+'09 Escenarios'!$D$10) -> 5170.1612 | I9: =H9*(1+'02 Assumptions'!I23+'09 Escenarios'!$D$10) -> 5092.6088 | J9: =I9*(1+'02 Assumptions'!J23+'09 Escenarios'!$D$10) -> 5067.1457 | K9: =J9*(1+'02 Assumptions'!K23+'09 Escenarios'!$D$10) -> 5041.81 | L9: =K9*(1+'02 Assumptions'!L23+'09 Escenarios'!$D$10) -> 5016.601 | M9: =L9*(1+'02 Assumptions'!M23+'09 Escenarios'!$D$10) -> 5016.601 | N9: =M9*(1+'02 Assumptions'!N23+'09 Escenarios'!$D$10) -> 5016.601 | ... P9: =O9*(1+'02 Assumptions'!P23+'09 Escenarios'!$D$10) -> 5066.8924
B10: ='00 Panel del Analista'!B21 -> QCT Automoción | C10: $M | F10: ='03 Historical'!F10 -> 5700 | G10: =F10*(1+'02 Assumptions'!G25+'09 Escenarios'!$D$10) -> 6868.5 | H10: =G10*(1+'02 Assumptions'!H25+'09 Escenarios'!$D$10) -> 7933.1175 | I10: =H10*(1+'02 Assumptions'!I25+'09 Escenarios'!$D$10) -> 9004.0884 | J10: =I10*(1+'02 Assumptions'!J25+'09 Escenarios'!$D$10) -> 10039.559 | K10: =J10*(1+'02 Assumptions'!K25+'09 Escenarios'!$D$10) -> 10993.317 | L10: =K10*(1+'02 Assumptions'!L25+'09 Escenarios'!$D$10) -> 11817.815 | M10: =L10*(1+'02 Assumptions'!M25+'09 Escenarios'!$D$10) -> 12585.973 | N10: =M10*(1+'02 Assumptions'!N25+'09 Escenarios'!$D$10) -> 13278.202 | ... P10: =O10*(1+'02 Assumptions'!P25+'09 Escenarios'!$D$10) -> 14361.371
B11: INGRESOS TOTALES | C11: $M | F11: =SUM(F7:F10) -> 42898 | G11: =SUM(G7:G10) -> 43045.11 | H11: =SUM(H7:H10) -> 46487.054 | I11: =SUM(I7:I10) -> 49806.456 | J11: =SUM(J7:J10) -> 52510.344 | K11: =SUM(K7:K10) -> 54948.593 | L11: =SUM(L7:L10) -> 57122.262 | M11: =SUM(M7:M10) -> 59082.357 | ... P11: =SUM(P7:P10) -> 63665.185
B12: Crecimiento | C12: % | G12: =G11/F11-1 -> 0.0034292974 | H12: =H11/G11-1 -> 0.079961333 | I12: =I11/H11-1 -> 0.07140486 | J12: =J11/I11-1 -> 0.0542879 | K12: =K11/J11-1 -> 0.0464337 | L12: =L11/K11-1 -> 0.039558223 | M12: =M11/L11-1 -> 0.034314022 | N12: =N11/M11-1 -> 0.028070392 | ... P12: =P11/O11-1 -> 0.021549941
B13: MÁRGENES Y GASTOS
B14: Gross Margin | C14: % | G14: ='02 Assumptions'!G29+'09 Escenarios'!$D$11 -> 0.53 | H14: ='02 Assumptions'!H29+'09 Escenarios'!$D$11 -> 0.535 | I14: ='02 Assumptions'!I29+'09 Escenarios'!$D$11 -> 0.54 | J14: ='02 Assumptions'!J29+'09 Escenarios'!$D$11 -> 0.54 | K14: ='02 Assumptions'!K29+'09 Escenarios'!$D$11 -> 0.54 | L14: ='02 Assumptions'!L29+'09 Escenarios'!$D$11 -> 0.54 | M14: ='02 Assumptions'!M29+'09 Escenarios'!$D$11 -> 0.54 | N14: ='02 Assumptions'!N29+'09 Escenarios'!$D$11 -> 0.54 | ... P14: ='02 Assumptions'!P29+'09 Escenarios'!$D$11 -> 0.54
B15: Margen bruto | C15: $M | G15: =G11*G14 -> 22813.908 | H15: =H11*H14 -> 24870.574 | I15: =I11*I14 -> 26895.486 | J15: =J11*J14 -> 28355.586 | K15: =K11*K14 -> 29672.24 | L15: =L11*L14 -> 30846.022 | M15: =M11*M14 -> 31904.473 | N15: =N11*N14 -> 32800.044 | ... P15: =P11*P14 -> 34379.2
B16: Coste de los ingresos | C16: $M | G16: =G11-G15 -> 20231.202 | H16: =H11-H15 -> 21616.48 | I16: =I11-I15 -> 22910.97 | J16: =J11-J15 -> 24154.758 | K16: =K11-K15 -> 25276.353 | L16: =L11-L15 -> 26276.241 | M16: =M11-M15 -> 27177.884 | N16: =N11-N15 -> 27940.778 | ... P16: =P11-P15 -> 29285.985
B17: Ventas y marketing | C17: $M | G17: =G11*('02 Assumptions'!G31+'09 Escenarios'!$D$12*'02 Assumptions'!$Q$32) -> 3831.0148 | H17: =H11*('02 Assumptions'!H31+'09 Escenarios'!$D$12*'02 Assumptions'!$Q$32) -> 3904.9126 | I17: =I11*('02 Assumptions'!I31+'09 Escenarios'!$D$12*'02 Assumptions'!$Q$32) -> 4034.3229 | J17: =J11*('02 Assumptions'!J31+'09 Escenarios'!$D$12*'02 Assumptions'!$Q$32) -> 4148.3172 | K17: =K11*('02 Assumptions'!K31+'09 Escenarios'!$D$12*'02 Assumptions'!$Q$32) -> 4231.0417 | L17: =L11*('02 Assumptions'!L31+'09 Escenarios'!$D$12*'02 Assumptions'!$Q$32) -> 4341.2919 | M17: =M11*('02 Assumptions'!M31+'09 Escenarios'!$D$12*'02 Assumptions'!$Q$32) -> 4431.1768 | N17: =N11*('02 Assumptions'!N31+'09 Escenarios'!$D$12*'02 Assumptions'!$Q$32) -> 4555.5616 | ... P17: =P11*('02 Assumptions'!P31+'09 Escenarios'!$D$12*'02 Assumptions'!$Q$32) -> 4774.8889
B18: I+D | C18: $M | G18: =G11*('02 Assumptions'!G33+'09 Escenarios'!$D$12*'02 Assumptions'!$Q$34) -> 10373.872 | H18: =H11*('02 Assumptions'!H33+'09 Escenarios'!$D$12*'02 Assumptions'!$Q$34) -> 10738.51 | I18: =I11*('02 Assumptions'!I33+'09 Escenarios'!$D$12*'02 Assumptions'!$Q$34) -> 11007.227 | J18: =J11*('02 Assumptions'!J33+'09 Escenarios'!$D$12*'02 Assumptions'!$Q$34) -> 11342.234 | K18: =K11*('02 Assumptions'!K33+'09 Escenarios'!$D$12*'02 Assumptions'!$Q$34) -> 11704.05 | L18: =L11*('02 Assumptions'!L33+'09 Escenarios'!$D$12*'02 Assumptions'!$Q$34) -> 12052.797 | M18: =M11*('02 Assumptions'!M33+'09 Escenarios'!$D$12*'02 Assumptions'!$Q$34) -> 12466.377 | N18: =N11*('02 Assumptions'!N33+'09 Escenarios'!$D$12*'02 Assumptions'!$Q$34) -> 12816.313 | ... P18: =P11*('02 Assumptions'!P33+'09 Escenarios'!$D$12*'02 Assumptions'!$Q$34) -> 13433.354
B19: G&A | C19: $M | G19: =G11*('02 Assumptions'!G35+'09 Escenarios'!$D$12*'02 Assumptions'!$Q$36) -> 0 | H19: =H11*('02 Assumptions'!H35+'09 Escenarios'!$D$12*'02 Assumptions'!$Q$36) -> 0 | I19: =I11*('02 Assumptions'!I35+'09 Escenarios'!$D$12*'02 Assumptions'!$Q$36) -> 0 | J19: =J11*('02 Assumptions'!J35+'09 Escenarios'!$D$12*'02 Assumptions'!$Q$36) -> 0 | K19: =K11*('02 Assumptions'!K35+'09 Escenarios'!$D$12*'02 Assumptions'!$Q$36) -> 0 | L19: =L11*('02 Assumptions'!L35+'09 Escenarios'!$D$12*'02 Assumptions'!$Q$36) -> 0 | M19: =M11*('02 Assumptions'!M35+'09 Escenarios'!$D$12*'02 Assumptions'!$Q$36) -> 0 | N19: =N11*('02 Assumptions'!N35+'09 Escenarios'!$D$12*'02 Assumptions'!$Q$36) -> 0 | ... P19: =P11*('02 Assumptions'!P35+'09 Escenarios'!$D$12*'02 Assumptions'!$Q$36) -> 0
B20: Amortización de intangibles | C20: $M | G20: ='02 Assumptions'!G37 -> 430 | H20: ='02 Assumptions'!H37 -> 350 | I20: ='02 Assumptions'!I37 -> 280 | J20: ='02 Assumptions'!J37 -> 210 | K20: ='02 Assumptions'!K37 -> 140 | L20: ='02 Assumptions'!L37 -> 100 | M20: ='02 Assumptions'!M37 -> 0 | N20: ='02 Assumptions'!N37 -> 0 | ... P20: ='02 Assumptions'!P37 -> 0
B21: Reestructuración normalizada | C21: $M | G21: ='02 Assumptions'!G38 -> 100 | H21: ='02 Assumptions'!H38 -> 100 | I21: ='02 Assumptions'!I38 -> 100 | J21: ='02 Assumptions'!J38 -> 100 | K21: ='02 Assumptions'!K38 -> 100 | L21: ='02 Assumptions'!L38 -> 100 | M21: ='02 Assumptions'!M38 -> 100 | N21: ='02 Assumptions'!N38 -> 100 | ... P21: ='02 Assumptions'!P38 -> 100
B22: Total gastos operativos | C22: $M | G22: =SUM(G17:G21) -> 14734.886 | H22: =SUM(H17:H21) -> 15093.422 | I22: =SUM(I17:I21) -> 15421.55 | J22: =SUM(J17:J21) -> 15800.551 | K22: =SUM(K17:K21) -> 16175.092 | L22: =SUM(L17:L21) -> 16594.089 | M22: =SUM(M17:M21) -> 16997.554 | N22: =SUM(N17:N21) -> 17471.875 | ... P22: =SUM(P17:P21) -> 18308.243
B23: EBIT reportado | C23: $M | G23: =G15-G22 -> 8079.022 | H23: =H15-H22 -> 9777.152 | I23: =I15-I22 -> 11473.937 | J23: =J15-J22 -> 12555.034 | K23: =K15-K22 -> 13497.148 | L23: =L15-L22 -> 14251.932 | M23: =M15-M22 -> 14906.919 | N23: =N15-N22 -> 15328.169 | ... P23: =P15-P22 -> 16070.957
B24: EBIT NORMALIZADO | C24: $M | G24: =G23+G21 -> 8179.022 | H24: =H23+H21 -> 9877.152 | I24: =I23+I21 -> 11573.937 | J24: =J23+J21 -> 12655.034 | K24: =K23+K21 -> 13597.148 | L24: =L23+L21 -> 14351.932 | M24: =M23+M21 -> 15006.919 | N24: =N23+N21 -> 15428.169 | ... P24: =P23+P21 -> 16170.957
B25: Margen EBIT normalizado | C25: % | G25: =G24/G11 -> 0.19001048 | H25: =H24/H11 -> 0.21247102 | I25: =I24/I11 -> 0.23237824 | J25: =J24/J11 -> 0.24100079 | K25: =K24/K11 -> 0.24745216 | L25: =L24/L11 -> 0.25124937 | M25: =M24/M11 -> 0.254 | N25: =N24/N11 -> 0.254 | ... P25: =P24/P11 -> 0.254
B26: CAPEX Y DEPRECIACIÓN
B27: PP&E neto inicial | C27: $M | G27: =F30 -> 5217 | H27: =G30 -> 6037.7417 | I27: =H30 -> 6501.7851 | J27: =I30 -> 6787.9951 | K27: =J30 -> 6889.8689 | L27: =K30 -> 7043.8771 | M27: =L30 -> 7230.3205 | N27: =M30 -> 7435.4415 | ... P27: =O30 -> 7857.9767
B28: Capex | C28: $M | G28: =G11*'02 Assumptions'!G41*'09 Escenarios'!$D$13 -> 2227.5844 | H28: =H11*'02 Assumptions'!H41*'09 Escenarios'!$D$13 -> 2031.4843 | I28: =I11*'02 Assumptions'!I41*'09 Escenarios'!$D$13 -> 1947.4324 | J28: =J11*'02 Assumptions'!J41*'09 Escenarios'!$D$13 -> 1811.6069 | K28: =K11*'02 Assumptions'!K41*'09 Escenarios'!$D$13 -> 1895.7265 | L28: =L11*'02 Assumptions'!L41*'09 Escenarios'!$D$13 -> 1970.718 | M28: =M11*'02 Assumptions'!M41*'09 Escenarios'!$D$13 -> 2038.3413 | N28: =N11*'02 Assumptions'!N41*'09 Escenarios'!$D$13 -> 2095.5583 | ... P28: =P11*'02 Assumptions'!P41*'09 Escenarios'!$D$13 -> 2196.4489
B29: Depreciación | C29: $M | G29: =(G27+G28/2)/'02 Assumptions'!$C$43 -> 1406.8427 | H29: =(H27+H28/2)/'02 Assumptions'!$C$43 -> 1567.4409 | I29: =(I27+I28/2)/'02 Assumptions'!$C$43 -> 1661.2225 | J29: =(J27+J28/2)/'02 Assumptions'!$C$43 -> 1709.733 | K29: =(K27+K28/2)/'02 Assumptions'!$C$43 -> 1741.7183 | L29: =(L27+L28/2)/'02 Assumptions'!$C$43 -> 1784.2747 | M29: =(M27+M28/2)/'02 Assumptions'!$C$43 -> 1833.2203 | N29: =(N27+N28/2)/'02 Assumptions'!$C$43 -> 1885.1602 | ... P29: =(P27+P28/2)/'02 Assumptions'!$C$43 -> 1990.2669
B30: PP&E neto final | C30: $M | F30: ='03 Historical'!F48 -> 5217 | G30: =G27+G28-G29 -> 6037.7417 | H30: =H27+H28-H29 -> 6501.7851 | I30: =I27+I28-I29 -> 6787.9951 | J30: =J27+J28-J29 -> 6889.8689 | K30: =K27+K28-K29 -> 7043.8771 | L30: =L27+L28-L29 -> 7230.3205 | M30: =M27+M28-M29 -> 7435.4415 | N30: =N27+N28-N29 -> 7645.8397 | ... P30: =P27+P28-P29 -> 8064.1587
B31: D&A total | C31: $M | G31: =G29+G20 -> 1836.8427 | H31: =H29+H20 -> 1917.4409 | I31: =I29+I20 -> 1941.2225 | J31: =J29+J20 -> 1919.733 | K31: =K29+K20 -> 1881.7183 | L31: =L29+L20 -> 1884.2747 | M31: =M29+M20 -> 1833.2203 | N31: =N29+N20 -> 1885.1602 | ... P31: =P29+P20 -> 1990.2669
B32: EBITDA | C32: $M | G32: =G24+G31 -> 10015.865 | H32: =H24+H31 -> 11794.593 | I32: =I24+I31 -> 13515.159 | J32: =J24+J31 -> 14574.767 | K32: =K24+K31 -> 15478.867 | L32: =L24+L31 -> 16236.207 | M32: =M24+M31 -> 16840.139 | N32: =N24+N31 -> 17313.329 | ... P32: =P24+P31 -> 18161.224
B33: CIRCULANTE
B34: Clientes | C34: $M | G34: =('02 Assumptions'!G47+'09 Escenarios'!$D$14)/365*G11 -> 5071.0678 | H34: =('02 Assumptions'!H47+'09 Escenarios'!$D$14)/365*H11 -> 5476.5571 | I34: =('02 Assumptions'!I47+'09 Escenarios'!$D$14)/365*I11 -> 5867.6099 | J34: =('02 Assumptions'!J47+'09 Escenarios'!$D$14)/365*J11 -> 6186.1501 | K34: =('02 Assumptions'!K47+'09 Escenarios'!$D$14)/365*K11 -> 6473.3959 | L34: =('02 Assumptions'!L47+'09 Escenarios'!$D$14)/365*L11 -> 6729.472 | M34: =('02 Assumptions'!M47+'09 Escenarios'!$D$14)/365*M11 -> 6960.3872 | N34: =('02 Assumptions'!N47+'09 Escenarios'!$D$14)/365*N11 -> 7155.768 | ... P34: =('02 Assumptions'!P47+'09 Escenarios'!$D$14)/365*P11 -> 7500.2821
B35: Otros activos corrientes | C35: $M | G35: =G11*'02 Assumptions'!G51 -> 9039.4731 | H35: =H11*'02 Assumptions'!H51 -> 9297.4109 | I35: =I11*'02 Assumptions'!I51 -> 9961.2912 | J35: =J11*'02 Assumptions'!J51 -> 10502.069 | K35: =K11*'02 Assumptions'!K51 -> 10989.719 | L35: =L11*'02 Assumptions'!L51 -> 11424.452 | M35: =M11*'02 Assumptions'!M51 -> 11816.471 | N35: =N11*'02 Assumptions'!N51 -> 12148.164 | ... P35: =P11*'02 Assumptions'!P51 -> 12733.037
B36: Proveedores | C36: $M | G36: =(G16+G28)*'02 Assumptions'!G49 -> 3009.4773 | H36: =(H16+H28)*'02 Assumptions'!H49 -> 3168.8273 | I36: =(I16+I28)*'02 Assumptions'!I49 -> 3331.0259 | J36: =(J16+J28)*'02 Assumptions'!J49 -> 3479.4929 | K36: =(K16+K28)*'02 Assumptions'!K49 -> 3641.0586 | L36: =(L16+L28)*'02 Assumptions'!L49 -> 3785.0925 | M36: =(M16+M28)*'02 Assumptions'!M49 -> 3914.9742 | N36: =(N16+N28)*'02 Assumptions'!N49 -> 4024.8691 | ... P36: =(P16+P28)*'02 Assumptions'!P49 -> 4218.6462
B37: Remuneraciones pendientes | C37: $M | G37: =G11*'02 Assumptions'!G52 -> 1635.7142 | H37: =H11*'02 Assumptions'!H52 -> 1766.5081 | I37: =I11*'02 Assumptions'!I52 -> 1892.6453 | J37: =J11*'02 Assumptions'!J52 -> 1995.3931 | K37: =K11*'02 Assumptions'!K52 -> 2088.0466 | L37: =L11*'02 Assumptions'!L52 -> 2170.646 | M37: =M11*'02 Assumptions'!M52 -> 2245.1296 | N37: =N11*'02 Assumptions'!N52 -> 2308.1512 | ... P37: =P11*'02 Assumptions'!P52 -> 2419.277
B38: Ingresos diferidos corrientes | C38: $M | G38: =G11*'02 Assumptions'!G50 -> 301.31577 | H38: =H11*'02 Assumptions'!H50 -> 325.40938 | I38: =I11*'02 Assumptions'!I50 -> 348.64519 | J38: =J11*'02 Assumptions'!J50 -> 367.57241 | K38: =K11*'02 Assumptions'!K50 -> 384.64015 | L38: =L11*'02 Assumptions'!L50 -> 399.85584 | M38: =M11*'02 Assumptions'!M50 -> 413.5765 | N38: =N11*'02 Assumptions'!N50 -> 425.18575 | ... P38: =P11*'02 Assumptions'!P50 -> 445.6563
B39: Otros pasivos corrientes | C39: $M | G39: =G11*'02 Assumptions'!G53 -> 4175.3757 | H39: =H11*'02 Assumptions'!H53 -> 4509.2443 | I39: =I11*'02 Assumptions'!I53 -> 4831.2262 | J39: =J11*'02 Assumptions'!J53 -> 5093.5034 | K39: =K11*'02 Assumptions'!K53 -> 5330.0136 | L39: =L11*'02 Assumptions'!L53 -> 5540.8594 | M39: =M11*'02 Assumptions'!M53 -> 5730.9886 | N39: =N11*'02 Assumptions'!N53 -> 5891.8597 | ... P39: =P11*'02 Assumptions'!P53 -> 6175.523
B40: CAPITAL CIRCULANTE NETO | C40: $M | F40: ='04 Operating Model'!F50 -> 5776 | G40: =G34+G35-G36-G37-G38-G39 -> 4988.6579 | H40: =H34+H35-H36-H37-H38-H39 -> 5003.979 | I40: =I34+I35-I36-I37-I38-I39 -> 5425.3584 | J40: =J34+J35-J36-J37-J38-J39 -> 5752.2571 | K40: =K34+K35-K36-K37-K38-K39 -> 6019.3557 | L40: =L34+L35-L36-L37-L38-L39 -> 6257.4707 | M40: =M34+M35-M36-M37-M38-M39 -> 6472.1897 | N40: =N34+N35-N36-N37-N38-N39 -> 6653.8666 | ... P40: =P34+P35-P36-P37-P38-P39 -> 6974.2167
B41: Variación del NWC | C41: $M | G41: =G40-F40 -> -787.34211 | H41: =H40-G40 -> 15.321105 | I41: =I40-H40 -> 421.37945 | J41: =J40-I40 -> 326.89869 | K41: =K40-J40 -> 267.09858 | L41: =L40-K40 -> 238.11502 | M41: =M40-L40 -> 214.71899 | N41: =N40-M40 -> 181.6769 | ... P41: =P40-O40 -> 147.12345
B42: FCFF
B43: Tipo impositivo de caja | C43: % | G43: ='02 Assumptions'!G56+'09 Escenarios'!$D$15 -> 0.16 | H43: ='02 Assumptions'!H56+'09 Escenarios'!$D$15 -> 0.165 | I43: ='02 Assumptions'!I56+'09 Escenarios'!$D$15 -> 0.17 | J43: ='02 Assumptions'!J56+'09 Escenarios'!$D$15 -> 0.175 | K43: ='02 Assumptions'!K56+'09 Escenarios'!$D$15 -> 0.18 | L43: ='02 Assumptions'!L56+'09 Escenarios'!$D$15 -> 0.185 | M43: ='02 Assumptions'!M56+'09 Escenarios'!$D$15 -> 0.19 | N43: ='02 Assumptions'!N56+'09 Escenarios'!$D$15 -> 0.19 | ... P43: ='02 Assumptions'!P56+'09 Escenarios'!$D$15 -> 0.19
B44: (−) Impuestos sobre el EBIT normalizado | C44: $M | G44: =-G24*G43 -> -1308.6435 | H44: =-H24*H43 -> -1629.7301 | I44: =-I24*I43 -> -1967.5692 | J44: =-J24*J43 -> -2214.631 | K44: =-K24*K43 -> -2447.4867 | L44: =-L24*L43 -> -2655.1075 | M44: =-M24*M43 -> -2851.3145 | N44: =-N24*N43 -> -2931.3521 | ... P44: =-P24*P43 -> -3072.4818
B45: NOPAT | C45: $M | G45: =G24+G44 -> 6870.3785 | H45: =H24+H44 -> 8247.4219 | I45: =I24+I44 -> 9606.3673 | J45: =J24+J44 -> 10440.403 | K45: =K24+K44 -> 11149.662 | L45: =L24+L44 -> 11696.825 | M45: =M24+M44 -> 12155.604 | N45: =N24+N44 -> 12496.817 | ... P45: =P24+P44 -> 13098.475
B46: (+) D&A | C46: $M | G46: =G31 -> 1836.8427 | H46: =H31 -> 1917.4409 | I46: =I31 -> 1941.2225 | J46: =J31 -> 1919.733 | K46: =K31 -> 1881.7183 | L46: =L31 -> 1884.2747 | M46: =M31 -> 1833.2203 | N46: =N31 -> 1885.1602 | ... P46: =P31 -> 1990.2669
B47: (−) Capex | C47: $M | G47: =-G28 -> -2227.5844 | H47: =-H28 -> -2031.4843 | I47: =-I28 -> -1947.4324 | J47: =-J28 -> -1811.6069 | K47: =-K28 -> -1895.7265 | L47: =-L28 -> -1970.718 | M47: =-M28 -> -2038.3413 | N47: =-N28 -> -2095.5583 | ... P47: =-P28 -> -2196.4489
B48: (−) Variación del NWC | C48: $M | G48: =-G41 -> 787.34211 | H48: =-H41 -> -15.321105 | I48: =-I41 -> -421.37945 | J48: =-J41 -> -326.89869 | K48: =-K41 -> -267.09858 | L48: =-L41 -> -238.11502 | M48: =-M41 -> -214.71899 | N48: =-N41 -> -181.6769 | ... P48: =-P41 -> -147.12345
B49: (−) Coste en caja de reestructuración | C49: $M | G49: =-G21 -> -100 | H49: =-H21 -> -100 | I49: =-I21 -> -100 | J49: =-J21 -> -100 | K49: =-K21 -> -100 | L49: =-L21 -> -100 | M49: =-M21 -> -100 | N49: =-N21 -> -100 | ... P49: =-P21 -> -100
B50: FCFF | C50: $M | G50: =SUM(G45:G49) -> 7166.9789 | H50: =SUM(H45:H49) -> 8018.0574 | I50: =SUM(I45:I49) -> 9078.778 | J50: =SUM(J45:J49) -> 10121.631 | K50: =SUM(K45:K49) -> 10768.555 | L50: =SUM(L45:L49) -> 11272.266 | M50: =SUM(M45:M49) -> 11635.764 | N50: =SUM(N45:N49) -> 12004.742 | ... P50: =SUM(P45:P49) -> 12645.17
B51: DESCUENTO Y VALOR TERMINAL
B52: WACC (base + delta del escenario) | C52: % | G52: ='07 WACC'!$C$36+'09 Escenarios'!$D$17 -> 0.12540544 | H52: ='07 WACC'!$C$36+'09 Escenarios'!$D$17 -> 0.12540544 | I52: ='07 WACC'!$C$36+'09 Escenarios'!$D$17 -> 0.12540544 | J52: ='07 WACC'!$C$36+'09 Escenarios'!$D$17 -> 0.12540544 | K52: ='07 WACC'!$C$36+'09 Escenarios'!$D$17 -> 0.12540544 | L52: ='07 WACC'!$C$36+'09 Escenarios'!$D$17 -> 0.12540544 | M52: ='07 WACC'!$C$36+'09 Escenarios'!$D$17 -> 0.12540544 | N52: ='07 WACC'!$C$36+'09 Escenarios'!$D$17 -> 0.12540544 | ... P52: ='07 WACC'!$C$36+'09 Escenarios'!$D$17 -> 0.12540544
B53: Crecimiento terminal g | C53: % | G53: ='02 Assumptions'!$C$62+'09 Escenarios'!$D$16 -> 0.0225 | H53: ='02 Assumptions'!$C$62+'09 Escenarios'!$D$16 -> 0.0225 | I53: ='02 Assumptions'!$C$62+'09 Escenarios'!$D$16 -> 0.0225 | J53: ='02 Assumptions'!$C$62+'09 Escenarios'!$D$16 -> 0.0225 | K53: ='02 Assumptions'!$C$62+'09 Escenarios'!$D$16 -> 0.0225 | L53: ='02 Assumptions'!$C$62+'09 Escenarios'!$D$16 -> 0.0225 | M53: ='02 Assumptions'!$C$62+'09 Escenarios'!$D$16 -> 0.0225 | N53: ='02 Assumptions'!$C$62+'09 Escenarios'!$D$16 -> 0.0225 | ... P53: ='02 Assumptions'!$C$62+'09 Escenarios'!$D$16 -> 0.0225
B54: ROIC terminal | C54: % | G54: ='02 Assumptions'!$C$66 -> 0.3 | H54: ='02 Assumptions'!$C$66 -> 0.3 | I54: ='02 Assumptions'!$C$66 -> 0.3 | J54: ='02 Assumptions'!$C$66 -> 0.3 | K54: ='02 Assumptions'!$C$66 -> 0.3 | L54: ='02 Assumptions'!$C$66 -> 0.3 | M54: ='02 Assumptions'!$C$66 -> 0.3 | N54: ='02 Assumptions'!$C$66 -> 0.3 | ... P54: ='02 Assumptions'!$C$66 -> 0.3
B55: Periodo de descuento t | C55: años | G55: =COLUMNS($G55:G55)-IF('02 Assumptions'!$C$12=2,0.5,0) -> 0.5 | H55: =COLUMNS($G55:H55)-IF('02 Assumptions'!$C$12=2,0.5,0) -> 1.5 | I55: =COLUMNS($G55:I55)-IF('02 Assumptions'!$C$12=2,0.5,0) -> 2.5 | J55: =COLUMNS($G55:J55)-IF('02 Assumptions'!$C$12=2,0.5,0) -> 3.5 | K55: =COLUMNS($G55:K55)-IF('02 Assumptions'!$C$12=2,0.5,0) -> 4.5 | L55: =COLUMNS($G55:L55)-IF('02 Assumptions'!$C$12=2,0.5,0) -> 5.5 | M55: =COLUMNS($G55:M55)-IF('02 Assumptions'!$C$12=2,0.5,0) -> 6.5 | N55: =COLUMNS($G55:N55)-IF('02 Assumptions'!$C$12=2,0.5,0) -> 7.5 | ... P55: =COLUMNS($G55:P55)-IF('02 Assumptions'!$C$12=2,0.5,0) -> 9.5
B56: Factor de descuento | C56: x | G56: =1/(1+G52)^G55 -> 0.9426392 | H56: =1/(1+H52)^H55 -> 0.83759964 | I56: =1/(1+I52)^I55 -> 0.74426479 | J56: =1/(1+J52)^J55 -> 0.66133036 | K56: =1/(1+K52)^K55 -> 0.58763743 | L56: =1/(1+L52)^L55 -> 0.5221562 | M56: =1/(1+M52)^M55 -> 0.46397163 | N56: =1/(1+N52)^N55 -> 0.41227065 | ... P56: =1/(1+P52)^P55 -> 0.32551004
B57: Valor presente del FCFF | C57: $M | G57: =G50*G56 -> 6755.8752 | H57: =H50*H56 -> 6715.922 | I57: =I50*I56 -> 6757.0148 | J57: =J50*J56 -> 6693.7417 | K57: =K50*K56 -> 6328.0059 | L57: =L50*L56 -> 5885.8838 | M57: =M50*M56 -> 5398.6644 | N57: =N50*N56 -> 4949.2026 | ... P57: =P50*P56 -> 4116.1298
B59: Valor presente del FCFF explícito | C59: $M | F59: =SUM(G57:P57) -> 58119.788
B60: Tasa de reinversión terminal = g / ROIC | C60: % | F60: =P53/P54 -> 0.075
B61: NOPAT terminal | C61: $M | F61: =P45*(1+P53) -> 13393.191
B62: FCFF terminal | C62: $M | F62: =F61*(1-F60) -> 12388.702
B63: Valor terminal | C63: $M | F63: =IF(P52<=P53,"FALLO: WACC<=g",F62/(P52-P53)) -> 120389.18
B64: Factor de descuento del valor terminal | C64: x | F64: =1/(1+P52)^'02 Assumptions'!$C$11 -> 0.30683853
B65: Valor presente del valor terminal | C65: $M | F65: =F63*F64 -> 36940.038
B66: ENTERPRISE VALUE | C66: $M | F66: =F59+F65 -> 95059.825
B67: Valor terminal / Enterprise Value | C67: % | F67: =F65/F66 -> 0.38859779
B68: Múltiplo de salida implícito (VT / EBITDA FY2036) | C68: x | F68: =IFERROR(F63/P32,"n/a") -> 6.6289132
B69: Puente a Equity (idéntico a '06 DCF' filas 46-52) | C69: $M | F69: =SUM('06 DCF'!$F$46:$F$52) -> -6444.96
B70: EQUITY VALUE | C70: $M | F70: =F66+F69 -> 88614.865
B71: Acciones diluidas | C71: M acc | F71: ='02 Assumptions'!$C$69 -> 1085.7
B72: VALOR INTRÍNSECO POR ACCIÓN | C72: $/acc | F72: =F70/F71 -> 81.620029
B73: Precio de mercado actual | C73: $/acc | F73: ='01 Summary'!$C$10 -> 198.27
B74: Upside / (Downside) | C74: % | F74: =IF(F73<=0,"introducir precio",F72/F73-1) -> -0.58833898
B75: Ingresos FY2036E | C75: $M | F75: =P11 -> 63665.185
B77: CONTROLES DE ESTE ESCENARIO
B78: CHECK: WACC > g | F78: =IF(P52>P53,"OK","FALLO") -> OK
B79: CHECK: FCFF positivo al final del horizonte | F79: =IF(P50>0,"OK","FALLO") -> OK
B80: CHECK: crecimiento del año 10 ≥ g | F80: =IF(P12>=P53,"OK","AVISO: el último año explícito crece menos que la perpetuidad") -> AVISO: el último año explícito crece menos que la perpetuidad
B81: CHECK: sin errores de fórmula en la hoja | F81: {=IF(SUMPRODUCT(--ISERROR($G$7:$P$57))=0,"OK","FALLO")} -> OK
B82: CHECK: reproduce '06 DCF' (sólo debe cumplirse en el escenario BASE) | F82: no aplica

Sheet Escenario Base
A1: ESCENARIO BASE — MODELO COMPLETO E INDEPENDIENTE
A2: No depende del interruptor '09 Escenarios'!C4. Lee los vectores Base de '02 Assumptions' y aplica los deltas de la COLUMNA E de '09 Escenarios'. Los tres escenarios se calculan simultáneamente.
B4: Partida | C4: Unidad | D4: ='00 Panel del Analista'!D14 -> FY2024A | E4: ='00 Panel del Analista'!E14 -> FY2025A | F4: ='00 Panel del Analista'!F14 -> FY2026E | G4: ='00 Panel del Analista'!G14 -> FY2027E | H4: ='00 Panel del Analista'!H14 -> FY2028E | I4: ='00 Panel del Analista'!I14 -> FY2029E | J4: ='00 Panel del Analista'!J14 -> FY2030E | K4: ='00 Panel del Analista'!K14 -> FY2031E | ... P4: ='00 Panel del Analista'!P14 -> FY2036E
B6: INGRESOS
